Workbook
Name DataBase: PARÂMETROS!$B$3

Sheet RESUMO
A1: Ed. Jardim · Equipamentos e Ferramentas (grupo 11) · R00
A2: Data-base out/26 (pagamentos até 07/10/2026). Realizado pelo financeiro; projeção pendente da medição e dos contratos.
A3: Projeção final: pendente (precisa da medição .xlsm, dos contratos e do cronograma)
A5: Linha | B5: Descrição | C5: Orçado sem INCC | D5: Base até a data-base | E5: Realizado pago | F5: A pagar lançado | G5: Realizado + a pagar | H5: Saldo do orçado | I5: Realizado / base até a data-base | J5: % do orçado consumido
A6: L01 | B6: Ferramentas manuais e pequenos equipamentos | C6: =PARÂMETROS!D11 -> 0 | D6: =SUMIFS(HISTOGRAMA!$D6:$BL6,HISTOGRAMA!$D$4:$BL$4,"<="&DataBase) -> 0 | E6: =HISTOGRAMA!C18 -> 299172.56 | F6: =HISTOGRAMA!C30 -> 19511.1 | G6: =E6+F6 -> 318683.66 | H6: =C6-G6 -> -318683.66 | I6: =IFERROR(E6/D6,"-") -> - | J6: =IFERROR(G6/C6,"-") -> -
A7: L02 | B7: Movimento de terra, manipulador e transporte vertical leve | C7: =PARÂMETROS!D12 -> 0 | D7: =SUMIFS(HISTOGRAMA!$D7:$BL7,HISTOGRAMA!$D$4:$BL$4,"<="&DataBase) -> 0 | E7: =HISTOGRAMA!C19 -> 22059.95 | F7: =HISTOGRAMA!C31 -> 0 | G7: =E7+F7 -> 22059.95 | H7: =C7-G7 -> -22059.95 | I7: =IFERROR(E7/D7,"-") -> - | J7: =IFERROR(G7/C7,"-") -> -
A8: L03 | B8: Equipamentos de produção civil e locações | C8: =PARÂMETROS!D13 -> 0 | D8: =SUMIFS(HISTOGRAMA!$D8:$BL8,HISTOGRAMA!$D$4:$BL$4,"<="&DataBase) -> 0 | E8: =HISTOGRAMA!C20 -> 363291.14 | F8: =HISTOGRAMA!C32 -> 3648.61 | G8: =E8+F8 -> 366939.75 | H8: =C8-G8 -> -366939.75 | I8: =IFERROR(E8/D8,"-") -> - | J8: =IFERROR(G8/C8,"-") -> -
A9: L04 | B9: Bandejas de proteção | C9: =PARÂMETROS!D14 -> 0 | D9: =SUMIFS(HISTOGRAMA!$D9:$BL9,HISTOGRAMA!$D$4:$BL$4,"<="&DataBase) -> 0 | E9: =HISTOGRAMA!C21 -> 92228.2 | F9: =HISTOGRAMA!C33 -> 0 | G9: =E9+F9 -> 92228.2 | H9: =C9-G9 -> -92228.2 | I9: =IFERROR(E9/D9,"-") -> - | J9: =IFERROR(G9/C9,"-") -> -
A10: L05 | B10: Elevador cremalheira | C10: =PARÂMETROS!D15 -> 0 | D10: =SUMIFS(HISTOGRAMA!$D10:$BL10,HISTOGRAMA!$D$4:$BL$4,"<="&DataBase) -> 0 | E10: =HISTOGRAMA!C22 -> 0 | F10: =HISTOGRAMA!C34 -> 0 | G10: =E10+F10 -> 0 | H10: =C10-G10 -> 0 | I10: =IFERROR(E10/D10,"-") -> - | J10: =IFERROR(G10/C10,"-") -> -
A11: L06 | B11: Grua | C11: =PARÂMETROS!D16 -> 0 | D11: =SUMIFS(HISTOGRAMA!$D11:$BL11,HISTOGRAMA!$D$4:$BL$4,"<="&DataBase) -> 0 | E11: =HISTOGRAMA!C23 -> 0 | F11: =HISTOGRAMA!C35 -> 0 | G11: =E11+F11 -> 0 | H11: =C11-G11 -> 0 | I11: =IFERROR(E11/D11,"-") -> - | J11: =IFERROR(G11/C11,"-") -> -
A12: L07 | B12: Equipamentos de fachada (andaimes, balancins) | C12: =PARÂMETROS!D17 -> 0 | D12: =SUMIFS(HISTOGRAMA!$D12:$BL12,HISTOGRAMA!$D$4:$BL$4,"<="&DataBase) -> 0 | E12: =HISTOGRAMA!C24 -> 7694.065 | F12: =HISTOGRAMA!C36 -> 4750 | G12: =E12+F12 -> 12444.065 | H12: =C12-G12 -> -12444.065 | I12: =IFERROR(E12/D12,"-") -> - | J12: =IFERROR(G12/C12,"-") -> -
A13: L08 | B13: Equipamentos de proteção coletiva (telas, sinalização) | C13: =PARÂMETROS!D18 -> 0 | D13: =SUMIFS(HISTOGRAMA!$D13:$BL13,HISTOGRAMA!$D$4:$BL$4,"<="&DataBase) -> 0 | E13: =HISTOGRAMA!C25 -> 303007.55 | F13: =HISTOGRAMA!C37 -> 9913.29 | G13: =E13+F13 -> 312920.84 | H13: =C13-G13 -> -312920.84 | I13: =IFERROR(E13/D13,"-") -> - | J13: =IFERROR(G13/C13,"-") -> -
A14: L10 | B14: A classificar (sem linha definida) | C14: =PARÂMETROS!D19 -> 0 | D14: =SUMIFS(HISTOGRAMA!$D14:$BL14,HISTOGRAMA!$D$4:$BL$4,"<="&DataBase) -> 0 | E14: =HISTOGRAMA!C26 -> 947954.74 | F14: =HISTOGRAMA!C38 -> 116739.49 | G14: =E14+F14 -> 1064694.2 | H14: =C14-G14 -> -1064694.2 | I14: =IFERROR(E14/D14,"-") -> - | J14: =IFERROR(G14/C14,"-") -> -
A15: TOTAL | C15: =SUM(C6:C14) -> 0 | D15: =SUM(D6:D14) -> 0 | E15: =SUM(E6:E14) -> 2035408.2 | F15: =SUM(F6:F14) -> 154562.49 | G15: =E15+F15 -> 2189970.7 | H15: =C15-G15 -> -2189970.7 | I15: =IFERROR(E15/D15,"-") -> - | J15: =IFERROR(G15/C15,"-") -> -
A17: CONFERÊNCIAS
A18: 1 | B18: Realizado pago = total PAGAS do financeiro | C18: =IF(ABS(E15-PARÂMETROS!B4)<0.01,"OK","VERIFICAR") -> OK
A19: 2 | B19: A pagar = total A PAGAR do financeiro | C19: =IF(ABS(F15-PARÂMETROS!B5)<0.01,"OK","VERIFICAR") -> OK
A20: 3 | B20: Base mensal = orçado sem INCC (ANÁLISE) | C20: =IF(PARÂMETROS!B7="","PENDENTE",IF(ABS(BASE!C14-PARÂMETROS!B7)<1,"OK","VERIFICAR")) -> PENDENTE
A21: 4 | B21: Lançamentos sem linha (L10) = zero | C21: =IF(G14<0.01,"OK","VERIFICAR") -> VERIFICAR
A22: 5 | B22: Realizado = ANÁLISE IEC (T) da medição | C22: PENDENTE

Sheet HISTOGRAMA
A1: Ed. Jardim · Histograma do grupo 11 (R$)
A2: Realizado = pagamentos do financeiro no mês (SUMIFS em LANÇAMENTOS). A pagar = títulos em aberto lançados no financeiro, no mês de vencimento.
A4: Linha | B4: Descrição | C4: Total | D4: 45444 | E4: 45474 | F4: 45505 | G4: 45536 | H4: 45566 | I4: 45597 | J4: 45627 | K4: 45658 | L4: 45689 | M4: 45717 | N4: 45748 | O4: 45778 | P4: 45809 | Q4: 45839 | R4: 45870 | S4: 45901 | T4: 45931 | U4: 45962 | V4: 45992 | W4: 46023 | X4: 46054 | Y4: 46082 | Z4: 46113 | AA4: 46143 | AB4: 46174 | AC4: 46204 | AD4: 46235 | AE4: 46266 | AF4: 46296 | AG4: 46327 | AH4: 46357 | AI4: 46388 | AJ4: 46419 | AK4: 46447 | AL4: 46478 | AM4: 46508 | AN4: 46539 | AO4: 46569 | AP4: 46600 | AQ4: 46631 | AR4: 46661 | AS4: 46692 | AT4: 46722 | AU4: 46753 | AV4: 46784 | AW4: 46813 | AX4: 46844 | AY4: 46874 | AZ4: 46905 | BA4: 46935 | BB4: 46966 | BC4: 46997 | BD4: 47027 | BE4: 47058 | BF4: 47088 | BG4: 47119 | BH4: 47150 | BI4: 47178 | BJ4: 47209 | BK4: 47239 | BL4: 47270
A5: BASE SEM INCC
A6: L01 | B6: Ferramentas manuais e pequenos equipamentos | C6: =SUM(D6:BL6) -> 0 | D6: =BASE!D5 -> 0 | E6: =BASE!E5 -> 0 | F6: =BASE!F5 -> 0 | G6: =BASE!G5 -> 0 | H6: =BASE!H5 -> 0 | I6: =BASE!I5 -> 0 | J6: =BASE!J5 -> 0 | K6: =BASE!K5 -> 0 | ... BL6: =BASE!BL5 -> 0
A7: L02 | B7: Movimento de terra, manipulador e transporte vertical leve | C7: =SUM(D7:BL7) -> 0 | D7: =BASE!D6 -> 0 | E7: =BASE!E6 -> 0 | F7: =BASE!F6 -> 0 | G7: =BASE!G6 -> 0 | H7: =BASE!H6 -> 0 | I7: =BASE!I6 -> 0 | J7: =BASE!J6 -> 0 | K7: =BASE!K6 -> 0 | ... BL7: =BASE!BL6 -> 0
A8: L03 | B8: Equipamentos de produção civil e locações | C8: =SUM(D8:BL8) -> 0 | D8: =BASE!D7 -> 0 | E8: =BASE!E7 -> 0 | F8: =BASE!F7 -> 0 | G8: =BASE!G7 -> 0 | H8: =BASE!H7 -> 0 | I8: =BASE!I7 -> 0 | J8: =BASE!J7 -> 0 | K8: =BASE!K7 -> 0 | ... BL8: =BASE!BL7 -> 0
A9: L04 | B9: Bandejas de proteção | C9: =SUM(D9:BL9) -> 0 | D9: =BASE!D8 -> 0 | E9: =BASE!E8 -> 0 | F9: =BASE!F8 -> 0 | G9: =BASE!G8 -> 0 | H9: =BASE!H8 -> 0 | I9: =BASE!I8 -> 0 | J9: =BASE!J8 -> 0 | K9: =BASE!K8 -> 0 | ... BL9: =BASE!BL8 -> 0
A10: L05 | B10: Elevador cremalheira | C10: =SUM(D10:BL10) -> 0 | D10: =BASE!D9 -> 0 | E10: =BASE!E9 -> 0 | F10: =BASE!F9 -> 0 | G10: =BASE!G9 -> 0 | H10: =BASE!H9 -> 0 | I10: =BASE!I9 -> 0 | J10: =BASE!J9 -> 0 | K10: =BASE!K9 -> 0 | ... BL10: =BASE!BL9 -> 0
A11: L06 | B11: Grua | C11: =SUM(D11:BL11) -> 0 | D11: =BASE!D10 -> 0 | E11: =BASE!E10 -> 0 | F11: =BASE!F10 -> 0 | G11: =BASE!G10 -> 0 | H11: =BASE!H10 -> 0 | I11: =BASE!I10 -> 0 | J11: =BASE!J10 -> 0 | K11: =BASE!K10 -> 0 | ... BL11: =BASE!BL10 -> 0
A12: L07 | B12: Equipamentos de fachada (andaimes, balancins) | C12: =SUM(D12:BL12) -> 0 | D12: =BASE!D11 -> 0 | E12: =BASE!E11 -> 0 | F12: =BASE!F11 -> 0 | G12: =BASE!G11 -> 0 | H12: =BASE!H11 -> 0 | I12: =BASE!I11 -> 0 | J12: =BASE!J11 -> 0 | K12: =BASE!K11 -> 0 | ... BL12: =BASE!BL11 -> 0
A13: L08 | B13: Equipamentos de proteção coletiva (telas, sinalização) | C13: =SUM(D13:BL13) -> 0 | D13: =BASE!D12 -> 0 | E13: =BASE!E12 -> 0 | F13: =BASE!F12 -> 0 | G13: =BASE!G12 -> 0 | H13: =BASE!H12 -> 0 | I13: =BASE!I12 -> 0 | J13: =BASE!J12 -> 0 | K13: =BASE!K12 -> 0 | ... BL13: =BASE!BL12 -> 0
A14: L10 | B14: A classificar (sem linha definida) | C14: =SUM(D14:BL14) -> 0 | D14: =BASE!D13 -> 0 | E14: =BASE!E13 -> 0 | F14: =BASE!F13 -> 0 | G14: =BASE!G13 -> 0 | H14: =BASE!H13 -> 0 | I14: =BASE!I13 -> 0 | J14: =BASE!J13 -> 0 | K14: =BASE!K13 -> 0 | ... BL14: =BASE!BL13 -> 0
A15: TOTAL | C15: =SUM(C6:C14) -> 0 | D15: =SUM(D6:D14) -> 0 | E15: =SUM(E6:E14) -> 0 | F15: =SUM(F6:F14) -> 0 | G15: =SUM(G6:G14) -> 0 | H15: =SUM(H6:H14) -> 0 | I15: =SUM(I6:I14) -> 0 | J15: =SUM(J6:J14) -> 0 | ... BL15: =SUM(BL6:BL14) -> 0
A17: REALIZADO (PAGO NO MÊS)
A18: L01 | B18: Ferramentas manuais e pequenos equipamentos | C18: =SUM(D18:BL18) -> 299172.56 | D18: =SUMIFS(LANÇAMENTOS!$F$5:$F$1323,LANÇAMENTOS!$D$5:$D$1323,$A18,LANÇAMENTOS!$A$5:$A$1323,D$4,LANÇAMENTOS!$B$5:$B$1323,"Pago") -> 0 | E18: =SUMIFS(LANÇAMENTOS!$F$5:$F$1323,LANÇAMENTOS!$D$5:$D$1323,$A18,LANÇAMENTOS!$A$5:$A$1323,E$4,LANÇAMENTOS!$B$5:$B$1323,"Pago") -> 0 | F18: =SUMIFS(LANÇAMENTOS!$F$5:$F$1323,LANÇAMENTOS!$D$5:$D$1323,$A18,LANÇAMENTOS!$A$5:$A$1323,F$4,LANÇAMENTOS!$B$5:$B$1323,"Pago") -> 0 | G18: =SUMIFS(LANÇAMENTOS!$F$5:$F$1323,LANÇAMENTOS!$D$5:$D$1323,$A18,LANÇAMENTOS!$A$5:$A$1323,G$4,LANÇAMENTOS!$B$5:$B$1323,"Pago") -> 543.38 | H18: =SUMIFS(LANÇAMENTOS!$F$5:$F$1323,LANÇAMENTOS!$D$5:$D$1323,$A18,LANÇAMENTOS!$A$5:$A$1323,H$4,LANÇAMENTOS!$B$5:$B$1323,"Pago") -> 1482.9816 | I18: =SUMIFS(LANÇAMENTOS!$F$5:$F$1323,LANÇAMENTOS!$D$5:$D$1323,$A18,LANÇAMENTOS!$A$5:$A$1323,I$4,LANÇAMENTOS!$B$5:$B$1323,"Pago") -> 1092.25 | J18: =SUMIFS(LANÇAMENTOS!$F$5:$F$1323,LANÇAMENTOS!$D$5:$D$1323,$A18,LANÇAMENTOS!$A$5:$A$1323,J$4,LANÇAMENTOS!$B$5:$B$1323,"Pago") -> 225.79 | K18: =SUMIFS(LANÇAMENTOS!$F$5:$F$1323,LANÇAMENTOS!$D$5:$D$1323,$A18,LANÇAMENTOS!$A$5:$A$1323,K$4,LANÇAMENTOS!$B$5:$B$1323,"Pago") -> 260.1 | ... BL18: =SUMIFS(LANÇAMENTOS!$F$5:$F$1323,LANÇAMENTOS!$D$5:$D$1323,$A18,LANÇAMENTOS!$A$5:$A$1323,BL$4,LANÇAMENTOS!$B$5:$B$1323,"Pago") -> 0
A19: L02 | B19: Movimento de terra, manipulador e transporte vertical leve | C19: =SUM(D19:BL19) -> 22059.95 | D19: =SUMIFS(LANÇAMENTOS!$F$5:$F$1323,LANÇAMENTOS!$D$5:$D$1323,$A19,LANÇAMENTOS!$A$5:$A$1323,D$4,LANÇAMENTOS!$B$5:$B$1323,"Pago") -> 0 | E19: =SUMIFS(LANÇAMENTOS!$F$5:$F$1323,LANÇAMENTOS!$D$5:$D$1323,$A19,LANÇAMENTOS!$A$5:$A$1323,E$4,LANÇAMENTOS!$B$5:$B$1323,"Pago") -> 0 | F19: =SUMIFS(LANÇAMENTOS!$F$5:$F$1323,LANÇAMENTOS!$D$5:$D$1323,$A19,LANÇAMENTOS!$A$5:$A$1323,F$4,LANÇAMENTOS!$B$5:$B$1323,"Pago") -> 0 | G19: =SUMIFS(LANÇAMENTOS!$F$5:$F$1323,LANÇAMENTOS!$D$5:$D$1323,$A19,LANÇAMENTOS!$A$5:$A$1323,G$4,LANÇAMENTOS!$B$5:$B$1323,"Pago") -> 0 | H19: =SUMIFS(LANÇAMENTOS!$F$5:$F$1323,LANÇAMENTOS!$D$5:$D$1323,$A19,LANÇAMENTOS!$A$5:$A$1323,H$4,LANÇAMENTOS!$B$5:$B$1323,"Pago") -> 0 | I19: =SUMIFS(LANÇAMENTOS!$F$5:$F$1323,LANÇAMENTOS!$D$5:$D$1323,$A19,LANÇAMENTOS!$A$5:$A$1323,I$4,LANÇAMENTOS!$B$5:$B$1323,"Pago") -> 0 | J19: =SUMIFS(LANÇAMENTOS!$F$5:$F$1323,LANÇAMENTOS!$D$5:$D$1323,$A19,LANÇAMENTOS!$A$5:$A$1323,J$4,LANÇAMENTOS!$B$5:$B$1323,"Pago") -> 0 | K19: =SUMIFS(LANÇAMENTOS!$F$5:$F$1323,LANÇAMENTOS!$D$5:$D$1323,$A19,LANÇAMENTOS!$A$5:$A$1323,K$4,LANÇAMENTOS!$B$5:$B$1323,"Pago") -> 0 | ... BL19: =SUMIFS(LANÇAMENTOS!$F$5:$F$1323,LANÇAMENTOS!$D$5:$D$1323,$A19,LANÇAMENTOS!$A$5:$A$1323,BL$4,LANÇAMENTOS!$B$5:$B$1323,"Pago") -> 0
A20: L03 | B20: Equipamentos de produção civil e locações | C20: =SUM(D20:BL20) -> 363291.14 | D20: =SUMIFS(LANÇAMENTOS!$F$5:$F$1323,LANÇAMENTOS!$D$5:$D$1323,$A20,LANÇAMENTOS!$A$5:$A$1323,D$4,LANÇAMENTOS!$B$5:$B$1323,"Pago") -> 1113 | E20: =SUMIFS(LANÇAMENTOS!$F$5:$F$1323,LANÇAMENTOS!$D$5:$D$1323,$A20,LANÇAMENTOS!$A$5:$A$1323,E$4,LANÇAMENTOS!$B$5:$B$1323,"Pago") -> 813 | F20: =SUMIFS(LANÇAMENTOS!$F$5:$F$1323,LANÇAMENTOS!$D$5:$D$1323,$A20,LANÇAMENTOS!$A$5:$A$1323,F$4,LANÇAMENTOS!$B$5:$B$1323,"Pago") -> 2067 | G20: =SUMIFS(LANÇAMENTOS!$F$5:$F$1323,LANÇAMENTOS!$D$5:$D$1323,$A20,LANÇAMENTOS!$A$5:$A$1323,G$4,LANÇAMENTOS!$B$5:$B$1323,"Pago") -> 800 | H20: =SUMIFS(LANÇAMENTOS!$F$5:$F$1323,LANÇAMENTOS!$D$5:$D$1323,$A20,LANÇAMENTOS!$A$5:$A$1323,H$4,LANÇAMENTOS!$B$5:$B$1323,"Pago") -> 1940 | I20: =SUMIFS(LANÇAMENTOS!$F$5:$F$1323,LANÇAMENTOS!$D$5:$D$1323,$A20,LANÇAMENTOS!$A$5:$A$1323,I$4,LANÇAMENTOS!$B$5:$B$1323,"Pago") -> 192.46 | J20: =SUMIFS(LANÇAMENTOS!$F$5:$F$1323,LANÇAMENTOS!$D$5:$D$1323,$A20,LANÇAMENTOS!$A$5:$A$1323,J$4,LANÇAMENTOS!$B$5:$B$1323,"Pago") -> 6820.02 | K20: =SUMIFS(LANÇAMENTOS!$F$5:$F$1323,LANÇAMENTOS!$D$5:$D$1323,$A20,LANÇAMENTOS!$A$5:$A$1323,K$4,LANÇAMENTOS!$B$5:$B$1323,"Pago") -> 4370 | ... BL20: =SUMIFS(LANÇAMENTOS!$F$5:$F$1323,LANÇAMENTOS!$D$5:$D$1323,$A20,LANÇAMENTOS!$A$5:$A$1323,BL$4,LANÇAMENTOS!$B$5:$B$1323,"Pago") -> 0
A21: L04 | B21: Bandejas de proteção | C21: =SUM(D21:BL21) -> 92228.2 | D21: =SUMIFS(LANÇAMENTOS!$F$5:$F$1323,LANÇAMENTOS!$D$5:$D$1323,$A21,LANÇAMENTOS!$A$5:$A$1323,D$4,LANÇAMENTOS!$B$5:$B$1323,"Pago") -> 0 | E21: =SUMIFS(LANÇAMENTOS!$F$5:$F$1323,LANÇAMENTOS!$D$5:$D$1323,$A21,LANÇAMENTOS!$A$5:$A$1323,E$4,LANÇAMENTOS!$B$5:$B$1323,"Pago") -> 0 | F21: =SUMIFS(LANÇAMENTOS!$F$5:$F$1323,LANÇAMENTOS!$D$5:$D$1323,$A21,LANÇAMENTOS!$A$5:$A$1323,F$4,LANÇAMENTOS!$B$5:$B$1323,"Pago") -> 0 | G21: =SUMIFS(LANÇAMENTOS!$F$5:$F$1323,LANÇAMENTOS!$D$5:$D$1323,$A21,LANÇAMENTOS!$A$5:$A$1323,G$4,LANÇAMENTOS!$B$5:$B$1323,"Pago") -> 0 | H21: =SUMIFS(LANÇAMENTOS!$F$5:$F$1323,LANÇAMENTOS!$D$5:$D$1323,$A21,LANÇAMENTOS!$A$5:$A$1323,H$4,LANÇAMENTOS!$B$5:$B$1323,"Pago") -> 0 | I21: =SUMIFS(LANÇAMENTOS!$F$5:$F$1323,LANÇAMENTOS!$D$5:$D$1323,$A21,LANÇAMENTOS!$A$5:$A$1323,I$4,LANÇAMENTOS!$B$5:$B$1323,"Pago") -> 0 | J21: =SUMIFS(LANÇAMENTOS!$F$5:$F$1323,LANÇAMENTOS!$D$5:$D$1323,$A21,LANÇAMENTOS!$A$5:$A$1323,J$4,LANÇAMENTOS!$B$5:$B$1323,"Pago") -> 0 | K21: =SUMIFS(LANÇAMENTOS!$F$5:$F$1323,LANÇAMENTOS!$D$5:$D$1323,$A21,LANÇAMENTOS!$A$5:$A$1323,K$4,LANÇAMENTOS!$B$5:$B$1323,"Pago") -> 0 | ... BL21: =SUMIFS(LANÇAMENTOS!$F$5:$F$1323,LANÇAMENTOS!$D$5:$D$1323,$A21,LANÇAMENTOS!$A$5:$A$1323,BL$4,LANÇAMENTOS!$B$5:$B$1323,"Pago") -> 0
A22: L05 | B22: Elevador cremalheira | C22: =SUM(D22:BL22) -> 0 | D22: =SUMIFS(LANÇAMENTOS!$F$5:$F$1323,LANÇAMENTOS!$D$5:$D$1323,$A22,LANÇAMENTOS!$A$5:$A$1323,D$4,LANÇAMENTOS!$B$5:$B$1323,"Pago") -> 0 | E22: =SUMIFS(LANÇAMENTOS!$F$5:$F$1323,LANÇAMENTOS!$D$5:$D$1323,$A22,LANÇAMENTOS!$A$5:$A$1323,E$4,LANÇAMENTOS!$B$5:$B$1323,"Pago") -> 0 | F22: =SUMIFS(LANÇAMENTOS!$F$5:$F$1323,LANÇAMENTOS!$D$5:$D$1323,$A22,LANÇAMENTOS!$A$5:$A$1323,F$4,LANÇAMENTOS!$B$5:$B$1323,"Pago") -> 0 | G22: =SUMIFS(LANÇAMENTOS!$F$5:$F$1323,LANÇAMENTOS!$D$5:$D$1323,$A22,LANÇAMENTOS!$A$5:$A$1323,G$4,LANÇAMENTOS!$B$5:$B$1323,"Pago") -> 0 | H22: =SUMIFS(LANÇAMENTOS!$F$5:$F$1323,LANÇAMENTOS!$D$5:$D$1323,$A22,LANÇAMENTOS!$A$5:$A$1323,H$4,LANÇAMENTOS!$B$5:$B$1323,"Pago") -> 0 | I22: =SUMIFS(LANÇAMENTOS!$F$5:$F$1323,LANÇAMENTOS!$D$5:$D$1323,$A22,LANÇAMENTOS!$A$5:$A$1323,I$4,LANÇAMENTOS!$B$5:$B$1323,"Pago") -> 0 | J22: =SUMIFS(LANÇAMENTOS!$F$5:$F$1323,LANÇAMENTOS!$D$5:$D$1323,$A22,LANÇAMENTOS!$A$5:$A$1323,J$4,LANÇAMENTOS!$B$5:$B$1323,"Pago") -> 0 | K22: =SUMIFS(LANÇAMENTOS!$F$5:$F$1323,LANÇAMENTOS!$D$5:$D$1323,$A22,LANÇAMENTOS!$A$5:$A$1323,K$4,LANÇAMENTOS!$B$5:$B$1323,"Pago") -> 0 | ... BL22: =SUMIFS(LANÇAMENTOS!$F$5:$F$1323,LANÇAMENTOS!$D$5:$D$1323,$A22,LANÇAMENTOS!$A$5:$A$1323,BL$4,LANÇAMENTOS!$B$5:$B$1323,"Pago") -> 0
A23: L06 | B23: Grua | C23: =SUM(D23:BL23) -> 0 | D23: =SUMIFS(LANÇAMENTOS!$F$5:$F$1323,LANÇAMENTOS!$D$5:$D$1323,$A23,LANÇAMENTOS!$A$5:$A$1323,D$4,LANÇAMENTOS!$B$5:$B$1323,"Pago") -> 0 | E23: =SUMIFS(LANÇAMENTOS!$F$5:$F$1323,LANÇAMENTOS!$D$5:$D$1323,$A23,LANÇAMENTOS!$A$5:$A$1323,E$4,LANÇAMENTOS!$B$5:$B$1323,"Pago") -> 0 | F23: =SUMIFS(LANÇAMENTOS!$F$5:$F$1323,LANÇAMENTOS!$D$5:$D$1323,$A23,LANÇAMENTOS!$A$5:$A$1323,F$4,LANÇAMENTOS!$B$5:$B$1323,"Pago") -> 0 | G23: =SUMIFS(LANÇAMENTOS!$F$5:$F$1323,LANÇAMENTOS!$D$5:$D$1323,$A23,LANÇAMENTOS!$A$5:$A$1323,G$4,LANÇAMENTOS!$B$5:$B$1323,"Pago") -> 0 | H23: =SUMIFS(LANÇAMENTOS!$F$5:$F$1323,LANÇAMENTOS!$D$5:$D$1323,$A23,LANÇAMENTOS!$A$5:$A$1323,H$4,LANÇAMENTOS!$B$5:$B$1323,"Pago") -> 0 | I23: =SUMIFS(LANÇAMENTOS!$F$5:$F$1323,LANÇAMENTOS!$D$5:$D$1323,$A23,LANÇAMENTOS!$A$5:$A$1323,I$4,LANÇAMENTOS!$B$5:$B$1323,"Pago") -> 0 | J23: =SUMIFS(LANÇAMENTOS!$F$5:$F$1323,LANÇAMENTOS!$D$5:$D$1323,$A23,LANÇAMENTOS!$A$5:$A$1323,J$4,LANÇAMENTOS!$B$5:$B$1323,"Pago") -> 0 | K23: =SUMIFS(LANÇAMENTOS!$F$5:$F$1323,LANÇAMENTOS!$D$5:$D$1323,$A23,LANÇAMENTOS!$A$5:$A$1323,K$4,LANÇAMENTOS!$B$5:$B$1323,"Pago") -> 0 | ... BL23: =SUMIFS(LANÇAMENTOS!$F$5:$F$1323,LANÇAMENTOS!$D$5:$D$1323,$A23,LANÇAMENTOS!$A$5:$A$1323,BL$4,LANÇAMENTOS!$B$5:$B$1323,"Pago") -> 0
A24: L07 | B24: Equipamentos de fachada (andaimes, balancins) | C24: =SUM(D24:BL24) -> 7694.065 | D24: =SUMIFS(LANÇAMENTOS!$F$5:$F$1323,LANÇAMENTOS!$D$5:$D$1323,$A24,LANÇAMENTOS!$A$5:$A$1323,D$4,LANÇAMENTOS!$B$5:$B$1323,"Pago") -> 0 | E24: =SUMIFS(LANÇAMENTOS!$F$5:$F$1323,LANÇAMENTOS!$D$5:$D$1323,$A24,LANÇAMENTOS!$A$5:$A$1323,E$4,LANÇAMENTOS!$B$5:$B$1323,"Pago") -> 0 | F24: =SUMIFS(LANÇAMENTOS!$F$5:$F$1323,LANÇAMENTOS!$D$5:$D$1323,$A24,LANÇAMENTOS!$A$5:$A$1323,F$4,LANÇAMENTOS!$B$5:$B$1323,"Pago") -> 0 | G24: =SUMIFS(LANÇAMENTOS!$F$5:$F$1323,LANÇAMENTOS!$D$5:$D$1323,$A24,LANÇAMENTOS!$A$5:$A$1323,G$4,LANÇAMENTOS!$B$5:$B$1323,"Pago") -> 0 | H24: =SUMIFS(LANÇAMENTOS!$F$5:$F$1323,LANÇAMENTOS!$D$5:$D$1323,$A24,LANÇAMENTOS!$A$5:$A$1323,H$4,LANÇAMENTOS!$B$5:$B$1323,"Pago") -> 0 | I24: =SUMIFS(LANÇAMENTOS!$F$5:$F$1323,LANÇAMENTOS!$D$5:$D$1323,$A24,LANÇAMENTOS!$A$5:$A$1323,I$4,LANÇAMENTOS!$B$5:$B$1323,"Pago") -> 0 | J24: =SUMIFS(LANÇAMENTOS!$F$5:$F$1323,LANÇAMENTOS!$D$5:$D$1323,$A24,LANÇAMENTOS!$A$5:$A$1323,J$4,LANÇAMENTOS!$B$5:$B$1323,"Pago") -> 0 | K24: =SUMIFS(LANÇAMENTOS!$F$5:$F$1323,LANÇAMENTOS!$D$5:$D$1323,$A24,LANÇAMENTOS!$A$5:$A$1323,K$4,LANÇAMENTOS!$B$5:$B$1323,"Pago") -> 0 | ... BL24: =SUMIFS(LANÇAMENTOS!$F$5:$F$1323,LANÇAMENTOS!$D$5:$D$1323,$A24,LANÇAMENTOS!$A$5:$A$1323,BL$4,LANÇAMENTOS!$B$5:$B$1323,"Pago") -> 0
A25: L08 | B25: Equipamentos de proteção coletiva (telas, sinalização) | C25: =SUM(D25:BL25) -> 303007.55 | D25: =SUMIFS(LANÇAMENTOS!$F$5:$F$1323,LANÇAMENTOS!$D$5:$D$1323,$A25,LANÇAMENTOS!$A$5:$A$1323,D$4,LANÇAMENTOS!$B$5:$B$1323,"Pago") -> 0 | E25: =SUMIFS(LANÇAMENTOS!$F$5:$F$1323,LANÇAMENTOS!$D$5:$D$1323,$A25,LANÇAMENTOS!$A$5:$A$1323,E$4,LANÇAMENTOS!$B$5:$B$1323,"Pago") -> 331.4 | F25: =SUMIFS(LANÇAMENTOS!$F$5:$F$1323,LANÇAMENTOS!$D$5:$D$1323,$A25,LANÇAMENTOS!$A$5:$A$1323,F$4,LANÇAMENTOS!$B$5:$B$1323,"Pago") -> 0 | G25: =SUMIFS(LANÇAMENTOS!$F$5:$F$1323,LANÇAMENTOS!$D$5:$D$1323,$A25,LANÇAMENTOS!$A$5:$A$1323,G$4,LANÇAMENTOS!$B$5:$B$1323,"Pago") -> 0 | H25: =SUMIFS(LANÇAMENTOS!$F$5:$F$1323,LANÇAMENTOS!$D$5:$D$1323,$A25,LANÇAMENTOS!$A$5:$A$1323,H$4,LANÇAMENTOS!$B$5:$B$1323,"Pago") -> 1499.2 | I25: =SUMIFS(LANÇAMENTOS!$F$5:$F$1323,LANÇAMENTOS!$D$5:$D$1323,$A25,LANÇAMENTOS!$A$5:$A$1323,I$4,LANÇAMENTOS!$B$5:$B$1323,"Pago") -> 0 | J25: =SUMIFS(LANÇAMENTOS!$F$5:$F$1323,LANÇAMENTOS!$D$5:$D$1323,$A25,LANÇAMENTOS!$A$5:$A$1323,J$4,LANÇAMENTOS!$B$5:$B$1323,"Pago") -> 101 | K25: =SUMIFS(LANÇAMENTOS!$F$5:$F$1323,LANÇAMENTOS!$D$5:$D$1323,$A25,LANÇAMENTOS!$A$5:$A$1323,K$4,LANÇAMENTOS!$B$5:$B$1323,"Pago") -> 1171.14 | ... BL25: =SUMIFS(LANÇAMENTOS!$F$5:$F$1323,LANÇAMENTOS!$D$5:$D$1323,$A25,LANÇAMENTOS!$A$5:$A$1323,BL$4,LANÇAMENTOS!$B$5:$B$1323,"Pago") -> 0
A26: L10 | B26: A classificar (sem linha definida) | C26: =SUM(D26:BL26) -> 947954.74 | D26: =SUMIFS(LANÇAMENTOS!$F$5:$F$1323,LANÇAMENTOS!$D$5:$D$1323,$A26,LANÇAMENTOS!$A$5:$A$1323,D$4,LANÇAMENTOS!$B$5:$B$1323,"Pago") -> 0 | E26: =SUMIFS(LANÇAMENTOS!$F$5:$F$1323,LANÇAMENTOS!$D$5:$D$1323,$A26,LANÇAMENTOS!$A$5:$A$1323,E$4,LANÇAMENTOS!$B$5:$B$1323,"Pago") -> 0 | F26: =SUMIFS(LANÇAMENTOS!$F$5:$F$1323,LANÇAMENTOS!$D$5:$D$1323,$A26,LANÇAMENTOS!$A$5:$A$1323,F$4,LANÇAMENTOS!$B$5:$B$1323,"Pago") -> 0 | G26: =SUMIFS(LANÇAMENTOS!$F$5:$F$1323,LANÇAMENTOS!$D$5:$D$1323,$A26,LANÇAMENTOS!$A$5:$A$1323,G$4,LANÇAMENTOS!$B$5:$B$1323,"Pago") -> 2457 | H26: =SUMIFS(LANÇAMENTOS!$F$5:$F$1323,LANÇAMENTOS!$D$5:$D$1323,$A26,LANÇAMENTOS!$A$5:$A$1323,H$4,LANÇAMENTOS!$B$5:$B$1323,"Pago") -> 143 | I26: =SUMIFS(LANÇAMENTOS!$F$5:$F$1323,LANÇAMENTOS!$D$5:$D$1323,$A26,LANÇAMENTOS!$A$5:$A$1323,I$4,LANÇAMENTOS!$B$5:$B$1323,"Pago") -> 0 | J26: =SUMIFS(LANÇAMENTOS!$F$5:$F$1323,LANÇAMENTOS!$D$5:$D$1323,$A26,LANÇAMENTOS!$A$5:$A$1323,J$4,LANÇAMENTOS!$B$5:$B$1323,"Pago") -> 1316.7 | K26: =SUMIFS(LANÇAMENTOS!$F$5:$F$1323,LANÇAMENTOS!$D$5:$D$1323,$A26,LANÇAMENTOS!$A$5:$A$1323,K$4,LANÇAMENTOS!$B$5:$B$1323,"Pago") -> 223.3 | ... BL26: =SUMIFS(LANÇAMENTOS!$F$5:$F$1323,LANÇAMENTOS!$D$5:$D$1323,$A26,LANÇAMENTOS!$A$5:$A$1323,BL$4,LANÇAMENTOS!$B$5:$B$1323,"Pago") -> 0
A27: TOTAL | C27: =SUM(C18:C26) -> 2035408.2 | D27: =SUM(D18:D26) -> 1113 | E27: =SUM(E18:E26) -> 1144.4 | F27: =SUM(F18:F26) -> 2067 | G27: =SUM(G18:G26) -> 3800.38 | H27: =SUM(H18:H26) -> 5065.1816 | I27: =SUM(I18:I26) -> 1284.71 | J27: =SUM(J18:J26) -> 8463.51 | ... BL27: =SUM(BL18:BL26) -> 0
A29: A PAGAR (LANÇADO NO FINANCEIRO)
A30: L01 | B30: Ferramentas manuais e pequenos equipamentos | C30: =SUM(D30:BL30) -> 19511.1 | D30: =SUMIFS(LANÇAMENTOS!$F$5:$F$1323,LANÇAMENTOS!$D$5:$D$1323,$A30,LANÇAMENTOS!$A$5:$A$1323,D$4,LANÇAMENTOS!$B$5:$B$1323,"A pagar") -> 0 | E30: =SUMIFS(LANÇAMENTOS!$F$5:$F$1323,LANÇAMENTOS!$D$5:$D$1323,$A30,LANÇAMENTOS!$A$5:$A$1323,E$4,LANÇAMENTOS!$B$5:$B$1323,"A pagar") -> 0 | F30: =SUMIFS(LANÇAMENTOS!$F$5:$F$1323,LANÇAMENTOS!$D$5:$D$1323,$A30,LANÇAMENTOS!$A$5:$A$1323,F$4,LANÇAMENTOS!$B$5:$B$1323,"A pagar") -> 0 | G30: =SUMIFS(LANÇAMENTOS!$F$5:$F$1323,LANÇAMENTOS!$D$5:$D$1323,$A30,LANÇAMENTOS!$A$5:$A$1323,G$4,LANÇAMENTOS!$B$5:$B$1323,"A pagar") -> 0 | H30: =SUMIFS(LANÇAMENTOS!$F$5:$F$1323,LANÇAMENTOS!$D$5:$D$1323,$A30,LANÇAMENTOS!$A$5:$A$1323,H$4,LANÇAMENTOS!$B$5:$B$1323,"A pagar") -> 0 | I30: =SUMIFS(LANÇAMENTOS!$F$5:$F$1323,LANÇAMENTOS!$D$5:$D$1323,$A30,LANÇAMENTOS!$A$5:$A$1323,I$4,LANÇAMENTOS!$B$5:$B$1323,"A pagar") -> 0 | J30: =SUMIFS(LANÇAMENTOS!$F$5:$F$1323,LANÇAMENTOS!$D$5:$D$1323,$A30,LANÇAMENTOS!$A$5:$A$1323,J$4,LANÇAMENTOS!$B$5:$B$1323,"A pagar") -> 0 | K30: =SUMIFS(LANÇAMENTOS!$F$5:$F$1323,LANÇAMENTOS!$D$5:$D$1323,$A30,LANÇAMENTOS!$A$5:$A$1323,K$4,LANÇAMENTOS!$B$5:$B$1323,"A pagar") -> 0 | ... BL30: =SUMIFS(LANÇAMENTOS!$F$5:$F$1323,LANÇAMENTOS!$D$5:$D$1323,$A30,LANÇAMENTOS!$A$5:$A$1323,BL$4,LANÇAMENTOS!$B$5:$B$1323,"A pagar") -> 0
A31: L02 | B31: Movimento de terra, manipulador e transporte vertical leve | C31: =SUM(D31:BL31) -> 0 | D31: =SUMIFS(LANÇAMENTOS!$F$5:$F$1323,LANÇAMENTOS!$D$5:$D$1323,$A31,LANÇAMENTOS!$A$5:$A$1323,D$4,LANÇAMENTOS!$B$5:$B$1323,"A pagar") -> 0 | E31: =SUMIFS(LANÇAMENTOS!$F$5:$F$1323,LANÇAMENTOS!$D$5:$D$1323,$A31,LANÇAMENTOS!$A$5:$A$1323,E$4,LANÇAMENTOS!$B$5:$B$1323,"A pagar") -> 0 | F31: =SUMIFS(LANÇAMENTOS!$F$5:$F$1323,LANÇAMENTOS!$D$5:$D$1323,$A31,LANÇAMENTOS!$A$5:$A$1323,F$4,LANÇAMENTOS!$B$5:$B$1323,"A pagar") -> 0 | G31: =SUMIFS(LANÇAMENTOS!$F$5:$F$1323,LANÇAMENTOS!$D$5:$D$1323,$A31,LANÇAMENTOS!$A$5:$A$1323,G$4,LANÇAMENTOS!$B$5:$B$1323,"A pagar") -> 0 | H31: =SUMIFS(LANÇAMENTOS!$F$5:$F$1323,LANÇAMENTOS!$D$5:$D$1323,$A31,LANÇAMENTOS!$A$5:$A$1323,H$4,LANÇAMENTOS!$B$5:$B$1323,"A pagar") -> 0 | I31: =SUMIFS(LANÇAMENTOS!$F$5:$F$1323,LANÇAMENTOS!$D$5:$D$1323,$A31,LANÇAMENTOS!$A$5:$A$1323,I$4,LANÇAMENTOS!$B$5:$B$1323,"A pagar") -> 0 | J31: =SUMIFS(LANÇAMENTOS!$F$5:$F$1323,LANÇAMENTOS!$D$5:$D$1323,$A31,LANÇAMENTOS!$A$5:$A$1323,J$4,LANÇAMENTOS!$B$5:$B$1323,"A pagar") -> 0 | K31: =SUMIFS(LANÇAMENTOS!$F$5:$F$1323,LANÇAMENTOS!$D$5:$D$1323,$A31,LANÇAMENTOS!$A$5:$A$1323,K$4,LANÇAMENTOS!$B$5:$B$1323,"A pagar") -> 0 | ... BL31: =SUMIFS(LANÇAMENTOS!$F$5:$F$1323,LANÇAMENTOS!$D$5:$D$1323,$A31,LANÇAMENTOS!$A$5:$A$1323,BL$4,LANÇAMENTOS!$B$5:$B$1323,"A pagar") -> 0
A32: L03 | B32: Equipamentos de produção civil e locações | C32: =SUM(D32:BL32) -> 3648.61 | D32: =SUMIFS(LANÇAMENTOS!$F$5:$F$1323,LANÇAMENTOS!$D$5:$D$1323,$A32,LANÇAMENTOS!$A$5:$A$1323,D$4,LANÇAMENTOS!$B$5:$B$1323,"A pagar") -> 0 | E32: =SUMIFS(LANÇAMENTOS!$F$5:$F$1323,LANÇAMENTOS!$D$5:$D$1323,$A32,LANÇAMENTOS!$A$5:$A$1323,E$4,LANÇAMENTOS!$B$5:$B$1323,"A pagar") -> 0 | F32: =SUMIFS(LANÇAMENTOS!$F$5:$F$1323,LANÇAMENTOS!$D$5:$D$1323,$A32,LANÇAMENTOS!$A$5:$A$1323,F$4,LANÇAMENTOS!$B$5:$B$1323,"A pagar") -> 0 | G32: =SUMIFS(LANÇAMENTOS!$F$5:$F$1323,LANÇAMENTOS!$D$5:$D$1323,$A32,LANÇAMENTOS!$A$5:$A$1323,G$4,LANÇAMENTOS!$B$5:$B$1323,"A pagar") -> 0 | H32: =SUMIFS(LANÇAMENTOS!$F$5:$F$1323,LANÇAMENTOS!$D$5:$D$1323,$A32,LANÇAMENTOS!$A$5:$A$1323,H$4,LANÇAMENTOS!$B$5:$B$1323,"A pagar") -> 0 | I32: =SUMIFS(LANÇAMENTOS!$F$5:$F$1323,LANÇAMENTOS!$D$5:$D$1323,$A32,LANÇAMENTOS!$A$5:$A$1323,I$4,LANÇAMENTOS!$B$5:$B$1323,"A pagar") -> 0 | J32: =SUMIFS(LANÇAMENTOS!$F$5:$F$1323,LANÇAMENTOS!$D$5:$D$1323,$A32,LANÇAMENTOS!$A$5:$A$1323,J$4,LANÇAMENTOS!$B$5:$B$1323,"A pagar") -> 0 | K32: =SUMIFS(LANÇAMENTOS!$F$5:$F$1323,LANÇAMENTOS!$D$5:$D$1323,$A32,LANÇAMENTOS!$A$5:$A$1323,K$4,LANÇAMENTOS!$B$5:$B$1323,"A pagar") -> 0 | ... BL32: =SUMIFS(LANÇAMENTOS!$F$5:$F$1323,LANÇAMENTOS!$D$5:$D$1323,$A32,LANÇAMENTOS!$A$5:$A$1323,BL$4,LANÇAMENTOS!$B$5:$B$1323,"A pagar") -> 0
A33: L04 | B33: Bandejas de proteção | C33: =SUM(D33:BL33) -> 0 | D33: =SUMIFS(LANÇAMENTOS!$F$5:$F$1323,LANÇAMENTOS!$D$5:$D$1323,$A33,LANÇAMENTOS!$A$5:$A$1323,D$4,LANÇAMENTOS!$B$5:$B$1323,"A pagar") -> 0 | E33: =SUMIFS(LANÇAMENTOS!$F$5:$F$1323,LANÇAMENTOS!$D$5:$D$1323,$A33,LANÇAMENTOS!$A$5:$A$1323,E$4,LANÇAMENTOS!$B$5:$B$1323,"A pagar") -> 0 | F33: =SUMIFS(LANÇAMENTOS!$F$5:$F$1323,LANÇAMENTOS!$D$5:$D$1323,$A33,LANÇAMENTOS!$A$5:$A$1323,F$4,LANÇAMENTOS!$B$5:$B$1323,"A pagar") -> 0 | G33: =SUMIFS(LANÇAMENTOS!$F$5:$F$1323,LANÇAMENTOS!$D$5:$D$1323,$A33,LANÇAMENTOS!$A$5:$A$1323,G$4,LANÇAMENTOS!$B$5:$B$1323,"A pagar") -> 0 | H33: =SUMIFS(LANÇAMENTOS!$F$5:$F$1323,LANÇAMENTOS!$D$5:$D$1323,$A33,LANÇAMENTOS!$A$5:$A$1323,H$4,LANÇAMENTOS!$B$5:$B$1323,"A pagar") -> 0 | I33: =SUMIFS(LANÇAMENTOS!$F$5:$F$1323,LANÇAMENTOS!$D$5:$D$1323,$A33,LANÇAMENTOS!$A$5:$A$1323,I$4,LANÇAMENTOS!$B$5:$B$1323,"A pagar") -> 0 | J33: =SUMIFS(LANÇAMENTOS!$F$5:$F$1323,LANÇAMENTOS!$D$5:$D$1323,$A33,LANÇAMENTOS!$A$5:$A$1323,J$4,LANÇAMENTOS!$B$5:$B$1323,"A pagar") -> 0 | K33: =SUMIFS(LANÇAMENTOS!$F$5:$F$1323,LANÇAMENTOS!$D$5:$D$1323,$A33,LANÇAMENTOS!$A$5:$A$1323,K$4,LANÇAMENTOS!$B$5:$B$1323,"A pagar") -> 0 | ... BL33: =SUMIFS(LANÇAMENTOS!$F$5:$F$1323,LANÇAMENTOS!$D$5:$D$1323,$A33,LANÇAMENTOS!$A$5:$A$1323,BL$4,LANÇAMENTOS!$B$5:$B$1323,"A pagar") -> 0
A34: L05 | B34: Elevador cremalheira | C34: =SUM(D34:BL34) -> 0 | D34: =SUMIFS(LANÇAMENTOS!$F$5:$F$1323,LANÇAMENTOS!$D$5:$D$1323,$A34,LANÇAMENTOS!$A$5:$A$1323,D$4,LANÇAMENTOS!$B$5:$B$1323,"A pagar") -> 0 | E34: =SUMIFS(LANÇAMENTOS!$F$5:$F$1323,LANÇAMENTOS!$D$5:$D$1323,$A34,LANÇAMENTOS!$A$5:$A$1323,E$4,LANÇAMENTOS!$B$5:$B$1323,"A pagar") -> 0 | F34: =SUMIFS(LANÇAMENTOS!$F$5:$F$1323,LANÇAMENTOS!$D$5:$D$1323,$A34,LANÇAMENTOS!$A$5:$A$1323,F$4,LANÇAMENTOS!$B$5:$B$1323,"A pagar") -> 0 | G34: =SUMIFS(LANÇAMENTOS!$F$5:$F$1323,LANÇAMENTOS!$D$5:$D$1323,$A34,LANÇAMENTOS!$A$5:$A$1323,G$4,LANÇAMENTOS!$B$5:$B$1323,"A pagar") -> 0 | H34: =SUMIFS(LANÇAMENTOS!$F$5:$F$1323,LANÇAMENTOS!$D$5:$D$1323,$A34,LANÇAMENTOS!$A$5:$A$1323,H$4,LANÇAMENTOS!$B$5:$B$1323,"A pagar") -> 0 | I34: =SUMIFS(LANÇAMENTOS!$F$5:$F$1323,LANÇAMENTOS!$D$5:$D$1323,$A34,LANÇAMENTOS!$A$5:$A$1323,I$4,LANÇAMENTOS!$B$5:$B$1323,"A pagar") -> 0 | J34: =SUMIFS(LANÇAMENTOS!$F$5:$F$1323,LANÇAMENTOS!$D$5:$D$1323,$A34,LANÇAMENTOS!$A$5:$A$1323,J$4,LANÇAMENTOS!$B$5:$B$1323,"A pagar") -> 0 | K34: =SUMIFS(LANÇAMENTOS!$F$5:$F$1323,LANÇAMENTOS!$D$5:$D$1323,$A34,LANÇAMENTOS!$A$5:$A$1323,K$4,LANÇAMENTOS!$B$5:$B$1323,"A pagar") -> 0 | ... BL34: =SUMIFS(LANÇAMENTOS!$F$5:$F$1323,LANÇAMENTOS!$D$5:$D$1323,$A34,LANÇAMENTOS!$A$5:$A$1323,BL$4,LANÇAMENTOS!$B$5:$B$1323,"A pagar") -> 0
A35: L06 | B35: Grua | C35: =SUM(D35:BL35) -> 0 | D35: =SUMIFS(LANÇAMENTOS!$F$5:$F$1323,LANÇAMENTOS!$D$5:$D$1323,$A35,LANÇAMENTOS!$A$5:$A$1323,D$4,LANÇAMENTOS!$B$5:$B$1323,"A pagar") -> 0 | E35: =SUMIFS(LANÇAMENTOS!$F$5:$F$1323,LANÇAMENTOS!$D$5:$D$1323,$A35,LANÇAMENTOS!$A$5:$A$1323,E$4,LANÇAMENTOS!$B$5:$B$1323,"A pagar") -> 0 | F35: =SUMIFS(LANÇAMENTOS!$F$5:$F$1323,LANÇAMENTOS!$D$5:$D$1323,$A35,LANÇAMENTOS!$A$5:$A$1323,F$4,LANÇAMENTOS!$B$5:$B$1323,"A pagar") -> 0 | G35: =SUMIFS(LANÇAMENTOS!$F$5:$F$1323,LANÇAMENTOS!$D$5:$D$1323,$A35,LANÇAMENTOS!$A$5:$A$1323,G$4,LANÇAMENTOS!$B$5:$B$1323,"A pagar") -> 0 | H35: =SUMIFS(LANÇAMENTOS!$F$5:$F$1323,LANÇAMENTOS!$D$5:$D$1323,$A35,LANÇAMENTOS!$A$5:$A$1323,H$4,LANÇAMENTOS!$B$5:$B$1323,"A pagar") -> 0 | I35: =SUMIFS(LANÇAMENTOS!$F$5:$F$1323,LANÇAMENTOS!$D$5:$D$1323,$A35,LANÇAMENTOS!$A$5:$A$1323,I$4,LANÇAMENTOS!$B$5:$B$1323,"A pagar") -> 0 | J35: =SUMIFS(LANÇAMENTOS!$F$5:$F$1323,LANÇAMENTOS!$D$5:$D$1323,$A35,LANÇAMENTOS!$A$5:$A$1323,J$4,LANÇAMENTOS!$B$5:$B$1323,"A pagar") -> 0 | K35: =SUMIFS(LANÇAMENTOS!$F$5:$F$1323,LANÇAMENTOS!$D$5:$D$1323,$A35,LANÇAMENTOS!$A$5:$A$1323,K$4,LANÇAMENTOS!$B$5:$B$1323,"A pagar") -> 0 | ... BL35: =SUMIFS(LANÇAMENTOS!$F$5:$F$1323,LANÇAMENTOS!$D$5:$D$1323,$A35,LANÇAMENTOS!$A$5:$A$1323,BL$4,LANÇAMENTOS!$B$5:$B$1323,"A pagar") -> 0
A36: L07 | B36: Equipamentos de fachada (andaimes, balancins) | C36: =SUM(D36:BL36) -> 4750 | D36: =SUMIFS(LANÇAMENTOS!$F$5:$F$1323,LANÇAMENTOS!$D$5:$D$1323,$A36,LANÇAMENTOS!$A$5:$A$1323,D$4,LANÇAMENTOS!$B$5:$B$1323,"A pagar") -> 0 | E36: =SUMIFS(LANÇAMENTOS!$F$5:$F$1323,LANÇAMENTOS!$D$5:$D$1323,$A36,LANÇAMENTOS!$A$5:$A$1323,E$4,LANÇAMENTOS!$B$5:$B$1323,"A pagar") -> 0 | F36: =SUMIFS(LANÇAMENTOS!$F$5:$F$1323,LANÇAMENTOS!$D$5:$D$1323,$A36,LANÇAMENTOS!$A$5:$A$1323,F$4,LANÇAMENTOS!$B$5:$B$1323,"A pagar") -> 0 | G36: =SUMIFS(LANÇAMENTOS!$F$5:$F$1323,LANÇAMENTOS!$D$5:$D$1323,$A36,LANÇAMENTOS!$A$5:$A$1323,G$4,LANÇAMENTOS!$B$5:$B$1323,"A pagar") -> 0 | H36: =SUMIFS(LANÇAMENTOS!$F$5:$F$1323,LANÇAMENTOS!$D$5:$D$1323,$A36,LANÇAMENTOS!$A$5:$A$1323,H$4,LANÇAMENTOS!$B$5:$B$1323,"A pagar") -> 0 | I36: =SUMIFS(LANÇAMENTOS!$F$5:$F$1323,LANÇAMENTOS!$D$5:$D$1323,$A36,LANÇAMENTOS!$A$5:$A$1323,I$4,LANÇAMENTOS!$B$5:$B$1323,"A pagar") -> 0 | J36: =SUMIFS(LANÇAMENTOS!$F$5:$F$1323,LANÇAMENTOS!$D$5:$D$1323,$A36,LANÇAMENTOS!$A$5:$A$1323,J$4,LANÇAMENTOS!$B$5:$B$1323,"A pagar") -> 0 | K36: =SUMIFS(LANÇAMENTOS!$F$5:$F$1323,LANÇAMENTOS!$D$5:$D$1323,$A36,LANÇAMENTOS!$A$5:$A$1323,K$4,LANÇAMENTOS!$B$5:$B$1323,"A pagar") -> 0 | ... BL36: =SUMIFS(LANÇAMENTOS!$F$5:$F$1323,LANÇAMENTOS!$D$5:$D$1323,$A36,LANÇAMENTOS!$A$5:$A$1323,BL$4,LANÇAMENTOS!$B$5:$B$1323,"A pagar") -> 0
A37: L08 | B37: Equipamentos de proteção coletiva (telas, sinalização) | C37: =SUM(D37:BL37) -> 9913.29 | D37: =SUMIFS(LANÇAMENTOS!$F$5:$F$1323,LANÇAMENTOS!$D$5:$D$1323,$A37,LANÇAMENTOS!$A$5:$A$1323,D$4,LANÇAMENTOS!$B$5:$B$1323,"A pagar") -> 0 | E37: =SUMIFS(LANÇAMENTOS!$F$5:$F$1323,LANÇAMENTOS!$D$5:$D$1323,$A37,LANÇAMENTOS!$A$5:$A$1323,E$4,LANÇAMENTOS!$B$5:$B$1323,"A pagar") -> 0 | F37: =SUMIFS(LANÇAMENTOS!$F$5:$F$1323,LANÇAMENTOS!$D$5:$D$1323,$A37,LANÇAMENTOS!$A$5:$A$1323,F$4,LANÇAMENTOS!$B$5:$B$1323,"A pagar") -> 0 | G37: =SUMIFS(LANÇAMENTOS!$F$5:$F$1323,LANÇAMENTOS!$D$5:$D$1323,$A37,LANÇAMENTOS!$A$5:$A$1323,G$4,LANÇAMENTOS!$B$5:$B$1323,"A pagar") -> 0 | H37: =SUMIFS(LANÇAMENTOS!$F$5:$F$1323,LANÇAMENTOS!$D$5:$D$1323,$A37,LANÇAMENTOS!$A$5:$A$1323,H$4,LANÇAMENTOS!$B$5:$B$1323,"A pagar") -> 0 | I37: =SUMIFS(LANÇAMENTOS!$F$5:$F$1323,LANÇAMENTOS!$D$5:$D$1323,$A37,LANÇAMENTOS!$A$5:$A$1323,I$4,LANÇAMENTOS!$B$5:$B$1323,"A pagar") -> 0 | J37: =SUMIFS(LANÇAMENTOS!$F$5:$F$1323,LANÇAMENTOS!$D$5:$D$1323,$A37,LANÇAMENTOS!$A$5:$A$1323,J$4,LANÇAMENTOS!$B$5:$B$1323,"A pagar") -> 0 | K37: =SUMIFS(LANÇAMENTOS!$F$5:$F$1323,LANÇAMENTOS!$D$5:$D$1323,$A37,LANÇAMENTOS!$A$5:$A$1323,K$4,LANÇAMENTOS!$B$5:$B$1323,"A pagar") -> 0 | ... BL37: =SUMIFS(LANÇAMENTOS!$F$5:$F$1323,LANÇAMENTOS!$D$5:$D$1323,$A37,LANÇAMENTOS!$A$5:$A$1323,BL$4,LANÇAMENTOS!$B$5:$B$1323,"A pagar") -> 0
A38: L10 | B38: A classificar (sem linha definida) | C38: =SUM(D38:BL38) -> 116739.49 | D38: =SUMIFS(LANÇAMENTOS!$F$5:$F$1323,LANÇAMENTOS!$D$5:$D$1323,$A38,LANÇAMENTOS!$A$5:$A$1323,D$4,LANÇAMENTOS!$B$5:$B$1323,"A pagar") -> 0 | E38: =SUMIFS(LANÇAMENTOS!$F$5:$F$1323,LANÇAMENTOS!$D$5:$D$1323,$A38,LANÇAMENTOS!$A$5:$A$1323,E$4,LANÇAMENTOS!$B$5:$B$1323,"A pagar") -> 0 | F38: =SUMIFS(LANÇAMENTOS!$F$5:$F$1323,LANÇAMENTOS!$D$5:$D$1323,$A38,LANÇAMENTOS!$A$5:$A$1323,F$4,LANÇAMENTOS!$B$5:$B$1323,"A pagar") -> 0 | G38: =SUMIFS(LANÇAMENTOS!$F$5:$F$1323,LANÇAMENTOS!$D$5:$D$1323,$A38,LANÇAMENTOS!$A$5:$A$1323,G$4,LANÇAMENTOS!$B$5:$B$1323,"A pagar") -> 0 | H38: =SUMIFS(LANÇAMENTOS!$F$5:$F$1323,LANÇAMENTOS!$D$5:$D$1323,$A38,LANÇAMENTOS!$A$5:$A$1323,H$4,LANÇAMENTOS!$B$5:$B$1323,"A pagar") -> 0 | I38: =SUMIFS(LANÇAMENTOS!$F$5:$F$1323,LANÇAMENTOS!$D$5:$D$1323,$A38,LANÇAMENTOS!$A$5:$A$1323,I$4,LANÇAMENTOS!$B$5:$B$1323,"A pagar") -> 0 | J38: =SUMIFS(LANÇAMENTOS!$F$5:$F$1323,LANÇAMENTOS!$D$5:$D$1323,$A38,LANÇAMENTOS!$A$5:$A$1323,J$4,LANÇAMENTOS!$B$5:$B$1323,"A pagar") -> 0 | K38: =SUMIFS(LANÇAMENTOS!$F$5:$F$1323,LANÇAMENTOS!$D$5:$D$1323,$A38,LANÇAMENTOS!$A$5:$A$1323,K$4,LANÇAMENTOS!$B$5:$B$1323,"A pagar") -> 0 | ... BL38: =SUMIFS(LANÇAMENTOS!$F$5:$F$1323,LANÇAMENTOS!$D$5:$D$1323,$A38,LANÇAMENTOS!$A$5:$A$1323,BL$4,LANÇAMENTOS!$B$5:$B$1323,"A pagar") -> 665
A39: TOTAL | C39: =SUM(C30:C38) -> 154562.49 | D39: =SUM(D30:D38) -> 0 | E39: =SUM(E30:E38) -> 0 | F39: =SUM(F30:F38) -> 0 | G39: =SUM(G30:G38) -> 0 | H39: =SUM(H30:H38) -> 0 | I39: =SUM(I30:I38) -> 0 | J39: =SUM(J30:J38) -> 0 | ... BL39: =SUM(BL30:BL38) -> 665
A41: ACUMULADO
A42: BAS | B42: Base sem INCC acumulada | D42: =D15 -> 0 | E42: =E15+D42 -> 0 | F42: =F15+E42 -> 0 | G42: =G15+F42 -> 0 | H42: =H15+G42 -> 0 | I42: =I15+H42 -> 0 | J42: =J15+I42 -> 0 | K42: =K15+J42 -> 0 | L42: =L15+K42 -> 0 | ... BL42: =BL15+BK42 -> 0
A43: REA | B43: Realizado acumulado (até a data-base) | D43: =IF(D$4>DataBase,NA(),D27) -> 1113 | E43: =IF(E$4>DataBase,NA(),E27+D43) -> 2257.4 | F43: =IF(F$4>DataBase,NA(),F27+E43) -> 4324.4 | G43: =IF(G$4>DataBase,NA(),G27+F43) -> 8124.78 | H43: =IF(H$4>DataBase,NA(),H27+G43) -> 13189.962 | I43: =IF(I$4>DataBase,NA(),I27+H43) -> 14474.672 | J43: =IF(J$4>DataBase,NA(),J27+I43) -> 22938.182 | K43: =IF(K$4>DataBase,NA(),K27+J43) -> 28962.722 | L43: =IF(L$4>DataBase,NA(),L27+K43) -> 30955.432 | ... BL43: =IF(BL$4>DataBase,NA(),BL27+BK43) -> #N/A
A44: R+A | B44: Realizado + a pagar acumulado | D44: =D27+D39 -> 1113 | E44: =E27+E39+D44 -> 2257.4 | F44: =F27+F39+E44 -> 4324.4 | G44: =G27+G39+F44 -> 8124.78 | H44: =H27+H39+G44 -> 13189.962 | I44: =I27+I39+H44 -> 14474.672 | J44: =J27+J39+I44 -> 22938.182 | K44: =K27+K39+J44 -> 28962.722 | L44: =L27+L39+K44 -> 30955.432 | ... BL44: =BL27+BL39+BK44 -> 2189970.7

Sheet LANÇAMENTOS
A1: Ed. Jardim · Lançamentos do grupo 11 (PL530.001)
A2: Fonte: planilha DADOS do financeiro, GRUPO 1 = obra, COD SERVIÇO = PL530.001, STATUS = PAGAS ou A PAGAR. Valor positivo = custo (sinal invertido do [VALOR REAL]).
A4: Mês | B4: Tipo | C4: Código | D4: Linha | E4: Fornecedor | F4: Valor (R$) | G4: Categoria (financeiro) | H4: Descrição | I4: Data | J4: Processo
A5: 45444 | B5: Pago | C5: PL530.001 | D5: =IFERROR(VLOOKUP(E5,FORNECEDORES!$A$5:$F$999,6,FALSE),"L10") -> L03 | E5: LOCAFAZ LOCACAO DE EQUIPAMENTOS LTDA | F5: 328 | G5: LOCAÇÕES | H5: LOCAFAZ LOCACAO DE EQUIPAMENTOS LTDA | I5: 45454 | J5: 1228
A6: 45444 | B6: Pago | C6: PL530.001 | D6: =IFERROR(VLOOKUP(E6,FORNECEDORES!$A$5:$F$999,6,FALSE),"L10") -> L03 | E6: LOCAFAZ LOCACAO DE EQUIPAMENTOS LTDA | F6: 190 | G6: LOCAÇÕES | H6: LOCAFAZ LOCACAO DE EQUIPAMENTOS LTDA | I6: 45450 | J6: 1227
A7: 45444 | B7: Pago | C7: PL530.001 | D7: =IFERROR(VLOOKUP(E7,FORNECEDORES!$A$5:$F$999,6,FALSE),"L10") -> L03 | E7: LOCAFAZ LOCACAO DE EQUIPAMENTOS LTDA | F7: 60 | G7: LOCAÇÕES | H7: LOCAFAZ LOCACAO DE EQUIPAMENTOS LTDA | I7: 45460 | J7: 1262
A8: 45444 | B8: Pago | C8: PL530.001 | D8: =IFERROR(VLOOKUP(E8,FORNECEDORES!$A$5:$F$999,6,FALSE),"L10") -> L03 | E8: LOCAFAZ LOCACAO DE EQUIPAMENTOS LTDA | F8: 60 | G8: LOCAÇÕES | H8: LOCAFAZ LOCACAO DE EQUIPAMENTOS LTDA | I8: 45450 | J8: 1229
A9: 45444 | B9: Pago | C9: PL530.001 | D9: =IFERROR(VLOOKUP(E9,FORNECEDORES!$A$5:$F$999,6,FALSE),"L10") -> L03 | E9: LOCAFAZ LOCACAO DE EQUIPAMENTOS LTDA | F9: 190 | G9: LOCAÇÕES | H9: LOCAFAZ LOCACAO DE EQUIPAMENTOS LTDA | I9: 45450 | J9: 1230
A10: 45444 | B10: Pago | C10: PL530.001 | D10: =IFERROR(VLOOKUP(E10,FORNECEDORES!$A$5:$F$999,6,FALSE),"L10") -> L03 | E10: LOCAFAZ LOCACAO DE EQUIPAMENTOS LTDA | F10: 285 | G10: LOCAÇÕES | H10: LOCAFAZ LOCACAO DE EQUIPAMENTOS LTDA | I10: 45456 | J10: 1261
A11: 45474 | B11: Pago | C11: PL530.001 | D11: =IFERROR(VLOOKUP(E11,FORNECEDORES!$A$5:$F$999,6,FALSE),"L10") -> L08 | E11: ALFA COMERCIO DE EPI LTDA | F11: 24 | G11: EQUIPAMENTOS DE PROTEÇÃO INDIVIDUAL | H11: ALFA COMERCIO DE EPI LTDA | I11: 45475 | J11: 1155
A12: 45474 | B12: Pago | C12: PL530.001 | D12: =IFERROR(VLOOKUP(E12,FORNECEDORES!$A$5:$F$999,6,FALSE),"L10") -> L08 | E12: ALFA COMERCIO DE EPI LTDA | F12: 71.4 | G12: EQUIPAMENTOS DE PROTEÇÃO INDIVIDUAL | H12: ALFA COMERCIO DE EPI LTDA | I12: 45475 | J12: 1155
A13: 45474 | B13: Pago | C13: PL530.001 | D13: =IFERROR(VLOOKUP(E13,FORNECEDORES!$A$5:$F$999,6,FALSE),"L10") -> L08 | E13: ALFA COMERCIO DE EPI LTDA | F13: 236 | G13: EQUIPAMENTOS DE PROTEÇÃO INDIVIDUAL | H13: ALFA COMERCIO DE EPI LTDA | I13: 45475 | J13: 1155
A14: 45474 | B14: Pago | C14: PL530.001 | D14: =IFERROR(VLOOKUP(E14,FORNECEDORES!$A$5:$F$999,6,FALSE),"L10") -> L03 | E14: LOCAFAZ LOCACAO DE EQUIPAMENTOS LTDA | F14: 100 | G14: LOCAÇÕES | H14: LOCAFAZ LOCACAO DE EQUIPAMENTOS LTDA | I14: 45498 | J14: 1387
A15: 45474 | B15: Pago | C15: PL530.001 | D15: =IFERROR(VLOOKUP(E15,FORNECEDORES!$A$5:$F$999,6,FALSE),"L10") -> L03 | E15: LOCAFAZ LOCACAO DE EQUIPAMENTOS LTDA | F15: 285 | G15: LOCAÇÕES | H15: LOCAFAZ LOCACAO DE EQUIPAMENTOS LTDA | I15: 45488 | J15: 1322
A16: 45474 | B16: Pago | C16: PL530.001 | D16: =IFERROR(VLOOKUP(E16,FORNECEDORES!$A$5:$F$999,6,FALSE),"L10") -> L03 | E16: LOCAFAZ LOCACAO DE EQUIPAMENTOS LTDA | F16: 328 | G16: LOCAÇÕES | H16: LOCAFAZ LOCACAO DE EQUIPAMENTOS LTDA | I16: 45483 | J16: 1321
... A1323: 47270 | B1323: A pagar | C1323: PL530.001 | D1323: =IFERROR(VLOOKUP(E1323,FORNECEDORES!$A$5:$F$999,6,FALSE),"L10") -> L10 | E1323: LN SERVICOS E MONTAGEM LTDA | F1323: 378 | G1323: NÃO CLASSIFICADO | H1323: RETENÇAO TECNICA | I1323: 47277 | J1323: 7035

Sheet FORNECEDORES
A1: Ed. Jardim · Fornecedores do grupo 11 e linha do histograma
A2: Linha (coluna F, cinza) = sugestão automática pelo nome e pela categoria do financeiro. Ajuste conforme a medição: os lançamentos e o histograma se recalculam.
A4: Fornecedor | B4: Categoria predominante | C4: Pago (R$) | D4: A pagar (R$) | E4: Total (R$) | F4: Linha | G4: Descrição da linha | H4: Critério da sugestão
A5: TELAS PERAM COMERCIO IMPORTACAO E REPRESENTACOES LTDA. | B5: SINALIZAÇÃO | C5: =SUMIFS(LANÇAMENTOS!$F$5:$F$1323,LANÇAMENTOS!$E$5:$E$1323,A5,LANÇAMENTOS!$B$5:$B$1323,"Pago") -> 206640.91 | D5: =SUMIFS(LANÇAMENTOS!$F$5:$F$1323,LANÇAMENTOS!$E$5:$E$1323,A5,LANÇAMENTOS!$B$5:$B$1323,"A pagar") -> 1596.49 | E5: =C5+D5 -> 208237.4 | F5: L08 | G5: =IFERROR(VLOOKUP(F5,PARÂMETROS!$A$11:$C$19,3,FALSE),"linha inválida") -> Equipamentos de proteção coletiva (telas, sinalização) | H5: Telas, sinalização e proteção (nome/categoria)
A6: CORTEZ LOCACAO DE EQUIPAMENTOS LTDA-ME | B6: NÃO CLASSIFICADO | C6: =SUMIFS(LANÇAMENTOS!$F$5:$F$1323,LANÇAMENTOS!$E$5:$E$1323,A6,LANÇAMENTOS!$B$5:$B$1323,"Pago") -> 201762 | D6: =SUMIFS(LANÇAMENTOS!$F$5:$F$1323,LANÇAMENTOS!$E$5:$E$1323,A6,LANÇAMENTOS!$B$5:$B$1323,"A pagar") -> 3377.5 | E6: =C6+D6 -> 205139.5 | F6: L10 | G6: =IFERROR(VLOOKUP(F6,PARÂMETROS!$A$11:$C$19,3,FALSE),"linha inválida") -> A classificar (sem linha definida) | H6: Sem critério no financeiro (NÃO CLASSIFICADO / contrato): classificar pela medição
A7: SOIMA BRASIL INDUSTRIA E COMERCIO LTDA | B7: INSUMOS PARA CONTRATO | C7: =SUMIFS(LANÇAMENTOS!$F$5:$F$1323,LANÇAMENTOS!$E$5:$E$1323,A7,LANÇAMENTOS!$B$5:$B$1323,"Pago") -> 141299.98 | D7: =SUMIFS(LANÇAMENTOS!$F$5:$F$1323,LANÇAMENTOS!$E$5:$E$1323,A7,LANÇAMENTOS!$B$5:$B$1323,"A pagar") -> 20000 | E7: =C7+D7 -> 161299.98 | F7: L10 | G7: =IFERROR(VLOOKUP(F7,PARÂMETROS!$A$11:$C$19,3,FALSE),"linha inválida") -> A classificar (sem linha definida) | H7: Sem critério no financeiro (NÃO CLASSIFICADO / contrato): classificar pela medição
A8: ORGUEL INDUSTRIA E LOCACAO DE EQUIPAMENTOS S/A | B8: NÃO CLASSIFICADO | C8: =SUMIFS(LANÇAMENTOS!$F$5:$F$1323,LANÇAMENTOS!$E$5:$E$1323,A8,LANÇAMENTOS!$B$5:$B$1323,"Pago") -> 113609.35 | D8: =SUMIFS(LANÇAMENTOS!$F$5:$F$1323,LANÇAMENTOS!$E$5:$E$1323,A8,LANÇAMENTOS!$B$5:$B$1323,"A pagar") -> 35057.05 | E8: =C8+D8 -> 148666.4 | F8: L10 | G8: =IFERROR(VLOOKUP(F8,PARÂMETROS!$A$11:$C$19,3,FALSE),"linha inválida") -> A classificar (sem linha definida) | H8: Sem critério no financeiro (NÃO CLASSIFICADO / contrato): classificar pela medição
A9: TECSU ENGENHARIA LTDA | B9: NÃO CLASSIFICADO | C9: =SUMIFS(LANÇAMENTOS!$F$5:$F$1323,LANÇAMENTOS!$E$5:$E$1323,A9,LANÇAMENTOS!$B$5:$B$1323,"Pago") -> 119642.88 | D9: =SUMIFS(LANÇAMENTOS!$F$5:$F$1323,LANÇAMENTOS!$E$5:$E$1323,A9,LANÇAMENTOS!$B$5:$B$1323,"A pagar") -> 27076.18 | E9: =C9+D9 -> 146719.06 | F9: L10 | G9: =IFERROR(VLOOKUP(F9,PARÂMETROS!$A$11:$C$19,3,FALSE),"linha inválida") -> A classificar (sem linha definida) | H9: Sem critério no financeiro (NÃO CLASSIFICADO / contrato): classificar pela medição
A10: FIAO LOCACOES E TRANSPORTES LTDA | B10: NÃO CLASSIFICADO | C10: =SUMIFS(LANÇAMENTOS!$F$5:$F$1323,LANÇAMENTOS!$E$5:$E$1323,A10,LANÇAMENTOS!$B$5:$B$1323,"Pago") -> 139740.55 | D10: =SUMIFS(LANÇAMENTOS!$F$5:$F$1323,LANÇAMENTOS!$E$5:$E$1323,A10,LANÇAMENTOS!$B$5:$B$1323,"A pagar") -> 117.75 | E10: =C10+D10 -> 139858.3 | F10: L10 | G10: =IFERROR(VLOOKUP(F10,PARÂMETROS!$A$11:$C$19,3,FALSE),"linha inválida") -> A classificar (sem linha definida) | H10: Sem critério no financeiro (NÃO CLASSIFICADO / contrato): classificar pela medição
A11: E.P.O. ENGENHARIA PLANEJAMENTO E OBRAS LTDA. | B11: DESPESAS | C11: =SUMIFS(LANÇAMENTOS!$F$5:$F$1323,LANÇAMENTOS!$E$5:$E$1323,A11,LANÇAMENTOS!$B$5:$B$1323,"Pago") -> 99670.42 | D11: =SUMIFS(LANÇAMENTOS!$F$5:$F$1323,LANÇAMENTOS!$E$5:$E$1323,A11,LANÇAMENTOS!$B$5:$B$1323,"A pagar") -> 0 | E11: =C11+D11 -> 99670.42 | F11: L01 | G11: =IFERROR(VLOOKUP(F11,PARÂMETROS!$A$11:$C$19,3,FALSE),"linha inválida") -> Ferramentas manuais e pequenos equipamentos | H11: Compra de ferramentas e materiais miúdos (categoria despesas)
A12: EUROLINK IMPORTACAO E LOCACAO DE EQUIPAMENTOS LTDA | B12: LOCAÇÕES | C12: =SUMIFS(LANÇAMENTOS!$F$5:$F$1323,LANÇAMENTOS!$E$5:$E$1323,A12,LANÇAMENTOS!$B$5:$B$1323,"Pago") -> 98186.45 | D12: =SUMIFS(LANÇAMENTOS!$F$5:$F$1323,LANÇAMENTOS!$E$5:$E$1323,A12,LANÇAMENTOS!$B$5:$B$1323,"A pagar") -> 0 | E12: =C12+D12 -> 98186.45 | F12: L03 | G12: =IFERROR(VLOOKUP(F12,PARÂMETROS!$A$11:$C$19,3,FALSE),"linha inválida") -> Equipamentos de produção civil e locações | H12: Categoria LOCAÇÕES no financeiro
A13: PGO PLANEJAMENTO GERENCIAMENTO E OBRAS LTDA. - ME | B13: NÃO CLASSIFICADO | C13: =SUMIFS(LANÇAMENTOS!$F$5:$F$1323,LANÇAMENTOS!$E$5:$E$1323,A13,LANÇAMENTOS!$B$5:$B$1323,"Pago") -> 70971.577 | D13: =SUMIFS(LANÇAMENTOS!$F$5:$F$1323,LANÇAMENTOS!$E$5:$E$1323,A13,LANÇAMENTOS!$B$5:$B$1323,"A pagar") -> 4236.6228 | E13: =C13+D13 -> 75208.2 | F13: L10 | G13: =IFERROR(VLOOKUP(F13,PARÂMETROS!$A$11:$C$19,3,FALSE),"linha inválida") -> A classificar (sem linha definida) | H13: Sem critério no financeiro (NÃO CLASSIFICADO / contrato): classificar pela medição
A14: LOCAFAZ LOCACAO DE EQUIPAMENTOS LTDA | B14: LOCAÇÕES | C14: =SUMIFS(LANÇAMENTOS!$F$5:$F$1323,LANÇAMENTOS!$E$5:$E$1323,A14,LANÇAMENTOS!$B$5:$B$1323,"Pago") -> 70925.98 | D14: =SUMIFS(LANÇAMENTOS!$F$5:$F$1323,LANÇAMENTOS!$E$5:$E$1323,A14,LANÇAMENTOS!$B$5:$B$1323,"A pagar") -> 1362.81 | E14: =C14+D14 -> 72288.79 | F14: L03 | G14: =IFERROR(VLOOKUP(F14,PARÂMETROS!$A$11:$C$19,3,FALSE),"linha inválida") -> Equipamentos de produção civil e locações | H14: Categoria LOCAÇÕES no financeiro
A15: PEREIRA TELAS E INSTALACOES LTDA | B15: NÃO CLASSIFICADO | C15: =SUMIFS(LANÇAMENTOS!$F$5:$F$1323,LANÇAMENTOS!$E$5:$E$1323,A15,LANÇAMENTOS!$B$5:$B$1323,"Pago") -> 60783.2 | D15: =SUMIFS(LANÇAMENTOS!$F$5:$F$1323,LANÇAMENTOS!$E$5:$E$1323,A15,LANÇAMENTOS!$B$5:$B$1323,"A pagar") -> 8316.8 | E15: =C15+D15 -> 69100 | F15: L08 | G15: =IFERROR(VLOOKUP(F15,PARÂMETROS!$A$11:$C$19,3,FALSE),"linha inválida") -> Equipamentos de proteção coletiva (telas, sinalização) | H15: Telas, sinalização e proteção (nome/categoria)
A16: ORIGINAL LOCACOES LTDA | B16: LOCAÇÕES | C16: =SUMIFS(LANÇAMENTOS!$F$5:$F$1323,LANÇAMENTOS!$E$5:$E$1323,A16,LANÇAMENTOS!$B$5:$B$1323,"Pago") -> 60187.07 | D16: =SUMIFS(LANÇAMENTOS!$F$5:$F$1323,LANÇAMENTOS!$E$5:$E$1323,A16,LANÇAMENTOS!$B$5:$B$1323,"A pagar") -> 0 | E16: =C16+D16 -> 60187.07 | F16: L03 | G16: =IFERROR(VLOOKUP(F16,PARÂMETROS!$A$11:$C$19,3,FALSE),"linha inválida") -> Equipamentos de produção civil e locações | H16: Categoria LOCAÇÕES no financeiro
... A92: SOMA BH DISTRIBUIDORA DE MATERIAIS LTDA | B92: LIMPEZA E HIGIÊNE | C92: =SUMIFS(LANÇAMENTOS!$F$5:$F$1323,LANÇAMENTOS!$E$5:$E$1323,A92,LANÇAMENTOS!$B$5:$B$1323,"Pago") -> 33.200001 | D92: =SUMIFS(LANÇAMENTOS!$F$5:$F$1323,LANÇAMENTOS!$E$5:$E$1323,A92,LANÇAMENTOS!$B$5:$B$1323,"A pagar") -> 0 | E92: =C92+D92 -> 33.200001 | F92: L10 | G92: =IFERROR(VLOOKUP(F92,PARÂMETROS!$A$11:$C$19,3,FALSE),"linha inválida") -> A classificar (sem linha definida) | H92: Sem critério no financeiro (NÃO CLASSIFICADO / contrato): classificar pela medição
A93: TOTAL | C93: =SUM(C5:C92) -> 2035408.2 | D93: =SUM(D5:D92) -> 154562.49 | E93: =SUM(E5:E92) -> 2189970.7

Sheet BASE
A1: Ed. Jardim · Orçamento mensal sem INCC por linha
A2: Fonte: PENDENTE: enviar o histograma de origem da obra (aba AUX. HISTOGRAMA - BASE).
A4: Linha | B4: Descrição | C4: Total | D4: 45444 | E4: 45474 | F4: 45505 | G4: 45536 | H4: 45566 | I4: 45597 | J4: 45627 | K4: 45658 | L4: 45689 | M4: 45717 | N4: 45748 | O4: 45778 | P4: 45809 | Q4: 45839 | R4: 45870 | S4: 45901 | T4: 45931 | U4: 45962 | V4: 45992 | W4: 46023 | X4: 46054 | Y4: 46082 | Z4: 46113 | AA4: 46143 | AB4: 46174 | AC4: 46204 | AD4: 46235 | AE4: 46266 | AF4: 46296 | AG4: 46327 | AH4: 46357 | AI4: 46388 | AJ4: 46419 | AK4: 46447 | AL4: 46478 | AM4: 46508 | AN4: 46539 | AO4: 46569 | AP4: 46600 | AQ4: 46631 | AR4: 46661 | AS4: 46692 | AT4: 46722 | AU4: 46753 | AV4: 46784 | AW4: 46813 | AX4: 46844 | AY4: 46874 | AZ4: 46905 | BA4: 46935 | BB4: 46966 | BC4: 46997 | BD4: 47027 | BE4: 47058 | BF4: 47088 | BG4: 47119 | BH4: 47150 | BI4: 47178 | BJ4: 47209 | BK4: 47239 | BL4: 47270
A5: L01 | B5: Ferramentas manuais e pequenos equipamentos | C5: =SUM(D5:BL5) -> 0
A6: L02 | B6: Movimento de terra, manipulador e transporte vertical leve | C6: =SUM(D6:BL6) -> 0
A7: L03 | B7: Equipamentos de produção civil e locações | C7: =SUM(D7:BL7) -> 0
A8: L04 | B8: Bandejas de proteção | C8: =SUM(D8:BL8) -> 0
A9: L05 | B9: Elevador cremalheira | C9: =SUM(D9:BL9) -> 0
A10: L06 | B10: Grua | C10: =SUM(D10:BL10) -> 0
A11: L07 | B11: Equipamentos de fachada (andaimes, balancins) | C11: =SUM(D11:BL11) -> 0
A12: L08 | B12: Equipamentos de proteção coletiva (telas, sinalização) | C12: =SUM(D12:BL12) -> 0
A13: L10 | B13: A classificar (sem linha definida) | C13: =SUM(D13:BL13) -> 0
A14: TOTAL | C14: =SUM(C5:C13) -> 0 | D14: =SUM(D5:D13) -> 0 | E14: =SUM(E5:E13) -> 0 | F14: =SUM(F5:F13) -> 0 | G14: =SUM(G5:G13) -> 0 | H14: =SUM(H5:H13) -> 0 | I14: =SUM(I5:I13) -> 0 | J14: =SUM(J5:J13) -> 0 | ... BL14: =SUM(BL5:BL13) -> 0

Sheet PARÂMETROS
A1: Ed. Jardim · Parâmetros
A2: Células cinza são entradas.
A3: Data-base (último mês com pagamentos) | B3: 46296
A4: Total pago no financeiro (DADOS) | B4: 2035408.2
A5: Total a pagar no financeiro (DADOS) | B5: 154562.49
A6: Nº de lançamentos | B6: 1319
A7: Orçado sem INCC do grupo 11 (ANÁLISE)
A10: Linha | B10: Código PL | C10: Descrição | D10: Orçado sem INCC
A11: L01 | B11: 11.01 | C11: Ferramentas manuais e pequenos equipamentos
A12: L02 | B12: 11.02 | C12: Movimento de terra, manipulador e transporte vertical leve
A13: L03 | B13: 11.03.01-03/06 | C13: Equipamentos de produção civil e locações
A14: L04 | B14: 11.03.04-05 | C14: Bandejas de proteção
A15: L05 | B15: 11.04.01 | C15: Elevador cremalheira
A16: L06 | B16: 11.04.02 | C16: Grua
A17: L07 | B17: 11.05 | C17: Equipamentos de fachada (andaimes, balancins)
A18: L08 | B18: 11.06 | C18: Equipamentos de proteção coletiva (telas, sinalização)
A19: L10 | B19: — | C19: A classificar (sem linha definida)

Sheet LEIA-ME
A1: Ed. Jardim · Leia-me
A4: Objetivo | B4: Abrir o realizado do grupo 11 (PL530.001, Equipamentos e Ferramentas) mês a mês e por linha, a partir do financeiro, e comparar com o orçamento mensal sem INCC.
A5: Fonte do realizado | B5: Planilha DADOS do financeiro: GRUPO 1 contém "CIDADE JARDIM", COD SERVIÇO = PL530.001, STATUS FINANCEIRO = PAGAS (realizado) ou A PAGAR (títulos em aberto). Mês = [INÍCIO DO MÊS]; valor = [VALOR REAL] com sinal invertido. Os lançamentos com código 1030-1070-450 (fora do PL530.001) não entram.
A6: Fonte do orçamento | B6: PENDENTE: o histograma de origem do Ed. Jardim não foi enviado. A aba BASE está vazia e a conferência 3 fica PENDENTE.
A7: Linhas (L01…L10) | B7: Cada fornecedor recebe uma linha na aba FORNECEDORES (coluna F). A sugestão é automática pelo nome e pela categoria do financeiro; os fornecedores lançados como NÃO CLASSIFICADO ou contrato (ex.: locadoras de grua/cremalheira) ficam em L10 até a classificação pela medição. Ao mudar a linha, LANÇAMENTOS, HISTOGRAMA e RESUMO se recalculam.
A8: Data-base | B8: out/26 (pagamentos até 07/10/2026, mês parcial). Alterar em PARÂMETROS!B3; o realizado acumulado some depois da data-base.
A9: Pendências para a R01 | B9: 1) Medição financeira (.xlsm): abas mensais, ANÁLISE IEC (linha do grupo 11, colunas I, T e X), AUX.IEC e AUX.EQUIPAM_02, para fechar o realizado com a ANÁLISE ao centavo e classificar os fornecedores por código. 2) Contratos e aditivos (grua, cremalheira, manipulador, balancins, bandejas, locadoras) e lista de LOCAÇÕES - GERAL, para a projeção (CADASTRO). 3) Cronograma atualizado, para o fim das locações. 4) Histograma de origem do Ed. Jardim.
A10: Rotina mensal | B10: Colar as novas linhas do financeiro na aba LANÇAMENTOS (mesmas colunas), classificar fornecedores novos em FORNECEDORES, atualizar a data-base e conferir o RESUMO (conferências 1 a 4 = OK).
