Workbook

Sheet LEIA-ME
A1: Ferramenta de Fluxo de Caixa Anual da Obra
A3: O que ela faz
A4: Você atualiza as abas de ENTRADA; as abas de RESULTADO se recalculam sozinhas, sem ajuste manual.
A5: O saldo de cada disciplina (Projeção − Realizado − Compromissos) é distribuído automaticamente nos meses futuros
A6: conforme os pesos da aba CURVA. Por isso o fluxo SEMPRE fecha com a projeção — não existe mais 'último mês de ajuste'.
A8: Atualização mensal (passo a passo)
A9: 1. INCC — acrescente o índice do novo mês (mês no formato 01/mm/aaaa).
A10: 2. PARAMETROS — mude a 'Data de corte' para o último mês com realizado fechado. Se quiser, mude o 'Ano do retrato'.
A11: 3. INCORRIDO — cole os lançamentos do ERP: Data | Grupo no ERP | Valor (R$). Pode colar linha a linha ou já somado por mês.
A12: Lançamentos com data DEPOIS da data de corte são tratados como COMPROMISSOS: ficam no mês deles e abatem o saldo.
A13: 4. DE_PARA — se a CONFERENCIA apontar 'SEM DE-PARA', cadastre o nome do ERP e a disciplina correspondente.
A14: 5. ORCAMENTO — atualize a coluna 'Projeção atual (R$)' de cada disciplina (IEC).
... A37: por isso aparecem na CONFERENCIA como 'saldo sem curva' — preencha os pesos delas na aba CURVA.

Sheet PARAMETROS
A1: Parâmetros
A2: Células amarelas: altere a cada atualização.
E3: Grupos (para subtotais)
B4: Obra | C4: BOTÂNICO | E4: INDIRETOS
B5: Mês inicial do fluxo | C5: 45627 | E5: INFRAESTRUTURA
B6: Data de corte (último mês realizado) | C6: 46235 | E6: ESTRUTURA
B7: Ano do retrato | C7: 2027 | E7: SISTEMAS E VEDAÇÕES
B8: Reajuste INCC projetado (% a.a.) | C8: 0 | E8: ACABAMENTOS
E9: TAXA DE ADMINISTRAÇÃO
B10: Calculados
B11: Mês inicial (1º dia) | C11: =DATE(YEAR(C5),MONTH(C5),1) -> 45627
B12: Mês de corte (1º dia) | C12: =DATE(YEAR(C6),MONTH(C6),1) -> 46235
B13: Último mês do horizonte | C13: =DATE(YEAR(C11),MONTH(C11)+71,1) -> 47788
B14: INCC no mês de corte | C14: =IFERROR(INDEX(INCC!$B$6:$B$305,MATCH(C12,INCC!$A$6:$A$305,0)),"FALTA INCC") -> 1296.889
E16: Até 12 grupos (E4:E15).

Sheet ORCAMENTO
A1: Orçamento e projeção por disciplina
A2: Valores em R$. Até 50 disciplinas (linhas 6 a 55). O nome da disciplina é a chave usada em todas as abas.
A5: Código | B5: Disciplina | C5: Grupo | D5: Orçamento base (R$) | E5: Projeção atual (R$) | F5: Variação (R$) | G5: CPU / observação
A6: 01 | B6: PROJETOS | C6: INDIRETOS | D6: 2400000 | E6: 2640655 | F6: =IF(B6="","",E6-D6) -> 240655 | G6: PL001.001
A7: 02 | B7: SEGUROS | C7: INDIRETOS | D7: 126154.98 | E7: 127911.99 | F7: =IF(B7="","",E7-D7) -> 1757.01 | G7: PL350.001
A8: 03 | B8: TAXAS DIVERSAS | C8: INDIRETOS | D8: 150000 | E8: 158047.46 | F8: =IF(B8="","",E8-D8) -> 8047.46 | G8: PL001.016
A9: 04 | B9: BARRACAO DE OBRA | C9: INDIRETOS | D9: 934513.13 | E9: 1249911.1 | F9: =IF(B9="","",E9-D9) -> 315397.94 | G9: PL010.005
A10: 05 | B10: LIGAÇÕES PROVISÓRIAS AGUA, ENERGIA,TELEFONIA, ESGOTO | C10: INDIRETOS | D10: 50000 | E10: 85665.05 | F10: =IF(B10="","",E10-D10) -> 35665.05 | G10: PL020.004
A11: 06 | B11: CONSUMO DE ÁGUA, ENERGIA, ETC. | C11: INDIRETOS | D11: 521400 | E11: 544229.22 | F11: =IF(B11="","",E11-D11) -> 22829.22 | G11: PL020.005
A12: 07 | B12: DIVERSOS | C12: INDIRETOS | D12: 158400 | E12: 194480.67 | F12: =IF(B12="","",E12-D12) -> 36080.67 | G12: PL310.007
A13: 08 | B13: TRANSPORTES | C13: INDIRETOS | D13: 779592 | E13: 817599.43 | F13: =IF(B13="","",E13-D13) -> 38007.43 | G13: PL570.001
A14: 09 | B14: CONSULTORIAS (OBRAS) | C14: INDIRETOS | D14: 1322661 | E14: 1371532.1 | F14: =IF(B14="","",E14-D14) -> 48871.13 | G14: PL001.051
A15: 10 | B15: MÃO DE OBRA PRÓPRIA | C15: INDIRETOS | D15: 20188025 | E15: 21271106 | F15: =IF(B15="","",E15-D15) -> 1083081.5 | G15: PL700.001
A16: 11 | B16: EQUIPAMENTOS E FERRAMENTAS | C16: INDIRETOS | D16: 6467911.7 | E16: 6774432.9 | F16: =IF(B16="","",E16-D16) -> 306521.28 | G16: PL530.001
A17: 12 | B17: SERVIÇOS INICIAIS | C17: INFRAESTRUTURA | D17: 175350.93 | E17: 176378.52 | F17: =IF(B17="","",E17-D17) -> 1027.59 | G17: PL010.022
... A42: 37 | B42: LIMPEZA FINAL DE OBRA | C42: ACABAMENTOS | D42: 887766.61 | E42: 935395.03 | F42: =IF(B42="","",E42-D42) -> 47628.42 | G42: PL360.001
A43: 38 | B43: TAXA DE ADMINISTRAÇÃO | C43: TAXA DE ADMINISTRAÇÃO | D43: 566105.29 | E43: 566105.29 | F43: =IF(B43="","",E43-D43) -> 0
F44: =IF(B44="","",E44-D44)
F45: =IF(B45="","",E45-D45)
F46: =IF(B46="","",E46-D46)
F47: =IF(B47="","",E47-D47)
F48: =IF(B48="","",E48-D48)
F49: =IF(B49="","",E49-D49)
F50: =IF(B50="","",E50-D50)
F51: =IF(B51="","",E51-D51)
F52: =IF(B52="","",E52-D52)
F53: =IF(B53="","",E53-D53)
F54: =IF(B54="","",E54-D54)
F55: =IF(B55="","",E55-D55)
B56: TOTAL | D56: =SUM(D6:D55) -> 1.5111833e+08 | E56: =SUM(E6:E55) -> 1.5933311e+08 | F56: =SUM(F6:F55) -> 8214784

Sheet INCORRIDO
A1: Realizado / compromissos (lançamentos do ERP)
A2: Cole nas colunas A:C (até 5000 linhas). Datas após a data de corte = compromissos. Colunas D:E são calculadas.
A5: Data | B5: Grupo no ERP | C5: Valor (R$) | D5: Disciplina (de-para) | E5: Mês
A6: 45627 | B6: PROJETOS | C6: 418594.15 | D6: =IF(B6="","",IFERROR(INDEX(DE_PARA!$B$6:$B$205,MATCH(B6,DE_PARA!$A$6:$A$205,0)),"SEM DE-PARA")) -> PROJETOS | E6: =IF(A6="","",DATE(YEAR(A6),MONTH(A6),1)) -> 45627
A7: 45658 | B7: PROJETOS | C7: 10917.03 | D7: =IF(B7="","",IFERROR(INDEX(DE_PARA!$B$6:$B$205,MATCH(B7,DE_PARA!$A$6:$A$205,0)),"SEM DE-PARA")) -> PROJETOS | E7: =IF(A7="","",DATE(YEAR(A7),MONTH(A7),1)) -> 45658
A8: 45689 | B8: PROJETOS | C8: 263811.08 | D8: =IF(B8="","",IFERROR(INDEX(DE_PARA!$B$6:$B$205,MATCH(B8,DE_PARA!$A$6:$A$205,0)),"SEM DE-PARA")) -> PROJETOS | E8: =IF(A8="","",DATE(YEAR(A8),MONTH(A8),1)) -> 45689
A9: 45717 | B9: PROJETOS | C9: 95377.59 | D9: =IF(B9="","",IFERROR(INDEX(DE_PARA!$B$6:$B$205,MATCH(B9,DE_PARA!$A$6:$A$205,0)),"SEM DE-PARA")) -> PROJETOS | E9: =IF(A9="","",DATE(YEAR(A9),MONTH(A9),1)) -> 45717
A10: 45748 | B10: PROJETOS | C10: 152105.86 | D10: =IF(B10="","",IFERROR(INDEX(DE_PARA!$B$6:$B$205,MATCH(B10,DE_PARA!$A$6:$A$205,0)),"SEM DE-PARA")) -> PROJETOS | E10: =IF(A10="","",DATE(YEAR(A10),MONTH(A10),1)) -> 45748
A11: 45778 | B11: PROJETOS | C11: 202477.1 | D11: =IF(B11="","",IFERROR(INDEX(DE_PARA!$B$6:$B$205,MATCH(B11,DE_PARA!$A$6:$A$205,0)),"SEM DE-PARA")) -> PROJETOS | E11: =IF(A11="","",DATE(YEAR(A11),MONTH(A11),1)) -> 45778
A12: 45809 | B12: PROJETOS | C12: 65133.61 | D12: =IF(B12="","",IFERROR(INDEX(DE_PARA!$B$6:$B$205,MATCH(B12,DE_PARA!$A$6:$A$205,0)),"SEM DE-PARA")) -> PROJETOS | E12: =IF(A12="","",DATE(YEAR(A12),MONTH(A12),1)) -> 45809
A13: 45839 | B13: PROJETOS | C13: 46336.42 | D13: =IF(B13="","",IFERROR(INDEX(DE_PARA!$B$6:$B$205,MATCH(B13,DE_PARA!$A$6:$A$205,0)),"SEM DE-PARA")) -> PROJETOS | E13: =IF(A13="","",DATE(YEAR(A13),MONTH(A13),1)) -> 45839
A14: 45870 | B14: PROJETOS | C14: 89390.73 | D14: =IF(B14="","",IFERROR(INDEX(DE_PARA!$B$6:$B$205,MATCH(B14,DE_PARA!$A$6:$A$205,0)),"SEM DE-PARA")) -> PROJETOS | E14: =IF(A14="","",DATE(YEAR(A14),MONTH(A14),1)) -> 45870
A15: 45901 | B15: PROJETOS | C15: 31201.11 | D15: =IF(B15="","",IFERROR(INDEX(DE_PARA!$B$6:$B$205,MATCH(B15,DE_PARA!$A$6:$A$205,0)),"SEM DE-PARA")) -> PROJETOS | E15: =IF(A15="","",DATE(YEAR(A15),MONTH(A15),1)) -> 45901
A16: 45931 | B16: PROJETOS | C16: 59081.79 | D16: =IF(B16="","",IFERROR(INDEX(DE_PARA!$B$6:$B$205,MATCH(B16,DE_PARA!$A$6:$A$205,0)),"SEM DE-PARA")) -> PROJETOS | E16: =IF(A16="","",DATE(YEAR(A16),MONTH(A16),1)) -> 45931
A17: 45962 | B17: PROJETOS | C17: 118743.26 | D17: =IF(B17="","",IFERROR(INDEX(DE_PARA!$B$6:$B$205,MATCH(B17,DE_PARA!$A$6:$A$205,0)),"SEM DE-PARA")) -> PROJETOS | E17: =IF(A17="","",DATE(YEAR(A17),MONTH(A17),1)) -> 45962
... A309: 45962 | B309: TAXA DE ADMINISTRAÇÃO | C309: 119467.69 | D309: =IF(B309="","",IFERROR(INDEX(DE_PARA!$B$6:$B$205,MATCH(B309,DE_PARA!$A$6:$A$205,0)),"SEM DE-PARA")) -> TAXA DE ADMINISTRAÇÃO | E309: =IF(A309="","",DATE(YEAR(A309),MONTH(A309),1)) -> 45962
D310: =IF(B310="","",IFERROR(INDEX(DE_PARA!$B$6:$B$205,MATCH(B310,DE_PARA!$A$6:$A$205,0)),"SEM DE-PARA")) | E310: =IF(A310="","",DATE(YEAR(A310),MONTH(A310),1))
D311: =IF(B311="","",IFERROR(INDEX(DE_PARA!$B$6:$B$205,MATCH(B311,DE_PARA!$A$6:$A$205,0)),"SEM DE-PARA")) | E311: =IF(A311="","",DATE(YEAR(A311),MONTH(A311),1))
D312: =IF(B312="","",IFERROR(INDEX(DE_PARA!$B$6:$B$205,MATCH(B312,DE_PARA!$A$6:$A$205,0)),"SEM DE-PARA")) | E312: =IF(A312="","",DATE(YEAR(A312),MONTH(A312),1))
D313: =IF(B313="","",IFERROR(INDEX(DE_PARA!$B$6:$B$205,MATCH(B313,DE_PARA!$A$6:$A$205,0)),"SEM DE-PARA")) | E313: =IF(A313="","",DATE(YEAR(A313),MONTH(A313),1))
D314: =IF(B314="","",IFERROR(INDEX(DE_PARA!$B$6:$B$205,MATCH(B314,DE_PARA!$A$6:$A$205,0)),"SEM DE-PARA")) | E314: =IF(A314="","",DATE(YEAR(A314),MONTH(A314),1))
D315: =IF(B315="","",IFERROR(INDEX(DE_PARA!$B$6:$B$205,MATCH(B315,DE_PARA!$A$6:$A$205,0)),"SEM DE-PARA")) | E315: =IF(A315="","",DATE(YEAR(A315),MONTH(A315),1))
D316: =IF(B316="","",IFERROR(INDEX(DE_PARA!$B$6:$B$205,MATCH(B316,DE_PARA!$A$6:$A$205,0)),"SEM DE-PARA")) | E316: =IF(A316="","",DATE(YEAR(A316),MONTH(A316),1))
D317: =IF(B317="","",IFERROR(INDEX(DE_PARA!$B$6:$B$205,MATCH(B317,DE_PARA!$A$6:$A$205,0)),"SEM DE-PARA")) | E317: =IF(A317="","",DATE(YEAR(A317),MONTH(A317),1))
D318: =IF(B318="","",IFERROR(INDEX(DE_PARA!$B$6:$B$205,MATCH(B318,DE_PARA!$A$6:$A$205,0)),"SEM DE-PARA")) | E318: =IF(A318="","",DATE(YEAR(A318),MONTH(A318),1))
D319: =IF(B319="","",IFERROR(INDEX(DE_PARA!$B$6:$B$205,MATCH(B319,DE_PARA!$A$6:$A$205,0)),"SEM DE-PARA")) | E319: =IF(A319="","",DATE(YEAR(A319),MONTH(A319),1))
D320: =IF(B320="","",IFERROR(INDEX(DE_PARA!$B$6:$B$205,MATCH(B320,DE_PARA!$A$6:$A$205,0)),"SEM DE-PARA")) | E320: =IF(A320="","",DATE(YEAR(A320),MONTH(A320),1))
D321: =IF(B321="","",IFERROR(INDEX(DE_PARA!$B$6:$B$205,MATCH(B321,DE_PARA!$A$6:$A$205,0)),"SEM DE-PARA")) | E321: =IF(A321="","",DATE(YEAR(A321),MONTH(A321),1))
... D5005: =IF(B5005="","",IFERROR(INDEX(DE_PARA!$B$6:$B$205,MATCH(B5005,DE_PARA!$A$6:$A$205,0)),"SEM DE-PARA")) | E5005: =IF(A5005="","",DATE(YEAR(A5005),MONTH(A5005),1))

Sheet DE_PARA
A1: De-para: nome no ERP → disciplina do orçamento
A2: A coluna B precisa ser exatamente igual a um nome da aba ORCAMENTO.
A5: Nome no ERP (como vem no relatório) | B5: Disciplina (ORCAMENTO)
A6: PROJETOS | B6: PROJETOS
A7: SEGUROS | B7: SEGUROS
A8: TAXAS DIVERSAS | B8: TAXAS DIVERSAS
A9: BARRACAO DE OBRA | B9: BARRACAO DE OBRA
A10: LIGAÇÕES PROVISÓRIAS AGUA, ENERGIA,TELEFONIA, ESGOTO | B10: LIGAÇÕES PROVISÓRIAS AGUA, ENERGIA,TELEFONIA, ESGOTO
A11: CONSUMO DE ÁGUA, ENERGIA, ETC. | B11: CONSUMO DE ÁGUA, ENERGIA, ETC.
A12: DIVERSOS | B12: DIVERSOS
A13: TRANSPORTES | B13: TRANSPORTES
A14: CONSULTORIAS (OBRAS) | B14: CONSULTORIAS (OBRAS)
A15: MÃO DE OBRA PRÓPRIA | B15: MÃO DE OBRA PRÓPRIA
A16: EQUIPAMENTOS E FERRAMENTAS | B16: EQUIPAMENTOS E FERRAMENTAS
... A48: FRETES E TRANSPORTES | B48: TRANSPORTES

Sheet CURVA
A1: Curva de distribuição do saldo (pesos por mês)
A2: Preencha pesos nos meses FUTUROS (fundo branco). Qualquer escala serve (%, R$, horas): só a proporção importa. Meses cinza (realizados) são ignorados.
A7: Código | B7: Disciplina | H7: Σ pesos futuros | J7: =FLUXO_MENSAL!J7 -> 45627 | K7: =FLUXO_MENSAL!K7 -> 45658 | L7: =FLUXO_MENSAL!L7 -> 45689 | M7: =FLUXO_MENSAL!M7 -> 45717 | N7: =FLUXO_MENSAL!N7 -> 45748 | O7: =FLUXO_MENSAL!O7 -> 45778 | P7: =FLUXO_MENSAL!P7 -> 45809 | Q7: =FLUXO_MENSAL!Q7 -> 45839 | ... CC7: =FLUXO_MENSAL!CC7 -> 47788
A8: =IF(ORCAMENTO!A6="","",ORCAMENTO!A6) -> 01 | B8: =IF(ORCAMENTO!B6="","",ORCAMENTO!B6) -> PROJETOS | H8: =SUMPRODUCT((J$7:CC$7>PARAMETROS!$C$12)*J8:CC8) -> 533315.27 | AE8: 14833 | AF8: 100000 | AG8: 100000 | AH8: 14833 | AI8: 14833 | AJ8: 1100 | AK8: 1100 | AL8: 1100 | AM8: 1100 | AN8: 1100 | AO8: 1100 | AP8: 1100 | AQ8: 1100 | AR8: 1100 | AS8: 1100 | AT8: 1100 | AU8: 1100 | AV8: 1100 | AW8: 1100 | AX8: 1100 | AY8: 1100 | AZ8: 1100 | BA8: 1100 | BB8: 1100 | BC8: 1100 | BD8: 1100 | BE8: 264616.27 | BF8: 1100
A9: =IF(ORCAMENTO!A7="","",ORCAMENTO!A7) -> 02 | B9: =IF(ORCAMENTO!B7="","",ORCAMENTO!B7) -> SEGUROS | H9: =SUMPRODUCT((J$7:CC$7>PARAMETROS!$C$12)*J9:CC9) -> 0
A10: =IF(ORCAMENTO!A8="","",ORCAMENTO!A8) -> 03 | B10: =IF(ORCAMENTO!B8="","",ORCAMENTO!B8) -> TAXAS DIVERSAS | H10: =SUMPRODUCT((J$7:CC$7>PARAMETROS!$C$12)*J10:CC10) -> 151217.5 | AE10: 924.76 | AH10: 924.76 | AK10: 924.76 | AN10: 924.76 | AQ10: 924.76 | BD10: 15961.4 | BE10: 24939.69 | BF10: 299.28 | BG10: 44891.44 | BH10: 60501.89
A11: =IF(ORCAMENTO!A9="","",ORCAMENTO!A9) -> 04 | B11: =IF(ORCAMENTO!B9="","",ORCAMENTO!B9) -> BARRACAO DE OBRA | H11: =SUMPRODUCT((J$7:CC$7>PARAMETROS!$C$12)*J11:CC11) -> 597111.3 | AE11: 12388.74 | AF11: 12388.74 | AG11: 12388.74 | AH11: 12388.74 | AI11: 12388.74 | AJ11: 102388.74 | AK11: 102388.74 | AL11: 52388.74 | AM11: 12388.74 | AN11: 12388.74 | AO11: 12388.74 | AP11: 12388.74 | AQ11: 12388.74 | AR11: 12388.74 | AS11: 12388.74 | AT11: 12388.74 | AU11: 12388.74 | AV11: 12388.74 | AW11: 12388.74 | AX11: 12388.74 | AY11: 12388.74 | AZ11: 12388.74 | BA11: 12388.74 | BB11: 12388.74 | BC11: 1300 | BD11: 1300 | BE11: 1300 | BF11: 1771.78 | BG11: 1729.71 | BH11: 1729.71 | BI11: 70650.34
A12: =IF(ORCAMENTO!A10="","",ORCAMENTO!A10) -> 05 | B12: =IF(ORCAMENTO!B10="","",ORCAMENTO!B10) -> LIGAÇÕES PROVISÓRIAS AGUA, ENERGIA,TELEFONIA, ESGOTO | H12: =SUMPRODUCT((J$7:CC$7>PARAMETROS!$C$12)*J12:CC12) -> 0
A13: =IF(ORCAMENTO!A11="","",ORCAMENTO!A11) -> 06 | B13: =IF(ORCAMENTO!B11="","",ORCAMENTO!B11) -> CONSUMO DE ÁGUA, ENERGIA, ETC. | H13: =SUMPRODUCT((J$7:CC$7>PARAMETROS!$C$12)*J13:CC13) -> 494508.3 | AE13: 10541.48 | AF13: 11379.4 | AG13: 11128.35 | AH13: 10642.17 | AI13: 10269.24 | AJ13: 11105.6 | AK13: 11301.04 | AL13: 10888.96 | AM13: 11189.99 | AN13: 11332.57 | AO13: 11583.14 | AP13: 11935.17 | AQ13: 12480.22 | AR13: 12867.83 | AS13: 12853.32 | AT13: 13195.68 | AU13: 12006.76 | AV13: 12952.12 | AW13: 12741.85 | AX13: 12613.6 | AY13: 12214.28 | AZ13: 12961.71 | BA13: 12457.67 | BB13: 12316.4 | BC13: 12207.86 | BD13: 11610.73 | BE13: 11025.61 | BF13: 10312.1 | BG13: 9972.52 | BH13: 9937.31 | BI13: 9524.9 | BJ13: 9124.11 | BK13: 9124.11 | BL13: 9124.11 | BN13: 107586.39
A14: =IF(ORCAMENTO!A12="","",ORCAMENTO!A12) -> 07 | B14: =IF(ORCAMENTO!B12="","",ORCAMENTO!B12) -> DIVERSOS | H14: =SUMPRODUCT((J$7:CC$7>PARAMETROS!$C$12)*J14:CC14) -> 155081.47 | AE14: 860.64 | AF14: 3259.22 | AG14: 4542.16 | AH14: 4253.68 | AI14: 4032.4 | AJ14: 4890.72 | AK14: 5097.2 | AL14: 4852.69 | AM14: 5121.82 | AN14: 5296.94 | AO14: 5355.1 | AP14: 5563.98 | AQ14: 5977.91 | AR14: 6207.91 | AS14: 6018.27 | AT14: 6221.41 | AU14: 5515.95 | AV14: 6076.89 | AW14: 5861.61 | AX14: 5785.51 | AY14: 5458.06 | AZ14: 5901.55 | BA14: 5602.48 | BB14: 5518.65 | BC14: 5273.22 | BD14: 4918.9 | BE14: 4571.72 | BF14: 3695.77 | BG14: 3222.74 | BH14: 3201.84 | BI14: 2504.57 | BJ14: 4419.96
A15: =IF(ORCAMENTO!A13="","",ORCAMENTO!A13) -> 08 | B15: =IF(ORCAMENTO!B13="","",ORCAMENTO!B13) -> TRANSPORTES | H15: =SUMPRODUCT((J$7:CC$7>PARAMETROS!$C$12)*J15:CC15) -> 745297.28 | AE15: 14226.77 | AF15: 17910.28 | AG15: 12060.18 | AH15: 12369.16 | AI15: 16309.5 | AJ15: 28235.87 | AK15: 25515.02 | AL15: 29900.88 | AM15: 30199.63 | AN15: 34501.02 | AO15: 32780.44 | AP15: 31177.91 | AQ15: 34021.99 | AR15: 29443.74 | AS15: 26464.19 | AT15: 29004.48 | AU15: 31522.3 | AV15: 31011.94 | AW15: 20653.6 | AX15: 12928.22 | AY15: 12928.22 | AZ15: 12928.22 | BA15: 12928.22 | BB15: 12928.22 | BC15: 12928.22 | BD15: 12928.22 | BE15: 12928.22 | BF15: 12928.22 | BG15: 12928.22 | BH15: 6000 | BI15: 65559.01 | BJ15: 19438.3 | BK15: 37708.87
A16: =IF(ORCAMENTO!A14="","",ORCAMENTO!A14) -> 09 | B16: =IF(ORCAMENTO!B14="","",ORCAMENTO!B14) -> CONSULTORIAS (OBRAS) | H16: =SUMPRODUCT((J$7:CC$7>PARAMETROS!$C$12)*J16:CC16) -> 671943.38 | AE16: 29236.97 | AF16: 24991.46 | AG16: 22791.46 | AH16: 22791.46 | AI16: 25692.74 | AJ16: 19492.74 | AK16: 19492.74 | AL16: 21692.74 | AM16: 19492.74 | AN16: 24517.74 | AO16: 21692.74 | AP16: 19492.74 | AQ16: 19492.74 | AR16: 21692.74 | AS16: 19492.74 | AT16: 15610.78 | AU16: 17385.68 | AV16: 15185.68 | AW16: 11185.68 | AX16: 13385.68 | AY16: 11185.68 | AZ16: 16210.68 | BA16: 13385.68 | BB16: 48685.68 | BC16: 50885.68 | BD16: 11185.68 | BE16: 10483.68 | BF16: 12683.68 | BG16: 9485.68 | BH16: 5685.68 | BI16: 77255.59
A17: =IF(ORCAMENTO!A15="","",ORCAMENTO!A15) -> 10 | B17: =IF(ORCAMENTO!B15="","",ORCAMENTO!B15) -> MÃO DE OBRA PRÓPRIA | H17: =SUMPRODUCT((J$7:CC$7>PARAMETROS!$C$12)*J17:CC17) -> 17058054 | AE17: 140080.31 | AF17: 252136.45 | AG17: 284644.73 | AH17: 328768.1 | AI17: 488589.71 | AJ17: 439669.52 | AK17: 437483.96 | AL17: 450976.08 | AM17: 456518.18 | AN17: 456518.18 | AO17: 456518.18 | AP17: 464593.44 | AQ17: 464593.44 | AR17: 463729.92 | AS17: 592235.93 | AT17: 583784.24 | AU17: 464593.44 | AV17: 464593.44 | AW17: 464593.44 | AX17: 446460.19 | AY17: 446460.19 | AZ17: 446460.19 | BA17: 430208.77 | BB17: 409025.96 | BC17: 409025.96 | BD17: 409025.96 | BE17: 580495.28 | BF17: 605762.34 | BG17: 473473.39 | BH17: 437920 | BI17: 437920 | BJ17: 615518.93 | BK17: 163135.14 | BL17: 63372.54 | BM17: 63372.54 | BP17: 2465795.8
A18: =IF(ORCAMENTO!A16="","",ORCAMENTO!A16) -> 11 | B18: =IF(ORCAMENTO!B16="","",ORCAMENTO!B16) -> EQUIPAMENTOS E FERRAMENTAS | H18: =SUMPRODUCT((J$7:CC$7>PARAMETROS!$C$12)*J18:CC18) -> 6128608.3 | AE18: 94939.97 | AF18: 158564.58 | AG18: 95745 | AH18: 201083.08 | AI18: 98138.38 | AJ18: 197907.52 | AK18: 162918.89 | AL18: 169058.89 | AM18: 273009.59 | AN18: 218406.22 | AO18: 267270.57 | AP18: 233262.22 | AQ18: 229592.22 | AR18: 286769.57 | AS18: 327219.86 | AT18: 263647.68 | AU18: 245007.68 | AV18: 249007.68 | AW18: 239688.68 | AX18: 250628.68 | AY18: 263254.68 | AZ18: 249749.3 | BA18: 260865.91 | BB18: 318689.62 | BC18: 209920.3 | BD18: 233466.97 | BE18: 18744.2 | BF18: 109412.33 | BG18: 104432.33 | BH18: 86124.89 | BI18: 6352.27 | BJ18: 2864.27 | BK18: 2864.27
A19: =IF(ORCAMENTO!A17="","",ORCAMENTO!A17) -> 12 | B19: =IF(ORCAMENTO!B17="","",ORCAMENTO!B17) -> SERVIÇOS INICIAIS | H19: =SUMPRODUCT((J$7:CC$7>PARAMETROS!$C$12)*J19:CC19) -> 56654.6 | AL19: 56654.6
A20: =IF(ORCAMENTO!A18="","",ORCAMENTO!A18) -> 13 | B20: =IF(ORCAMENTO!B18="","",ORCAMENTO!B18) -> CONTENÇÃO | H20: =SUMPRODUCT((J$7:CC$7>PARAMETROS!$C$12)*J20:CC20) -> 384571.25 | AF20: 70000 | AG20: 70000 | AI20: 130000 | AJ20: 114571.25
A21: =IF(ORCAMENTO!A19="","",ORCAMENTO!A19) -> 14 | B21: =IF(ORCAMENTO!B19="","",ORCAMENTO!B19) -> TERRAPLENAGEM | H21: =SUMPRODUCT((J$7:CC$7>PARAMETROS!$C$12)*J21:CC21) -> 251741.15 | AE21: 50000 | AF21: 75000 | AG21: 75000 | AL21: 51741.15
A22: =IF(ORCAMENTO!A20="","",ORCAMENTO!A20) -> 15 | B22: =IF(ORCAMENTO!B20="","",ORCAMENTO!B20) -> FUNDAÇÃO PROFUNDA | H22: =SUMPRODUCT((J$7:CC$7>PARAMETROS!$C$12)*J22:CC22) -> 0
A23: =IF(ORCAMENTO!A21="","",ORCAMENTO!A21) -> 16 | B23: =IF(ORCAMENTO!B21="","",ORCAMENTO!B21) -> FUNDAÇÃO SUPERFICIAL | H23: =SUMPRODUCT((J$7:CC$7>PARAMETROS!$C$12)*J23:CC23) -> 1267966.1 | AF23: 50000 | AG23: 50000 | AL23: 250000 | AM23: 250000 | AN23: 200000 | AO23: 125000 | AS23: 92971.37 | AW23: 125000 | AX23: 124994.68
A24: =IF(ORCAMENTO!A22="","",ORCAMENTO!A22) -> 17 | B24: =IF(ORCAMENTO!B22="","",ORCAMENTO!B22) -> ESTRUTURA EM CONCRETO ARMADO | H24: =SUMPRODUCT((J$7:CC$7>PARAMETROS!$C$12)*J24:CC24) -> 23773298 | AF24: 686964.52 | AG24: 1047212.7 | AH24: 1620508.1 | AI24: 1912666.9 | AJ24: 1716911.8 | AK24: 1724029 | AL24: 1240873.8 | AM24: 1377375.7 | AN24: 1690022.9 | AO24: 1533152.9 | AP24: 1541765.8 | AQ24: 1266058.1 | AR24: 1261900.4 | AS24: 1261551.8 | AT24: 1261500.2 | AU24: 374755.37 | AV24: 374517.08 | AW24: 361591.02 | AX24: 340999.31 | BH24: 1178940.2
A25: =IF(ORCAMENTO!A23="","",ORCAMENTO!A23) -> 18 | B25: =IF(ORCAMENTO!B23="","",ORCAMENTO!B23) -> ALVENARIA | H25: =SUMPRODUCT((J$7:CC$7>PARAMETROS!$C$12)*J25:CC25) -> 6245483 | AL25: 70130.98 | AM25: 134575.67 | AN25: 221133.72 | AO25: 416363.21 | AP25: 387299.92 | AQ25: 545884.39 | AR25: 564206.9 | AS25: 634337.88 | AT25: 680460.06 | AU25: 484598.76 | AV25: 518716.54 | AW25: 434685.72 | AX25: 521875.59 | AY25: 272310.39 | AZ25: 237560.8 | BA25: 69499.17 | BB25: 51843.25
A26: =IF(ORCAMENTO!A24="","",ORCAMENTO!A24) -> 19 | B26: =IF(ORCAMENTO!B24="","",ORCAMENTO!B24) -> IMPERMEABILIZAÇÃO | H26: =SUMPRODUCT((J$7:CC$7>PARAMETROS!$C$12)*J26:CC26) -> 4139097.7 | AQ26: 166232.94 | AR26: 232391.14 | AS26: 221504.35 | AT26: 421235.12 | AU26: 177119.74 | AV26: 332465.89 | AW26: 232391.14 | AX26: 574068.93 | AY26: 359682.87 | AZ26: 430865.74 | BA26: 621803.33 | BB26: 317810.59 | BC26: 40639.16 | BD26: 10886.79
A27: =IF(ORCAMENTO!A25="","",ORCAMENTO!A25) -> 20 | B27: =IF(ORCAMENTO!B25="","",ORCAMENTO!B25) -> INSTALAÇÕES ELÉTRICAS | H27: =SUMPRODUCT((J$7:CC$7>PARAMETROS!$C$12)*J27:CC27) -> 11269054 | AF27: 7000 | AG27: 7000 | AH27: 7000 | AK27: 104809.94 | AL27: 88705.57 | AM27: 55797.55 | AN27: 82184.09 | AO27: 81171.83 | AP27: 188717.89 | AQ27: 212785.42 | AR27: 257411.13 | AS27: 535693.44 | AT27: 467282.37 | AU27: 626135.18 | AV27: 673675.08 | AW27: 1450546.5 | AX27: 812816.23 | AY27: 539171.96 | AZ27: 863834.65 | BA27: 813975.74 | BB27: 542650.49 | BC27: 743245.65 | BD27: 164650.36 | BE27: 441773.16 | BF27: 288717.89 | BG27: 154214.78 | BH27: 336257.78 | BI27: 721829.79
A28: =IF(ORCAMENTO!A26="","",ORCAMENTO!A26) -> 21 | B28: =IF(ORCAMENTO!B26="","",ORCAMENTO!B26) -> INSTALAÇÕES HIDROSANITÁRIAS | H28: =SUMPRODUCT((J$7:CC$7>PARAMETROS!$C$12)*J28:CC28) -> 7741725.1 | AG28: 150000 | AH28: 50000 | AI28: 50000 | AJ28: 70000 | AK28: 120258.03 | AL28: 120258.03 | AM28: 87246.02 | AN28: 3930 | AO28: 89604.02 | AP28: 109254.03 | AQ28: 195714.05 | AR28: 279816.06 | AS28: 174492.04 | AT28: 363132.08 | AU28: 316758.07 | AV28: 424440.1 | AW28: 456666.11 | AX28: 983286.23 | AY28: 550986.13 | AZ28: 365490.08 | BA28: 585570.13 | BB28: 551772.13 | BC28: 367848.08 | BD28: 503826.12 | BE28: 111612.03 | BF28: 299466.07 | BG28: 195714.05 | BH28: 104538.02 | BI28: 60047.36
A29: =IF(ORCAMENTO!A27="","",ORCAMENTO!A27) -> 22 | B29: =IF(ORCAMENTO!B27="","",ORCAMENTO!B27) -> INSTALAÇÕES COMBATE INCÊNDIO | H29: =SUMPRODUCT((J$7:CC$7>PARAMETROS!$C$12)*J29:CC29) -> 823490.46 | AL29: 4858.59 | AM29: 51303.46 | AN29: 48915.33 | AO29: 53691.58 | AP29: 57973.73 | AQ29: 62667.62 | AR29: 58632.52 | AS29: 70490.78 | AT29: 67773.27 | AU29: 60444.2 | AV29: 60526.55 | AW29: 68349.71 | AX29: 85807.71 | AY29: 33186.67 | AZ29: 7905.51 | BA29: 15234.57 | BB29: 2305.77 | BC29: 2305.77 | BD29: 2223.42 | BE29: 2305.77 | BF29: 2223.42 | BG29: 1894.03 | BH29: 2141.08 | BI29: 329.4
A30: =IF(ORCAMENTO!A28="","",ORCAMENTO!A28) -> 23 | B30: =IF(ORCAMENTO!B28="","",ORCAMENTO!B28) -> INSTALAÇÕES ESPECIAIS | H30: =SUMPRODUCT((J$7:CC$7>PARAMETROS!$C$12)*J30:CC30) -> 2828799.6 | AO30: 15275.52 | AP30: 96462.07 | AQ30: 145117.42 | AR30: 138894.06 | AS30: 143703.02 | AT30: 242711.01 | AU30: 167182.06 | AV30: 140591.34 | AW30: 140025.58 | AX30: 216403.17 | AY30: 153320.94 | AZ30: 121072.63 | BA30: 186135.02 | BB30: 138328.3 | BC30: 273262.05 | BD30: 155018.22 | BE30: 40451.84 | BF30: 79489.27 | BG30: 44129.27 | BH30: 95896.31 | BI30: 68174.07 | BJ30: 27156.48
A31: =IF(ORCAMENTO!A29="","",ORCAMENTO!A29) -> 24 | B31: =IF(ORCAMENTO!B29="","",ORCAMENTO!B29) -> ELEVADORES | H31: =SUMPRODUCT((J$7:CC$7>PARAMETROS!$C$12)*J31:CC31) -> 3409802.3 | AP31: 305454.55 | AQ31: 305454.55 | AR31: 305454.55 | AS31: 305454.55 | AT31: 305454.55 | AU31: 305454.55 | AV31: 305454.55 | AW31: 312051.99 | AX31: 312051.99 | AY31: 312051.99 | AZ31: 305454.55 | BC31: 30009.97
A32: =IF(ORCAMENTO!A30="","",ORCAMENTO!A30) -> 25 | B32: =IF(ORCAMENTO!B30="","",ORCAMENTO!B30) -> ESQUADRIAS | H32: =SUMPRODUCT((J$7:CC$7>PARAMETROS!$C$12)*J32:CC32) -> 11781363 | AN32: 783232 | AO32: 939878.4 | AP32: 939878.4 | AQ32: 156646.4 | AU32: 1409305.4 | AV32: 1625375 | AW32: 1625375 | AX32: 545027.03 | AY32: 93987.84 | AZ32: 418092.23 | BA32: 547733.98 | BB32: 547733.98 | BC32: 547733.98 | BD32: 223629.59 | BE32: 129641.75 | BF32: 129641.75 | BG32: 129641.75 | BH32: 129641.75 | BI32: 129641.75 | BJ32: 129641.75 | BL32: 599883.07
A33: =IF(ORCAMENTO!A31="","",ORCAMENTO!A31) -> 26 | B33: =IF(ORCAMENTO!B31="","",ORCAMENTO!B31) -> SERRALHERIA | H33: =SUMPRODUCT((J$7:CC$7>PARAMETROS!$C$12)*J33:CC33) -> 508667.04 | AQ33: 27010.22 | AR33: 26959.35 | AT33: 27010.22 | AV33: 26959.35 | AW33: 22076.15 | AX33: 102649.01 | AY33: 59259.71 | AZ33: 24365.15 | BA33: 38709.56 | BB33: 24263.42 | BC33: 8647.34 | BD33: 8189.54 | BE33: 8342.14 | BF33: 24619.49 | BG33: 75130.12 | BH33: 4323.67 | BI33: 152.6
A34: =IF(ORCAMENTO!A32="","",ORCAMENTO!A32) -> 27 | B34: =IF(ORCAMENTO!B32="","",ORCAMENTO!B32) -> MARCENARIA | H34: =SUMPRODUCT((J$7:CC$7>PARAMETROS!$C$12)*J34:CC34) -> 3137103.3 | AW34: 207362.53 | AX34: 274182.83 | AY34: 231518.22 | AZ34: 300534.5 | BA34: 282966.72 | BB34: 275123.96 | BC34: 299279.65 | BD34: 238419.85 | BE34: 250027.13 | BF34: 300220.78 | BG34: 356374.93 | BH34: 121092.19
A35: =IF(ORCAMENTO!A33="","",ORCAMENTO!A33) -> 28 | B35: =IF(ORCAMENTO!B33="","",ORCAMENTO!B33) -> REVESTIMENTOS DE MASSA EM PISOS | H35: =SUMPRODUCT((J$7:CC$7>PARAMETROS!$C$12)*J35:CC35) -> 1154877.4 | AM35: 1847.8 | AN35: 3811.1 | AO35: 32567.54 | AP35: 96547.75 | AQ35: 87886.17 | AR35: 95970.31 | AS35: 93083.11 | AT35: 121493.1 | AU35: 175887.82 | AV35: 88579.09 | AW35: 99896.89 | AX35: 87539.7 | AY35: 65712.52 | AZ35: 36840.59 | BA35: 9123.53 | BB35: 49775.21 | BC35: 8315.12
A36: =IF(ORCAMENTO!A34="","",ORCAMENTO!A34) -> 29 | B36: =IF(ORCAMENTO!B34="","",ORCAMENTO!B34) -> REVESTIMENTOS DE MASSA EM PAREDES | H36: =SUMPRODUCT((J$7:CC$7>PARAMETROS!$C$12)*J36:CC36) -> 2653291.4 | AM36: 6102.57 | AN36: 31574.17 | AO36: 161320.12 | AP36: 184934.41 | AQ36: 161850.78 | AR36: 268513.09 | AS36: 315741.68 | AT36: 238796.23 | AU36: 170871.97 | AV36: 244898.8 | AW36: 238000.24 | AX36: 223937.79 | AY36: 109846.26 | AZ36: 205099.43 | BA36: 91803.88
A37: =IF(ORCAMENTO!A35="","",ORCAMENTO!A35) -> 30 | B37: =IF(ORCAMENTO!B35="","",ORCAMENTO!B35) -> REVESTIMENTOS DE ACABAMENTO | H37: =SUMPRODUCT((J$7:CC$7>PARAMETROS!$C$12)*J37:CC37) -> 10951845 | AQ37: 52610.11 | AR37: 438417.58 | AS37: 592959.78 | AT37: 625841.1 | AU37: 431841.32 | AV37: 607208.35 | AW37: 773807.03 | AX37: 887795.61 | AY37: 788055.61 | AZ37: 839569.67 | BA37: 905332.31 | BB37: 708044.4 | BC37: 574327.03 | BD37: 584191.43 | BE37: 486643.52 | BF37: 562270.55 | BG37: 516236.7 | BH37: 416496.7 | BI37: 160196.29
A38: =IF(ORCAMENTO!A36="","",ORCAMENTO!A36) -> 31 | B38: =IF(ORCAMENTO!B36="","",ORCAMENTO!B36) -> PAVIMENTAÇÃO | H38: =SUMPRODUCT((J$7:CC$7>PARAMETROS!$C$12)*J38:CC38) -> 112630.58 | AU38: 17063.53 | AV38: 35839.05 | AW38: 35839.05 | AX38: 23888.95
A39: =IF(ORCAMENTO!A37="","",ORCAMENTO!A37) -> 32 | B39: =IF(ORCAMENTO!B37="","",ORCAMENTO!B37) -> REVESTIMENTO DIVERSOS - FACHADA | H39: =SUMPRODUCT((J$7:CC$7>PARAMETROS!$C$12)*J39:CC39) -> 5326855 | AQ39: 124648.41 | AR39: 342516.77 | AS39: 420821.54 | AT39: 361160.76 | AU39: 278594.51 | AV39: 267408.12 | AW39: 422419.6 | AX39: 359562.71 | AY39: 299369.25 | AZ39: 266342.75 | BA39: 314817.13 | BB39: 406971.72 | BC39: 621643.97 | BD39: 275931.09 | BE39: 254090.98 | BF39: 176851.58 | BG39: 113994.7 | BH39: 10653.71 | BI39: 9055.65
A40: =IF(ORCAMENTO!A38="","",ORCAMENTO!A38) -> 33 | B40: =IF(ORCAMENTO!B38="","",ORCAMENTO!B38) -> FORRO | H40: =SUMPRODUCT((J$7:CC$7>PARAMETROS!$C$12)*J40:CC40) -> 1781242.1 | AS40: 69290.32 | AT40: 132168.16 | AU40: 113999.49 | AV40: 155680.56 | AW40: 148199.34 | AX40: 290876.84 | AY40: 198252.25 | AZ40: 153008.7 | BA40: 144814.98 | BB40: 139827.51 | BC40: 132524.41 | BD40: 29746.74 | BE40: 56643.5 | BF40: 16209.3
A41: =IF(ORCAMENTO!A39="","",ORCAMENTO!A39) -> 34 | B41: =IF(ORCAMENTO!B39="","",ORCAMENTO!B39) -> LOUÇAS SANITÁRIAS | H41: =SUMPRODUCT((J$7:CC$7>PARAMETROS!$C$12)*J41:CC41) -> 2160628.3 | AX41: 204179.37 | AY41: 174146.64 | AZ41: 227082.03 | BA41: 213686.14 | BB41: 207420.32 | BC41: 226001.72 | BD41: 177603.65 | BE41: 186894.35 | BF41: 176091.21 | BG41: 151676.11 | BH41: 187326.47 | BI41: 28520.29
A42: =IF(ORCAMENTO!A40="","",ORCAMENTO!A40) -> 35 | B42: =IF(ORCAMENTO!B40="","",ORCAMENTO!B40) -> PINTURA | H42: =SUMPRODUCT((J$7:CC$7>PARAMETROS!$C$12)*J42:CC42) -> 3759701.6 | AL42: 6143.06 | AM42: 11788.04 | AN42: 19370.02 | AO42: 36470.97 | AP42: 33925.2 | AQ42: 47816.27 | AR42: 49421.21 | AS42: 55564.28 | AT42: 120000 | AU42: 297136.05 | AV42: 318055.67 | AW42: 266531.43 | AX42: 319992.67 | AY42: 166969.54 | AZ42: 158467.79 | BA42: 158467.79 | BB42: 158467.79 | BC42: 158467.79 | BD42: 158467.79 | BE42: 158467.79 | BF42: 158467.79 | BG42: 158467.79 | BH42: 158467.79 | BI42: 158467.79 | BJ42: 158467.79 | BK42: 267371.55
A43: =IF(ORCAMENTO!A41="","",ORCAMENTO!A41) -> 36 | B43: =IF(ORCAMENTO!B41="","",ORCAMENTO!B41) -> PAISAGISMO | H43: =SUMPRODUCT((J$7:CC$7>PARAMETROS!$C$12)*J43:CC43) -> 1176926.3 | BC43: 377793.34 | BD43: 346604.79 | BE43: 267750.73 | BF43: 123341.88 | BG43: 61435.55
A44: =IF(ORCAMENTO!A42="","",ORCAMENTO!A42) -> 37 | B44: =IF(ORCAMENTO!B42="","",ORCAMENTO!B42) -> LIMPEZA FINAL DE OBRA | H44: =SUMPRODUCT((J$7:CC$7>PARAMETROS!$C$12)*J44:CC44) -> 934927.34 | AX44: 19082.06 | AY44: 36106.25 | AZ44: 66038.89 | BA44: 81005.21 | BB44: 86430.5 | BC44: 83343.7 | BD44: 83437.24 | BE44: 77824.87 | BF44: 69219.23 | BG44: 55843.08 | BH44: 95784.45 | BI44: 86711.12 | BJ44: 81940.6 | BK44: 12160.14
A45: =IF(ORCAMENTO!A43="","",ORCAMENTO!A43) -> 38 | B45: =IF(ORCAMENTO!B43="","",ORCAMENTO!B43) -> TAXA DE ADMINISTRAÇÃO | H45: =SUMPRODUCT((J$7:CC$7>PARAMETROS!$C$12)*J45:CC45) -> 0
A46: =IF(ORCAMENTO!A44="","",ORCAMENTO!A44) | B46: =IF(ORCAMENTO!B44="","",ORCAMENTO!B44) | H46: =SUMPRODUCT((J$7:CC$7>PARAMETROS!$C$12)*J46:CC46) -> 0
A47: =IF(ORCAMENTO!A45="","",ORCAMENTO!A45) | B47: =IF(ORCAMENTO!B45="","",ORCAMENTO!B45) | H47: =SUMPRODUCT((J$7:CC$7>PARAMETROS!$C$12)*J47:CC47) -> 0
A48: =IF(ORCAMENTO!A46="","",ORCAMENTO!A46) | B48: =IF(ORCAMENTO!B46="","",ORCAMENTO!B46) | H48: =SUMPRODUCT((J$7:CC$7>PARAMETROS!$C$12)*J48:CC48) -> 0
A49: =IF(ORCAMENTO!A47="","",ORCAMENTO!A47) | B49: =IF(ORCAMENTO!B47="","",ORCAMENTO!B47) | H49: =SUMPRODUCT((J$7:CC$7>PARAMETROS!$C$12)*J49:CC49) -> 0
A50: =IF(ORCAMENTO!A48="","",ORCAMENTO!A48) | B50: =IF(ORCAMENTO!B48="","",ORCAMENTO!B48) | H50: =SUMPRODUCT((J$7:CC$7>PARAMETROS!$C$12)*J50:CC50) -> 0
A51: =IF(ORCAMENTO!A49="","",ORCAMENTO!A49) | B51: =IF(ORCAMENTO!B49="","",ORCAMENTO!B49) | H51: =SUMPRODUCT((J$7:CC$7>PARAMETROS!$C$12)*J51:CC51) -> 0
A52: =IF(ORCAMENTO!A50="","",ORCAMENTO!A50) | B52: =IF(ORCAMENTO!B50="","",ORCAMENTO!B50) | H52: =SUMPRODUCT((J$7:CC$7>PARAMETROS!$C$12)*J52:CC52) -> 0
A53: =IF(ORCAMENTO!A51="","",ORCAMENTO!A51) | B53: =IF(ORCAMENTO!B51="","",ORCAMENTO!B51) | H53: =SUMPRODUCT((J$7:CC$7>PARAMETROS!$C$12)*J53:CC53) -> 0
A54: =IF(ORCAMENTO!A52="","",ORCAMENTO!A52) | B54: =IF(ORCAMENTO!B52="","",ORCAMENTO!B52) | H54: =SUMPRODUCT((J$7:CC$7>PARAMETROS!$C$12)*J54:CC54) -> 0
A55: =IF(ORCAMENTO!A53="","",ORCAMENTO!A53) | B55: =IF(ORCAMENTO!B53="","",ORCAMENTO!B53) | H55: =SUMPRODUCT((J$7:CC$7>PARAMETROS!$C$12)*J55:CC55) -> 0
A56: =IF(ORCAMENTO!A54="","",ORCAMENTO!A54) | B56: =IF(ORCAMENTO!B54="","",ORCAMENTO!B54) | H56: =SUMPRODUCT((J$7:CC$7>PARAMETROS!$C$12)*J56:CC56) -> 0
A57: =IF(ORCAMENTO!A55="","",ORCAMENTO!A55) | B57: =IF(ORCAMENTO!B55="","",ORCAMENTO!B55) | H57: =SUMPRODUCT((J$7:CC$7>PARAMETROS!$C$12)*J57:CC57) -> 0

Sheet INCC
A1: INCC-DI (FGV) — índice mensal
A2: Acrescente uma linha por mês. Fonte: FGV.
A5: Mês | B5: Índice | C5: Variação no mês
A6: 45536 | B6: 1136.521
A7: 45566 | B7: 1144.136 | C7: =IF(OR(B7="",B6="",NOT(ISNUMBER(B6))),"",B7/B6-1) -> 0.0067002721
A8: 45597 | B8: 1149.158 | C8: =IF(OR(B8="",B7="",NOT(ISNUMBER(B7))),"",B8/B7-1) -> 0.0043893383
A9: 45627 | B9: 1154.99 | C9: =IF(OR(B9="",B8="",NOT(ISNUMBER(B8))),"",B9/B8-1) -> 0.0050750201
A10: 45658 | B10: 1163.221 | C10: =IF(OR(B10="",B9="",NOT(ISNUMBER(B9))),"",B10/B9-1) -> 0.0071264686
A11: 45689 | B11: 1169.156 | C11: =IF(OR(B11="",B10="",NOT(ISNUMBER(B10))),"",B11/B10-1) -> 0.0051022119
A12: 45717 | B12: 1173.586 | C12: =IF(OR(B12="",B11="",NOT(ISNUMBER(B11))),"",B12/B11-1) -> 0.0037890581
A13: 45748 | B13: 1180.564 | C13: =IF(OR(B13="",B12="",NOT(ISNUMBER(B12))),"",B13/B12-1) -> 0.0059458787
A14: 45778 | B14: 1183.606 | C14: =IF(OR(B14="",B13="",NOT(ISNUMBER(B13))),"",B14/B13-1) -> 0.0025767345
A15: 45809 | B15: 1194.912 | C15: =IF(OR(B15="",B14="",NOT(ISNUMBER(B14))),"",B15/B14-1) -> 0.0095521652
A16: 45839 | B16: 1205.838 | C16: =IF(OR(B16="",B15="",NOT(ISNUMBER(B15))),"",B16/B15-1) -> 0.0091437696
A17: 45870 | B17: 1214.239 | C17: =IF(OR(B17="",B16="",NOT(ISNUMBER(B16))),"",B17/B16-1) -> 0.0069669392
A18: 45901 | B18: 1216.825 | C18: =IF(OR(B18="",B17="",NOT(ISNUMBER(B17))),"",B18/B17-1) -> 0.002129729
... A29: 46235 | B29: 1296.889 | C29: =IF(OR(B29="",B28="",NOT(ISNUMBER(B28))),"",B29/B28-1) -> 0.0065645735
C30: =IF(OR(B30="",B29="",NOT(ISNUMBER(B29))),"",B30/B29-1)
C31: =IF(OR(B31="",B30="",NOT(ISNUMBER(B30))),"",B31/B30-1)
C32: =IF(OR(B32="",B31="",NOT(ISNUMBER(B31))),"",B32/B31-1)
C33: =IF(OR(B33="",B32="",NOT(ISNUMBER(B32))),"",B33/B32-1)
C34: =IF(OR(B34="",B33="",NOT(ISNUMBER(B33))),"",B34/B33-1)
C35: =IF(OR(B35="",B34="",NOT(ISNUMBER(B34))),"",B35/B34-1)
C36: =IF(OR(B36="",B35="",NOT(ISNUMBER(B35))),"",B36/B35-1)
C37: =IF(OR(B37="",B36="",NOT(ISNUMBER(B36))),"",B37/B36-1)
C38: =IF(OR(B38="",B37="",NOT(ISNUMBER(B37))),"",B38/B37-1)
C39: =IF(OR(B39="",B38="",NOT(ISNUMBER(B38))),"",B39/B38-1)
C40: =IF(OR(B40="",B39="",NOT(ISNUMBER(B39))),"",B40/B39-1)
C41: =IF(OR(B41="",B40="",NOT(ISNUMBER(B40))),"",B41/B40-1)
... C305: =IF(OR(B305="",B304="",NOT(ISNUMBER(B304))),"",B305/B304-1)

Sheet CONFERENCIA
A1: Conferência
A2: Tudo deve estar 'OK' antes de usar o fluxo.
A3: Verificação | C3: Resultado | D3: Status
A4: Lançamentos sem de-para | C4: =COUNTIF(INCORRIDO!$D$6:$D$5005,"SEM DE-PARA") -> 0 | D4: =IF(C4=0,"OK","⚠ Cadastre em DE_PARA") -> OK
A5: Lançamentos com disciplina que não está no ORCAMENTO | C5: =SUMPRODUCT((INCORRIDO!$D$6:$D$5005<>"")*(INCORRIDO!$D$6:$D$5005<>"SEM DE-PARA")*(COUNTIF(ORCAMENTO!$B$6:$B$55,INCORRIDO!$D$6:$D$5005)=0)) -> 0 | D5: =IF(C5=0,"OK","⚠ Corrija DE_PARA ou ORCAMENTO") -> OK
A6: Lançamentos após o último mês do horizonte | C6: =COUNTIF(INCORRIDO!$E$6:$E$5005,">"&PARAMETROS!$C$13) -> 0 | D6: =IF(C6=0,"OK","⚠ Ficam fora do fluxo") -> OK
A7: Lançamentos sem data ou sem valor | C7: =SUMPRODUCT(((INCORRIDO!$A$6:$A$5005="")<>(INCORRIDO!$C$6:$C$5005=""))*1) -> 0 | D7: =IF(C7=0,"OK","⚠ Complete a linha") -> OK
A8: INCC do mês de corte informado | C8: =IF(ISNUMBER(PARAMETROS!C14),1,0) -> 1 | D8: =IF(C8=1,"OK","⚠ Inclua o índice na aba INCC") -> OK
A9: Realizado na base × realizado no fluxo (R$) | C9: =SUM(INCORRIDO!$C$6:$C$5005)-FLUXO_MENSAL!E58-FLUXO_MENSAL!F58 -> 0 | D9: =IF(ABS(C9)<1,"OK","⚠ Há lançamento que não entrou (ver linhas acima)") -> OK
A10: Disciplinas com pendência (tabela abaixo) | C10: =COUNTIF(H14:H63,"⚠*") -> 3 | D10: =IF(C10=0,"OK","⚠ Ver tabela") -> ⚠ Ver tabela
A13: Disciplina | B13: Projeção (R$) | C13: Realizado | D13: Compromissos | E13: Saldo distribuído | F13: Total no fluxo (a preços da projeção) | G13: Diferença | H13: Status | I13: Reajuste projetado (R$)
A14: =FLUXO_MENSAL!B8 -> PROJETOS | B14: =FLUXO_MENSAL!D8 -> 2640655 | C14: =FLUXO_MENSAL!E8 -> 2106293.6 | D14: =FLUXO_MENSAL!F8 -> 1046.09 | E14: =IF(FLUXO_MENSAL!H8>0,FLUXO_MENSAL!G8,0) -> 533315.27 | F14: =C14+D14+E14 -> 2640655 | G14: =B14-F14 -> 0 | H14: =IF(A14="","",IF(C14+D14>B14+1,"⚠ Realizado + compromissos acima da projeção",IF(AND(FLUXO_MENSAL!G8>1,FLUXO_MENSAL!H8=0),"⚠ Saldo sem curva (preencha CURVA)",IF(ABS(G14)>1,"⚠ Verificar","OK")))) -> OK | I14: =FLUXO_MENSAL!I8-F14 -> 0
A15: =FLUXO_MENSAL!B9 -> SEGUROS | B15: =FLUXO_MENSAL!D9 -> 127911.99 | C15: =FLUXO_MENSAL!E9 -> 0 | D15: =FLUXO_MENSAL!F9 -> 0 | E15: =IF(FLUXO_MENSAL!H9>0,FLUXO_MENSAL!G9,0) -> 0 | F15: =C15+D15+E15 -> 0 | G15: =B15-F15 -> 127911.99 | H15: =IF(A15="","",IF(C15+D15>B15+1,"⚠ Realizado + compromissos acima da projeção",IF(AND(FLUXO_MENSAL!G9>1,FLUXO_MENSAL!H9=0),"⚠ Saldo sem curva (preencha CURVA)",IF(ABS(G15)>1,"⚠ Verificar","OK")))) -> ⚠ Saldo sem curva (preencha CURVA) | I15: =FLUXO_MENSAL!I9-F15 -> 0
A16: =FLUXO_MENSAL!B10 -> TAXAS DIVERSAS | B16: =FLUXO_MENSAL!D10 -> 158047.46 | C16: =FLUXO_MENSAL!E10 -> 5905.19 | D16: =FLUXO_MENSAL!F10 -> 0 | E16: =IF(FLUXO_MENSAL!H10>0,FLUXO_MENSAL!G10,0) -> 152142.27 | F16: =C16+D16+E16 -> 158047.46 | G16: =B16-F16 -> 0 | H16: =IF(A16="","",IF(C16+D16>B16+1,"⚠ Realizado + compromissos acima da projeção",IF(AND(FLUXO_MENSAL!G10>1,FLUXO_MENSAL!H10=0),"⚠ Saldo sem curva (preencha CURVA)",IF(ABS(G16)>1,"⚠ Verificar","OK")))) -> OK | I16: =FLUXO_MENSAL!I10-F16 -> 0
A17: =FLUXO_MENSAL!B11 -> BARRACAO DE OBRA | B17: =FLUXO_MENSAL!D11 -> 1249911.1 | C17: =FLUXO_MENSAL!E11 -> 631109.61 | D17: =FLUXO_MENSAL!F11 -> 21690.09 | E17: =IF(FLUXO_MENSAL!H11>0,FLUXO_MENSAL!G11,0) -> 597111.37 | F17: =C17+D17+E17 -> 1249911.1 | G17: =B17-F17 -> 0 | H17: =IF(A17="","",IF(C17+D17>B17+1,"⚠ Realizado + compromissos acima da projeção",IF(AND(FLUXO_MENSAL!G11>1,FLUXO_MENSAL!H11=0),"⚠ Saldo sem curva (preencha CURVA)",IF(ABS(G17)>1,"⚠ Verificar","OK")))) -> OK | I17: =FLUXO_MENSAL!I11-F17 -> 0
A18: =FLUXO_MENSAL!B12 -> LIGAÇÕES PROVISÓRIAS AGUA, ENERGIA,TELEFONIA, ESGOTO | B18: =FLUXO_MENSAL!D12 -> 85665.05 | C18: =FLUXO_MENSAL!E12 -> 0 | D18: =FLUXO_MENSAL!F12 -> 0 | E18: =IF(FLUXO_MENSAL!H12>0,FLUXO_MENSAL!G12,0) -> 0 | F18: =C18+D18+E18 -> 0 | G18: =B18-F18 -> 85665.05 | H18: =IF(A18="","",IF(C18+D18>B18+1,"⚠ Realizado + compromissos acima da projeção",IF(AND(FLUXO_MENSAL!G12>1,FLUXO_MENSAL!H12=0),"⚠ Saldo sem curva (preencha CURVA)",IF(ABS(G18)>1,"⚠ Verificar","OK")))) -> ⚠ Saldo sem curva (preencha CURVA) | I18: =FLUXO_MENSAL!I12-F18 -> 0
A19: =FLUXO_MENSAL!B13 -> CONSUMO DE ÁGUA, ENERGIA, ETC. | B19: =FLUXO_MENSAL!D13 -> 544229.22 | C19: =FLUXO_MENSAL!E13 -> 36058.03 | D19: =FLUXO_MENSAL!F13 -> 10197.92 | E19: =IF(FLUXO_MENSAL!H13>0,FLUXO_MENSAL!G13,0) -> 497973.27 | F19: =C19+D19+E19 -> 544229.22 | G19: =B19-F19 -> 0 | H19: =IF(A19="","",IF(C19+D19>B19+1,"⚠ Realizado + compromissos acima da projeção",IF(AND(FLUXO_MENSAL!G13>1,FLUXO_MENSAL!H13=0),"⚠ Saldo sem curva (preencha CURVA)",IF(ABS(G19)>1,"⚠ Verificar","OK")))) -> OK | I19: =FLUXO_MENSAL!I13-F19 -> 0
A20: =FLUXO_MENSAL!B14 -> DIVERSOS | B20: =FLUXO_MENSAL!D14 -> 194480.67 | C20: =FLUXO_MENSAL!E14 -> 34023.01 | D20: =FLUXO_MENSAL!F14 -> 5376.16 | E20: =IF(FLUXO_MENSAL!H14>0,FLUXO_MENSAL!G14,0) -> 155081.5 | F20: =C20+D20+E20 -> 194480.67 | G20: =B20-F20 -> 0 | H20: =IF(A20="","",IF(C20+D20>B20+1,"⚠ Realizado + compromissos acima da projeção",IF(AND(FLUXO_MENSAL!G14>1,FLUXO_MENSAL!H14=0),"⚠ Saldo sem curva (preencha CURVA)",IF(ABS(G20)>1,"⚠ Verificar","OK")))) -> OK | I20: =FLUXO_MENSAL!I14-F20 -> 0
A21: =FLUXO_MENSAL!B15 -> TRANSPORTES | B21: =FLUXO_MENSAL!D15 -> 817599.43 | C21: =FLUXO_MENSAL!E15 -> 70284.77 | D21: =FLUXO_MENSAL!F15 -> 2017.36 | E21: =IF(FLUXO_MENSAL!H15>0,FLUXO_MENSAL!G15,0) -> 745297.3 | F21: =C21+D21+E21 -> 817599.43 | G21: =B21-F21 -> 0 | H21: =IF(A21="","",IF(C21+D21>B21+1,"⚠ Realizado + compromissos acima da projeção",IF(AND(FLUXO_MENSAL!G15>1,FLUXO_MENSAL!H15=0),"⚠ Saldo sem curva (preencha CURVA)",IF(ABS(G21)>1,"⚠ Verificar","OK")))) -> OK | I21: =FLUXO_MENSAL!I15-F21 -> 0
A22: =FLUXO_MENSAL!B16 -> CONSULTORIAS (OBRAS) | B22: =FLUXO_MENSAL!D16 -> 1371532.1 | C22: =FLUXO_MENSAL!E16 -> 674559.83 | D22: =FLUXO_MENSAL!F16 -> 25028.91 | E22: =IF(FLUXO_MENSAL!H16>0,FLUXO_MENSAL!G16,0) -> 671943.37 | F22: =C22+D22+E22 -> 1371532.1 | G22: =B22-F22 -> 0 | H22: =IF(A22="","",IF(C22+D22>B22+1,"⚠ Realizado + compromissos acima da projeção",IF(AND(FLUXO_MENSAL!G16>1,FLUXO_MENSAL!H16=0),"⚠ Saldo sem curva (preencha CURVA)",IF(ABS(G22)>1,"⚠ Verificar","OK")))) -> OK | I22: =FLUXO_MENSAL!I16-F22 -> 0
A23: =FLUXO_MENSAL!B17 -> MÃO DE OBRA PRÓPRIA | B23: =FLUXO_MENSAL!D17 -> 21271106 | C23: =FLUXO_MENSAL!E17 -> 3300360.2 | D23: =FLUXO_MENSAL!F17 -> 475302.52 | E23: =IF(FLUXO_MENSAL!H17>0,FLUXO_MENSAL!G17,0) -> 17495443 | F23: =C23+D23+E23 -> 21271106 | G23: =B23-F23 -> 0 | H23: =IF(A23="","",IF(C23+D23>B23+1,"⚠ Realizado + compromissos acima da projeção",IF(AND(FLUXO_MENSAL!G17>1,FLUXO_MENSAL!H17=0),"⚠ Saldo sem curva (preencha CURVA)",IF(ABS(G23)>1,"⚠ Verificar","OK")))) -> OK | I23: =FLUXO_MENSAL!I17-F23 -> 0
A24: =FLUXO_MENSAL!B18 -> EQUIPAMENTOS E FERRAMENTAS | B24: =FLUXO_MENSAL!D18 -> 6774432.9 | C24: =FLUXO_MENSAL!E18 -> 543667.72 | D24: =FLUXO_MENSAL!F18 -> 102156.96 | E24: =IF(FLUXO_MENSAL!H18>0,FLUXO_MENSAL!G18,0) -> 6128608.3 | F24: =C24+D24+E24 -> 6774432.9 | G24: =B24-F24 -> 0 | H24: =IF(A24="","",IF(C24+D24>B24+1,"⚠ Realizado + compromissos acima da projeção",IF(AND(FLUXO_MENSAL!G18>1,FLUXO_MENSAL!H18=0),"⚠ Saldo sem curva (preencha CURVA)",IF(ABS(G24)>1,"⚠ Verificar","OK")))) -> OK | I24: =FLUXO_MENSAL!I18-F24 -> 0
A25: =FLUXO_MENSAL!B19 -> SERVIÇOS INICIAIS | B25: =FLUXO_MENSAL!D19 -> 176378.52 | C25: =FLUXO_MENSAL!E19 -> 108365.04 | D25: =FLUXO_MENSAL!F19 -> 6706 | E25: =IF(FLUXO_MENSAL!H19>0,FLUXO_MENSAL!G19,0) -> 61307.48 | F25: =C25+D25+E25 -> 176378.52 | G25: =B25-F25 -> 0 | H25: =IF(A25="","",IF(C25+D25>B25+1,"⚠ Realizado + compromissos acima da projeção",IF(AND(FLUXO_MENSAL!G19>1,FLUXO_MENSAL!H19=0),"⚠ Saldo sem curva (preencha CURVA)",IF(ABS(G25)>1,"⚠ Verificar","OK")))) -> OK | I25: =FLUXO_MENSAL!I19-F25 -> 0
... A63: =FLUXO_MENSAL!B57 | B63: =FLUXO_MENSAL!D57 -> 0 | C63: =FLUXO_MENSAL!E57 -> 0 | D63: =FLUXO_MENSAL!F57 -> 0 | E63: =IF(FLUXO_MENSAL!H57>0,FLUXO_MENSAL!G57,0) -> 0 | F63: =C63+D63+E63 -> 0 | G63: =B63-F63 -> 0 | H63: =IF(A63="","",IF(C63+D63>B63+1,"⚠ Realizado + compromissos acima da projeção",IF(AND(FLUXO_MENSAL!G57>1,FLUXO_MENSAL!H57=0),"⚠ Saldo sem curva (preencha CURVA)",IF(ABS(G63)>1,"⚠ Verificar","OK")))) | I63: =FLUXO_MENSAL!I57-F63 -> 0
A64: TOTAL | B64: =SUM(B14:B63) -> 1.5933311e+08 | C64: =SUM(C14:C63) -> 21047425 | D64: =SUM(D14:D63) -> 3113839.3 | E64: =SUM(E14:E63) -> 1.3472967e+08 | F64: =SUM(F14:F63) -> 1.5889094e+08 | G64: =SUM(G14:G63) -> 442170.81 | I64: =SUM(I14:I63) -> 0

Sheet FLUXO_MENSAL
A1: Fluxo de caixa mensal por disciplina (R$)
A2: Realizado até a data de corte; depois = compromissos + saldo distribuído pela CURVA × fator de reajuste. Não editar.
H5: Situação → | J5: =IF(J$7<=PARAMETROS!$C$12,"Realizado","Projetado") -> Realizado | K5: =IF(K$7<=PARAMETROS!$C$12,"Realizado","Projetado") -> Realizado | L5: =IF(L$7<=PARAMETROS!$C$12,"Realizado","Projetado") -> Realizado | M5: =IF(M$7<=PARAMETROS!$C$12,"Realizado","Projetado") -> Realizado | N5: =IF(N$7<=PARAMETROS!$C$12,"Realizado","Projetado") -> Realizado | O5: =IF(O$7<=PARAMETROS!$C$12,"Realizado","Projetado") -> Realizado | P5: =IF(P$7<=PARAMETROS!$C$12,"Realizado","Projetado") -> Realizado | Q5: =IF(Q$7<=PARAMETROS!$C$12,"Realizado","Projetado") -> Realizado | ... CC5: =IF(CC$7<=PARAMETROS!$C$12,"Realizado","Projetado") -> Projetado
H6: Fator de reajuste → | J6: =IF(J$7<=PARAMETROS!$C$12,1,(1+PARAMETROS!$C$8)^(((YEAR(J$7)-YEAR(PARAMETROS!$C$12))*12+MONTH(J$7)-MONTH(PARAMETROS!$C$12))/12)) -> 1 | K6: =IF(K$7<=PARAMETROS!$C$12,1,(1+PARAMETROS!$C$8)^(((YEAR(K$7)-YEAR(PARAMETROS!$C$12))*12+MONTH(K$7)-MONTH(PARAMETROS!$C$12))/12)) -> 1 | L6: =IF(L$7<=PARAMETROS!$C$12,1,(1+PARAMETROS!$C$8)^(((YEAR(L$7)-YEAR(PARAMETROS!$C$12))*12+MONTH(L$7)-MONTH(PARAMETROS!$C$12))/12)) -> 1 | M6: =IF(M$7<=PARAMETROS!$C$12,1,(1+PARAMETROS!$C$8)^(((YEAR(M$7)-YEAR(PARAMETROS!$C$12))*12+MONTH(M$7)-MONTH(PARAMETROS!$C$12))/12)) -> 1 | N6: =IF(N$7<=PARAMETROS!$C$12,1,(1+PARAMETROS!$C$8)^(((YEAR(N$7)-YEAR(PARAMETROS!$C$12))*12+MONTH(N$7)-MONTH(PARAMETROS!$C$12))/12)) -> 1 | O6: =IF(O$7<=PARAMETROS!$C$12,1,(1+PARAMETROS!$C$8)^(((YEAR(O$7)-YEAR(PARAMETROS!$C$12))*12+MONTH(O$7)-MONTH(PARAMETROS!$C$12))/12)) -> 1 | P6: =IF(P$7<=PARAMETROS!$C$12,1,(1+PARAMETROS!$C$8)^(((YEAR(P$7)-YEAR(PARAMETROS!$C$12))*12+MONTH(P$7)-MONTH(PARAMETROS!$C$12))/12)) -> 1 | Q6: =IF(Q$7<=PARAMETROS!$C$12,1,(1+PARAMETROS!$C$8)^(((YEAR(Q$7)-YEAR(PARAMETROS!$C$12))*12+MONTH(Q$7)-MONTH(PARAMETROS!$C$12))/12)) -> 1 | ... CC6: =IF(CC$7<=PARAMETROS!$C$12,1,(1+PARAMETROS!$C$8)^(((YEAR(CC$7)-YEAR(PARAMETROS!$C$12))*12+MONTH(CC$7)-MONTH(PARAMETROS!$C$12))/12)) -> 1
A7: Código | B7: Disciplina | C7: Grupo | D7: Projeção (R$) | E7: Realizado até o corte | F7: Compromissos após o corte | G7: Saldo a distribuir | H7: Σ pesos futuros | I7: Total no fluxo | J7: =PARAMETROS!$C$11 -> 45627 | K7: =DATE(YEAR(J7),MONTH(J7)+1,1) -> 45658 | L7: =DATE(YEAR(K7),MONTH(K7)+1,1) -> 45689 | M7: =DATE(YEAR(L7),MONTH(L7)+1,1) -> 45717 | N7: =DATE(YEAR(M7),MONTH(M7)+1,1) -> 45748 | O7: =DATE(YEAR(N7),MONTH(N7)+1,1) -> 45778 | P7: =DATE(YEAR(O7),MONTH(O7)+1,1) -> 45809 | Q7: =DATE(YEAR(P7),MONTH(P7)+1,1) -> 45839 | R7: =DATE(YEAR(Q7),MONTH(Q7)+1,1) -> 45870 | ... CC7: =DATE(YEAR(CB7),MONTH(CB7)+1,1) -> 47788
A8: =IF(ORCAMENTO!A6="","",ORCAMENTO!A6) -> 01 | B8: =IF(ORCAMENTO!B6="","",ORCAMENTO!B6) -> PROJETOS | C8: =IF(ORCAMENTO!C6="","",ORCAMENTO!C6) -> INDIRETOS | D8: =IF($B8="",0,ORCAMENTO!E6) -> 2640655 | E8: =IF($B8="",0,SUMIFS(INCORRIDO!$C$6:$C$5005,INCORRIDO!$D$6:$D$5005,$B8,INCORRIDO!$E$6:$E$5005,"<="&PARAMETROS!$C$12)) -> 2106293.6 | F8: =IF($B8="",0,SUMIFS(INCORRIDO!$C$6:$C$5005,INCORRIDO!$D$6:$D$5005,$B8,INCORRIDO!$E$6:$E$5005,">"&PARAMETROS!$C$12)) -> 1046.09 | G8: =MAX(0,D8-E8-F8) -> 533315.27 | H8: =CURVA!H8 -> 533315.27 | I8: =SUM(J8:CC8) -> 2640655 | J8: =IF($B8="",0,SUMIFS(INCORRIDO!$C$6:$C$5005,INCORRIDO!$D$6:$D$5005,$B8,INCORRIDO!$E$6:$E$5005,"<="&J$7)+IF(J$7>PARAMETROS!$C$12,IF($H8>0,$G8*CURVA!J8/$H8,0)*J$6,0)) -> 418594.15 | K8: =IF($B8="",0,SUMIFS(INCORRIDO!$C$6:$C$5005,INCORRIDO!$D$6:$D$5005,$B8,INCORRIDO!$E$6:$E$5005,K$7)+IF(K$7>PARAMETROS!$C$12,IF($H8>0,$G8*CURVA!K8/$H8,0)*K$6,0)) -> 10917.03 | L8: =IF($B8="",0,SUMIFS(INCORRIDO!$C$6:$C$5005,INCORRIDO!$D$6:$D$5005,$B8,INCORRIDO!$E$6:$E$5005,L$7)+IF(L$7>PARAMETROS!$C$12,IF($H8>0,$G8*CURVA!L8/$H8,0)*L$6,0)) -> 263811.08 | M8: =IF($B8="",0,SUMIFS(INCORRIDO!$C$6:$C$5005,INCORRIDO!$D$6:$D$5005,$B8,INCORRIDO!$E$6:$E$5005,M$7)+IF(M$7>PARAMETROS!$C$12,IF($H8>0,$G8*CURVA!M8/$H8,0)*M$6,0)) -> 95377.59 | N8: =IF($B8="",0,SUMIFS(INCORRIDO!$C$6:$C$5005,INCORRIDO!$D$6:$D$5005,$B8,INCORRIDO!$E$6:$E$5005,N$7)+IF(N$7>PARAMETROS!$C$12,IF($H8>0,$G8*CURVA!N8/$H8,0)*N$6,0)) -> 152105.86 | O8: =IF($B8="",0,SUMIFS(INCORRIDO!$C$6:$C$5005,INCORRIDO!$D$6:$D$5005,$B8,INCORRIDO!$E$6:$E$5005,O$7)+IF(O$7>PARAMETROS!$C$12,IF($H8>0,$G8*CURVA!O8/$H8,0)*O$6,0)) -> 202477.1 | P8: =IF($B8="",0,SUMIFS(INCORRIDO!$C$6:$C$5005,INCORRIDO!$D$6:$D$5005,$B8,INCORRIDO!$E$6:$E$5005,P$7)+IF(P$7>PARAMETROS!$C$12,IF($H8>0,$G8*CURVA!P8/$H8,0)*P$6,0)) -> 65133.61 | Q8: =IF($B8="",0,SUMIFS(INCORRIDO!$C$6:$C$5005,INCORRIDO!$D$6:$D$5005,$B8,INCORRIDO!$E$6:$E$5005,Q$7)+IF(Q$7>PARAMETROS!$C$12,IF($H8>0,$G8*CURVA!Q8/$H8,0)*Q$6,0)) -> 46336.42 | R8: =IF($B8="",0,SUMIFS(INCORRIDO!$C$6:$C$5005,INCORRIDO!$D$6:$D$5005,$B8,INCORRIDO!$E$6:$E$5005,R$7)+IF(R$7>PARAMETROS!$C$12,IF($H8>0,$G8*CURVA!R8/$H8,0)*R$6,0)) -> 89390.73 | ... CC8: =IF($B8="",0,SUMIFS(INCORRIDO!$C$6:$C$5005,INCORRIDO!$D$6:$D$5005,$B8,INCORRIDO!$E$6:$E$5005,CC$7)+IF(CC$7>PARAMETROS!$C$12,IF($H8>0,$G8*CURVA!CC8/$H8,0)*CC$6,0)) -> 0
A9: =IF(ORCAMENTO!A7="","",ORCAMENTO!A7) -> 02 | B9: =IF(ORCAMENTO!B7="","",ORCAMENTO!B7) -> SEGUROS | C9: =IF(ORCAMENTO!C7="","",ORCAMENTO!C7) -> INDIRETOS | D9: =IF($B9="",0,ORCAMENTO!E7) -> 127911.99 | E9: =IF($B9="",0,SUMIFS(INCORRIDO!$C$6:$C$5005,INCORRIDO!$D$6:$D$5005,$B9,INCORRIDO!$E$6:$E$5005,"<="&PARAMETROS!$C$12)) -> 0 | F9: =IF($B9="",0,SUMIFS(INCORRIDO!$C$6:$C$5005,INCORRIDO!$D$6:$D$5005,$B9,INCORRIDO!$E$6:$E$5005,">"&PARAMETROS!$C$12)) -> 0 | G9: =MAX(0,D9-E9-F9) -> 127911.99 | H9: =CURVA!H9 -> 0 | I9: =SUM(J9:CC9) -> 0 | J9: =IF($B9="",0,SUMIFS(INCORRIDO!$C$6:$C$5005,INCORRIDO!$D$6:$D$5005,$B9,INCORRIDO!$E$6:$E$5005,"<="&J$7)+IF(J$7>PARAMETROS!$C$12,IF($H9>0,$G9*CURVA!J9/$H9,0)*J$6,0)) -> 0 | K9: =IF($B9="",0,SUMIFS(INCORRIDO!$C$6:$C$5005,INCORRIDO!$D$6:$D$5005,$B9,INCORRIDO!$E$6:$E$5005,K$7)+IF(K$7>PARAMETROS!$C$12,IF($H9>0,$G9*CURVA!K9/$H9,0)*K$6,0)) -> 0 | L9: =IF($B9="",0,SUMIFS(INCORRIDO!$C$6:$C$5005,INCORRIDO!$D$6:$D$5005,$B9,INCORRIDO!$E$6:$E$5005,L$7)+IF(L$7>PARAMETROS!$C$12,IF($H9>0,$G9*CURVA!L9/$H9,0)*L$6,0)) -> 0 | M9: =IF($B9="",0,SUMIFS(INCORRIDO!$C$6:$C$5005,INCORRIDO!$D$6:$D$5005,$B9,INCORRIDO!$E$6:$E$5005,M$7)+IF(M$7>PARAMETROS!$C$12,IF($H9>0,$G9*CURVA!M9/$H9,0)*M$6,0)) -> 0 | N9: =IF($B9="",0,SUMIFS(INCORRIDO!$C$6:$C$5005,INCORRIDO!$D$6:$D$5005,$B9,INCORRIDO!$E$6:$E$5005,N$7)+IF(N$7>PARAMETROS!$C$12,IF($H9>0,$G9*CURVA!N9/$H9,0)*N$6,0)) -> 0 | O9: =IF($B9="",0,SUMIFS(INCORRIDO!$C$6:$C$5005,INCORRIDO!$D$6:$D$5005,$B9,INCORRIDO!$E$6:$E$5005,O$7)+IF(O$7>PARAMETROS!$C$12,IF($H9>0,$G9*CURVA!O9/$H9,0)*O$6,0)) -> 0 | P9: =IF($B9="",0,SUMIFS(INCORRIDO!$C$6:$C$5005,INCORRIDO!$D$6:$D$5005,$B9,INCORRIDO!$E$6:$E$5005,P$7)+IF(P$7>PARAMETROS!$C$12,IF($H9>0,$G9*CURVA!P9/$H9,0)*P$6,0)) -> 0 | Q9: =IF($B9="",0,SUMIFS(INCORRIDO!$C$6:$C$5005,INCORRIDO!$D$6:$D$5005,$B9,INCORRIDO!$E$6:$E$5005,Q$7)+IF(Q$7>PARAMETROS!$C$12,IF($H9>0,$G9*CURVA!Q9/$H9,0)*Q$6,0)) -> 0 | R9: =IF($B9="",0,SUMIFS(INCORRIDO!$C$6:$C$5005,INCORRIDO!$D$6:$D$5005,$B9,INCORRIDO!$E$6:$E$5005,R$7)+IF(R$7>PARAMETROS!$C$12,IF($H9>0,$G9*CURVA!R9/$H9,0)*R$6,0)) -> 0 | ... CC9: =IF($B9="",0,SUMIFS(INCORRIDO!$C$6:$C$5005,INCORRIDO!$D$6:$D$5005,$B9,INCORRIDO!$E$6:$E$5005,CC$7)+IF(CC$7>PARAMETROS!$C$12,IF($H9>0,$G9*CURVA!CC9/$H9,0)*CC$6,0)) -> 0
A10: =IF(ORCAMENTO!A8="","",ORCAMENTO!A8) -> 03 | B10: =IF(ORCAMENTO!B8="","",ORCAMENTO!B8) -> TAXAS DIVERSAS | C10: =IF(ORCAMENTO!C8="","",ORCAMENTO!C8) -> INDIRETOS | D10: =IF($B10="",0,ORCAMENTO!E8) -> 158047.46 | E10: =IF($B10="",0,SUMIFS(INCORRIDO!$C$6:$C$5005,INCORRIDO!$D$6:$D$5005,$B10,INCORRIDO!$E$6:$E$5005,"<="&PARAMETROS!$C$12)) -> 5905.19 | F10: =IF($B10="",0,SUMIFS(INCORRIDO!$C$6:$C$5005,INCORRIDO!$D$6:$D$5005,$B10,INCORRIDO!$E$6:$E$5005,">"&PARAMETROS!$C$12)) -> 0 | G10: =MAX(0,D10-E10-F10) -> 152142.27 | H10: =CURVA!H10 -> 151217.5 | I10: =SUM(J10:CC10) -> 158047.46 | J10: =IF($B10="",0,SUMIFS(INCORRIDO!$C$6:$C$5005,INCORRIDO!$D$6:$D$5005,$B10,INCORRIDO!$E$6:$E$5005,"<="&J$7)+IF(J$7>PARAMETROS!$C$12,IF($H10>0,$G10*CURVA!J10/$H10,0)*J$6,0)) -> 154.1 | K10: =IF($B10="",0,SUMIFS(INCORRIDO!$C$6:$C$5005,INCORRIDO!$D$6:$D$5005,$B10,INCORRIDO!$E$6:$E$5005,K$7)+IF(K$7>PARAMETROS!$C$12,IF($H10>0,$G10*CURVA!K10/$H10,0)*K$6,0)) -> 40.62 | L10: =IF($B10="",0,SUMIFS(INCORRIDO!$C$6:$C$5005,INCORRIDO!$D$6:$D$5005,$B10,INCORRIDO!$E$6:$E$5005,L$7)+IF(L$7>PARAMETROS!$C$12,IF($H10>0,$G10*CURVA!L10/$H10,0)*L$6,0)) -> 0 | M10: =IF($B10="",0,SUMIFS(INCORRIDO!$C$6:$C$5005,INCORRIDO!$D$6:$D$5005,$B10,INCORRIDO!$E$6:$E$5005,M$7)+IF(M$7>PARAMETROS!$C$12,IF($H10>0,$G10*CURVA!M10/$H10,0)*M$6,0)) -> 0 | N10: =IF($B10="",0,SUMIFS(INCORRIDO!$C$6:$C$5005,INCORRIDO!$D$6:$D$5005,$B10,INCORRIDO!$E$6:$E$5005,N$7)+IF(N$7>PARAMETROS!$C$12,IF($H10>0,$G10*CURVA!N10/$H10,0)*N$6,0)) -> 0 | O10: =IF($B10="",0,SUMIFS(INCORRIDO!$C$6:$C$5005,INCORRIDO!$D$6:$D$5005,$B10,INCORRIDO!$E$6:$E$5005,O$7)+IF(O$7>PARAMETROS!$C$12,IF($H10>0,$G10*CURVA!O10/$H10,0)*O$6,0)) -> 0 | P10: =IF($B10="",0,SUMIFS(INCORRIDO!$C$6:$C$5005,INCORRIDO!$D$6:$D$5005,$B10,INCORRIDO!$E$6:$E$5005,P$7)+IF(P$7>PARAMETROS!$C$12,IF($H10>0,$G10*CURVA!P10/$H10,0)*P$6,0)) -> 64.24 | Q10: =IF($B10="",0,SUMIFS(INCORRIDO!$C$6:$C$5005,INCORRIDO!$D$6:$D$5005,$B10,INCORRIDO!$E$6:$E$5005,Q$7)+IF(Q$7>PARAMETROS!$C$12,IF($H10>0,$G10*CURVA!Q10/$H10,0)*Q$6,0)) -> 0 | R10: =IF($B10="",0,SUMIFS(INCORRIDO!$C$6:$C$5005,INCORRIDO!$D$6:$D$5005,$B10,INCORRIDO!$E$6:$E$5005,R$7)+IF(R$7>PARAMETROS!$C$12,IF($H10>0,$G10*CURVA!R10/$H10,0)*R$6,0)) -> 0 | ... CC10: =IF($B10="",0,SUMIFS(INCORRIDO!$C$6:$C$5005,INCORRIDO!$D$6:$D$5005,$B10,INCORRIDO!$E$6:$E$5005,CC$7)+IF(CC$7>PARAMETROS!$C$12,IF($H10>0,$G10*CURVA!CC10/$H10,0)*CC$6,0)) -> 0
A11: =IF(ORCAMENTO!A9="","",ORCAMENTO!A9) -> 04 | B11: =IF(ORCAMENTO!B9="","",ORCAMENTO!B9) -> BARRACAO DE OBRA | C11: =IF(ORCAMENTO!C9="","",ORCAMENTO!C9) -> INDIRETOS | D11: =IF($B11="",0,ORCAMENTO!E9) -> 1249911.1 | E11: =IF($B11="",0,SUMIFS(INCORRIDO!$C$6:$C$5005,INCORRIDO!$D$6:$D$5005,$B11,INCORRIDO!$E$6:$E$5005,"<="&PARAMETROS!$C$12)) -> 631109.61 | F11: =IF($B11="",0,SUMIFS(INCORRIDO!$C$6:$C$5005,INCORRIDO!$D$6:$D$5005,$B11,INCORRIDO!$E$6:$E$5005,">"&PARAMETROS!$C$12)) -> 21690.09 | G11: =MAX(0,D11-E11-F11) -> 597111.37 | H11: =CURVA!H11 -> 597111.3 | I11: =SUM(J11:CC11) -> 1249911.1 | J11: =IF($B11="",0,SUMIFS(INCORRIDO!$C$6:$C$5005,INCORRIDO!$D$6:$D$5005,$B11,INCORRIDO!$E$6:$E$5005,"<="&J$7)+IF(J$7>PARAMETROS!$C$12,IF($H11>0,$G11*CURVA!J11/$H11,0)*J$6,0)) -> 61380.97 | K11: =IF($B11="",0,SUMIFS(INCORRIDO!$C$6:$C$5005,INCORRIDO!$D$6:$D$5005,$B11,INCORRIDO!$E$6:$E$5005,K$7)+IF(K$7>PARAMETROS!$C$12,IF($H11>0,$G11*CURVA!K11/$H11,0)*K$6,0)) -> 0 | L11: =IF($B11="",0,SUMIFS(INCORRIDO!$C$6:$C$5005,INCORRIDO!$D$6:$D$5005,$B11,INCORRIDO!$E$6:$E$5005,L$7)+IF(L$7>PARAMETROS!$C$12,IF($H11>0,$G11*CURVA!L11/$H11,0)*L$6,0)) -> 0 | M11: =IF($B11="",0,SUMIFS(INCORRIDO!$C$6:$C$5005,INCORRIDO!$D$6:$D$5005,$B11,INCORRIDO!$E$6:$E$5005,M$7)+IF(M$7>PARAMETROS!$C$12,IF($H11>0,$G11*CURVA!M11/$H11,0)*M$6,0)) -> 0 | N11: =IF($B11="",0,SUMIFS(INCORRIDO!$C$6:$C$5005,INCORRIDO!$D$6:$D$5005,$B11,INCORRIDO!$E$6:$E$5005,N$7)+IF(N$7>PARAMETROS!$C$12,IF($H11>0,$G11*CURVA!N11/$H11,0)*N$6,0)) -> 0 | O11: =IF($B11="",0,SUMIFS(INCORRIDO!$C$6:$C$5005,INCORRIDO!$D$6:$D$5005,$B11,INCORRIDO!$E$6:$E$5005,O$7)+IF(O$7>PARAMETROS!$C$12,IF($H11>0,$G11*CURVA!O11/$H11,0)*O$6,0)) -> 0 | P11: =IF($B11="",0,SUMIFS(INCORRIDO!$C$6:$C$5005,INCORRIDO!$D$6:$D$5005,$B11,INCORRIDO!$E$6:$E$5005,P$7)+IF(P$7>PARAMETROS!$C$12,IF($H11>0,$G11*CURVA!P11/$H11,0)*P$6,0)) -> 61557.78 | Q11: =IF($B11="",0,SUMIFS(INCORRIDO!$C$6:$C$5005,INCORRIDO!$D$6:$D$5005,$B11,INCORRIDO!$E$6:$E$5005,Q$7)+IF(Q$7>PARAMETROS!$C$12,IF($H11>0,$G11*CURVA!Q11/$H11,0)*Q$6,0)) -> 70633.03 | R11: =IF($B11="",0,SUMIFS(INCORRIDO!$C$6:$C$5005,INCORRIDO!$D$6:$D$5005,$B11,INCORRIDO!$E$6:$E$5005,R$7)+IF(R$7>PARAMETROS!$C$12,IF($H11>0,$G11*CURVA!R11/$H11,0)*R$6,0)) -> 66792.52 | ... CC11: =IF($B11="",0,SUMIFS(INCORRIDO!$C$6:$C$5005,INCORRIDO!$D$6:$D$5005,$B11,INCORRIDO!$E$6:$E$5005,CC$7)+IF(CC$7>PARAMETROS!$C$12,IF($H11>0,$G11*CURVA!CC11/$H11,0)*CC$6,0)) -> 0
A12: =IF(ORCAMENTO!A10="","",ORCAMENTO!A10) -> 05 | B12: =IF(ORCAMENTO!B10="","",ORCAMENTO!B10) -> LIGAÇÕES PROVISÓRIAS AGUA, ENERGIA,TELEFONIA, ESGOTO | C12: =IF(ORCAMENTO!C10="","",ORCAMENTO!C10) -> INDIRETOS | D12: =IF($B12="",0,ORCAMENTO!E10) -> 85665.05 | E12: =IF($B12="",0,SUMIFS(INCORRIDO!$C$6:$C$5005,INCORRIDO!$D$6:$D$5005,$B12,INCORRIDO!$E$6:$E$5005,"<="&PARAMETROS!$C$12)) -> 0 | F12: =IF($B12="",0,SUMIFS(INCORRIDO!$C$6:$C$5005,INCORRIDO!$D$6:$D$5005,$B12,INCORRIDO!$E$6:$E$5005,">"&PARAMETROS!$C$12)) -> 0 | G12: =MAX(0,D12-E12-F12) -> 85665.05 | H12: =CURVA!H12 -> 0 | I12: =SUM(J12:CC12) -> 0 | J12: =IF($B12="",0,SUMIFS(INCORRIDO!$C$6:$C$5005,INCORRIDO!$D$6:$D$5005,$B12,INCORRIDO!$E$6:$E$5005,"<="&J$7)+IF(J$7>PARAMETROS!$C$12,IF($H12>0,$G12*CURVA!J12/$H12,0)*J$6,0)) -> 0 | K12: =IF($B12="",0,SUMIFS(INCORRIDO!$C$6:$C$5005,INCORRIDO!$D$6:$D$5005,$B12,INCORRIDO!$E$6:$E$5005,K$7)+IF(K$7>PARAMETROS!$C$12,IF($H12>0,$G12*CURVA!K12/$H12,0)*K$6,0)) -> 0 | L12: =IF($B12="",0,SUMIFS(INCORRIDO!$C$6:$C$5005,INCORRIDO!$D$6:$D$5005,$B12,INCORRIDO!$E$6:$E$5005,L$7)+IF(L$7>PARAMETROS!$C$12,IF($H12>0,$G12*CURVA!L12/$H12,0)*L$6,0)) -> 0 | M12: =IF($B12="",0,SUMIFS(INCORRIDO!$C$6:$C$5005,INCORRIDO!$D$6:$D$5005,$B12,INCORRIDO!$E$6:$E$5005,M$7)+IF(M$7>PARAMETROS!$C$12,IF($H12>0,$G12*CURVA!M12/$H12,0)*M$6,0)) -> 0 | N12: =IF($B12="",0,SUMIFS(INCORRIDO!$C$6:$C$5005,INCORRIDO!$D$6:$D$5005,$B12,INCORRIDO!$E$6:$E$5005,N$7)+IF(N$7>PARAMETROS!$C$12,IF($H12>0,$G12*CURVA!N12/$H12,0)*N$6,0)) -> 0 | O12: =IF($B12="",0,SUMIFS(INCORRIDO!$C$6:$C$5005,INCORRIDO!$D$6:$D$5005,$B12,INCORRIDO!$E$6:$E$5005,O$7)+IF(O$7>PARAMETROS!$C$12,IF($H12>0,$G12*CURVA!O12/$H12,0)*O$6,0)) -> 0 | P12: =IF($B12="",0,SUMIFS(INCORRIDO!$C$6:$C$5005,INCORRIDO!$D$6:$D$5005,$B12,INCORRIDO!$E$6:$E$5005,P$7)+IF(P$7>PARAMETROS!$C$12,IF($H12>0,$G12*CURVA!P12/$H12,0)*P$6,0)) -> 0 | Q12: =IF($B12="",0,SUMIFS(INCORRIDO!$C$6:$C$5005,INCORRIDO!$D$6:$D$5005,$B12,INCORRIDO!$E$6:$E$5005,Q$7)+IF(Q$7>PARAMETROS!$C$12,IF($H12>0,$G12*CURVA!Q12/$H12,0)*Q$6,0)) -> 0 | R12: =IF($B12="",0,SUMIFS(INCORRIDO!$C$6:$C$5005,INCORRIDO!$D$6:$D$5005,$B12,INCORRIDO!$E$6:$E$5005,R$7)+IF(R$7>PARAMETROS!$C$12,IF($H12>0,$G12*CURVA!R12/$H12,0)*R$6,0)) -> 0 | ... CC12: =IF($B12="",0,SUMIFS(INCORRIDO!$C$6:$C$5005,INCORRIDO!$D$6:$D$5005,$B12,INCORRIDO!$E$6:$E$5005,CC$7)+IF(CC$7>PARAMETROS!$C$12,IF($H12>0,$G12*CURVA!CC12/$H12,0)*CC$6,0)) -> 0
A13: =IF(ORCAMENTO!A11="","",ORCAMENTO!A11) -> 06 | B13: =IF(ORCAMENTO!B11="","",ORCAMENTO!B11) -> CONSUMO DE ÁGUA, ENERGIA, ETC. | C13: =IF(ORCAMENTO!C11="","",ORCAMENTO!C11) -> INDIRETOS | D13: =IF($B13="",0,ORCAMENTO!E11) -> 544229.22 | E13: =IF($B13="",0,SUMIFS(INCORRIDO!$C$6:$C$5005,INCORRIDO!$D$6:$D$5005,$B13,INCORRIDO!$E$6:$E$5005,"<="&PARAMETROS!$C$12)) -> 36058.03 | F13: =IF($B13="",0,SUMIFS(INCORRIDO!$C$6:$C$5005,INCORRIDO!$D$6:$D$5005,$B13,INCORRIDO!$E$6:$E$5005,">"&PARAMETROS!$C$12)) -> 10197.92 | G13: =MAX(0,D13-E13-F13) -> 497973.27 | H13: =CURVA!H13 -> 494508.3 | I13: =SUM(J13:CC13) -> 544229.22 | J13: =IF($B13="",0,SUMIFS(INCORRIDO!$C$6:$C$5005,INCORRIDO!$D$6:$D$5005,$B13,INCORRIDO!$E$6:$E$5005,"<="&J$7)+IF(J$7>PARAMETROS!$C$12,IF($H13>0,$G13*CURVA!J13/$H13,0)*J$6,0)) -> 0 | K13: =IF($B13="",0,SUMIFS(INCORRIDO!$C$6:$C$5005,INCORRIDO!$D$6:$D$5005,$B13,INCORRIDO!$E$6:$E$5005,K$7)+IF(K$7>PARAMETROS!$C$12,IF($H13>0,$G13*CURVA!K13/$H13,0)*K$6,0)) -> 0 | L13: =IF($B13="",0,SUMIFS(INCORRIDO!$C$6:$C$5005,INCORRIDO!$D$6:$D$5005,$B13,INCORRIDO!$E$6:$E$5005,L$7)+IF(L$7>PARAMETROS!$C$12,IF($H13>0,$G13*CURVA!L13/$H13,0)*L$6,0)) -> 0 | M13: =IF($B13="",0,SUMIFS(INCORRIDO!$C$6:$C$5005,INCORRIDO!$D$6:$D$5005,$B13,INCORRIDO!$E$6:$E$5005,M$7)+IF(M$7>PARAMETROS!$C$12,IF($H13>0,$G13*CURVA!M13/$H13,0)*M$6,0)) -> 0 | N13: =IF($B13="",0,SUMIFS(INCORRIDO!$C$6:$C$5005,INCORRIDO!$D$6:$D$5005,$B13,INCORRIDO!$E$6:$E$5005,N$7)+IF(N$7>PARAMETROS!$C$12,IF($H13>0,$G13*CURVA!N13/$H13,0)*N$6,0)) -> 0 | O13: =IF($B13="",0,SUMIFS(INCORRIDO!$C$6:$C$5005,INCORRIDO!$D$6:$D$5005,$B13,INCORRIDO!$E$6:$E$5005,O$7)+IF(O$7>PARAMETROS!$C$12,IF($H13>0,$G13*CURVA!O13/$H13,0)*O$6,0)) -> 0 | P13: =IF($B13="",0,SUMIFS(INCORRIDO!$C$6:$C$5005,INCORRIDO!$D$6:$D$5005,$B13,INCORRIDO!$E$6:$E$5005,P$7)+IF(P$7>PARAMETROS!$C$12,IF($H13>0,$G13*CURVA!P13/$H13,0)*P$6,0)) -> 0 | Q13: =IF($B13="",0,SUMIFS(INCORRIDO!$C$6:$C$5005,INCORRIDO!$D$6:$D$5005,$B13,INCORRIDO!$E$6:$E$5005,Q$7)+IF(Q$7>PARAMETROS!$C$12,IF($H13>0,$G13*CURVA!Q13/$H13,0)*Q$6,0)) -> 0 | R13: =IF($B13="",0,SUMIFS(INCORRIDO!$C$6:$C$5005,INCORRIDO!$D$6:$D$5005,$B13,INCORRIDO!$E$6:$E$5005,R$7)+IF(R$7>PARAMETROS!$C$12,IF($H13>0,$G13*CURVA!R13/$H13,0)*R$6,0)) -> 0 | ... CC13: =IF($B13="",0,SUMIFS(INCORRIDO!$C$6:$C$5005,INCORRIDO!$D$6:$D$5005,$B13,INCORRIDO!$E$6:$E$5005,CC$7)+IF(CC$7>PARAMETROS!$C$12,IF($H13>0,$G13*CURVA!CC13/$H13,0)*CC$6,0)) -> 0
A14: =IF(ORCAMENTO!A12="","",ORCAMENTO!A12) -> 07 | B14: =IF(ORCAMENTO!B12="","",ORCAMENTO!B12) -> DIVERSOS | C14: =IF(ORCAMENTO!C12="","",ORCAMENTO!C12) -> INDIRETOS | D14: =IF($B14="",0,ORCAMENTO!E12) -> 194480.67 | E14: =IF($B14="",0,SUMIFS(INCORRIDO!$C$6:$C$5005,INCORRIDO!$D$6:$D$5005,$B14,INCORRIDO!$E$6:$E$5005,"<="&PARAMETROS!$C$12)) -> 34023.01 | F14: =IF($B14="",0,SUMIFS(INCORRIDO!$C$6:$C$5005,INCORRIDO!$D$6:$D$5005,$B14,INCORRIDO!$E$6:$E$5005,">"&PARAMETROS!$C$12)) -> 5376.16 | G14: =MAX(0,D14-E14-F14) -> 155081.5 | H14: =CURVA!H14 -> 155081.47 | I14: =SUM(J14:CC14) -> 194480.67 | J14: =IF($B14="",0,SUMIFS(INCORRIDO!$C$6:$C$5005,INCORRIDO!$D$6:$D$5005,$B14,INCORRIDO!$E$6:$E$5005,"<="&J$7)+IF(J$7>PARAMETROS!$C$12,IF($H14>0,$G14*CURVA!J14/$H14,0)*J$6,0)) -> 7617.91 | K14: =IF($B14="",0,SUMIFS(INCORRIDO!$C$6:$C$5005,INCORRIDO!$D$6:$D$5005,$B14,INCORRIDO!$E$6:$E$5005,K$7)+IF(K$7>PARAMETROS!$C$12,IF($H14>0,$G14*CURVA!K14/$H14,0)*K$6,0)) -> 1467.74 | L14: =IF($B14="",0,SUMIFS(INCORRIDO!$C$6:$C$5005,INCORRIDO!$D$6:$D$5005,$B14,INCORRIDO!$E$6:$E$5005,L$7)+IF(L$7>PARAMETROS!$C$12,IF($H14>0,$G14*CURVA!L14/$H14,0)*L$6,0)) -> 0 | M14: =IF($B14="",0,SUMIFS(INCORRIDO!$C$6:$C$5005,INCORRIDO!$D$6:$D$5005,$B14,INCORRIDO!$E$6:$E$5005,M$7)+IF(M$7>PARAMETROS!$C$12,IF($H14>0,$G14*CURVA!M14/$H14,0)*M$6,0)) -> 0 | N14: =IF($B14="",0,SUMIFS(INCORRIDO!$C$6:$C$5005,INCORRIDO!$D$6:$D$5005,$B14,INCORRIDO!$E$6:$E$5005,N$7)+IF(N$7>PARAMETROS!$C$12,IF($H14>0,$G14*CURVA!N14/$H14,0)*N$6,0)) -> 66.6 | O14: =IF($B14="",0,SUMIFS(INCORRIDO!$C$6:$C$5005,INCORRIDO!$D$6:$D$5005,$B14,INCORRIDO!$E$6:$E$5005,O$7)+IF(O$7>PARAMETROS!$C$12,IF($H14>0,$G14*CURVA!O14/$H14,0)*O$6,0)) -> 0 | P14: =IF($B14="",0,SUMIFS(INCORRIDO!$C$6:$C$5005,INCORRIDO!$D$6:$D$5005,$B14,INCORRIDO!$E$6:$E$5005,P$7)+IF(P$7>PARAMETROS!$C$12,IF($H14>0,$G14*CURVA!P14/$H14,0)*P$6,0)) -> 0 | Q14: =IF($B14="",0,SUMIFS(INCORRIDO!$C$6:$C$5005,INCORRIDO!$D$6:$D$5005,$B14,INCORRIDO!$E$6:$E$5005,Q$7)+IF(Q$7>PARAMETROS!$C$12,IF($H14>0,$G14*CURVA!Q14/$H14,0)*Q$6,0)) -> 0 | R14: =IF($B14="",0,SUMIFS(INCORRIDO!$C$6:$C$5005,INCORRIDO!$D$6:$D$5005,$B14,INCORRIDO!$E$6:$E$5005,R$7)+IF(R$7>PARAMETROS!$C$12,IF($H14>0,$G14*CURVA!R14/$H14,0)*R$6,0)) -> 0 | ... CC14: =IF($B14="",0,SUMIFS(INCORRIDO!$C$6:$C$5005,INCORRIDO!$D$6:$D$5005,$B14,INCORRIDO!$E$6:$E$5005,CC$7)+IF(CC$7>PARAMETROS!$C$12,IF($H14>0,$G14*CURVA!CC14/$H14,0)*CC$6,0)) -> 0
A15: =IF(ORCAMENTO!A13="","",ORCAMENTO!A13) -> 08 | B15: =IF(ORCAMENTO!B13="","",ORCAMENTO!B13) -> TRANSPORTES | C15: =IF(ORCAMENTO!C13="","",ORCAMENTO!C13) -> INDIRETOS | D15: =IF($B15="",0,ORCAMENTO!E13) -> 817599.43 | E15: =IF($B15="",0,SUMIFS(INCORRIDO!$C$6:$C$5005,INCORRIDO!$D$6:$D$5005,$B15,INCORRIDO!$E$6:$E$5005,"<="&PARAMETROS!$C$12)) -> 70284.77 | F15: =IF($B15="",0,SUMIFS(INCORRIDO!$C$6:$C$5005,INCORRIDO!$D$6:$D$5005,$B15,INCORRIDO!$E$6:$E$5005,">"&PARAMETROS!$C$12)) -> 2017.36 | G15: =MAX(0,D15-E15-F15) -> 745297.3 | H15: =CURVA!H15 -> 745297.28 | I15: =SUM(J15:CC15) -> 817599.43 | J15: =IF($B15="",0,SUMIFS(INCORRIDO!$C$6:$C$5005,INCORRIDO!$D$6:$D$5005,$B15,INCORRIDO!$E$6:$E$5005,"<="&J$7)+IF(J$7>PARAMETROS!$C$12,IF($H15>0,$G15*CURVA!J15/$H15,0)*J$6,0)) -> 230 | K15: =IF($B15="",0,SUMIFS(INCORRIDO!$C$6:$C$5005,INCORRIDO!$D$6:$D$5005,$B15,INCORRIDO!$E$6:$E$5005,K$7)+IF(K$7>PARAMETROS!$C$12,IF($H15>0,$G15*CURVA!K15/$H15,0)*K$6,0)) -> 0 | L15: =IF($B15="",0,SUMIFS(INCORRIDO!$C$6:$C$5005,INCORRIDO!$D$6:$D$5005,$B15,INCORRIDO!$E$6:$E$5005,L$7)+IF(L$7>PARAMETROS!$C$12,IF($H15>0,$G15*CURVA!L15/$H15,0)*L$6,0)) -> 101.63 | M15: =IF($B15="",0,SUMIFS(INCORRIDO!$C$6:$C$5005,INCORRIDO!$D$6:$D$5005,$B15,INCORRIDO!$E$6:$E$5005,M$7)+IF(M$7>PARAMETROS!$C$12,IF($H15>0,$G15*CURVA!M15/$H15,0)*M$6,0)) -> 3.37 | N15: =IF($B15="",0,SUMIFS(INCORRIDO!$C$6:$C$5005,INCORRIDO!$D$6:$D$5005,$B15,INCORRIDO!$E$6:$E$5005,N$7)+IF(N$7>PARAMETROS!$C$12,IF($H15>0,$G15*CURVA!N15/$H15,0)*N$6,0)) -> 0 | O15: =IF($B15="",0,SUMIFS(INCORRIDO!$C$6:$C$5005,INCORRIDO!$D$6:$D$5005,$B15,INCORRIDO!$E$6:$E$5005,O$7)+IF(O$7>PARAMETROS!$C$12,IF($H15>0,$G15*CURVA!O15/$H15,0)*O$6,0)) -> 53.21 | P15: =IF($B15="",0,SUMIFS(INCORRIDO!$C$6:$C$5005,INCORRIDO!$D$6:$D$5005,$B15,INCORRIDO!$E$6:$E$5005,P$7)+IF(P$7>PARAMETROS!$C$12,IF($H15>0,$G15*CURVA!P15/$H15,0)*P$6,0)) -> 50.16 | Q15: =IF($B15="",0,SUMIFS(INCORRIDO!$C$6:$C$5005,INCORRIDO!$D$6:$D$5005,$B15,INCORRIDO!$E$6:$E$5005,Q$7)+IF(Q$7>PARAMETROS!$C$12,IF($H15>0,$G15*CURVA!Q15/$H15,0)*Q$6,0)) -> 1010.05 | R15: =IF($B15="",0,SUMIFS(INCORRIDO!$C$6:$C$5005,INCORRIDO!$D$6:$D$5005,$B15,INCORRIDO!$E$6:$E$5005,R$7)+IF(R$7>PARAMETROS!$C$12,IF($H15>0,$G15*CURVA!R15/$H15,0)*R$6,0)) -> 1873.32 | ... CC15: =IF($B15="",0,SUMIFS(INCORRIDO!$C$6:$C$5005,INCORRIDO!$D$6:$D$5005,$B15,INCORRIDO!$E$6:$E$5005,CC$7)+IF(CC$7>PARAMETROS!$C$12,IF($H15>0,$G15*CURVA!CC15/$H15,0)*CC$6,0)) -> 0
A16: =IF(ORCAMENTO!A14="","",ORCAMENTO!A14) -> 09 | B16: =IF(ORCAMENTO!B14="","",ORCAMENTO!B14) -> CONSULTORIAS (OBRAS) | C16: =IF(ORCAMENTO!C14="","",ORCAMENTO!C14) -> INDIRETOS | D16: =IF($B16="",0,ORCAMENTO!E14) -> 1371532.1 | E16: =IF($B16="",0,SUMIFS(INCORRIDO!$C$6:$C$5005,INCORRIDO!$D$6:$D$5005,$B16,INCORRIDO!$E$6:$E$5005,"<="&PARAMETROS!$C$12)) -> 674559.83 | F16: =IF($B16="",0,SUMIFS(INCORRIDO!$C$6:$C$5005,INCORRIDO!$D$6:$D$5005,$B16,INCORRIDO!$E$6:$E$5005,">"&PARAMETROS!$C$12)) -> 25028.91 | G16: =MAX(0,D16-E16-F16) -> 671943.37 | H16: =CURVA!H16 -> 671943.38 | I16: =SUM(J16:CC16) -> 1371532.1 | J16: =IF($B16="",0,SUMIFS(INCORRIDO!$C$6:$C$5005,INCORRIDO!$D$6:$D$5005,$B16,INCORRIDO!$E$6:$E$5005,"<="&J$7)+IF(J$7>PARAMETROS!$C$12,IF($H16>0,$G16*CURVA!J16/$H16,0)*J$6,0)) -> 43088.09 | K16: =IF($B16="",0,SUMIFS(INCORRIDO!$C$6:$C$5005,INCORRIDO!$D$6:$D$5005,$B16,INCORRIDO!$E$6:$E$5005,K$7)+IF(K$7>PARAMETROS!$C$12,IF($H16>0,$G16*CURVA!K16/$H16,0)*K$6,0)) -> 0 | L16: =IF($B16="",0,SUMIFS(INCORRIDO!$C$6:$C$5005,INCORRIDO!$D$6:$D$5005,$B16,INCORRIDO!$E$6:$E$5005,L$7)+IF(L$7>PARAMETROS!$C$12,IF($H16>0,$G16*CURVA!L16/$H16,0)*L$6,0)) -> 14421.7 | M16: =IF($B16="",0,SUMIFS(INCORRIDO!$C$6:$C$5005,INCORRIDO!$D$6:$D$5005,$B16,INCORRIDO!$E$6:$E$5005,M$7)+IF(M$7>PARAMETROS!$C$12,IF($H16>0,$G16*CURVA!M16/$H16,0)*M$6,0)) -> 608.73 | N16: =IF($B16="",0,SUMIFS(INCORRIDO!$C$6:$C$5005,INCORRIDO!$D$6:$D$5005,$B16,INCORRIDO!$E$6:$E$5005,N$7)+IF(N$7>PARAMETROS!$C$12,IF($H16>0,$G16*CURVA!N16/$H16,0)*N$6,0)) -> 0 | O16: =IF($B16="",0,SUMIFS(INCORRIDO!$C$6:$C$5005,INCORRIDO!$D$6:$D$5005,$B16,INCORRIDO!$E$6:$E$5005,O$7)+IF(O$7>PARAMETROS!$C$12,IF($H16>0,$G16*CURVA!O16/$H16,0)*O$6,0)) -> 0 | P16: =IF($B16="",0,SUMIFS(INCORRIDO!$C$6:$C$5005,INCORRIDO!$D$6:$D$5005,$B16,INCORRIDO!$E$6:$E$5005,P$7)+IF(P$7>PARAMETROS!$C$12,IF($H16>0,$G16*CURVA!P16/$H16,0)*P$6,0)) -> 0 | Q16: =IF($B16="",0,SUMIFS(INCORRIDO!$C$6:$C$5005,INCORRIDO!$D$6:$D$5005,$B16,INCORRIDO!$E$6:$E$5005,Q$7)+IF(Q$7>PARAMETROS!$C$12,IF($H16>0,$G16*CURVA!Q16/$H16,0)*Q$6,0)) -> 20181.97 | R16: =IF($B16="",0,SUMIFS(INCORRIDO!$C$6:$C$5005,INCORRIDO!$D$6:$D$5005,$B16,INCORRIDO!$E$6:$E$5005,R$7)+IF(R$7>PARAMETROS!$C$12,IF($H16>0,$G16*CURVA!R16/$H16,0)*R$6,0)) -> 6015.91 | ... CC16: =IF($B16="",0,SUMIFS(INCORRIDO!$C$6:$C$5005,INCORRIDO!$D$6:$D$5005,$B16,INCORRIDO!$E$6:$E$5005,CC$7)+IF(CC$7>PARAMETROS!$C$12,IF($H16>0,$G16*CURVA!CC16/$H16,0)*CC$6,0)) -> 0
A17: =IF(ORCAMENTO!A15="","",ORCAMENTO!A15) -> 10 | B17: =IF(ORCAMENTO!B15="","",ORCAMENTO!B15) -> MÃO DE OBRA PRÓPRIA | C17: =IF(ORCAMENTO!C15="","",ORCAMENTO!C15) -> INDIRETOS | D17: =IF($B17="",0,ORCAMENTO!E15) -> 21271106 | E17: =IF($B17="",0,SUMIFS(INCORRIDO!$C$6:$C$5005,INCORRIDO!$D$6:$D$5005,$B17,INCORRIDO!$E$6:$E$5005,"<="&PARAMETROS!$C$12)) -> 3300360.2 | F17: =IF($B17="",0,SUMIFS(INCORRIDO!$C$6:$C$5005,INCORRIDO!$D$6:$D$5005,$B17,INCORRIDO!$E$6:$E$5005,">"&PARAMETROS!$C$12)) -> 475302.52 | G17: =MAX(0,D17-E17-F17) -> 17495443 | H17: =CURVA!H17 -> 17058054 | I17: =SUM(J17:CC17) -> 21271106 | J17: =IF($B17="",0,SUMIFS(INCORRIDO!$C$6:$C$5005,INCORRIDO!$D$6:$D$5005,$B17,INCORRIDO!$E$6:$E$5005,"<="&J$7)+IF(J$7>PARAMETROS!$C$12,IF($H17>0,$G17*CURVA!J17/$H17,0)*J$6,0)) -> 387208.85 | K17: =IF($B17="",0,SUMIFS(INCORRIDO!$C$6:$C$5005,INCORRIDO!$D$6:$D$5005,$B17,INCORRIDO!$E$6:$E$5005,K$7)+IF(K$7>PARAMETROS!$C$12,IF($H17>0,$G17*CURVA!K17/$H17,0)*K$6,0)) -> 940 | L17: =IF($B17="",0,SUMIFS(INCORRIDO!$C$6:$C$5005,INCORRIDO!$D$6:$D$5005,$B17,INCORRIDO!$E$6:$E$5005,L$7)+IF(L$7>PARAMETROS!$C$12,IF($H17>0,$G17*CURVA!L17/$H17,0)*L$6,0)) -> 61357.36 | M17: =IF($B17="",0,SUMIFS(INCORRIDO!$C$6:$C$5005,INCORRIDO!$D$6:$D$5005,$B17,INCORRIDO!$E$6:$E$5005,M$7)+IF(M$7>PARAMETROS!$C$12,IF($H17>0,$G17*CURVA!M17/$H17,0)*M$6,0)) -> 118973.07 | N17: =IF($B17="",0,SUMIFS(INCORRIDO!$C$6:$C$5005,INCORRIDO!$D$6:$D$5005,$B17,INCORRIDO!$E$6:$E$5005,N$7)+IF(N$7>PARAMETROS!$C$12,IF($H17>0,$G17*CURVA!N17/$H17,0)*N$6,0)) -> 60617.36 | O17: =IF($B17="",0,SUMIFS(INCORRIDO!$C$6:$C$5005,INCORRIDO!$D$6:$D$5005,$B17,INCORRIDO!$E$6:$E$5005,O$7)+IF(O$7>PARAMETROS!$C$12,IF($H17>0,$G17*CURVA!O17/$H17,0)*O$6,0)) -> 23912.84 | P17: =IF($B17="",0,SUMIFS(INCORRIDO!$C$6:$C$5005,INCORRIDO!$D$6:$D$5005,$B17,INCORRIDO!$E$6:$E$5005,P$7)+IF(P$7>PARAMETROS!$C$12,IF($H17>0,$G17*CURVA!P17/$H17,0)*P$6,0)) -> 27131.75 | Q17: =IF($B17="",0,SUMIFS(INCORRIDO!$C$6:$C$5005,INCORRIDO!$D$6:$D$5005,$B17,INCORRIDO!$E$6:$E$5005,Q$7)+IF(Q$7>PARAMETROS!$C$12,IF($H17>0,$G17*CURVA!Q17/$H17,0)*Q$6,0)) -> 51487.59 | R17: =IF($B17="",0,SUMIFS(INCORRIDO!$C$6:$C$5005,INCORRIDO!$D$6:$D$5005,$B17,INCORRIDO!$E$6:$E$5005,R$7)+IF(R$7>PARAMETROS!$C$12,IF($H17>0,$G17*CURVA!R17/$H17,0)*R$6,0)) -> 89901.3 | ... CC17: =IF($B17="",0,SUMIFS(INCORRIDO!$C$6:$C$5005,INCORRIDO!$D$6:$D$5005,$B17,INCORRIDO!$E$6:$E$5005,CC$7)+IF(CC$7>PARAMETROS!$C$12,IF($H17>0,$G17*CURVA!CC17/$H17,0)*CC$6,0)) -> 0
A18: =IF(ORCAMENTO!A16="","",ORCAMENTO!A16) -> 11 | B18: =IF(ORCAMENTO!B16="","",ORCAMENTO!B16) -> EQUIPAMENTOS E FERRAMENTAS | C18: =IF(ORCAMENTO!C16="","",ORCAMENTO!C16) -> INDIRETOS | D18: =IF($B18="",0,ORCAMENTO!E16) -> 6774432.9 | E18: =IF($B18="",0,SUMIFS(INCORRIDO!$C$6:$C$5005,INCORRIDO!$D$6:$D$5005,$B18,INCORRIDO!$E$6:$E$5005,"<="&PARAMETROS!$C$12)) -> 543667.72 | F18: =IF($B18="",0,SUMIFS(INCORRIDO!$C$6:$C$5005,INCORRIDO!$D$6:$D$5005,$B18,INCORRIDO!$E$6:$E$5005,">"&PARAMETROS!$C$12)) -> 102156.96 | G18: =MAX(0,D18-E18-F18) -> 6128608.3 | H18: =CURVA!H18 -> 6128608.3 | I18: =SUM(J18:CC18) -> 6774432.9 | J18: =IF($B18="",0,SUMIFS(INCORRIDO!$C$6:$C$5005,INCORRIDO!$D$6:$D$5005,$B18,INCORRIDO!$E$6:$E$5005,"<="&J$7)+IF(J$7>PARAMETROS!$C$12,IF($H18>0,$G18*CURVA!J18/$H18,0)*J$6,0)) -> 0 | K18: =IF($B18="",0,SUMIFS(INCORRIDO!$C$6:$C$5005,INCORRIDO!$D$6:$D$5005,$B18,INCORRIDO!$E$6:$E$5005,K$7)+IF(K$7>PARAMETROS!$C$12,IF($H18>0,$G18*CURVA!K18/$H18,0)*K$6,0)) -> 0 | L18: =IF($B18="",0,SUMIFS(INCORRIDO!$C$6:$C$5005,INCORRIDO!$D$6:$D$5005,$B18,INCORRIDO!$E$6:$E$5005,L$7)+IF(L$7>PARAMETROS!$C$12,IF($H18>0,$G18*CURVA!L18/$H18,0)*L$6,0)) -> 0 | M18: =IF($B18="",0,SUMIFS(INCORRIDO!$C$6:$C$5005,INCORRIDO!$D$6:$D$5005,$B18,INCORRIDO!$E$6:$E$5005,M$7)+IF(M$7>PARAMETROS!$C$12,IF($H18>0,$G18*CURVA!M18/$H18,0)*M$6,0)) -> 0 | N18: =IF($B18="",0,SUMIFS(INCORRIDO!$C$6:$C$5005,INCORRIDO!$D$6:$D$5005,$B18,INCORRIDO!$E$6:$E$5005,N$7)+IF(N$7>PARAMETROS!$C$12,IF($H18>0,$G18*CURVA!N18/$H18,0)*N$6,0)) -> 0 | O18: =IF($B18="",0,SUMIFS(INCORRIDO!$C$6:$C$5005,INCORRIDO!$D$6:$D$5005,$B18,INCORRIDO!$E$6:$E$5005,O$7)+IF(O$7>PARAMETROS!$C$12,IF($H18>0,$G18*CURVA!O18/$H18,0)*O$6,0)) -> 0 | P18: =IF($B18="",0,SUMIFS(INCORRIDO!$C$6:$C$5005,INCORRIDO!$D$6:$D$5005,$B18,INCORRIDO!$E$6:$E$5005,P$7)+IF(P$7>PARAMETROS!$C$12,IF($H18>0,$G18*CURVA!P18/$H18,0)*P$6,0)) -> 0 | Q18: =IF($B18="",0,SUMIFS(INCORRIDO!$C$6:$C$5005,INCORRIDO!$D$6:$D$5005,$B18,INCORRIDO!$E$6:$E$5005,Q$7)+IF(Q$7>PARAMETROS!$C$12,IF($H18>0,$G18*CURVA!Q18/$H18,0)*Q$6,0)) -> 672.9 | R18: =IF($B18="",0,SUMIFS(INCORRIDO!$C$6:$C$5005,INCORRIDO!$D$6:$D$5005,$B18,INCORRIDO!$E$6:$E$5005,R$7)+IF(R$7>PARAMETROS!$C$12,IF($H18>0,$G18*CURVA!R18/$H18,0)*R$6,0)) -> 5281.41 | ... CC18: =IF($B18="",0,SUMIFS(INCORRIDO!$C$6:$C$5005,INCORRIDO!$D$6:$D$5005,$B18,INCORRIDO!$E$6:$E$5005,CC$7)+IF(CC$7>PARAMETROS!$C$12,IF($H18>0,$G18*CURVA!CC18/$H18,0)*CC$6,0)) -> 0
A19: =IF(ORCAMENTO!A17="","",ORCAMENTO!A17) -> 12 | B19: =IF(ORCAMENTO!B17="","",ORCAMENTO!B17) -> SERVIÇOS INICIAIS | C19: =IF(ORCAMENTO!C17="","",ORCAMENTO!C17) -> INFRAESTRUTURA | D19: =IF($B19="",0,ORCAMENTO!E17) -> 176378.52 | E19: =IF($B19="",0,SUMIFS(INCORRIDO!$C$6:$C$5005,INCORRIDO!$D$6:$D$5005,$B19,INCORRIDO!$E$6:$E$5005,"<="&PARAMETROS!$C$12)) -> 108365.04 | F19: =IF($B19="",0,SUMIFS(INCORRIDO!$C$6:$C$5005,INCORRIDO!$D$6:$D$5005,$B19,INCORRIDO!$E$6:$E$5005,">"&PARAMETROS!$C$12)) -> 6706 | G19: =MAX(0,D19-E19-F19) -> 61307.48 | H19: =CURVA!H19 -> 56654.6 | I19: =SUM(J19:CC19) -> 176378.52 | J19: =IF($B19="",0,SUMIFS(INCORRIDO!$C$6:$C$5005,INCORRIDO!$D$6:$D$5005,$B19,INCORRIDO!$E$6:$E$5005,"<="&J$7)+IF(J$7>PARAMETROS!$C$12,IF($H19>0,$G19*CURVA!J19/$H19,0)*J$6,0)) -> 0 | K19: =IF($B19="",0,SUMIFS(INCORRIDO!$C$6:$C$5005,INCORRIDO!$D$6:$D$5005,$B19,INCORRIDO!$E$6:$E$5005,K$7)+IF(K$7>PARAMETROS!$C$12,IF($H19>0,$G19*CURVA!K19/$H19,0)*K$6,0)) -> 0 | L19: =IF($B19="",0,SUMIFS(INCORRIDO!$C$6:$C$5005,INCORRIDO!$D$6:$D$5005,$B19,INCORRIDO!$E$6:$E$5005,L$7)+IF(L$7>PARAMETROS!$C$12,IF($H19>0,$G19*CURVA!L19/$H19,0)*L$6,0)) -> 0 | M19: =IF($B19="",0,SUMIFS(INCORRIDO!$C$6:$C$5005,INCORRIDO!$D$6:$D$5005,$B19,INCORRIDO!$E$6:$E$5005,M$7)+IF(M$7>PARAMETROS!$C$12,IF($H19>0,$G19*CURVA!M19/$H19,0)*M$6,0)) -> 0 | N19: =IF($B19="",0,SUMIFS(INCORRIDO!$C$6:$C$5005,INCORRIDO!$D$6:$D$5005,$B19,INCORRIDO!$E$6:$E$5005,N$7)+IF(N$7>PARAMETROS!$C$12,IF($H19>0,$G19*CURVA!N19/$H19,0)*N$6,0)) -> 0 | O19: =IF($B19="",0,SUMIFS(INCORRIDO!$C$6:$C$5005,INCORRIDO!$D$6:$D$5005,$B19,INCORRIDO!$E$6:$E$5005,O$7)+IF(O$7>PARAMETROS!$C$12,IF($H19>0,$G19*CURVA!O19/$H19,0)*O$6,0)) -> 0 | P19: =IF($B19="",0,SUMIFS(INCORRIDO!$C$6:$C$5005,INCORRIDO!$D$6:$D$5005,$B19,INCORRIDO!$E$6:$E$5005,P$7)+IF(P$7>PARAMETROS!$C$12,IF($H19>0,$G19*CURVA!P19/$H19,0)*P$6,0)) -> 29688.12 | Q19: =IF($B19="",0,SUMIFS(INCORRIDO!$C$6:$C$5005,INCORRIDO!$D$6:$D$5005,$B19,INCORRIDO!$E$6:$E$5005,Q$7)+IF(Q$7>PARAMETROS!$C$12,IF($H19>0,$G19*CURVA!Q19/$H19,0)*Q$6,0)) -> 5465.88 | R19: =IF($B19="",0,SUMIFS(INCORRIDO!$C$6:$C$5005,INCORRIDO!$D$6:$D$5005,$B19,INCORRIDO!$E$6:$E$5005,R$7)+IF(R$7>PARAMETROS!$C$12,IF($H19>0,$G19*CURVA!R19/$H19,0)*R$6,0)) -> 0 | ... CC19: =IF($B19="",0,SUMIFS(INCORRIDO!$C$6:$C$5005,INCORRIDO!$D$6:$D$5005,$B19,INCORRIDO!$E$6:$E$5005,CC$7)+IF(CC$7>PARAMETROS!$C$12,IF($H19>0,$G19*CURVA!CC19/$H19,0)*CC$6,0)) -> 0
... A57: =IF(ORCAMENTO!A55="","",ORCAMENTO!A55) | B57: =IF(ORCAMENTO!B55="","",ORCAMENTO!B55) | C57: =IF(ORCAMENTO!C55="","",ORCAMENTO!C55) | D57: =IF($B57="",0,ORCAMENTO!E55) -> 0 | E57: =IF($B57="",0,SUMIFS(INCORRIDO!$C$6:$C$5005,INCORRIDO!$D$6:$D$5005,$B57,INCORRIDO!$E$6:$E$5005,"<="&PARAMETROS!$C$12)) -> 0 | F57: =IF($B57="",0,SUMIFS(INCORRIDO!$C$6:$C$5005,INCORRIDO!$D$6:$D$5005,$B57,INCORRIDO!$E$6:$E$5005,">"&PARAMETROS!$C$12)) -> 0 | G57: =MAX(0,D57-E57-F57) -> 0 | H57: =CURVA!H57 -> 0 | I57: =SUM(J57:CC57) -> 0 | J57: =IF($B57="",0,SUMIFS(INCORRIDO!$C$6:$C$5005,INCORRIDO!$D$6:$D$5005,$B57,INCORRIDO!$E$6:$E$5005,"<="&J$7)+IF(J$7>PARAMETROS!$C$12,IF($H57>0,$G57*CURVA!J57/$H57,0)*J$6,0)) -> 0 | K57: =IF($B57="",0,SUMIFS(INCORRIDO!$C$6:$C$5005,INCORRIDO!$D$6:$D$5005,$B57,INCORRIDO!$E$6:$E$5005,K$7)+IF(K$7>PARAMETROS!$C$12,IF($H57>0,$G57*CURVA!K57/$H57,0)*K$6,0)) -> 0 | L57: =IF($B57="",0,SUMIFS(INCORRIDO!$C$6:$C$5005,INCORRIDO!$D$6:$D$5005,$B57,INCORRIDO!$E$6:$E$5005,L$7)+IF(L$7>PARAMETROS!$C$12,IF($H57>0,$G57*CURVA!L57/$H57,0)*L$6,0)) -> 0 | M57: =IF($B57="",0,SUMIFS(INCORRIDO!$C$6:$C$5005,INCORRIDO!$D$6:$D$5005,$B57,INCORRIDO!$E$6:$E$5005,M$7)+IF(M$7>PARAMETROS!$C$12,IF($H57>0,$G57*CURVA!M57/$H57,0)*M$6,0)) -> 0 | N57: =IF($B57="",0,SUMIFS(INCORRIDO!$C$6:$C$5005,INCORRIDO!$D$6:$D$5005,$B57,INCORRIDO!$E$6:$E$5005,N$7)+IF(N$7>PARAMETROS!$C$12,IF($H57>0,$G57*CURVA!N57/$H57,0)*N$6,0)) -> 0 | O57: =IF($B57="",0,SUMIFS(INCORRIDO!$C$6:$C$5005,INCORRIDO!$D$6:$D$5005,$B57,INCORRIDO!$E$6:$E$5005,O$7)+IF(O$7>PARAMETROS!$C$12,IF($H57>0,$G57*CURVA!O57/$H57,0)*O$6,0)) -> 0 | P57: =IF($B57="",0,SUMIFS(INCORRIDO!$C$6:$C$5005,INCORRIDO!$D$6:$D$5005,$B57,INCORRIDO!$E$6:$E$5005,P$7)+IF(P$7>PARAMETROS!$C$12,IF($H57>0,$G57*CURVA!P57/$H57,0)*P$6,0)) -> 0 | Q57: =IF($B57="",0,SUMIFS(INCORRIDO!$C$6:$C$5005,INCORRIDO!$D$6:$D$5005,$B57,INCORRIDO!$E$6:$E$5005,Q$7)+IF(Q$7>PARAMETROS!$C$12,IF($H57>0,$G57*CURVA!Q57/$H57,0)*Q$6,0)) -> 0 | R57: =IF($B57="",0,SUMIFS(INCORRIDO!$C$6:$C$5005,INCORRIDO!$D$6:$D$5005,$B57,INCORRIDO!$E$6:$E$5005,R$7)+IF(R$7>PARAMETROS!$C$12,IF($H57>0,$G57*CURVA!R57/$H57,0)*R$6,0)) -> 0 | ... CC57: =IF($B57="",0,SUMIFS(INCORRIDO!$C$6:$C$5005,INCORRIDO!$D$6:$D$5005,$B57,INCORRIDO!$E$6:$E$5005,CC$7)+IF(CC$7>PARAMETROS!$C$12,IF($H57>0,$G57*CURVA!CC57/$H57,0)*CC$6,0)) -> 0
B58: TOTAL | D58: =SUM(D8:D57) -> 1.5933311e+08 | E58: =SUM(E8:E57) -> 21047425 | F58: =SUM(F8:F57) -> 3113839.3 | G58: =SUM(G8:G57) -> 1.3517185e+08 | I58: =SUM(I8:I57) -> 1.5889094e+08 | J58: =SUM(J8:J57) -> 1055724.1 | K58: =SUM(K8:K57) -> 50287.85 | L58: =SUM(L8:L57) -> 339691.77 | M58: =SUM(M8:M57) -> 249008.27 | N58: =SUM(N8:N57) -> 226944.64 | O58: =SUM(O8:O57) -> 298199.84 | P58: =SUM(P8:P57) -> 190147.17 | ... CC58: =SUM(CC8:CC57) -> 0
B59: TOTAL ACUMULADO | J59: =J58 -> 1055724.1 | K59: =J59+K58 -> 1106011.9 | L59: =K59+L58 -> 1445703.7 | M59: =L59+M58 -> 1694712 | N59: =M59+N58 -> 1921656.6 | O59: =N59+O58 -> 2219856.4 | P59: =O59+P58 -> 2410003.6 | Q59: =P59+Q58 -> 2631372 | R59: =Q59+R58 -> 3026613.5 | ... CC59: =CB59+CC58 -> 1.5889094e+08
B60: % acumulado da projeção | J60: =IF($D$58=0,0,J59/$D$58) -> 0.0066258926 | K60: =IF($D$58=0,0,K59/$D$58) -> 0.0069415071 | L60: =IF($D$58=0,0,L59/$D$58) -> 0.0090734668 | M60: =IF($D$58=0,0,M59/$D$58) -> 0.010636282 | N60: =IF($D$58=0,0,N59/$D$58) -> 0.012060623 | O60: =IF($D$58=0,0,O59/$D$58) -> 0.013932173 | P60: =IF($D$58=0,0,P59/$D$58) -> 0.015125567 | Q60: =IF($D$58=0,0,Q59/$D$58) -> 0.01651491 | ... CC60: =IF($D$58=0,0,CC59/$D$58) -> 0.99722487

Sheet FLUXO_ANUAL
A1: Fluxo de caixa anual por disciplina (R$)
A2: Soma dos meses de FLUXO_MENSAL por ano civil. Não editar.
A5: Código | B5: Disciplina | C5: Grupo | D5: Projeção (R$) | E5: =YEAR(PARAMETROS!$C$11) -> 2024 | F5: =E5+1 -> 2025 | G5: =F5+1 -> 2026 | H5: =G5+1 -> 2027 | I5: =H5+1 -> 2028 | J5: =I5+1 -> 2029 | K5: =J5+1 -> 2030 | L5: Total | M5: Dif. vs projeção
A6: =FLUXO_MENSAL!A8 -> 01 | B6: =FLUXO_MENSAL!B8 -> PROJETOS | C6: =FLUXO_MENSAL!C8 -> INDIRETOS | D6: =FLUXO_MENSAL!D8 -> 2640655 | E6: =SUMPRODUCT((YEAR(FLUXO_MENSAL!$J$7:$CC$7)=E$5)*FLUXO_MENSAL!$J8:$CC8) -> 418594.15 | F6: =SUMPRODUCT((YEAR(FLUXO_MENSAL!$J$7:$CC$7)=F$5)*FLUXO_MENSAL!$J8:$CC8) -> 1208388.3 | G6: =SUMPRODUCT((YEAR(FLUXO_MENSAL!$J$7:$CC$7)=G$5)*FLUXO_MENSAL!$J8:$CC8) -> 710023.32 | H6: =SUMPRODUCT((YEAR(FLUXO_MENSAL!$J$7:$CC$7)=H$5)*FLUXO_MENSAL!$J8:$CC8) -> 26933 | I6: =SUMPRODUCT((YEAR(FLUXO_MENSAL!$J$7:$CC$7)=I$5)*FLUXO_MENSAL!$J8:$CC8) -> 276716.27 | J6: =SUMPRODUCT((YEAR(FLUXO_MENSAL!$J$7:$CC$7)=J$5)*FLUXO_MENSAL!$J8:$CC8) -> 0 | K6: =SUMPRODUCT((YEAR(FLUXO_MENSAL!$J$7:$CC$7)=K$5)*FLUXO_MENSAL!$J8:$CC8) -> 0 | L6: =SUM(E6:K6) -> 2640655 | M6: =IF(B6="",0,L6-D6) -> 0
A7: =FLUXO_MENSAL!A9 -> 02 | B7: =FLUXO_MENSAL!B9 -> SEGUROS | C7: =FLUXO_MENSAL!C9 -> INDIRETOS | D7: =FLUXO_MENSAL!D9 -> 127911.99 | E7: =SUMPRODUCT((YEAR(FLUXO_MENSAL!$J$7:$CC$7)=E$5)*FLUXO_MENSAL!$J9:$CC9) -> 0 | F7: =SUMPRODUCT((YEAR(FLUXO_MENSAL!$J$7:$CC$7)=F$5)*FLUXO_MENSAL!$J9:$CC9) -> 0 | G7: =SUMPRODUCT((YEAR(FLUXO_MENSAL!$J$7:$CC$7)=G$5)*FLUXO_MENSAL!$J9:$CC9) -> 0 | H7: =SUMPRODUCT((YEAR(FLUXO_MENSAL!$J$7:$CC$7)=H$5)*FLUXO_MENSAL!$J9:$CC9) -> 0 | I7: =SUMPRODUCT((YEAR(FLUXO_MENSAL!$J$7:$CC$7)=I$5)*FLUXO_MENSAL!$J9:$CC9) -> 0 | J7: =SUMPRODUCT((YEAR(FLUXO_MENSAL!$J$7:$CC$7)=J$5)*FLUXO_MENSAL!$J9:$CC9) -> 0 | K7: =SUMPRODUCT((YEAR(FLUXO_MENSAL!$J$7:$CC$7)=K$5)*FLUXO_MENSAL!$J9:$CC9) -> 0 | L7: =SUM(E7:K7) -> 0 | M7: =IF(B7="",0,L7-D7) -> -127911.99
A8: =FLUXO_MENSAL!A10 -> 03 | B8: =FLUXO_MENSAL!B10 -> TAXAS DIVERSAS | C8: =FLUXO_MENSAL!C10 -> INDIRETOS | D8: =FLUXO_MENSAL!D10 -> 158047.46 | E8: =SUMPRODUCT((YEAR(FLUXO_MENSAL!$J$7:$CC$7)=E$5)*FLUXO_MENSAL!$J10:$CC10) -> 154.1 | F8: =SUMPRODUCT((YEAR(FLUXO_MENSAL!$J$7:$CC$7)=F$5)*FLUXO_MENSAL!$J10:$CC10) -> 207.89 | G8: =SUMPRODUCT((YEAR(FLUXO_MENSAL!$J$7:$CC$7)=G$5)*FLUXO_MENSAL!$J10:$CC10) -> 7404.0307 | H8: =SUMPRODUCT((YEAR(FLUXO_MENSAL!$J$7:$CC$7)=H$5)*FLUXO_MENSAL!$J10:$CC10) -> 2791.2461 | I8: =SUMPRODUCT((YEAR(FLUXO_MENSAL!$J$7:$CC$7)=I$5)*FLUXO_MENSAL!$J10:$CC10) -> 41452.331 | J8: =SUMPRODUCT((YEAR(FLUXO_MENSAL!$J$7:$CC$7)=J$5)*FLUXO_MENSAL!$J10:$CC10) -> 106037.86 | K8: =SUMPRODUCT((YEAR(FLUXO_MENSAL!$J$7:$CC$7)=K$5)*FLUXO_MENSAL!$J10:$CC10) -> 0 | L8: =SUM(E8:K8) -> 158047.46 | M8: =IF(B8="",0,L8-D8) -> 0
A9: =FLUXO_MENSAL!A11 -> 04 | B9: =FLUXO_MENSAL!B11 -> BARRACAO DE OBRA | C9: =FLUXO_MENSAL!C11 -> INDIRETOS | D9: =FLUXO_MENSAL!D11 -> 1249911.1 | E9: =SUMPRODUCT((YEAR(FLUXO_MENSAL!$J$7:$CC$7)=E$5)*FLUXO_MENSAL!$J11:$CC11) -> 61380.97 | F9: =SUMPRODUCT((YEAR(FLUXO_MENSAL!$J$7:$CC$7)=F$5)*FLUXO_MENSAL!$J11:$CC11) -> 421604.66 | G9: =SUMPRODUCT((YEAR(FLUXO_MENSAL!$J$7:$CC$7)=G$5)*FLUXO_MENSAL!$J11:$CC11) -> 218851.04 | H9: =SUMPRODUCT((YEAR(FLUXO_MENSAL!$J$7:$CC$7)=H$5)*FLUXO_MENSAL!$J11:$CC11) -> 369182.92 | I9: =SUMPRODUCT((YEAR(FLUXO_MENSAL!$J$7:$CC$7)=I$5)*FLUXO_MENSAL!$J11:$CC11) -> 104781.71 | J9: =SUMPRODUCT((YEAR(FLUXO_MENSAL!$J$7:$CC$7)=J$5)*FLUXO_MENSAL!$J11:$CC11) -> 74109.769 | K9: =SUMPRODUCT((YEAR(FLUXO_MENSAL!$J$7:$CC$7)=K$5)*FLUXO_MENSAL!$J11:$CC11) -> 0 | L9: =SUM(E9:K9) -> 1249911.1 | M9: =IF(B9="",0,L9-D9) -> 0
A10: =FLUXO_MENSAL!A12 -> 05 | B10: =FLUXO_MENSAL!B12 -> LIGAÇÕES PROVISÓRIAS AGUA, ENERGIA,TELEFONIA, ESGOTO | C10: =FLUXO_MENSAL!C12 -> INDIRETOS | D10: =FLUXO_MENSAL!D12 -> 85665.05 | E10: =SUMPRODUCT((YEAR(FLUXO_MENSAL!$J$7:$CC$7)=E$5)*FLUXO_MENSAL!$J12:$CC12) -> 0 | F10: =SUMPRODUCT((YEAR(FLUXO_MENSAL!$J$7:$CC$7)=F$5)*FLUXO_MENSAL!$J12:$CC12) -> 0 | G10: =SUMPRODUCT((YEAR(FLUXO_MENSAL!$J$7:$CC$7)=G$5)*FLUXO_MENSAL!$J12:$CC12) -> 0 | H10: =SUMPRODUCT((YEAR(FLUXO_MENSAL!$J$7:$CC$7)=H$5)*FLUXO_MENSAL!$J12:$CC12) -> 0 | I10: =SUMPRODUCT((YEAR(FLUXO_MENSAL!$J$7:$CC$7)=I$5)*FLUXO_MENSAL!$J12:$CC12) -> 0 | J10: =SUMPRODUCT((YEAR(FLUXO_MENSAL!$J$7:$CC$7)=J$5)*FLUXO_MENSAL!$J12:$CC12) -> 0 | K10: =SUMPRODUCT((YEAR(FLUXO_MENSAL!$J$7:$CC$7)=K$5)*FLUXO_MENSAL!$J12:$CC12) -> 0 | L10: =SUM(E10:K10) -> 0 | M10: =IF(B10="",0,L10-D10) -> -85665.05
A11: =FLUXO_MENSAL!A13 -> 06 | B11: =FLUXO_MENSAL!B13 -> CONSUMO DE ÁGUA, ENERGIA, ETC. | C11: =FLUXO_MENSAL!C13 -> INDIRETOS | D11: =FLUXO_MENSAL!D13 -> 544229.22 | E11: =SUMPRODUCT((YEAR(FLUXO_MENSAL!$J$7:$CC$7)=E$5)*FLUXO_MENSAL!$J13:$CC13) -> 0 | F11: =SUMPRODUCT((YEAR(FLUXO_MENSAL!$J$7:$CC$7)=F$5)*FLUXO_MENSAL!$J13:$CC13) -> 3408.11 | G11: =SUMPRODUCT((YEAR(FLUXO_MENSAL!$J$7:$CC$7)=G$5)*FLUXO_MENSAL!$J13:$CC13) -> 82048.381 | H11: =SUMPRODUCT((YEAR(FLUXO_MENSAL!$J$7:$CC$7)=H$5)*FLUXO_MENSAL!$J13:$CC13) -> 143909.55 | I11: =SUMPRODUCT((YEAR(FLUXO_MENSAL!$J$7:$CC$7)=I$5)*FLUXO_MENSAL!$J13:$CC13) -> 148358.44 | J11: =SUMPRODUCT((YEAR(FLUXO_MENSAL!$J$7:$CC$7)=J$5)*FLUXO_MENSAL!$J13:$CC13) -> 166504.74 | K11: =SUMPRODUCT((YEAR(FLUXO_MENSAL!$J$7:$CC$7)=K$5)*FLUXO_MENSAL!$J13:$CC13) -> 0 | L11: =SUM(E11:K11) -> 544229.22 | M11: =IF(B11="",0,L11-D11) -> 0
A12: =FLUXO_MENSAL!A14 -> 07 | B12: =FLUXO_MENSAL!B14 -> DIVERSOS | C12: =FLUXO_MENSAL!C14 -> INDIRETOS | D12: =FLUXO_MENSAL!D14 -> 194480.67 | E12: =SUMPRODUCT((YEAR(FLUXO_MENSAL!$J$7:$CC$7)=E$5)*FLUXO_MENSAL!$J14:$CC14) -> 7617.91 | F12: =SUMPRODUCT((YEAR(FLUXO_MENSAL!$J$7:$CC$7)=F$5)*FLUXO_MENSAL!$J14:$CC14) -> 9086.08 | G12: =SUMPRODUCT((YEAR(FLUXO_MENSAL!$J$7:$CC$7)=G$5)*FLUXO_MENSAL!$J14:$CC14) -> 35610.882 | H12: =SUMPRODUCT((YEAR(FLUXO_MENSAL!$J$7:$CC$7)=H$5)*FLUXO_MENSAL!$J14:$CC14) -> 64636.363 | I12: =SUMPRODUCT((YEAR(FLUXO_MENSAL!$J$7:$CC$7)=I$5)*FLUXO_MENSAL!$J14:$CC14) -> 64180.322 | J12: =SUMPRODUCT((YEAR(FLUXO_MENSAL!$J$7:$CC$7)=J$5)*FLUXO_MENSAL!$J14:$CC14) -> 13349.113 | K12: =SUMPRODUCT((YEAR(FLUXO_MENSAL!$J$7:$CC$7)=K$5)*FLUXO_MENSAL!$J14:$CC14) -> 0 | L12: =SUM(E12:K12) -> 194480.67 | M12: =IF(B12="",0,L12-D12) -> 0
A13: =FLUXO_MENSAL!A15 -> 08 | B13: =FLUXO_MENSAL!B15 -> TRANSPORTES | C13: =FLUXO_MENSAL!C15 -> INDIRETOS | D13: =FLUXO_MENSAL!D15 -> 817599.43 | E13: =SUMPRODUCT((YEAR(FLUXO_MENSAL!$J$7:$CC$7)=E$5)*FLUXO_MENSAL!$J15:$CC15) -> 230 | F13: =SUMPRODUCT((YEAR(FLUXO_MENSAL!$J$7:$CC$7)=F$5)*FLUXO_MENSAL!$J15:$CC15) -> 38732.89 | G13: =SUMPRODUCT((YEAR(FLUXO_MENSAL!$J$7:$CC$7)=G$5)*FLUXO_MENSAL!$J15:$CC15) -> 89905.632 | H13: =SUMPRODUCT((YEAR(FLUXO_MENSAL!$J$7:$CC$7)=H$5)*FLUXO_MENSAL!$J15:$CC15) -> 347554.68 | I13: =SUMPRODUCT((YEAR(FLUXO_MENSAL!$J$7:$CC$7)=I$5)*FLUXO_MENSAL!$J15:$CC15) -> 199541.83 | J13: =SUMPRODUCT((YEAR(FLUXO_MENSAL!$J$7:$CC$7)=J$5)*FLUXO_MENSAL!$J15:$CC15) -> 141634.4 | K13: =SUMPRODUCT((YEAR(FLUXO_MENSAL!$J$7:$CC$7)=K$5)*FLUXO_MENSAL!$J15:$CC15) -> 0 | L13: =SUM(E13:K13) -> 817599.43 | M13: =IF(B13="",0,L13-D13) -> 0
A14: =FLUXO_MENSAL!A16 -> 09 | B14: =FLUXO_MENSAL!B16 -> CONSULTORIAS (OBRAS) | C14: =FLUXO_MENSAL!C16 -> INDIRETOS | D14: =FLUXO_MENSAL!D16 -> 1371532.1 | E14: =SUMPRODUCT((YEAR(FLUXO_MENSAL!$J$7:$CC$7)=E$5)*FLUXO_MENSAL!$J16:$CC16) -> 43088.09 | F14: =SUMPRODUCT((YEAR(FLUXO_MENSAL!$J$7:$CC$7)=F$5)*FLUXO_MENSAL!$J16:$CC16) -> 396498.82 | G14: =SUMPRODUCT((YEAR(FLUXO_MENSAL!$J$7:$CC$7)=G$5)*FLUXO_MENSAL!$J16:$CC16) -> 359813.18 | H14: =SUMPRODUCT((YEAR(FLUXO_MENSAL!$J$7:$CC$7)=H$5)*FLUXO_MENSAL!$J16:$CC16) -> 247855.92 | I14: =SUMPRODUCT((YEAR(FLUXO_MENSAL!$J$7:$CC$7)=I$5)*FLUXO_MENSAL!$J16:$CC16) -> 231849.16 | J14: =SUMPRODUCT((YEAR(FLUXO_MENSAL!$J$7:$CC$7)=J$5)*FLUXO_MENSAL!$J16:$CC16) -> 92426.949 | K14: =SUMPRODUCT((YEAR(FLUXO_MENSAL!$J$7:$CC$7)=K$5)*FLUXO_MENSAL!$J16:$CC16) -> 0 | L14: =SUM(E14:K14) -> 1371532.1 | M14: =IF(B14="",0,L14-D14) -> 0
A15: =FLUXO_MENSAL!A17 -> 10 | B15: =FLUXO_MENSAL!B17 -> MÃO DE OBRA PRÓPRIA | C15: =FLUXO_MENSAL!C17 -> INDIRETOS | D15: =FLUXO_MENSAL!D17 -> 21271106 | E15: =SUMPRODUCT((YEAR(FLUXO_MENSAL!$J$7:$CC$7)=E$5)*FLUXO_MENSAL!$J17:$CC17) -> 387208.85 | F15: =SUMPRODUCT((YEAR(FLUXO_MENSAL!$J$7:$CC$7)=F$5)*FLUXO_MENSAL!$J17:$CC17) -> 1129350.6 | G15: =SUMPRODUCT((YEAR(FLUXO_MENSAL!$J$7:$CC$7)=G$5)*FLUXO_MENSAL!$J17:$CC17) -> 3275935 | H15: =SUMPRODUCT((YEAR(FLUXO_MENSAL!$J$7:$CC$7)=H$5)*FLUXO_MENSAL!$J17:$CC17) -> 5917364.9 | I15: =SUMPRODUCT((YEAR(FLUXO_MENSAL!$J$7:$CC$7)=I$5)*FLUXO_MENSAL!$J17:$CC17) -> 5719698.8 | J15: =SUMPRODUCT((YEAR(FLUXO_MENSAL!$J$7:$CC$7)=J$5)*FLUXO_MENSAL!$J17:$CC17) -> 4841548 | K15: =SUMPRODUCT((YEAR(FLUXO_MENSAL!$J$7:$CC$7)=K$5)*FLUXO_MENSAL!$J17:$CC17) -> 0 | L15: =SUM(E15:K15) -> 21271106 | M15: =IF(B15="",0,L15-D15) -> 0
A16: =FLUXO_MENSAL!A18 -> 11 | B16: =FLUXO_MENSAL!B18 -> EQUIPAMENTOS E FERRAMENTAS | C16: =FLUXO_MENSAL!C18 -> INDIRETOS | D16: =FLUXO_MENSAL!D18 -> 6774432.9 | E16: =SUMPRODUCT((YEAR(FLUXO_MENSAL!$J$7:$CC$7)=E$5)*FLUXO_MENSAL!$J18:$CC18) -> 0 | F16: =SUMPRODUCT((YEAR(FLUXO_MENSAL!$J$7:$CC$7)=F$5)*FLUXO_MENSAL!$J18:$CC18) -> 136581.26 | G16: =SUMPRODUCT((YEAR(FLUXO_MENSAL!$J$7:$CC$7)=G$5)*FLUXO_MENSAL!$J18:$CC18) -> 1056426.3 | H16: =SUMPRODUCT((YEAR(FLUXO_MENSAL!$J$7:$CC$7)=H$5)*FLUXO_MENSAL!$J18:$CC18) -> 2728658 | I16: =SUMPRODUCT((YEAR(FLUXO_MENSAL!$J$7:$CC$7)=I$5)*FLUXO_MENSAL!$J18:$CC18) -> 2650129.4 | J16: =SUMPRODUCT((YEAR(FLUXO_MENSAL!$J$7:$CC$7)=J$5)*FLUXO_MENSAL!$J18:$CC18) -> 202638.03 | K16: =SUMPRODUCT((YEAR(FLUXO_MENSAL!$J$7:$CC$7)=K$5)*FLUXO_MENSAL!$J18:$CC18) -> 0 | L16: =SUM(E16:K16) -> 6774432.9 | M16: =IF(B16="",0,L16-D16) -> 0
A17: =FLUXO_MENSAL!A19 -> 12 | B17: =FLUXO_MENSAL!B19 -> SERVIÇOS INICIAIS | C17: =FLUXO_MENSAL!C19 -> INFRAESTRUTURA | D17: =FLUXO_MENSAL!D19 -> 176378.52 | E17: =SUMPRODUCT((YEAR(FLUXO_MENSAL!$J$7:$CC$7)=E$5)*FLUXO_MENSAL!$J19:$CC19) -> 0 | F17: =SUMPRODUCT((YEAR(FLUXO_MENSAL!$J$7:$CC$7)=F$5)*FLUXO_MENSAL!$J19:$CC19) -> 82151.56 | G17: =SUMPRODUCT((YEAR(FLUXO_MENSAL!$J$7:$CC$7)=G$5)*FLUXO_MENSAL!$J19:$CC19) -> 30014.48 | H17: =SUMPRODUCT((YEAR(FLUXO_MENSAL!$J$7:$CC$7)=H$5)*FLUXO_MENSAL!$J19:$CC19) -> 64212.48 | I17: =SUMPRODUCT((YEAR(FLUXO_MENSAL!$J$7:$CC$7)=I$5)*FLUXO_MENSAL!$J19:$CC19) -> 0 | J17: =SUMPRODUCT((YEAR(FLUXO_MENSAL!$J$7:$CC$7)=J$5)*FLUXO_MENSAL!$J19:$CC19) -> 0 | K17: =SUMPRODUCT((YEAR(FLUXO_MENSAL!$J$7:$CC$7)=K$5)*FLUXO_MENSAL!$J19:$CC19) -> 0 | L17: =SUM(E17:K17) -> 176378.52 | M17: =IF(B17="",0,L17-D17) -> 0
... A55: =FLUXO_MENSAL!A57 | B55: =FLUXO_MENSAL!B57 | C55: =FLUXO_MENSAL!C57 | D55: =FLUXO_MENSAL!D57 -> 0 | E55: =SUMPRODUCT((YEAR(FLUXO_MENSAL!$J$7:$CC$7)=E$5)*FLUXO_MENSAL!$J57:$CC57) -> 0 | F55: =SUMPRODUCT((YEAR(FLUXO_MENSAL!$J$7:$CC$7)=F$5)*FLUXO_MENSAL!$J57:$CC57) -> 0 | G55: =SUMPRODUCT((YEAR(FLUXO_MENSAL!$J$7:$CC$7)=G$5)*FLUXO_MENSAL!$J57:$CC57) -> 0 | H55: =SUMPRODUCT((YEAR(FLUXO_MENSAL!$J$7:$CC$7)=H$5)*FLUXO_MENSAL!$J57:$CC57) -> 0 | I55: =SUMPRODUCT((YEAR(FLUXO_MENSAL!$J$7:$CC$7)=I$5)*FLUXO_MENSAL!$J57:$CC57) -> 0 | J55: =SUMPRODUCT((YEAR(FLUXO_MENSAL!$J$7:$CC$7)=J$5)*FLUXO_MENSAL!$J57:$CC57) -> 0 | K55: =SUMPRODUCT((YEAR(FLUXO_MENSAL!$J$7:$CC$7)=K$5)*FLUXO_MENSAL!$J57:$CC57) -> 0 | L55: =SUM(E55:K55) -> 0 | M55: =IF(B55="",0,L55-D55) -> 0
B56: TOTAL | D56: =SUM(D6:D55) -> 1.5933311e+08 | E56: =SUM(E6:E55) -> 1055724.1 | F56: =SUM(F6:F55) -> 7574836.7 | G56: =SUM(G6:G55) -> 21524568 | H56: =SUM(H6:H55) -> 48540176 | I56: =SUM(I6:I55) -> 66970447 | J56: =SUM(J6:J55) -> 13225187 | K56: =SUM(K6:K55) -> 0 | ... M56: =SUM(M6:M55) -> -442170.81
B58: Resumo por grupo
B59: Grupo | D59: Projeção (R$) | E59: =E5 -> 2024 | F59: =F5 -> 2025 | G59: =G5 -> 2026 | H59: =H5 -> 2027 | I59: =I5 -> 2028 | J59: =J5 -> 2029 | K59: =K5 -> 2030 | L59: Total
B60: =IF(PARAMETROS!E4="","",PARAMETROS!E4) -> INDIRETOS | D60: =IF($B60="","",SUMIF($C$6:$C$55,$B60,D$6:D$55)) -> 35235571 | E60: =IF($B60="","",SUMIF($C$6:$C$55,$B60,E$6:E$55)) -> 918274.07 | F60: =IF($B60="","",SUMIF($C$6:$C$55,$B60,F$6:F$55)) -> 3343858.6 | G60: =IF($B60="","",SUMIF($C$6:$C$55,$B60,G$6:G$55)) -> 5836017.7 | H60: =IF($B60="","",SUMIF($C$6:$C$55,$B60,H$6:H$55)) -> 9848886.5 | I60: =IF($B60="","",SUMIF($C$6:$C$55,$B60,I$6:I$55)) -> 9436708.2 | J60: =IF($B60="","",SUMIF($C$6:$C$55,$B60,J$6:J$55)) -> 5638248.8 | K60: =IF($B60="","",SUMIF($C$6:$C$55,$B60,K$6:K$55)) -> 0 | L60: =IF($B60="","",SUMIF($C$6:$C$55,$B60,L$6:L$55)) -> 35021994
B61: =IF(PARAMETROS!E5="","",PARAMETROS!E5) -> INFRAESTRUTURA | D61: =IF($B61="","",SUMIF($C$6:$C$55,$B61,D$6:D$55)) -> 14305656 | E61: =IF($B61="","",SUMIF($C$6:$C$55,$B61,E$6:E$55)) -> 0 | F61: =IF($B61="","",SUMIF($C$6:$C$55,$B61,F$6:F$55)) -> 3800087.7 | G61: =IF($B61="","",SUMIF($C$6:$C$55,$B61,G$6:G$55)) -> 8702719.9 | H61: =IF($B61="","",SUMIF($C$6:$C$55,$B61,H$6:H$55)) -> 1318864.3 | I61: =IF($B61="","",SUMIF($C$6:$C$55,$B61,I$6:I$55)) -> 255390.47 | J61: =IF($B61="","",SUMIF($C$6:$C$55,$B61,J$6:J$55)) -> 0 | K61: =IF($B61="","",SUMIF($C$6:$C$55,$B61,K$6:K$55)) -> 0 | L61: =IF($B61="","",SUMIF($C$6:$C$55,$B61,L$6:L$55)) -> 14077062
B62: =IF(PARAMETROS!E6="","",PARAMETROS!E6) -> ESTRUTURA | D62: =IF($B62="","",SUMIF($C$6:$C$55,$B62,D$6:D$55)) -> 26850931 | E62: =IF($B62="","",SUMIF($C$6:$C$55,$B62,E$6:E$55)) -> 0 | F62: =IF($B62="","",SUMIF($C$6:$C$55,$B62,F$6:F$55)) -> 0 | G62: =IF($B62="","",SUMIF($C$6:$C$55,$B62,G$6:G$55)) -> 6406093.9 | H62: =IF($B62="","",SUMIF($C$6:$C$55,$B62,H$6:H$55)) -> 17796165 | I62: =IF($B62="","",SUMIF($C$6:$C$55,$B62,I$6:I$55)) -> 1466212.5 | J62: =IF($B62="","",SUMIF($C$6:$C$55,$B62,J$6:J$55)) -> 1182460.3 | K62: =IF($B62="","",SUMIF($C$6:$C$55,$B62,K$6:K$55)) -> 0 | L62: =IF($B62="","",SUMIF($C$6:$C$55,$B62,L$6:L$55)) -> 26850931
B63: =IF(PARAMETROS!E7="","",PARAMETROS!E7) -> SISTEMAS E VEDAÇÕES | D63: =IF($B63="","",SUMIF($C$6:$C$55,$B63,D$6:D$55)) -> 36811424 | E63: =IF($B63="","",SUMIF($C$6:$C$55,$B63,E$6:E$55)) -> 0 | F63: =IF($B63="","",SUMIF($C$6:$C$55,$B63,F$6:F$55)) -> 2235.2 | G63: =IF($B63="","",SUMIF($C$6:$C$55,$B63,G$6:G$55)) -> 572736.31 | H63: =IF($B63="","",SUMIF($C$6:$C$55,$B63,H$6:H$55)) -> 11219763 | I63: =IF($B63="","",SUMIF($C$6:$C$55,$B63,I$6:I$55)) -> 23204368 | J63: =IF($B63="","",SUMIF($C$6:$C$55,$B63,J$6:J$55)) -> 1812322.4 | K63: =IF($B63="","",SUMIF($C$6:$C$55,$B63,K$6:K$55)) -> 0 | L63: =IF($B63="","",SUMIF($C$6:$C$55,$B63,L$6:L$55)) -> 36811424
B64: =IF(PARAMETROS!E8="","",PARAMETROS!E8) -> ACABAMENTOS | D64: =IF($B64="","",SUMIF($C$6:$C$55,$B64,D$6:D$55)) -> 45563422 | E64: =IF($B64="","",SUMIF($C$6:$C$55,$B64,E$6:E$55)) -> 0 | F64: =IF($B64="","",SUMIF($C$6:$C$55,$B64,F$6:F$55)) -> 0 | G64: =IF($B64="","",SUMIF($C$6:$C$55,$B64,G$6:G$55)) -> 7000 | H64: =IF($B64="","",SUMIF($C$6:$C$55,$B64,H$6:H$55)) -> 8356498.1 | I64: =IF($B64="","",SUMIF($C$6:$C$55,$B64,I$6:I$55)) -> 32607768 | J64: =IF($B64="","",SUMIF($C$6:$C$55,$B64,J$6:J$55)) -> 4592155.8 | K64: =IF($B64="","",SUMIF($C$6:$C$55,$B64,K$6:K$55)) -> 0 | L64: =IF($B64="","",SUMIF($C$6:$C$55,$B64,L$6:L$55)) -> 45563422
B65: =IF(PARAMETROS!E9="","",PARAMETROS!E9) -> TAXA DE ADMINISTRAÇÃO | D65: =IF($B65="","",SUMIF($C$6:$C$55,$B65,D$6:D$55)) -> 566105.29 | E65: =IF($B65="","",SUMIF($C$6:$C$55,$B65,E$6:E$55)) -> 137450 | F65: =IF($B65="","",SUMIF($C$6:$C$55,$B65,F$6:F$55)) -> 428655.29 | G65: =IF($B65="","",SUMIF($C$6:$C$55,$B65,G$6:G$55)) -> 0 | H65: =IF($B65="","",SUMIF($C$6:$C$55,$B65,H$6:H$55)) -> 0 | I65: =IF($B65="","",SUMIF($C$6:$C$55,$B65,I$6:I$55)) -> 0 | J65: =IF($B65="","",SUMIF($C$6:$C$55,$B65,J$6:J$55)) -> 0 | K65: =IF($B65="","",SUMIF($C$6:$C$55,$B65,K$6:K$55)) -> 0 | L65: =IF($B65="","",SUMIF($C$6:$C$55,$B65,L$6:L$55)) -> 566105.29
B66: =IF(PARAMETROS!E10="","",PARAMETROS!E10) | D66: =IF($B66="","",SUMIF($C$6:$C$55,$B66,D$6:D$55)) | E66: =IF($B66="","",SUMIF($C$6:$C$55,$B66,E$6:E$55)) | F66: =IF($B66="","",SUMIF($C$6:$C$55,$B66,F$6:F$55)) | G66: =IF($B66="","",SUMIF($C$6:$C$55,$B66,G$6:G$55)) | H66: =IF($B66="","",SUMIF($C$6:$C$55,$B66,H$6:H$55)) | I66: =IF($B66="","",SUMIF($C$6:$C$55,$B66,I$6:I$55)) | J66: =IF($B66="","",SUMIF($C$6:$C$55,$B66,J$6:J$55)) | K66: =IF($B66="","",SUMIF($C$6:$C$55,$B66,K$6:K$55)) | L66: =IF($B66="","",SUMIF($C$6:$C$55,$B66,L$6:L$55))
B67: =IF(PARAMETROS!E11="","",PARAMETROS!E11) | D67: =IF($B67="","",SUMIF($C$6:$C$55,$B67,D$6:D$55)) | E67: =IF($B67="","",SUMIF($C$6:$C$55,$B67,E$6:E$55)) | F67: =IF($B67="","",SUMIF($C$6:$C$55,$B67,F$6:F$55)) | G67: =IF($B67="","",SUMIF($C$6:$C$55,$B67,G$6:G$55)) | H67: =IF($B67="","",SUMIF($C$6:$C$55,$B67,H$6:H$55)) | I67: =IF($B67="","",SUMIF($C$6:$C$55,$B67,I$6:I$55)) | J67: =IF($B67="","",SUMIF($C$6:$C$55,$B67,J$6:J$55)) | K67: =IF($B67="","",SUMIF($C$6:$C$55,$B67,K$6:K$55)) | L67: =IF($B67="","",SUMIF($C$6:$C$55,$B67,L$6:L$55))
B68: =IF(PARAMETROS!E12="","",PARAMETROS!E12) | D68: =IF($B68="","",SUMIF($C$6:$C$55,$B68,D$6:D$55)) | E68: =IF($B68="","",SUMIF($C$6:$C$55,$B68,E$6:E$55)) | F68: =IF($B68="","",SUMIF($C$6:$C$55,$B68,F$6:F$55)) | G68: =IF($B68="","",SUMIF($C$6:$C$55,$B68,G$6:G$55)) | H68: =IF($B68="","",SUMIF($C$6:$C$55,$B68,H$6:H$55)) | I68: =IF($B68="","",SUMIF($C$6:$C$55,$B68,I$6:I$55)) | J68: =IF($B68="","",SUMIF($C$6:$C$55,$B68,J$6:J$55)) | K68: =IF($B68="","",SUMIF($C$6:$C$55,$B68,K$6:K$55)) | L68: =IF($B68="","",SUMIF($C$6:$C$55,$B68,L$6:L$55))
B69: =IF(PARAMETROS!E13="","",PARAMETROS!E13) | D69: =IF($B69="","",SUMIF($C$6:$C$55,$B69,D$6:D$55)) | E69: =IF($B69="","",SUMIF($C$6:$C$55,$B69,E$6:E$55)) | F69: =IF($B69="","",SUMIF($C$6:$C$55,$B69,F$6:F$55)) | G69: =IF($B69="","",SUMIF($C$6:$C$55,$B69,G$6:G$55)) | H69: =IF($B69="","",SUMIF($C$6:$C$55,$B69,H$6:H$55)) | I69: =IF($B69="","",SUMIF($C$6:$C$55,$B69,I$6:I$55)) | J69: =IF($B69="","",SUMIF($C$6:$C$55,$B69,J$6:J$55)) | K69: =IF($B69="","",SUMIF($C$6:$C$55,$B69,K$6:K$55)) | L69: =IF($B69="","",SUMIF($C$6:$C$55,$B69,L$6:L$55))
B70: =IF(PARAMETROS!E14="","",PARAMETROS!E14) | D70: =IF($B70="","",SUMIF($C$6:$C$55,$B70,D$6:D$55)) | E70: =IF($B70="","",SUMIF($C$6:$C$55,$B70,E$6:E$55)) | F70: =IF($B70="","",SUMIF($C$6:$C$55,$B70,F$6:F$55)) | G70: =IF($B70="","",SUMIF($C$6:$C$55,$B70,G$6:G$55)) | H70: =IF($B70="","",SUMIF($C$6:$C$55,$B70,H$6:H$55)) | I70: =IF($B70="","",SUMIF($C$6:$C$55,$B70,I$6:I$55)) | J70: =IF($B70="","",SUMIF($C$6:$C$55,$B70,J$6:J$55)) | K70: =IF($B70="","",SUMIF($C$6:$C$55,$B70,K$6:K$55)) | L70: =IF($B70="","",SUMIF($C$6:$C$55,$B70,L$6:L$55))
B71: =IF(PARAMETROS!E15="","",PARAMETROS!E15) | D71: =IF($B71="","",SUMIF($C$6:$C$55,$B71,D$6:D$55)) | E71: =IF($B71="","",SUMIF($C$6:$C$55,$B71,E$6:E$55)) | F71: =IF($B71="","",SUMIF($C$6:$C$55,$B71,F$6:F$55)) | G71: =IF($B71="","",SUMIF($C$6:$C$55,$B71,G$6:G$55)) | H71: =IF($B71="","",SUMIF($C$6:$C$55,$B71,H$6:H$55)) | I71: =IF($B71="","",SUMIF($C$6:$C$55,$B71,I$6:I$55)) | J71: =IF($B71="","",SUMIF($C$6:$C$55,$B71,J$6:J$55)) | K71: =IF($B71="","",SUMIF($C$6:$C$55,$B71,K$6:K$55)) | L71: =IF($B71="","",SUMIF($C$6:$C$55,$B71,L$6:L$55))
B72: Sem grupo | D72: =D56-SUM(D60:D71) -> 0 | E72: =E56-SUM(E60:E71) -> 0 | F72: =F56-SUM(F60:F71) -> 0 | G72: =G56-SUM(G60:G71) -> 0 | H72: =H56-SUM(H60:H71) -> 0 | I72: =I56-SUM(I60:I71) -> 0 | J72: =J56-SUM(J60:J71) -> 0 | K72: =K56-SUM(K60:K71) -> 0 | L72: =L56-SUM(L60:L71) -> 0

Sheet RETRATO
A1: =PARAMETROS!C4&" — RETRATO DE "&PARAMETROS!$C$7 -> BOTÂNICO — RETRATO DE 2027
A2: ="Ano escolhido em PARAMETROS!C7. Avanço financeiro = acumulado no fim do ano ÷ projeção." -> Ano escolhido em PARAMETROS!C7. Avanço financeiro = acumulado no fim do ano ÷ projeção.
A4: Código | B4: Disciplina | C4: Grupo | D4: Projeção (R$) | E4: Acumulado até o ano anterior | F4: Desembolso no ano | G4: Acumulado no fim do ano | H4: Avanço financeiro acumulado | I4: Saldo após o ano | J4: Observações / justificativa
A5: =FLUXO_MENSAL!A8 -> 01 | B5: =FLUXO_MENSAL!B8 -> PROJETOS | C5: =FLUXO_MENSAL!C8 -> INDIRETOS | D5: =FLUXO_MENSAL!D8 -> 2640655 | E5: =SUMPRODUCT((FLUXO_MENSAL!$J$7:$CC$7<DATE(PARAMETROS!$C$7,1,1))*FLUXO_MENSAL!$J8:$CC8) -> 2337005.7 | F5: =SUMPRODUCT((YEAR(FLUXO_MENSAL!$J$7:$CC$7)=PARAMETROS!$C$7)*FLUXO_MENSAL!$J8:$CC8) -> 26933 | G5: =E5+F5 -> 2363938.7 | H5: =IF(D5=0,0,G5/D5) -> 0.89520923 | I5: =D5-G5 -> 276716.27
A6: =FLUXO_MENSAL!A9 -> 02 | B6: =FLUXO_MENSAL!B9 -> SEGUROS | C6: =FLUXO_MENSAL!C9 -> INDIRETOS | D6: =FLUXO_MENSAL!D9 -> 127911.99 | E6: =SUMPRODUCT((FLUXO_MENSAL!$J$7:$CC$7<DATE(PARAMETROS!$C$7,1,1))*FLUXO_MENSAL!$J9:$CC9) -> 0 | F6: =SUMPRODUCT((YEAR(FLUXO_MENSAL!$J$7:$CC$7)=PARAMETROS!$C$7)*FLUXO_MENSAL!$J9:$CC9) -> 0 | G6: =E6+F6 -> 0 | H6: =IF(D6=0,0,G6/D6) -> 0 | I6: =D6-G6 -> 127911.99
A7: =FLUXO_MENSAL!A10 -> 03 | B7: =FLUXO_MENSAL!B10 -> TAXAS DIVERSAS | C7: =FLUXO_MENSAL!C10 -> INDIRETOS | D7: =FLUXO_MENSAL!D10 -> 158047.46 | E7: =SUMPRODUCT((FLUXO_MENSAL!$J$7:$CC$7<DATE(PARAMETROS!$C$7,1,1))*FLUXO_MENSAL!$J10:$CC10) -> 7766.0207 | F7: =SUMPRODUCT((YEAR(FLUXO_MENSAL!$J$7:$CC$7)=PARAMETROS!$C$7)*FLUXO_MENSAL!$J10:$CC10) -> 2791.2461 | G7: =E7+F7 -> 10557.267 | H7: =IF(D7=0,0,G7/D7) -> 0.06679808 | I7: =D7-G7 -> 147490.19
A8: =FLUXO_MENSAL!A11 -> 04 | B8: =FLUXO_MENSAL!B11 -> BARRACAO DE OBRA | C8: =FLUXO_MENSAL!C11 -> INDIRETOS | D8: =FLUXO_MENSAL!D11 -> 1249911.1 | E8: =SUMPRODUCT((FLUXO_MENSAL!$J$7:$CC$7<DATE(PARAMETROS!$C$7,1,1))*FLUXO_MENSAL!$J11:$CC11) -> 701836.67 | F8: =SUMPRODUCT((YEAR(FLUXO_MENSAL!$J$7:$CC$7)=PARAMETROS!$C$7)*FLUXO_MENSAL!$J11:$CC11) -> 369182.92 | G8: =E8+F8 -> 1071019.6 | H8: =IF(D8=0,0,G8/D8) -> 0.85687663 | I8: =D8-G8 -> 178891.48
A9: =FLUXO_MENSAL!A12 -> 05 | B9: =FLUXO_MENSAL!B12 -> LIGAÇÕES PROVISÓRIAS AGUA, ENERGIA,TELEFONIA, ESGOTO | C9: =FLUXO_MENSAL!C12 -> INDIRETOS | D9: =FLUXO_MENSAL!D12 -> 85665.05 | E9: =SUMPRODUCT((FLUXO_MENSAL!$J$7:$CC$7<DATE(PARAMETROS!$C$7,1,1))*FLUXO_MENSAL!$J12:$CC12) -> 0 | F9: =SUMPRODUCT((YEAR(FLUXO_MENSAL!$J$7:$CC$7)=PARAMETROS!$C$7)*FLUXO_MENSAL!$J12:$CC12) -> 0 | G9: =E9+F9 -> 0 | H9: =IF(D9=0,0,G9/D9) -> 0 | I9: =D9-G9 -> 85665.05
A10: =FLUXO_MENSAL!A13 -> 06 | B10: =FLUXO_MENSAL!B13 -> CONSUMO DE ÁGUA, ENERGIA, ETC. | C10: =FLUXO_MENSAL!C13 -> INDIRETOS | D10: =FLUXO_MENSAL!D13 -> 544229.22 | E10: =SUMPRODUCT((FLUXO_MENSAL!$J$7:$CC$7<DATE(PARAMETROS!$C$7,1,1))*FLUXO_MENSAL!$J13:$CC13) -> 85456.491 | F10: =SUMPRODUCT((YEAR(FLUXO_MENSAL!$J$7:$CC$7)=PARAMETROS!$C$7)*FLUXO_MENSAL!$J13:$CC13) -> 143909.55 | G10: =E10+F10 -> 229366.04 | H10: =IF(D10=0,0,G10/D10) -> 0.42145117 | I10: =D10-G10 -> 314863.18
A11: =FLUXO_MENSAL!A14 -> 07 | B11: =FLUXO_MENSAL!B14 -> DIVERSOS | C11: =FLUXO_MENSAL!C14 -> INDIRETOS | D11: =FLUXO_MENSAL!D14 -> 194480.67 | E11: =SUMPRODUCT((FLUXO_MENSAL!$J$7:$CC$7<DATE(PARAMETROS!$C$7,1,1))*FLUXO_MENSAL!$J14:$CC14) -> 52314.872 | F11: =SUMPRODUCT((YEAR(FLUXO_MENSAL!$J$7:$CC$7)=PARAMETROS!$C$7)*FLUXO_MENSAL!$J14:$CC14) -> 64636.363 | G11: =E11+F11 -> 116951.24 | H11: =IF(D11=0,0,G11/D11) -> 0.60135146 | I11: =D11-G11 -> 77529.435
A12: =FLUXO_MENSAL!A15 -> 08 | B12: =FLUXO_MENSAL!B15 -> TRANSPORTES | C12: =FLUXO_MENSAL!C15 -> INDIRETOS | D12: =FLUXO_MENSAL!D15 -> 817599.43 | E12: =SUMPRODUCT((FLUXO_MENSAL!$J$7:$CC$7<DATE(PARAMETROS!$C$7,1,1))*FLUXO_MENSAL!$J15:$CC15) -> 128868.52 | F12: =SUMPRODUCT((YEAR(FLUXO_MENSAL!$J$7:$CC$7)=PARAMETROS!$C$7)*FLUXO_MENSAL!$J15:$CC15) -> 347554.68 | G12: =E12+F12 -> 476423.2 | H12: =IF(D12=0,0,G12/D12) -> 0.5827098 | I12: =D12-G12 -> 341176.23
A13: =FLUXO_MENSAL!A16 -> 09 | B13: =FLUXO_MENSAL!B16 -> CONSULTORIAS (OBRAS) | C13: =FLUXO_MENSAL!C16 -> INDIRETOS | D13: =FLUXO_MENSAL!D16 -> 1371532.1 | E13: =SUMPRODUCT((FLUXO_MENSAL!$J$7:$CC$7<DATE(PARAMETROS!$C$7,1,1))*FLUXO_MENSAL!$J16:$CC16) -> 799400.09 | F13: =SUMPRODUCT((YEAR(FLUXO_MENSAL!$J$7:$CC$7)=PARAMETROS!$C$7)*FLUXO_MENSAL!$J16:$CC16) -> 247855.92 | G13: =E13+F13 -> 1047256 | H13: =IF(D13=0,0,G13/D13) -> 0.76356652 | I13: =D13-G13 -> 324276.11
A14: =FLUXO_MENSAL!A17 -> 10 | B14: =FLUXO_MENSAL!B17 -> MÃO DE OBRA PRÓPRIA | C14: =FLUXO_MENSAL!C17 -> INDIRETOS | D14: =FLUXO_MENSAL!D17 -> 21271106 | E14: =SUMPRODUCT((FLUXO_MENSAL!$J$7:$CC$7<DATE(PARAMETROS!$C$7,1,1))*FLUXO_MENSAL!$J17:$CC17) -> 4792494.5 | F14: =SUMPRODUCT((YEAR(FLUXO_MENSAL!$J$7:$CC$7)=PARAMETROS!$C$7)*FLUXO_MENSAL!$J17:$CC17) -> 5917364.9 | G14: =E14+F14 -> 10709859 | H14: =IF(D14=0,0,G14/D14) -> 0.5034933 | I14: =D14-G14 -> 10561247
A15: =FLUXO_MENSAL!A18 -> 11 | B15: =FLUXO_MENSAL!B18 -> EQUIPAMENTOS E FERRAMENTAS | C15: =FLUXO_MENSAL!C18 -> INDIRETOS | D15: =FLUXO_MENSAL!D18 -> 6774432.9 | E15: =SUMPRODUCT((FLUXO_MENSAL!$J$7:$CC$7<DATE(PARAMETROS!$C$7,1,1))*FLUXO_MENSAL!$J18:$CC18) -> 1193007.5 | F15: =SUMPRODUCT((YEAR(FLUXO_MENSAL!$J$7:$CC$7)=PARAMETROS!$C$7)*FLUXO_MENSAL!$J18:$CC18) -> 2728658 | G15: =E15+F15 -> 3921665.5 | H15: =IF(D15=0,0,G15/D15) -> 0.57889207 | I15: =D15-G15 -> 2852767.4
A16: =FLUXO_MENSAL!A19 -> 12 | B16: =FLUXO_MENSAL!B19 -> SERVIÇOS INICIAIS | C16: =FLUXO_MENSAL!C19 -> INFRAESTRUTURA | D16: =FLUXO_MENSAL!D19 -> 176378.52 | E16: =SUMPRODUCT((FLUXO_MENSAL!$J$7:$CC$7<DATE(PARAMETROS!$C$7,1,1))*FLUXO_MENSAL!$J19:$CC19) -> 112166.04 | F16: =SUMPRODUCT((YEAR(FLUXO_MENSAL!$J$7:$CC$7)=PARAMETROS!$C$7)*FLUXO_MENSAL!$J19:$CC19) -> 64212.48 | G16: =E16+F16 -> 176378.52 | H16: =IF(D16=0,0,G16/D16) -> 1 | I16: =D16-G16 -> 0
... A54: =FLUXO_MENSAL!A57 | B54: =FLUXO_MENSAL!B57 | C54: =FLUXO_MENSAL!C57 | D54: =FLUXO_MENSAL!D57 -> 0 | E54: =SUMPRODUCT((FLUXO_MENSAL!$J$7:$CC$7<DATE(PARAMETROS!$C$7,1,1))*FLUXO_MENSAL!$J57:$CC57) -> 0 | F54: =SUMPRODUCT((YEAR(FLUXO_MENSAL!$J$7:$CC$7)=PARAMETROS!$C$7)*FLUXO_MENSAL!$J57:$CC57) -> 0 | G54: =E54+F54 -> 0 | H54: =IF(D54=0,0,G54/D54) -> 0 | I54: =D54-G54 -> 0
B55: TOTAL (com taxa de administração) | D55: =SUM(D5:D54) -> 1.5933311e+08 | E55: =SUM(E5:E54) -> 30155129 | F55: =SUM(F5:F54) -> 48540176 | G55: =SUM(G5:G54) -> 78695305 | H55: =IF(D55=0,0,G55/D55) -> 0.49390428 | I55: =SUM(I5:I54) -> 80637805
B56: TOTAL sem taxa de administração | D56: =D55-SUMIF($C$5:$C$54,"TAXA DE ADMINISTRAÇÃO",D$5:D$54) -> 1.58767e+08 | E56: =E55-SUMIF($C$5:$C$54,"TAXA DE ADMINISTRAÇÃO",E$5:E$54) -> 29589023 | F56: =F55-SUMIF($C$5:$C$54,"TAXA DE ADMINISTRAÇÃO",F$5:F$54) -> 48540176 | G56: =G55-SUMIF($C$5:$C$54,"TAXA DE ADMINISTRAÇÃO",G$5:G$54) -> 78129200 | H56: =IF(D56=0,0,G56/D56) -> 0.49209973 | I56: =I55-SUMIF($C$5:$C$54,"TAXA DE ADMINISTRAÇÃO",I$5:I$54) -> 80637805
B58: Resumo por grupo
B59: Grupo | D59: Projeção (R$) | E59: Acumulado até o ano anterior | F59: Desembolso no ano | G59: Acumulado no fim do ano | H59: Avanço financeiro acumulado | I59: Saldo após o ano
B60: =IF(PARAMETROS!E4="","",PARAMETROS!E4) -> INDIRETOS | D60: =IF($B60="","",SUMIF($C$5:$C$54,$B60,D$5:D$54)) -> 35235571 | E60: =IF($B60="","",SUMIF($C$5:$C$54,$B60,E$5:E$54)) -> 10098150 | F60: =IF($B60="","",SUMIF($C$5:$C$54,$B60,F$5:F$54)) -> 9848886.5 | G60: =IF($B60="","",SUMIF($C$5:$C$54,$B60,G$5:G$54)) -> 19947037 | H60: =IF($B60="","",IF(D60=0,0,G60/D60)) -> 0.56610511 | I60: =IF($B60="","",SUMIF($C$5:$C$54,$B60,I$5:I$54)) -> 15288534
B61: =IF(PARAMETROS!E5="","",PARAMETROS!E5) -> INFRAESTRUTURA | D61: =IF($B61="","",SUMIF($C$5:$C$54,$B61,D$5:D$54)) -> 14305656 | E61: =IF($B61="","",SUMIF($C$5:$C$54,$B61,E$5:E$54)) -> 12502808 | F61: =IF($B61="","",SUMIF($C$5:$C$54,$B61,F$5:F$54)) -> 1318864.3 | G61: =IF($B61="","",SUMIF($C$5:$C$54,$B61,G$5:G$54)) -> 13821672 | H61: =IF($B61="","",IF(D61=0,0,G61/D61)) -> 0.96616833 | I61: =IF($B61="","",SUMIF($C$5:$C$54,$B61,I$5:I$54)) -> 483984.24
B62: =IF(PARAMETROS!E6="","",PARAMETROS!E6) -> ESTRUTURA | D62: =IF($B62="","",SUMIF($C$5:$C$54,$B62,D$5:D$54)) -> 26850931 | E62: =IF($B62="","",SUMIF($C$5:$C$54,$B62,E$5:E$54)) -> 6406093.9 | F62: =IF($B62="","",SUMIF($C$5:$C$54,$B62,F$5:F$54)) -> 17796165 | G62: =IF($B62="","",SUMIF($C$5:$C$54,$B62,G$5:G$54)) -> 24202259 | H62: =IF($B62="","",IF(D62=0,0,G62/D62)) -> 0.90135639 | I62: =IF($B62="","",SUMIF($C$5:$C$54,$B62,I$5:I$54)) -> 2648672.7
B63: =IF(PARAMETROS!E7="","",PARAMETROS!E7) -> SISTEMAS E VEDAÇÕES | D63: =IF($B63="","",SUMIF($C$5:$C$54,$B63,D$5:D$54)) -> 36811424 | E63: =IF($B63="","",SUMIF($C$5:$C$54,$B63,E$5:E$54)) -> 574971.51 | F63: =IF($B63="","",SUMIF($C$5:$C$54,$B63,F$5:F$54)) -> 11219763 | G63: =IF($B63="","",SUMIF($C$5:$C$54,$B63,G$5:G$54)) -> 11794734 | H63: =IF($B63="","",IF(D63=0,0,G63/D63)) -> 0.32040961 | I63: =IF($B63="","",SUMIF($C$5:$C$54,$B63,I$5:I$54)) -> 25016690
B64: =IF(PARAMETROS!E8="","",PARAMETROS!E8) -> ACABAMENTOS | D64: =IF($B64="","",SUMIF($C$5:$C$54,$B64,D$5:D$54)) -> 45563422 | E64: =IF($B64="","",SUMIF($C$5:$C$54,$B64,E$5:E$54)) -> 7000 | F64: =IF($B64="","",SUMIF($C$5:$C$54,$B64,F$5:F$54)) -> 8356498.1 | G64: =IF($B64="","",SUMIF($C$5:$C$54,$B64,G$5:G$54)) -> 8363498.1 | H64: =IF($B64="","",IF(D64=0,0,G64/D64)) -> 0.18355729 | I64: =IF($B64="","",SUMIF($C$5:$C$54,$B64,I$5:I$54)) -> 37199924
B65: =IF(PARAMETROS!E9="","",PARAMETROS!E9) -> TAXA DE ADMINISTRAÇÃO | D65: =IF($B65="","",SUMIF($C$5:$C$54,$B65,D$5:D$54)) -> 566105.29 | E65: =IF($B65="","",SUMIF($C$5:$C$54,$B65,E$5:E$54)) -> 566105.29 | F65: =IF($B65="","",SUMIF($C$5:$C$54,$B65,F$5:F$54)) -> 0 | G65: =IF($B65="","",SUMIF($C$5:$C$54,$B65,G$5:G$54)) -> 566105.29 | H65: =IF($B65="","",IF(D65=0,0,G65/D65)) -> 1 | I65: =IF($B65="","",SUMIF($C$5:$C$54,$B65,I$5:I$54)) -> 0
B66: =IF(PARAMETROS!E10="","",PARAMETROS!E10) | D66: =IF($B66="","",SUMIF($C$5:$C$54,$B66,D$5:D$54)) | E66: =IF($B66="","",SUMIF($C$5:$C$54,$B66,E$5:E$54)) | F66: =IF($B66="","",SUMIF($C$5:$C$54,$B66,F$5:F$54)) | G66: =IF($B66="","",SUMIF($C$5:$C$54,$B66,G$5:G$54)) | H66: =IF($B66="","",IF(D66=0,0,G66/D66)) | I66: =IF($B66="","",SUMIF($C$5:$C$54,$B66,I$5:I$54))
B67: =IF(PARAMETROS!E11="","",PARAMETROS!E11) | D67: =IF($B67="","",SUMIF($C$5:$C$54,$B67,D$5:D$54)) | E67: =IF($B67="","",SUMIF($C$5:$C$54,$B67,E$5:E$54)) | F67: =IF($B67="","",SUMIF($C$5:$C$54,$B67,F$5:F$54)) | G67: =IF($B67="","",SUMIF($C$5:$C$54,$B67,G$5:G$54)) | H67: =IF($B67="","",IF(D67=0,0,G67/D67)) | I67: =IF($B67="","",SUMIF($C$5:$C$54,$B67,I$5:I$54))
B68: =IF(PARAMETROS!E12="","",PARAMETROS!E12) | D68: =IF($B68="","",SUMIF($C$5:$C$54,$B68,D$5:D$54)) | E68: =IF($B68="","",SUMIF($C$5:$C$54,$B68,E$5:E$54)) | F68: =IF($B68="","",SUMIF($C$5:$C$54,$B68,F$5:F$54)) | G68: =IF($B68="","",SUMIF($C$5:$C$54,$B68,G$5:G$54)) | H68: =IF($B68="","",IF(D68=0,0,G68/D68)) | I68: =IF($B68="","",SUMIF($C$5:$C$54,$B68,I$5:I$54))
B69: =IF(PARAMETROS!E13="","",PARAMETROS!E13) | D69: =IF($B69="","",SUMIF($C$5:$C$54,$B69,D$5:D$54)) | E69: =IF($B69="","",SUMIF($C$5:$C$54,$B69,E$5:E$54)) | F69: =IF($B69="","",SUMIF($C$5:$C$54,$B69,F$5:F$54)) | G69: =IF($B69="","",SUMIF($C$5:$C$54,$B69,G$5:G$54)) | H69: =IF($B69="","",IF(D69=0,0,G69/D69)) | I69: =IF($B69="","",SUMIF($C$5:$C$54,$B69,I$5:I$54))
B70: =IF(PARAMETROS!E14="","",PARAMETROS!E14) | D70: =IF($B70="","",SUMIF($C$5:$C$54,$B70,D$5:D$54)) | E70: =IF($B70="","",SUMIF($C$5:$C$54,$B70,E$5:E$54)) | F70: =IF($B70="","",SUMIF($C$5:$C$54,$B70,F$5:F$54)) | G70: =IF($B70="","",SUMIF($C$5:$C$54,$B70,G$5:G$54)) | H70: =IF($B70="","",IF(D70=0,0,G70/D70)) | I70: =IF($B70="","",SUMIF($C$5:$C$54,$B70,I$5:I$54))
B71: =IF(PARAMETROS!E15="","",PARAMETROS!E15) | D71: =IF($B71="","",SUMIF($C$5:$C$54,$B71,D$5:D$54)) | E71: =IF($B71="","",SUMIF($C$5:$C$54,$B71,E$5:E$54)) | F71: =IF($B71="","",SUMIF($C$5:$C$54,$B71,F$5:F$54)) | G71: =IF($B71="","",SUMIF($C$5:$C$54,$B71,G$5:G$54)) | H71: =IF($B71="","",IF(D71=0,0,G71/D71)) | I71: =IF($B71="","",SUMIF($C$5:$C$54,$B71,I$5:I$54))
