Workbook

Sheet LEIA-ME
A1: PLANILHA EM BRANCO — como começar uma obra nova
A2: Preencha só as células/abas de ENTRADA (texto azul, fundo amarelo nos parâmetros). O resto é fórmula e se calcula sozinho.
A3: Os exemplos em cinza mostram o formato esperado (valores do Botânico, só como referência).
A5: 1. VALOR POR PL — parâmetros e orçamento
A6: P9 = nome da obra · K6 = início do fluxo (1º mês; o realizado anterior entra acumulado nele) · K5 = data de corte (último mês fechado)
A7: H6 = INCC base do orçamento · K7 = limite de avanço físico para usar o Prevision (padrão 10%)
A8: Por PL (linhas 11 a 48): F = orçamento base (R$) · L = projeção atual (R$) · I = DIRETO/INDIRETO
A9: Exemplo: 01 PROJETOS | F: 2.400.000,00 | L: 2.640.655,00 | I: INDIRETO
A10: 2. "INCC-FGV" — índices mensais (já preenchidos até ago/2026; acrescente os meses seguintes)
A11: Exemplo: A = 01/09/2026 | B = 1.305,42 (número-índice do INCC-DI, não a variação %)
A12: 3. DADOS BRUTOS — cole a tabela dinâmica do ERP a partir de A1 (Colar especial → Valores)
A13: Linha 2 = meses (datas) a partir de B2 · coluna A = grupos a partir da linha 3
... A58: • Tabela, PREMISSAS e AUX.ESTRUTURA foram copiadas como estavam (somente valores), para consulta.

Sheet DASHBOARD
B2: ='VALOR POR PL'!$P$9&" · FLUXO DE CAIXA DA OBRA"
B3: ="Data de corte: "&CHOOSE(MONTH('VALOR POR PL'!$P$5),"Janeiro","Fevereiro","Março","Abril","Maio","Junho","Julho","Agosto","Setembro","Outubro","Novembro","Dezembro")&"/"&YEAR('VALOR POR PL'!$P$5)&" · Ano do retrato: "&'RETRATO 2027'!$D$5&" · Cenário: "&IF('VALOR POR PL'!$K$8="PADRÃO","padrão (curvas digitadas)","Prevision")&" · R$ nominais, com taxa de adm."
B5: PROJEÇÃO TOTAL | D5: REALIZADO ATÉ O CORTE | E5: % REALIZADO | F5: ="DESEMBOLSO EM "&'RETRATO 2027'!$D$5 | H5: SALDO A REALIZAR | I5: CONFERÊNCIA
B6: ='VALOR POR PL'!L50 | D6: =SUMPRODUCT(('MODELO PARA BI'!$H$1:$CA$1<='VALOR POR PL'!$P$5)*'MODELO PARA BI'!$H$63:$CA$63) | E6: =IF(B6=0,0,D6/B6) | F6: =SUMPRODUCT((YEAR('MODELO PARA BI'!$H$1:$CA$1)='RETRATO 2027'!$D$5)*'MODELO PARA BI'!$H$63:$CA$63) | H6: =SUM('MODELO PARA BI'!$H$63:$CA$63)-D6 | I6: =IF(COUNTIF('VALOR POR PL'!$F$54:$F$59,"⚠*")=0,"✓ Tudo OK","⚠ "&COUNTIF('VALOR POR PL'!$F$54:$F$59,"⚠*")&" pendência(s)")
B7: orçamento projetado (IEC) | D7: incorrido no ERP | E7: da projeção | F7: realizado + previsto | H7: após a data de corte | I7: detalhes em VALOR POR PL
B10: REALIZADO (ATUAL)
B11: =CHOOSE(MONTH(DATE(YEAR('VALOR POR PL'!$P$5),MONTH('VALOR POR PL'!$P$5)+1,1)),"Janeiro","Fevereiro","Março","Abril","Maio","Junho","Julho","Agosto","Setembro","Outubro","Novembro","Dezembro")&"/"&YEAR(DATE(YEAR('VALOR POR PL'!$P$5),MONTH('VALOR POR PL'!$P$5)+1,1)) | H11: COMPOSIÇÃO DO ANO
B12: Ano | C12: Anual R$ | D12: Acumulado R$ | E12: Anual % | F12: Acumulado % | H12: Realizado R$ | I12: A realizar R$
B13: =YEAR('VALOR POR PL'!$P$6)+0 | C13: =SUMPRODUCT((YEAR('MODELO PARA BI'!$H$1:$CA$1)=B13)*'MODELO PARA BI'!$H$63:$CA$63) | D13: =C13 | E13: =IF($C$20=0,0,C13/$C$20) | F13: =IF($C$20=0,0,D13/$C$20) | H13: =SUMPRODUCT((YEAR('MODELO PARA BI'!$H$1:$CA$1)=B13)*('MODELO PARA BI'!$H$1:$CA$1<='VALOR POR PL'!$P$5)*'MODELO PARA BI'!$H$63:$CA$63) | I13: =C13-H13
B14: =YEAR('VALOR POR PL'!$P$6)+1 | C14: =SUMPRODUCT((YEAR('MODELO PARA BI'!$H$1:$CA$1)=B14)*'MODELO PARA BI'!$H$63:$CA$63) | D14: =D13+C14 | E14: =IF($C$20=0,0,C14/$C$20) | F14: =IF($C$20=0,0,D14/$C$20) | H14: =SUMPRODUCT((YEAR('MODELO PARA BI'!$H$1:$CA$1)=B14)*('MODELO PARA BI'!$H$1:$CA$1<='VALOR POR PL'!$P$5)*'MODELO PARA BI'!$H$63:$CA$63) | I14: =C14-H14
B15: =YEAR('VALOR POR PL'!$P$6)+2 | C15: =SUMPRODUCT((YEAR('MODELO PARA BI'!$H$1:$CA$1)=B15)*'MODELO PARA BI'!$H$63:$CA$63) | D15: =D14+C15 | E15: =IF($C$20=0,0,C15/$C$20) | F15: =IF($C$20=0,0,D15/$C$20) | H15: =SUMPRODUCT((YEAR('MODELO PARA BI'!$H$1:$CA$1)=B15)*('MODELO PARA BI'!$H$1:$CA$1<='VALOR POR PL'!$P$5)*'MODELO PARA BI'!$H$63:$CA$63) | I15: =C15-H15
B16: =YEAR('VALOR POR PL'!$P$6)+3 | C16: =SUMPRODUCT((YEAR('MODELO PARA BI'!$H$1:$CA$1)=B16)*'MODELO PARA BI'!$H$63:$CA$63) | D16: =D15+C16 | E16: =IF($C$20=0,0,C16/$C$20) | F16: =IF($C$20=0,0,D16/$C$20) | H16: =SUMPRODUCT((YEAR('MODELO PARA BI'!$H$1:$CA$1)=B16)*('MODELO PARA BI'!$H$1:$CA$1<='VALOR POR PL'!$P$5)*'MODELO PARA BI'!$H$63:$CA$63) | I16: =C16-H16
B17: =YEAR('VALOR POR PL'!$P$6)+4 | C17: =SUMPRODUCT((YEAR('MODELO PARA BI'!$H$1:$CA$1)=B17)*'MODELO PARA BI'!$H$63:$CA$63) | D17: =D16+C17 | E17: =IF($C$20=0,0,C17/$C$20) | F17: =IF($C$20=0,0,D17/$C$20) | H17: =SUMPRODUCT((YEAR('MODELO PARA BI'!$H$1:$CA$1)=B17)*('MODELO PARA BI'!$H$1:$CA$1<='VALOR POR PL'!$P$5)*'MODELO PARA BI'!$H$63:$CA$63) | I17: =C17-H17
B18: =YEAR('VALOR POR PL'!$P$6)+5 | C18: =SUMPRODUCT((YEAR('MODELO PARA BI'!$H$1:$CA$1)=B18)*'MODELO PARA BI'!$H$63:$CA$63) | D18: =D17+C18 | E18: =IF($C$20=0,0,C18/$C$20) | F18: =IF($C$20=0,0,D18/$C$20) | H18: =SUMPRODUCT((YEAR('MODELO PARA BI'!$H$1:$CA$1)=B18)*('MODELO PARA BI'!$H$1:$CA$1<='VALOR POR PL'!$P$5)*'MODELO PARA BI'!$H$63:$CA$63) | I18: =C18-H18
B19: =YEAR('VALOR POR PL'!$P$6)+6 | C19: =SUMPRODUCT((YEAR('MODELO PARA BI'!$H$1:$CA$1)=B19)*'MODELO PARA BI'!$H$63:$CA$63) | D19: =D18+C19 | E19: =IF($C$20=0,0,C19/$C$20) | F19: =IF($C$20=0,0,D19/$C$20) | H19: =SUMPRODUCT((YEAR('MODELO PARA BI'!$H$1:$CA$1)=B19)*('MODELO PARA BI'!$H$1:$CA$1<='VALOR POR PL'!$P$5)*'MODELO PARA BI'!$H$63:$CA$63) | I19: =C19-H19
B20: TOTAL | C20: =SUM(C13:C19) | E20: =SUM(E13:E19) | H20: =SUM(H13:H19) | I20: =SUM(I13:I19)
B21: Linha destacada = ano do retrato (RETRATO 2027!D5). Realizado = até a data de corte; a realizar = previsto depois dela.
B24: ="DESEMBOLSO EM "&'RETRATO 2027'!$D$5&" POR GRUPO"
B25: Grupo | D25: R$ | E25: % do ano | F25: Avanço financeiro
B26: Indiretos (01 a 11) | D26: =SUM('RETRATO 2027'!F12:F22) | E26: =IF($D$32=0,0,D26/$D$32) | F26: =IFERROR(SUMPRODUCT('RETRATO 2027'!J12:J22,'RETRATO 2027'!M12:M22)/SUM('RETRATO 2027'!M12:M22),0)
B27: Infraestrutura (12 a 16) | D27: =SUM('RETRATO 2027'!F24:F28) | E27: =IF($D$32=0,0,D27/$D$32) | F27: =IFERROR(SUMPRODUCT('RETRATO 2027'!J24:J28,'RETRATO 2027'!M24:M28)/SUM('RETRATO 2027'!M24:M28),0)
B28: Estrutura (17) | D28: =SUM('RETRATO 2027'!F30:F30) | E28: =IF($D$32=0,0,D28/$D$32) | F28: =IFERROR(SUMPRODUCT('RETRATO 2027'!J30:J30,'RETRATO 2027'!M30:M30)/SUM('RETRATO 2027'!M30:M30),0)
B29: Vedações, instalações e elevadores (18 a 24) | D29: =SUM('RETRATO 2027'!F31:F37) | E29: =IF($D$32=0,0,D29/$D$32) | F29: =IFERROR(SUMPRODUCT('RETRATO 2027'!J31:J37,'RETRATO 2027'!M31:M37)/SUM('RETRATO 2027'!M31:M37),0)
B30: Acabamentos (25 a 37) | D30: =SUM('RETRATO 2027'!F38:F50) | E30: =IF($D$32=0,0,D30/$D$32) | F30: =IFERROR(SUMPRODUCT('RETRATO 2027'!J38:J50,'RETRATO 2027'!M38:M50)/SUM('RETRATO 2027'!M38:M50),0)
B31: Taxa de administração | D31: =SUM('RETRATO 2027'!F52:F52) | E31: =IF($D$32=0,0,D31/$D$32)
B32: TOTAL | D32: =SUM(D26:D31) | E32: =SUM(E26:E31)
B33: Avanço financeiro = acumulado até dezembro do ano ÷ projeção. | F33: =IF(ABS(D32-F6)<1,"✓ confere com o cartão","⚠ diferente do cartão")
B36: CURVA S — % ACUMULADO DA PROJEÇÃO

Sheet Tabela

Sheet VALOR POR PL
B3: ORÇAMENTO - NOVA OBRA | J3: ACOMPANHAMENTO IEC
B5: INCC 10-25 | D5: TOTAL | E5: =E50 | F5: =F50 | G5: =G50 | H5: INCC BASE DO ORÇAMENTO | J5: DATA DE CORTE -> | K5: 46235 | O5: Corte (1º dia do mês) | P5: =DATE(YEAR(K5),MONTH(K5),1)
B6: ORÇ EM INCC | J6: INÍCIO DO FLUXO -> | K6: 45627 | O6: Início (1º dia do mês) | P6: =DATE(YEAR(K6),MONTH(K6),1)
B7: ORÇ 10-25 | C7: =C6*C5 | D7: TAXA DE ADMINISTRAÇÃO | E7: =IF(F49=0,0,F48/F49) | F7: =F48 | G7: =G48 | J7: LIMITE DE AVANÇO FÍSICO P/ USAR PREVISION -> | K7: 1 | O7: INCC no mês de corte | P7: =IFERROR(INDEX('"INCC-FGV"'!$B$2:$B$400,MATCH(P5,'"INCC-FGV"'!$A$2:$A$400,0)),IFERROR(INDEX('"INCC-FGV"'!$B$2:$B$400,MATCH(P5,'"INCC-FGV"'!$A$2:$A$400,1)),"FALTA INCC"))
D8: SUBTOTAL | E8: =IF(F50=0,0,F49/F50) | F8: =F49 | G8: =G49 | J8: CENÁRIO DAS CURVAS -> | K8: PREVISION | O8: Último mês do horizonte | P8: =DATE(YEAR(P6),MONTH(P6)+71,1)
O9: Obra | P9: NOVA OBRA
B10: CPU | C10: CÓDIGO | D10: DESCRIÇÃO / SERVIÇO | E10: PESO DO ORÇAMENTO | F10: VALOR EM R$ (orçamento base) | G10: VALOR EM INCC (F ÷ INCC base) | H10: VALOR EM INCC | I10: TIPO | J10: PL | K10: ORÇAMENTO REAJUSTADO (INCC do corte) | L10: PROJEÇÃO (R$) | M10: VARIAÇÃO | N10: CONFERÊNCIA | O10: FONTE DA CURVA | P10: AVANÇO FÍSICO (Prevision, corte) | Q10: CÓD. NO PREVISION | R10: CURVA PREVISTA DE OUTRO PL (cód. Prevision)
B11: PL001.001 | C11: 01 | D11: PROJETOS | E11: =IF($F$50=0,0,F11/$F$50) | G11: =IF($H$6=0,0,F11/$H$6) | H11: =G11 | I11: INDIRETO | J11: PROJETOS | K11: =IF(ISNUMBER($P$7),G11*$P$7,0) | M11: =L11-K11 | N11: =IF(D11="","",IF('PROJETO'!$C$78>L11+1,"⚠ Incorrido acima da projeção",IF(AND('PROJETO'!$K$18>1,'PROJETO'!$K$17=0),"⚠ Saldo sem curva (preencha a coluna H da aba)",IF(ABS('PROJETO'!$D$80)>1,"⚠ Verificar","OK")))) | O11: ='PROJETO'!$K$16 | P11: ='PROJETO'!$K$14 | Q11: 01
B12: PL350.001 | C12: 02 | D12: SEGUROS | E12: =IF($F$50=0,0,F12/$F$50) | G12: =IF($H$6=0,0,F12/$H$6) | H12: =G12 | I12: INDIRETO | J12: SEGURO DE OBRA | K12: =IF(ISNUMBER($P$7),G12*$P$7,0) | M12: =L12-K12 | N12: =IF(D12="","",IF('SEGUROS'!$C$78>L12+1,"⚠ Incorrido acima da projeção",IF(AND('SEGUROS'!$K$18>1,'SEGUROS'!$K$17=0),"⚠ Saldo sem curva (preencha a coluna H da aba)",IF(ABS('SEGUROS'!$D$80)>1,"⚠ Verificar","OK")))) | O12: ='SEGUROS'!$K$16 | P12: ='SEGUROS'!$K$14 | Q12: 02
B13: PL001.016 | C13: 03 | D13: TAXAS DIVERSAS | E13: =IF($F$50=0,0,F13/$F$50) | G13: =IF($H$6=0,0,F13/$H$6) | H13: =G13 | I13: INDIRETO | J13: TAXAS DIVERSAS | K13: =IF(ISNUMBER($P$7),G13*$P$7,0) | M13: =L13-K13 | N13: =IF(D13="","",IF('TAX. DIVERSAS'!$C$78>L13+1,"⚠ Incorrido acima da projeção",IF(AND('TAX. DIVERSAS'!$K$18>1,'TAX. DIVERSAS'!$K$17=0),"⚠ Saldo sem curva (preencha a coluna H da aba)",IF(ABS('TAX. DIVERSAS'!$D$80)>1,"⚠ Verificar","OK")))) | O13: ='TAX. DIVERSAS'!$K$16 | P13: ='TAX. DIVERSAS'!$K$14 | Q13: 03
B14: PL010.005 | C14: 04 | D14: BARRACAO DE OBRA | E14: =IF($F$50=0,0,F14/$F$50) | G14: =IF($H$6=0,0,F14/$H$6) | H14: =G14 | I14: INDIRETO | J14: BARRACAO DE OBRA | K14: =IF(ISNUMBER($P$7),G14*$P$7,0) | M14: =L14-K14 | N14: =IF(D14="","",IF('BARRACÃO DE OBRA'!$C$78>L14+1,"⚠ Incorrido acima da projeção",IF(AND('BARRACÃO DE OBRA'!$K$18>1,'BARRACÃO DE OBRA'!$K$17=0),"⚠ Saldo sem curva (preencha a coluna H da aba)",IF(ABS('BARRACÃO DE OBRA'!$D$80)>1,"⚠ Verificar","OK")))) | O14: ='BARRACÃO DE OBRA'!$K$16 | P14: ='BARRACÃO DE OBRA'!$K$14 | Q14: 04
B15: PL020.004 | C15: 05 | D15: LIGAÇÕES PROVISÓRIAS AGUA, ENERGIA,TELEFONIA, ESGOTO | E15: =IF($F$50=0,0,F15/$F$50) | G15: =IF($H$6=0,0,F15/$H$6) | H15: =G15 | I15: INDIRETO | J15: LIGAÇÕES PROVISÓRIAS AGUA, ESGOTO, ENERGIA,TELEFONE, INTERNET | K15: =IF(ISNUMBER($P$7),G15*$P$7,0) | M15: =L15-K15 | N15: =IF(D15="","",IF('LIG. PROVISÓRIAS'!$C$78>L15+1,"⚠ Incorrido acima da projeção",IF(AND('LIG. PROVISÓRIAS'!$K$18>1,'LIG. PROVISÓRIAS'!$K$17=0),"⚠ Saldo sem curva (preencha a coluna H da aba)",IF(ABS('LIG. PROVISÓRIAS'!$D$80)>1,"⚠ Verificar","OK")))) | O15: ='LIG. PROVISÓRIAS'!$K$16 | P15: ='LIG. PROVISÓRIAS'!$K$14 | Q15: 05
B16: PL020.005 | C16: 06 | D16: CONSUMO DE ÁGUA, ENERGIA, ETC. | E16: =IF($F$50=0,0,F16/$F$50) | G16: =IF($H$6=0,0,F16/$H$6) | H16: =G16 | I16: INDIRETO | J16: CONSUMO DE ÁGUA, ENERGIA, TELEFONE, INTERNET | K16: =IF(ISNUMBER($P$7),G16*$P$7,0) | M16: =L16-K16 | N16: =IF(D16="","",IF('CONSUMOS'!$C$78>L16+1,"⚠ Incorrido acima da projeção",IF(AND('CONSUMOS'!$K$18>1,'CONSUMOS'!$K$17=0),"⚠ Saldo sem curva (preencha a coluna H da aba)",IF(ABS('CONSUMOS'!$D$80)>1,"⚠ Verificar","OK")))) | O16: ='CONSUMOS'!$K$16 | P16: ='CONSUMOS'!$K$14 | Q16: 06
B17: PL310.007 | C17: 07 | D17: DIVERSOS | E17: =IF($F$50=0,0,F17/$F$50) | G17: =IF($H$6=0,0,F17/$H$6) | H17: =G17 | I17: INDIRETO | J17: DIVERSOS | K17: =IF(ISNUMBER($P$7),G17*$P$7,0) | M17: =L17-K17 | N17: =IF(D17="","",IF('DIVERSOS'!$C$78>L17+1,"⚠ Incorrido acima da projeção",IF(AND('DIVERSOS'!$K$18>1,'DIVERSOS'!$K$17=0),"⚠ Saldo sem curva (preencha a coluna H da aba)",IF(ABS('DIVERSOS'!$D$80)>1,"⚠ Verificar","OK")))) | O17: ='DIVERSOS'!$K$16 | P17: ='DIVERSOS'!$K$14 | Q17: 07
B18: PL570.001 | C18: 08 | D18: TRANSPORTES | E18: =IF($F$50=0,0,F18/$F$50) | G18: =IF($H$6=0,0,F18/$H$6) | H18: =G18 | I18: INDIRETO | J18: FRETES E TRANSPORTES | K18: =IF(ISNUMBER($P$7),G18*$P$7,0) | M18: =L18-K18 | N18: =IF(D18="","",IF('TRANSPORTES'!$C$78>L18+1,"⚠ Incorrido acima da projeção",IF(AND('TRANSPORTES'!$K$18>1,'TRANSPORTES'!$K$17=0),"⚠ Saldo sem curva (preencha a coluna H da aba)",IF(ABS('TRANSPORTES'!$D$80)>1,"⚠ Verificar","OK")))) | O18: ='TRANSPORTES'!$K$16 | P18: ='TRANSPORTES'!$K$14 | Q18: 08
B19: PL001.051 | C19: 09 | D19: CONSULTORIAS (OBRAS) | E19: =IF($F$50=0,0,F19/$F$50) | G19: =IF($H$6=0,0,F19/$H$6) | H19: =G19 | I19: INDIRETO | J19: CONSULTORIAS (OBRAS) | K19: =IF(ISNUMBER($P$7),G19*$P$7,0) | M19: =L19-K19 | N19: =IF(D19="","",IF('CONSULTORIAS'!$C$78>L19+1,"⚠ Incorrido acima da projeção",IF(AND('CONSULTORIAS'!$K$18>1,'CONSULTORIAS'!$K$17=0),"⚠ Saldo sem curva (preencha a coluna H da aba)",IF(ABS('CONSULTORIAS'!$D$80)>1,"⚠ Verificar","OK")))) | O19: ='CONSULTORIAS'!$K$16 | P19: ='CONSULTORIAS'!$K$14 | Q19: 09
B20: PL700.001 | C20: 10 | D20: MÃO DE OBRA PRÓPRIA | E20: =IF($F$50=0,0,F20/$F$50) | G20: =IF($H$6=0,0,F20/$H$6) | H20: =G20 | I20: INDIRETO | J20: MÃO DE OBRA PRÓPRIA | K20: =IF(ISNUMBER($P$7),G20*$P$7,0) | M20: =L20-K20 | N20: =IF(D20="","",IF('MDO'!$C$78>L20+1,"⚠ Incorrido acima da projeção",IF(AND('MDO'!$K$18>1,'MDO'!$K$17=0),"⚠ Saldo sem curva (preencha a coluna H da aba)",IF(ABS('MDO'!$D$80)>1,"⚠ Verificar","OK")))) | O20: ='MDO'!$K$16 | P20: ='MDO'!$K$14 | Q20: 10
B21: PL530.001 | C21: 11 | D21: EQUIPAMENTOS E FERRAMENTAS | E21: =IF($F$50=0,0,F21/$F$50) | G21: =IF($H$6=0,0,F21/$H$6) | H21: =G21 | I21: INDIRETO | J21: EQUIPAMENTOS E FERRAMENTAS | K21: =IF(ISNUMBER($P$7),G21*$P$7,0) | M21: =L21-K21 | N21: =IF(D21="","",IF('EQUIP E FER'!$C$78>L21+1,"⚠ Incorrido acima da projeção",IF(AND('EQUIP E FER'!$K$18>1,'EQUIP E FER'!$K$17=0),"⚠ Saldo sem curva (preencha a coluna H da aba)",IF(ABS('EQUIP E FER'!$D$80)>1,"⚠ Verificar","OK")))) | O21: ='EQUIP E FER'!$K$16 | P21: ='EQUIP E FER'!$K$14 | Q21: 11
B22: PL010.022 | C22: 12 | D22: SERVIÇOS INICIAIS | E22: =IF($F$50=0,0,F22/$F$50) | G22: =IF($H$6=0,0,F22/$H$6) | H22: =G22 | I22: DIRETO | J22: SERVIÇOS INICIAIS | K22: =IF(ISNUMBER($P$7),G22*$P$7,0) | M22: =L22-K22 | N22: =IF(D22="","",IF('SERV. INICIAIS'!$C$78>L22+1,"⚠ Incorrido acima da projeção",IF(AND('SERV. INICIAIS'!$K$18>1,'SERV. INICIAIS'!$K$17=0),"⚠ Saldo sem curva (preencha a coluna H da aba)",IF(ABS('SERV. INICIAIS'!$D$80)>1,"⚠ Verificar","OK")))) | O22: ='SERV. INICIAIS'!$K$16 | P22: ='SERV. INICIAIS'!$K$14 | Q22: 12
B23: PL001.023 | C23: 13 | D23: CONTENÇÃO | E23: =IF($F$50=0,0,F23/$F$50) | G23: =IF($H$6=0,0,F23/$H$6) | H23: =G23 | I23: DIRETO | J23: CONTENÇÕES | K23: =IF(ISNUMBER($P$7),G23*$P$7,0) | M23: =L23-K23 | N23: =IF(D23="","",IF('CONTENÇÃO'!$C$78>L23+1,"⚠ Incorrido acima da projeção",IF(AND('CONTENÇÃO'!$K$18>1,'CONTENÇÃO'!$K$17=0),"⚠ Saldo sem curva (preencha a coluna H da aba)",IF(ABS('CONTENÇÃO'!$D$80)>1,"⚠ Verificar","OK")))) | O23: ='CONTENÇÃO'!$K$16 | P23: ='CONTENÇÃO'!$K$14 | Q23: 13
B24: PL040.001 | C24: 14 | D24: TERRAPLENAGEM | E24: =IF($F$50=0,0,F24/$F$50) | G24: =IF($H$6=0,0,F24/$H$6) | H24: =G24 | I24: DIRETO | J24: TERRAPLENAGEM | K24: =IF(ISNUMBER($P$7),G24*$P$7,0) | M24: =L24-K24 | N24: =IF(D24="","",IF('TERRAPLENAGEM'!$C$78>L24+1,"⚠ Incorrido acima da projeção",IF(AND('TERRAPLENAGEM'!$K$18>1,'TERRAPLENAGEM'!$K$17=0),"⚠ Saldo sem curva (preencha a coluna H da aba)",IF(ABS('TERRAPLENAGEM'!$D$80)>1,"⚠ Verificar","OK")))) | O24: ='TERRAPLENAGEM'!$K$16 | P24: ='TERRAPLENAGEM'!$K$14 | Q24: 14
B25: PL050.004 | C25: 15 | D25: FUNDAÇÃO PROFUNDA | E25: =IF($F$50=0,0,F25/$F$50) | G25: =IF($H$6=0,0,F25/$H$6) | H25: =G25 | I25: DIRETO | J25: FUNDAÇÃO PROFUNDA | K25: =IF(ISNUMBER($P$7),G25*$P$7,0) | M25: =L25-K25 | N25: =IF(D25="","",IF('FUND. PROF'!$C$78>L25+1,"⚠ Incorrido acima da projeção",IF(AND('FUND. PROF'!$K$18>1,'FUND. PROF'!$K$17=0),"⚠ Saldo sem curva (preencha a coluna H da aba)",IF(ABS('FUND. PROF'!$D$80)>1,"⚠ Verificar","OK")))) | O25: ='FUND. PROF'!$K$16 | P25: ='FUND. PROF'!$K$14 | Q25: 15
B26: PL060.004 | C26: 16 | D26: FUNDAÇÃO SUPERFICIAL | E26: =IF($F$50=0,0,F26/$F$50) | G26: =IF($H$6=0,0,F26/$H$6) | H26: =G26 | I26: DIRETO | J26: FUNDAÇÃO SUPERFICIAL | K26: =IF(ISNUMBER($P$7),G26*$P$7,0) | M26: =L26-K26 | N26: =IF(D26="","",IF('FUND. SUP'!$C$78>L26+1,"⚠ Incorrido acima da projeção",IF(AND('FUND. SUP'!$K$18>1,'FUND. SUP'!$K$17=0),"⚠ Saldo sem curva (preencha a coluna H da aba)",IF(ABS('FUND. SUP'!$D$80)>1,"⚠ Verificar","OK")))) | O26: ='FUND. SUP'!$K$16 | P26: ='FUND. SUP'!$K$14 | Q26: 16
B27: PL100.011 | C27: 17 | D27: ESTRUTURA EM CONCRETO ARMADO | E27: =IF($F$50=0,0,F27/$F$50) | G27: =IF($H$6=0,0,F27/$H$6) | H27: =G27 | I27: DIRETO | J27: ESTRUTURA EM CONCRETO ARMADO | K27: =IF(ISNUMBER($P$7),G27*$P$7,0) | M27: =L27-K27 | N27: =IF(D27="","",IF('ESTRUTURA'!$C$78>L27+1,"⚠ Incorrido acima da projeção",IF(AND('ESTRUTURA'!$K$18>1,'ESTRUTURA'!$K$17=0),"⚠ Saldo sem curva (preencha a coluna H da aba)",IF(ABS('ESTRUTURA'!$D$80)>1,"⚠ Verificar","OK")))) | O27: ='ESTRUTURA'!$K$16 | P27: ='ESTRUTURA'!$K$14 | Q27: 17
B28: PL120.001 | C28: 18 | D28: ALVENARIA | E28: =IF($F$50=0,0,F28/$F$50) | G28: =IF($H$6=0,0,F28/$H$6) | H28: =G28 | I28: DIRETO | J28: ALVENARIA | K28: =IF(ISNUMBER($P$7),G28*$P$7,0) | M28: =L28-K28 | N28: =IF(D28="","",IF('ALVENARIA'!$C$78>L28+1,"⚠ Incorrido acima da projeção",IF(AND('ALVENARIA'!$K$18>1,'ALVENARIA'!$K$17=0),"⚠ Saldo sem curva (preencha a coluna H da aba)",IF(ABS('ALVENARIA'!$D$80)>1,"⚠ Verificar","OK")))) | O28: ='ALVENARIA'!$K$16 | P28: ='ALVENARIA'!$K$14 | Q28: 18
B29: PL140.004 | C29: 19 | D29: IMPERMEABILIZAÇÃO | E29: =IF($F$50=0,0,F29/$F$50) | G29: =IF($H$6=0,0,F29/$H$6) | H29: =G29 | I29: DIRETO | J29: IMPERMEABILIZAÇÃO | K29: =IF(ISNUMBER($P$7),G29*$P$7,0) | M29: =L29-K29 | N29: =IF(D29="","",IF('IMPERMEABILIZAÇÃO'!$C$78>L29+1,"⚠ Incorrido acima da projeção",IF(AND('IMPERMEABILIZAÇÃO'!$K$18>1,'IMPERMEABILIZAÇÃO'!$K$17=0),"⚠ Saldo sem curva (preencha a coluna H da aba)",IF(ABS('IMPERMEABILIZAÇÃO'!$D$80)>1,"⚠ Verificar","OK")))) | O29: ='IMPERMEABILIZAÇÃO'!$K$16 | P29: ='IMPERMEABILIZAÇÃO'!$K$14 | Q29: 19
B30: PL110.018 | C30: 20 | D30: INSTALAÇÕES ELÉTRICAS | E30: =IF($F$50=0,0,F30/$F$50) | G30: =IF($H$6=0,0,F30/$H$6) | H30: =G30 | I30: DIRETO | J30: INSTALAÇÕES ELÉTRICAS | K30: =IF(ISNUMBER($P$7),G30*$P$7,0) | M30: =L30-K30 | N30: =IF(D30="","",IF('INST. ELÉTRICA'!$C$78>L30+1,"⚠ Incorrido acima da projeção",IF(AND('INST. ELÉTRICA'!$K$18>1,'INST. ELÉTRICA'!$K$17=0),"⚠ Saldo sem curva (preencha a coluna H da aba)",IF(ABS('INST. ELÉTRICA'!$D$80)>1,"⚠ Verificar","OK")))) | O30: ='INST. ELÉTRICA'!$K$16 | P30: ='INST. ELÉTRICA'!$K$14 | Q30: 20
B31: PL110.007 | C31: 21 | D31: INSTALAÇÕES HIDROSANITÁRIAS | E31: =IF($F$50=0,0,F31/$F$50) | G31: =IF($H$6=0,0,F31/$H$6) | H31: =G31 | I31: DIRETO | J31: INSTALAÇÕES HIDROSANITÁRIAS | K31: =IF(ISNUMBER($P$7),G31*$P$7,0) | M31: =L31-K31 | N31: =IF(D31="","",IF('INST. HIDRO'!$C$78>L31+1,"⚠ Incorrido acima da projeção",IF(AND('INST. HIDRO'!$K$18>1,'INST. HIDRO'!$K$17=0),"⚠ Saldo sem curva (preencha a coluna H da aba)",IF(ABS('INST. HIDRO'!$D$80)>1,"⚠ Verificar","OK")))) | O31: ='INST. HIDRO'!$K$16 | P31: ='INST. HIDRO'!$K$14 | Q31: 21
B32: PL110.017 | C32: 22 | D32: INSTALAÇÕES COMBATE INCÊNDIO | E32: =IF($F$50=0,0,F32/$F$50) | G32: =IF($H$6=0,0,F32/$H$6) | H32: =G32 | I32: DIRETO | J32: INSTALAÇÕES COMBATE INCÊNDIO | K32: =IF(ISNUMBER($P$7),G32*$P$7,0) | M32: =L32-K32 | N32: =IF(D32="","",IF('INST. INC'!$C$78>L32+1,"⚠ Incorrido acima da projeção",IF(AND('INST. INC'!$K$18>1,'INST. INC'!$K$17=0),"⚠ Saldo sem curva (preencha a coluna H da aba)",IF(ABS('INST. INC'!$D$80)>1,"⚠ Verificar","OK")))) | O32: ='INST. INC'!$K$16 | P32: ='INST. INC'!$K$14 | Q32: 22
B33: PL110.027 | C33: 23 | D33: INSTALAÇÕES ESPECIAIS | E33: =IF($F$50=0,0,F33/$F$50) | G33: =IF($H$6=0,0,F33/$H$6) | H33: =G33 | I33: DIRETO | J33: INSTALAÇÕES ESPECIAIS | K33: =IF(ISNUMBER($P$7),G33*$P$7,0) | M33: =L33-K33 | N33: =IF(D33="","",IF('INST. ESP'!$C$78>L33+1,"⚠ Incorrido acima da projeção",IF(AND('INST. ESP'!$K$18>1,'INST. ESP'!$K$17=0),"⚠ Saldo sem curva (preencha a coluna H da aba)",IF(ABS('INST. ESP'!$D$80)>1,"⚠ Verificar","OK")))) | O33: ='INST. ESP'!$K$16 | P33: ='INST. ESP'!$K$14 | Q33: 23
B34: PL220.002 | C34: 24 | D34: ELEVADORES | E34: =IF($F$50=0,0,F34/$F$50) | G34: =IF($H$6=0,0,F34/$H$6) | H34: =G34 | I34: DIRETO | J34: ELEVADORES | K34: =IF(ISNUMBER($P$7),G34*$P$7,0) | M34: =L34-K34 | N34: =IF(D34="","",IF('ELEVADORES '!$C$78>L34+1,"⚠ Incorrido acima da projeção",IF(AND('ELEVADORES '!$K$18>1,'ELEVADORES '!$K$17=0),"⚠ Saldo sem curva (preencha a coluna H da aba)",IF(ABS('ELEVADORES '!$D$80)>1,"⚠ Verificar","OK")))) | O34: ='ELEVADORES '!$K$16 | P34: ='ELEVADORES '!$K$14 | Q34: 24
B35: PL250.001 | C35: 25 | D35: ESQUADRIAS | E35: =IF($F$50=0,0,F35/$F$50) | G35: =IF($H$6=0,0,F35/$H$6) | H35: =G35 | I35: DIRETO | J35: ESQUADRIAS | K35: =IF(ISNUMBER($P$7),G35*$P$7,0) | M35: =L35-K35 | N35: =IF(D35="","",IF('ESQUADRIAS'!$C$78>L35+1,"⚠ Incorrido acima da projeção",IF(AND('ESQUADRIAS'!$K$18>1,'ESQUADRIAS'!$K$17=0),"⚠ Saldo sem curva (preencha a coluna H da aba)",IF(ABS('ESQUADRIAS'!$D$80)>1,"⚠ Verificar","OK")))) | O35: ='ESQUADRIAS'!$K$16 | P35: ='ESQUADRIAS'!$K$14 | Q35: 25
B36: PL240.000 | C36: 26 | D36: SERRALHERIA | E36: =IF($F$50=0,0,F36/$F$50) | G36: =IF($H$6=0,0,F36/$H$6) | H36: =G36 | I36: DIRETO | J36: SERRALHERIA | K36: =IF(ISNUMBER($P$7),G36*$P$7,0) | M36: =L36-K36 | N36: =IF(D36="","",IF('SERRALHERIA'!$C$78>L36+1,"⚠ Incorrido acima da projeção",IF(AND('SERRALHERIA'!$K$18>1,'SERRALHERIA'!$K$17=0),"⚠ Saldo sem curva (preencha a coluna H da aba)",IF(ABS('SERRALHERIA'!$D$80)>1,"⚠ Verificar","OK")))) | O36: ='SERRALHERIA'!$K$16 | P36: ='SERRALHERIA'!$K$14 | Q36: 26
B37: PL240.020 | C37: 27 | D37: MARCENARIA | E37: =IF($F$50=0,0,F37/$F$50) | G37: =IF($H$6=0,0,F37/$H$6) | H37: =G37 | I37: DIRETO | J37: MARCENARIA | K37: =IF(ISNUMBER($P$7),G37*$P$7,0) | M37: =L37-K37 | N37: =IF(D37="","",IF('MARCENARIA'!$C$78>L37+1,"⚠ Incorrido acima da projeção",IF(AND('MARCENARIA'!$K$18>1,'MARCENARIA'!$K$17=0),"⚠ Saldo sem curva (preencha a coluna H da aba)",IF(ABS('MARCENARIA'!$D$80)>1,"⚠ Verificar","OK")))) | O37: ='MARCENARIA'!$K$16 | P37: ='MARCENARIA'!$K$14 | Q37: 27
B38: PL160.001 | C38: 28 | D38: REVESTIMENTOS DE MASSA EM PISOS | E38: =IF($F$50=0,0,F38/$F$50) | G38: =IF($H$6=0,0,F38/$H$6) | H38: =G38 | I38: DIRETO | J38: REVESTIMENTOS DE MASSA EM PISOS | K38: =IF(ISNUMBER($P$7),G38*$P$7,0) | M38: =L38-K38 | N38: =IF(D38="","",IF('REV. PISOS'!$C$78>L38+1,"⚠ Incorrido acima da projeção",IF(AND('REV. PISOS'!$K$18>1,'REV. PISOS'!$K$17=0),"⚠ Saldo sem curva (preencha a coluna H da aba)",IF(ABS('REV. PISOS'!$D$80)>1,"⚠ Verificar","OK")))) | O38: ='REV. PISOS'!$K$16 | P38: ='REV. PISOS'!$K$14 | Q38: 28
B39: PL150.001 | C39: 29 | D39: REVESTIMENTOS DE MASSA EM PAREDES | E39: =IF($F$50=0,0,F39/$F$50) | G39: =IF($H$6=0,0,F39/$H$6) | H39: =G39 | I39: DIRETO | J39: REVESTIMENTOS DE MASSA EM PAREDES | K39: =IF(ISNUMBER($P$7),G39*$P$7,0) | M39: =L39-K39 | N39: =IF(D39="","",IF('REV. PAREDE'!$C$78>L39+1,"⚠ Incorrido acima da projeção",IF(AND('REV. PAREDE'!$K$18>1,'REV. PAREDE'!$K$17=0),"⚠ Saldo sem curva (preencha a coluna H da aba)",IF(ABS('REV. PAREDE'!$D$80)>1,"⚠ Verificar","OK")))) | O39: ='REV. PAREDE'!$K$16 | P39: ='REV. PAREDE'!$K$14 | Q39: 29
B40: PL170.004 | C40: 30 | D40: REVESTIMENTOS DE ACABAMENTO | E40: =IF($F$50=0,0,F40/$F$50) | G40: =IF($H$6=0,0,F40/$H$6) | H40: =G40 | I40: DIRETO | J40: REVESTIMENTOS DE ACABAMENTO | K40: =IF(ISNUMBER($P$7),G40*$P$7,0) | M40: =L40-K40 | N40: =IF(D40="","",IF('REV. ACAB'!$C$78>L40+1,"⚠ Incorrido acima da projeção",IF(AND('REV. ACAB'!$K$18>1,'REV. ACAB'!$K$17=0),"⚠ Saldo sem curva (preencha a coluna H da aba)",IF(ABS('REV. ACAB'!$D$80)>1,"⚠ Verificar","OK")))) | O40: ='REV. ACAB'!$K$16 | P40: ='REV. ACAB'!$K$14 | Q40: 30
B41: PL320.001 | C41: 31 | D41: PAVIMENTAÇÃO | E41: =IF($F$50=0,0,F41/$F$50) | G41: =IF($H$6=0,0,F41/$H$6) | H41: =G41 | I41: DIRETO | J41: PAVIMENTÇÃO | K41: =IF(ISNUMBER($P$7),G41*$P$7,0) | M41: =L41-K41 | N41: =IF(D41="","",IF('PAVIMENTAÇÃO'!$C$78>L41+1,"⚠ Incorrido acima da projeção",IF(AND('PAVIMENTAÇÃO'!$K$18>1,'PAVIMENTAÇÃO'!$K$17=0),"⚠ Saldo sem curva (preencha a coluna H da aba)",IF(ABS('PAVIMENTAÇÃO'!$D$80)>1,"⚠ Verificar","OK")))) | O41: ='PAVIMENTAÇÃO'!$K$16 | P41: ='PAVIMENTAÇÃO'!$K$14 | Q41: 31
B42: PL190.003 | C42: 32 | D42: REVESTIMENTO DIVERSOS - FACHADA | E42: =IF($F$50=0,0,F42/$F$50) | G42: =IF($H$6=0,0,F42/$H$6) | H42: =G42 | I42: DIRETO | J42: REVESTIMENTO DIVERSOS - FACHADA | K42: =IF(ISNUMBER($P$7),G42*$P$7,0) | M42: =L42-K42 | N42: =IF(D42="","",IF('REV. FACHADA'!$C$78>L42+1,"⚠ Incorrido acima da projeção",IF(AND('REV. FACHADA'!$K$18>1,'REV. FACHADA'!$K$17=0),"⚠ Saldo sem curva (preencha a coluna H da aba)",IF(ABS('REV. FACHADA'!$D$80)>1,"⚠ Verificar","OK")))) | O42: ='REV. FACHADA'!$K$16 | P42: ='REV. FACHADA'!$K$14 | Q42: 32
B43: PL180.001 | C43: 33 | D43: FORRO | E43: =IF($F$50=0,0,F43/$F$50) | G43: =IF($H$6=0,0,F43/$H$6) | H43: =G43 | I43: DIRETO | J43: FORROS DIVERSOS | K43: =IF(ISNUMBER($P$7),G43*$P$7,0) | M43: =L43-K43 | N43: =IF(D43="","",IF('FORRO'!$C$78>L43+1,"⚠ Incorrido acima da projeção",IF(AND('FORRO'!$K$18>1,'FORRO'!$K$17=0),"⚠ Saldo sem curva (preencha a coluna H da aba)",IF(ABS('FORRO'!$D$80)>1,"⚠ Verificar","OK")))) | O43: ='FORRO'!$K$16 | P43: ='FORRO'!$K$14 | Q43: 33
B44: PL290.002 | C44: 34 | D44: LOUÇAS SANITÁRIAS | E44: =IF($F$50=0,0,F44/$F$50) | G44: =IF($H$6=0,0,F44/$H$6) | H44: =G44 | I44: DIRETO | J44: LOUÇAS E METAIS | K44: =IF(ISNUMBER($P$7),G44*$P$7,0) | M44: =L44-K44 | N44: =IF(D44="","",IF('LOUÇAS'!$C$78>L44+1,"⚠ Incorrido acima da projeção",IF(AND('LOUÇAS'!$K$18>1,'LOUÇAS'!$K$17=0),"⚠ Saldo sem curva (preencha a coluna H da aba)",IF(ABS('LOUÇAS'!$D$80)>1,"⚠ Verificar","OK")))) | O44: ='LOUÇAS'!$K$16 | P44: ='LOUÇAS'!$K$14 | Q44: 34
B45: PL280.003 | C45: 35 | D45: PINTURA | E45: =IF($F$50=0,0,F45/$F$50) | G45: =IF($H$6=0,0,F45/$H$6) | H45: =G45 | I45: DIRETO | J45: PINTURAS | K45: =IF(ISNUMBER($P$7),G45*$P$7,0) | M45: =L45-K45 | N45: =IF(D45="","",IF('PINTURA'!$C$78>L45+1,"⚠ Incorrido acima da projeção",IF(AND('PINTURA'!$K$18>1,'PINTURA'!$K$17=0),"⚠ Saldo sem curva (preencha a coluna H da aba)",IF(ABS('PINTURA'!$D$80)>1,"⚠ Verificar","OK")))) | O45: ='PINTURA'!$K$16 | P45: ='PINTURA'!$K$14 | Q45: 35
B46: PL330.002 | C46: 36 | D46: PAISAGISMO | E46: =IF($F$50=0,0,F46/$F$50) | G46: =IF($H$6=0,0,F46/$H$6) | H46: =G46 | I46: DIRETO | J46: PAISAGISMO | K46: =IF(ISNUMBER($P$7),G46*$P$7,0) | M46: =L46-K46 | N46: =IF(D46="","",IF('PAISAGISMO'!$C$78>L46+1,"⚠ Incorrido acima da projeção",IF(AND('PAISAGISMO'!$K$18>1,'PAISAGISMO'!$K$17=0),"⚠ Saldo sem curva (preencha a coluna H da aba)",IF(ABS('PAISAGISMO'!$D$80)>1,"⚠ Verificar","OK")))) | O46: ='PAISAGISMO'!$K$16 | P46: ='PAISAGISMO'!$K$14 | Q46: 36
B47: PL360.001 | C47: 37 | D47: LIMPEZA FINAL DE OBRA | E47: =IF($F$50=0,0,F47/$F$50) | G47: =IF($H$6=0,0,F47/$H$6) | H47: =G47 | I47: DIRETO | J47: LIMPEZA FINAL DE OBRA | K47: =IF(ISNUMBER($P$7),G47*$P$7,0) | M47: =L47-K47 | N47: =IF(D47="","",IF('LIMPEZA'!$C$78>L47+1,"⚠ Incorrido acima da projeção",IF(AND('LIMPEZA'!$K$18>1,'LIMPEZA'!$K$17=0),"⚠ Saldo sem curva (preencha a coluna H da aba)",IF(ABS('LIMPEZA'!$D$80)>1,"⚠ Verificar","OK")))) | O47: ='LIMPEZA'!$K$16 | P47: ='LIMPEZA'!$K$14 | Q47: 37
C48: 38 | D48: TAXA DE ADMINISTRAÇÃO | E48: =IF($F$50=0,0,F48/$F$50) | G48: =IF($H$6=0,0,F48/$H$6) | H48: =G48 | I48: INDIRETO | J48: TAXA DE ADMINISTRAÇÃO | K48: =IF(ISNUMBER($P$7),G48*$P$7,0) | L48: ='TAX. ADM'!$C$78 | M48: =L48-K48 | N48: =IF(D48="","",IF('TAX. ADM'!$C$78>L48+1,"⚠ Incorrido acima da projeção",IF(AND('TAX. ADM'!$K$18>1,'TAX. ADM'!$K$17=0),"⚠ Saldo sem curva (preencha a coluna H da aba)",IF(ABS('TAX. ADM'!$D$80)>1,"⚠ Verificar","OK")))) | O48: ='TAX. ADM'!$K$16 | P48: ='TAX. ADM'!$K$14 | Q48: 00
D49: TOTAIS (sem taxa de adm.) | E49: =SUM(E11:E47) | F49: =SUM(F11:F47) | G49: =SUM(G11:G47) | H49: =SUM(H11:H47) | K49: =SUM(K11:K47) | L49: =SUM(L11:L47) | M49: =SUM(M11:M47)
D50: TOTAL COM TAXA DE ADMINISTRAÇÃO | E50: =SUM(E11:E48) | F50: =SUM(F11:F48) | G50: =SUM(G11:G48) | H50: =SUM(H11:H48) | K50: =SUM(K11:K48) | L50: =SUM(L11:L48) | M50: =SUM(M11:M48)
D53: CONFERÊNCIA GERAL | E53: RESULTADO | F53: STATUS
D54: Disciplinas com pendência (coluna N) | E54: =COUNTIF(N11:N48,"⚠*") | F54: =IF(E54=0,"OK","⚠ Veja a coluna N")
D55: Grupos do ERP sem correspondência | E55: ='DADOS HISTORICOS'!C2 | F55: =IF(E55=0,"OK","⚠ Veja nomes em vermelho em DADOS BRUTOS")
D56: Valores do ERP fora do horizonte (R$) | E56: ='DADOS HISTORICOS'!BX44 | F56: =IF(ABS(E56)<1,"OK","⚠ Aumente o horizonte ou revise datas")
D57: INCC do mês de corte | E57: =IF(ISNUMBER(P7),P7,0) | F57: =IF(COUNTIF('"INCC-FGV"'!$A$2:$A$400,P5)>0,"OK",IF(E57>0,"⚠ INCC do mês de corte não cadastrado: usando o último índice disponível","⚠ Inclua o índice na aba INCC-FGV"))
D58: Meses realizados sem INCC | E58: =SUMPRODUCT(('MODELO PARA BI'!$H$1:$CA$1<=P5)*(COUNTIF('"INCC-FGV"'!$A$2:$A$400,'MODELO PARA BI'!$H$1:$CA$1)=0)) | F58: =IF(E58=0,"OK","⚠ Complete a aba INCC-FGV")
D59: Fluxo total − projeção total (R$) | E59: ='MODELO PARA BI'!E64-L50 | F59: =IF(L50=0,"⚠ Preencha o orçamento e a projeção (colunas F e L)",IF(ABS(E59)<1,"OK","⚠ Há saldo sem distribuição"))

Sheet RETRATO 2027
B2: ='VALOR POR PL'!$P$9&" · RETRATO DE "&D5
B3: ="Execução física (Prevision), desembolso do ano (fluxo financeiro) e situação da obra em 31/12/"&D5&" · Corte: "&CHOOSE(MONTH('VALOR POR PL'!$P$5),"jan","fev","mar","abr","mai","jun","jul","ago","set","out","nov","dez")&"/"&YEAR('VALOR POR PL'!$P$5)&" · Cenário: "&IF('VALOR POR PL'!$K$8="PADRÃO","padrão","Prevision")
B5: ANO DO RETRATO → | D5: 2027 | E5: INCC → | F5: ='VALOR POR PL'!$P$5 | G5: =IFERROR(INDEX('"INCC-FGV"'!$B$2:$B$400,MATCH(DATE(YEAR(F5),MONTH(F5),1),'"INCC-FGV"'!$A$2:$A$400,0)),IFERROR(INDEX('"INCC-FGV"'!$B$2:$B$400,MATCH(DATE(YEAR(F5),MONTH(F5),1),'"INCC-FGV"'!$A$2:$A$400,1)),"FALTA INCC")) | J5: SITUAÇÃO EM → | K5: =DATE(D5,12,31)
B7: DESEMBOLSO NO ANO (R$ NOMINAL) | D7: DESEMBOLSO NO ANO (INCC) | F7: EM R$ DO INCC SELECIONADO | H7: EXECUÇÃO FÍSICA NO FIM DO ANO | J7: AVANÇO FINANCEIRO | K7: MAIOR DESEMBOLSO DO ANO
B8: =F53 | D8: =G53 | F8: =H53 | H8: =IFERROR(SUMPRODUCT(D12:D50,N12:N50)/SUMPRODUCT(ISNUMBER(D12:D50)*N12:N50),0) | J8: =IFERROR(SUMPRODUCT(J12:J50,M12:M50)/SUM(M12:M50),0) | K8: =INDEX(C12:C50,MATCH(MAX(F12:F50),F12:F50,0))
B9: com taxa de administração | D9: pontos de índice | F9: INCC × índice do mês escolhido | H9: itens diretos, ponderado pela projeção | J9: acumulado no fim do ano | K9: ="R$ "&TEXT(MAX(F12:F50)/1000000,"0.0")&" mi no ano"
B11: Cód. | C11: PL / serviço | D11: Execução física fim do ano (Prevision) | E11: Execução física no corte (Prevision) | F11: Desembolso no ano R$ nominal | G11: Desembolso no ano INCC | H11: Desembolso no ano R$ do INCC selecionado | I11: % do ano | J11: Avanço financeiro fim do ano | K11: ="Situação em 31/12/"&D5&" (cronograma de atividades do Prevision)" | L11: Anotação do modelo anterior / justificativa
B12: ='VALOR POR PL'!C11 | C12: ='VALOR POR PL'!D11 | D12: =IF(OR('VALOR POR PL'!I11<>"DIRETO",'CP RESUMO'!$C$5=""),"",IFERROR(INDEX('CP RESUMO'!$D$5:$BW$5,MATCH(DATE($D$5,12,1),'CP RESUMO'!$D$4:$BW$4,0))/100,"")) | E12: =IF('VALOR POR PL'!I11<>"DIRETO","",'PROJETO'!$K$14) | F12: =SUMPRODUCT((YEAR('PROJETO'!$B$5:$B$76)=$D$5)*('PROJETO'!$C$5:$C$76+'PROJETO'!$D$5:$D$76)) | G12: =SUMPRODUCT((YEAR('MODELO PARA BI'!$H$1:$CA$1)=$D$5)*'MODELO PARA BI'!$H$29:$CA$29) | H12: =IF(ISNUMBER($G$5),G12*$G$5,0) | I12: =IF($F$53=0,0,F12/$F$53) | J12: =IF('VALOR POR PL'!L11=0,0,SUMPRODUCT(('PROJETO'!$B$5:$B$76<=DATE($D$5,12,1))*('PROJETO'!$C$5:$C$76+'PROJETO'!$D$5:$D$76))/'VALOR POR PL'!L11) | K12: {=IF(COUNTIF('CRONOGRAMA ATIVIDADES'!$M$5:$M$3004,B12)=0,"",IF(COUNTIFS('CRONOGRAMA ATIVIDADES'!$M$5:$M$3004,B12,'CRONOGRAMA ATIVIDADES'!$O$5:$O$3004,"CONCLUÍDA")=COUNTIF('CRONOGRAMA ATIVIDADES'!$M$5:$M$3004,B12),"Concluído (todas as "&COUNTIF('CRONOGRAMA ATIVIDADES'!$M$5:$M$3004,B12)&" atividades)",IF(COUNTIFS('CRONOGRAMA ATIVIDADES'!$M$5:$M$3004,B12,'CRONOGRAMA ATIVIDADES'!$O$5:$O$3004,"A INICIAR")=COUNTIF('CRONOGRAMA ATIVIDADES'!$M$5:$M$3004,B12),"Não iniciado · início previsto em "&CHOOSE(MONTH(_xlfn.MINIFS('CRONOGRAMA ATIVIDADES'!$F$5:$F$3004,'CRONOGRAMA ATIVIDADES'!$M$5:$M$3004,B12)),"jan","fev","mar","abr","mai","jun","jul","ago","set","out","nov","dez")&"/"&YEAR(_xlfn.MINIFS('CRONOGRAMA ATIVIDADES'!$F$5:$F$3004,'CRONOGRAMA ATIVIDADES'!$M$5:$M$3004,B12)),_xlfn.TEXTJOIN(" / ",TRUE,IF(('CRONOGRAMA ATIVIDADES'!$S$5:$S$304=B12)*('CRONOGRAMA ATIVIDADES'!$AA$5:$AA$304<>""),'CRONOGRAMA ATIVIDADES'!$AA$5:$AA$304,"")))))} | M12: ='VALOR POR PL'!L11 | N12: =IF('VALOR POR PL'!I11="DIRETO",'VALOR POR PL'!L11,0)
B13: ='VALOR POR PL'!C12 | C13: ='VALOR POR PL'!D12 | D13: =IF(OR('VALOR POR PL'!I12<>"DIRETO",'CP RESUMO'!$C$6=""),"",IFERROR(INDEX('CP RESUMO'!$D$6:$BW$6,MATCH(DATE($D$5,12,1),'CP RESUMO'!$D$4:$BW$4,0))/100,"")) | E13: =IF('VALOR POR PL'!I12<>"DIRETO","",'SEGUROS'!$K$14) | F13: =SUMPRODUCT((YEAR('SEGUROS'!$B$5:$B$76)=$D$5)*('SEGUROS'!$C$5:$C$76+'SEGUROS'!$D$5:$D$76)) | G13: =SUMPRODUCT((YEAR('MODELO PARA BI'!$H$1:$CA$1)=$D$5)*'MODELO PARA BI'!$H$40:$CA$40) | H13: =IF(ISNUMBER($G$5),G13*$G$5,0) | I13: =IF($F$53=0,0,F13/$F$53) | J13: =IF('VALOR POR PL'!L12=0,0,SUMPRODUCT(('SEGUROS'!$B$5:$B$76<=DATE($D$5,12,1))*('SEGUROS'!$C$5:$C$76+'SEGUROS'!$D$5:$D$76))/'VALOR POR PL'!L12) | K13: {=IF(COUNTIF('CRONOGRAMA ATIVIDADES'!$M$5:$M$3004,B13)=0,"",IF(COUNTIFS('CRONOGRAMA ATIVIDADES'!$M$5:$M$3004,B13,'CRONOGRAMA ATIVIDADES'!$O$5:$O$3004,"CONCLUÍDA")=COUNTIF('CRONOGRAMA ATIVIDADES'!$M$5:$M$3004,B13),"Concluído (todas as "&COUNTIF('CRONOGRAMA ATIVIDADES'!$M$5:$M$3004,B13)&" atividades)",IF(COUNTIFS('CRONOGRAMA ATIVIDADES'!$M$5:$M$3004,B13,'CRONOGRAMA ATIVIDADES'!$O$5:$O$3004,"A INICIAR")=COUNTIF('CRONOGRAMA ATIVIDADES'!$M$5:$M$3004,B13),"Não iniciado · início previsto em "&CHOOSE(MONTH(_xlfn.MINIFS('CRONOGRAMA ATIVIDADES'!$F$5:$F$3004,'CRONOGRAMA ATIVIDADES'!$M$5:$M$3004,B13)),"jan","fev","mar","abr","mai","jun","jul","ago","set","out","nov","dez")&"/"&YEAR(_xlfn.MINIFS('CRONOGRAMA ATIVIDADES'!$F$5:$F$3004,'CRONOGRAMA ATIVIDADES'!$M$5:$M$3004,B13)),_xlfn.TEXTJOIN(" / ",TRUE,IF(('CRONOGRAMA ATIVIDADES'!$S$5:$S$304=B13)*('CRONOGRAMA ATIVIDADES'!$AA$5:$AA$304<>""),'CRONOGRAMA ATIVIDADES'!$AA$5:$AA$304,"")))))} | M13: ='VALOR POR PL'!L12 | N13: =IF('VALOR POR PL'!I12="DIRETO",'VALOR POR PL'!L12,0)
B14: ='VALOR POR PL'!C13 | C14: ='VALOR POR PL'!D13 | D14: =IF(OR('VALOR POR PL'!I13<>"DIRETO",'CP RESUMO'!$C$7=""),"",IFERROR(INDEX('CP RESUMO'!$D$7:$BW$7,MATCH(DATE($D$5,12,1),'CP RESUMO'!$D$4:$BW$4,0))/100,"")) | E14: =IF('VALOR POR PL'!I13<>"DIRETO","",'TAX. DIVERSAS'!$K$14) | F14: =SUMPRODUCT((YEAR('TAX. DIVERSAS'!$B$5:$B$76)=$D$5)*('TAX. DIVERSAS'!$C$5:$C$76+'TAX. DIVERSAS'!$D$5:$D$76)) | G14: =SUMPRODUCT((YEAR('MODELO PARA BI'!$H$1:$CA$1)=$D$5)*'MODELO PARA BI'!$H$50:$CA$50) | H14: =IF(ISNUMBER($G$5),G14*$G$5,0) | I14: =IF($F$53=0,0,F14/$F$53) | J14: =IF('VALOR POR PL'!L13=0,0,SUMPRODUCT(('TAX. DIVERSAS'!$B$5:$B$76<=DATE($D$5,12,1))*('TAX. DIVERSAS'!$C$5:$C$76+'TAX. DIVERSAS'!$D$5:$D$76))/'VALOR POR PL'!L13) | K14: {=IF(COUNTIF('CRONOGRAMA ATIVIDADES'!$M$5:$M$3004,B14)=0,"",IF(COUNTIFS('CRONOGRAMA ATIVIDADES'!$M$5:$M$3004,B14,'CRONOGRAMA ATIVIDADES'!$O$5:$O$3004,"CONCLUÍDA")=COUNTIF('CRONOGRAMA ATIVIDADES'!$M$5:$M$3004,B14),"Concluído (todas as "&COUNTIF('CRONOGRAMA ATIVIDADES'!$M$5:$M$3004,B14)&" atividades)",IF(COUNTIFS('CRONOGRAMA ATIVIDADES'!$M$5:$M$3004,B14,'CRONOGRAMA ATIVIDADES'!$O$5:$O$3004,"A INICIAR")=COUNTIF('CRONOGRAMA ATIVIDADES'!$M$5:$M$3004,B14),"Não iniciado · início previsto em "&CHOOSE(MONTH(_xlfn.MINIFS('CRONOGRAMA ATIVIDADES'!$F$5:$F$3004,'CRONOGRAMA ATIVIDADES'!$M$5:$M$3004,B14)),"jan","fev","mar","abr","mai","jun","jul","ago","set","out","nov","dez")&"/"&YEAR(_xlfn.MINIFS('CRONOGRAMA ATIVIDADES'!$F$5:$F$3004,'CRONOGRAMA ATIVIDADES'!$M$5:$M$3004,B14)),_xlfn.TEXTJOIN(" / ",TRUE,IF(('CRONOGRAMA ATIVIDADES'!$S$5:$S$304=B14)*('CRONOGRAMA ATIVIDADES'!$AA$5:$AA$304<>""),'CRONOGRAMA ATIVIDADES'!$AA$5:$AA$304,"")))))} | M14: ='VALOR POR PL'!L13 | N14: =IF('VALOR POR PL'!I13="DIRETO",'VALOR POR PL'!L13,0)
B15: ='VALOR POR PL'!C14 | C15: ='VALOR POR PL'!D14 | D15: =IF(OR('VALOR POR PL'!I14<>"DIRETO",'CP RESUMO'!$C$8=""),"",IFERROR(INDEX('CP RESUMO'!$D$8:$BW$8,MATCH(DATE($D$5,12,1),'CP RESUMO'!$D$4:$BW$4,0))/100,"")) | E15: =IF('VALOR POR PL'!I14<>"DIRETO","",'BARRACÃO DE OBRA'!$K$14) | F15: =SUMPRODUCT((YEAR('BARRACÃO DE OBRA'!$B$5:$B$76)=$D$5)*('BARRACÃO DE OBRA'!$C$5:$C$76+'BARRACÃO DE OBRA'!$D$5:$D$76)) | G15: =SUMPRODUCT((YEAR('MODELO PARA BI'!$H$1:$CA$1)=$D$5)*'MODELO PARA BI'!$H$3:$CA$3) | H15: =IF(ISNUMBER($G$5),G15*$G$5,0) | I15: =IF($F$53=0,0,F15/$F$53) | J15: =IF('VALOR POR PL'!L14=0,0,SUMPRODUCT(('BARRACÃO DE OBRA'!$B$5:$B$76<=DATE($D$5,12,1))*('BARRACÃO DE OBRA'!$C$5:$C$76+'BARRACÃO DE OBRA'!$D$5:$D$76))/'VALOR POR PL'!L14) | K15: {=IF(COUNTIF('CRONOGRAMA ATIVIDADES'!$M$5:$M$3004,B15)=0,"",IF(COUNTIFS('CRONOGRAMA ATIVIDADES'!$M$5:$M$3004,B15,'CRONOGRAMA ATIVIDADES'!$O$5:$O$3004,"CONCLUÍDA")=COUNTIF('CRONOGRAMA ATIVIDADES'!$M$5:$M$3004,B15),"Concluído (todas as "&COUNTIF('CRONOGRAMA ATIVIDADES'!$M$5:$M$3004,B15)&" atividades)",IF(COUNTIFS('CRONOGRAMA ATIVIDADES'!$M$5:$M$3004,B15,'CRONOGRAMA ATIVIDADES'!$O$5:$O$3004,"A INICIAR")=COUNTIF('CRONOGRAMA ATIVIDADES'!$M$5:$M$3004,B15),"Não iniciado · início previsto em "&CHOOSE(MONTH(_xlfn.MINIFS('CRONOGRAMA ATIVIDADES'!$F$5:$F$3004,'CRONOGRAMA ATIVIDADES'!$M$5:$M$3004,B15)),"jan","fev","mar","abr","mai","jun","jul","ago","set","out","nov","dez")&"/"&YEAR(_xlfn.MINIFS('CRONOGRAMA ATIVIDADES'!$F$5:$F$3004,'CRONOGRAMA ATIVIDADES'!$M$5:$M$3004,B15)),_xlfn.TEXTJOIN(" / ",TRUE,IF(('CRONOGRAMA ATIVIDADES'!$S$5:$S$304=B15)*('CRONOGRAMA ATIVIDADES'!$AA$5:$AA$304<>""),'CRONOGRAMA ATIVIDADES'!$AA$5:$AA$304,"")))))} | M15: ='VALOR POR PL'!L14 | N15: =IF('VALOR POR PL'!I14="DIRETO",'VALOR POR PL'!L14,0)
B16: ='VALOR POR PL'!C15 | C16: ='VALOR POR PL'!D15 | D16: =IF(OR('VALOR POR PL'!I15<>"DIRETO",'CP RESUMO'!$C$9=""),"",IFERROR(INDEX('CP RESUMO'!$D$9:$BW$9,MATCH(DATE($D$5,12,1),'CP RESUMO'!$D$4:$BW$4,0))/100,"")) | E16: =IF('VALOR POR PL'!I15<>"DIRETO","",'LIG. PROVISÓRIAS'!$K$14) | F16: =SUMPRODUCT((YEAR('LIG. PROVISÓRIAS'!$B$5:$B$76)=$D$5)*('LIG. PROVISÓRIAS'!$C$5:$C$76+'LIG. PROVISÓRIAS'!$D$5:$D$76)) | G16: =SUMPRODUCT((YEAR('MODELO PARA BI'!$H$1:$CA$1)=$D$5)*'MODELO PARA BI'!$H$42:$CA$42) | H16: =IF(ISNUMBER($G$5),G16*$G$5,0) | I16: =IF($F$53=0,0,F16/$F$53) | J16: =IF('VALOR POR PL'!L15=0,0,SUMPRODUCT(('LIG. PROVISÓRIAS'!$B$5:$B$76<=DATE($D$5,12,1))*('LIG. PROVISÓRIAS'!$C$5:$C$76+'LIG. PROVISÓRIAS'!$D$5:$D$76))/'VALOR POR PL'!L15) | K16: {=IF(COUNTIF('CRONOGRAMA ATIVIDADES'!$M$5:$M$3004,B16)=0,"",IF(COUNTIFS('CRONOGRAMA ATIVIDADES'!$M$5:$M$3004,B16,'CRONOGRAMA ATIVIDADES'!$O$5:$O$3004,"CONCLUÍDA")=COUNTIF('CRONOGRAMA ATIVIDADES'!$M$5:$M$3004,B16),"Concluído (todas as "&COUNTIF('CRONOGRAMA ATIVIDADES'!$M$5:$M$3004,B16)&" atividades)",IF(COUNTIFS('CRONOGRAMA ATIVIDADES'!$M$5:$M$3004,B16,'CRONOGRAMA ATIVIDADES'!$O$5:$O$3004,"A INICIAR")=COUNTIF('CRONOGRAMA ATIVIDADES'!$M$5:$M$3004,B16),"Não iniciado · início previsto em "&CHOOSE(MONTH(_xlfn.MINIFS('CRONOGRAMA ATIVIDADES'!$F$5:$F$3004,'CRONOGRAMA ATIVIDADES'!$M$5:$M$3004,B16)),"jan","fev","mar","abr","mai","jun","jul","ago","set","out","nov","dez")&"/"&YEAR(_xlfn.MINIFS('CRONOGRAMA ATIVIDADES'!$F$5:$F$3004,'CRONOGRAMA ATIVIDADES'!$M$5:$M$3004,B16)),_xlfn.TEXTJOIN(" / ",TRUE,IF(('CRONOGRAMA ATIVIDADES'!$S$5:$S$304=B16)*('CRONOGRAMA ATIVIDADES'!$AA$5:$AA$304<>""),'CRONOGRAMA ATIVIDADES'!$AA$5:$AA$304,"")))))} | M16: ='VALOR POR PL'!L15 | N16: =IF('VALOR POR PL'!I15="DIRETO",'VALOR POR PL'!L15,0)
B17: ='VALOR POR PL'!C16 | C17: ='VALOR POR PL'!D16 | D17: =IF(OR('VALOR POR PL'!I16<>"DIRETO",'CP RESUMO'!$C$10=""),"",IFERROR(INDEX('CP RESUMO'!$D$10:$BW$10,MATCH(DATE($D$5,12,1),'CP RESUMO'!$D$4:$BW$4,0))/100,"")) | E17: =IF('VALOR POR PL'!I16<>"DIRETO","",'CONSUMOS'!$K$14) | F17: =SUMPRODUCT((YEAR('CONSUMOS'!$B$5:$B$76)=$D$5)*('CONSUMOS'!$C$5:$C$76+'CONSUMOS'!$D$5:$D$76)) | G17: =SUMPRODUCT((YEAR('MODELO PARA BI'!$H$1:$CA$1)=$D$5)*'MODELO PARA BI'!$H$5:$CA$5) | H17: =IF(ISNUMBER($G$5),G17*$G$5,0) | I17: =IF($F$53=0,0,F17/$F$53) | J17: =IF('VALOR POR PL'!L16=0,0,SUMPRODUCT(('CONSUMOS'!$B$5:$B$76<=DATE($D$5,12,1))*('CONSUMOS'!$C$5:$C$76+'CONSUMOS'!$D$5:$D$76))/'VALOR POR PL'!L16) | K17: {=IF(COUNTIF('CRONOGRAMA ATIVIDADES'!$M$5:$M$3004,B17)=0,"",IF(COUNTIFS('CRONOGRAMA ATIVIDADES'!$M$5:$M$3004,B17,'CRONOGRAMA ATIVIDADES'!$O$5:$O$3004,"CONCLUÍDA")=COUNTIF('CRONOGRAMA ATIVIDADES'!$M$5:$M$3004,B17),"Concluído (todas as "&COUNTIF('CRONOGRAMA ATIVIDADES'!$M$5:$M$3004,B17)&" atividades)",IF(COUNTIFS('CRONOGRAMA ATIVIDADES'!$M$5:$M$3004,B17,'CRONOGRAMA ATIVIDADES'!$O$5:$O$3004,"A INICIAR")=COUNTIF('CRONOGRAMA ATIVIDADES'!$M$5:$M$3004,B17),"Não iniciado · início previsto em "&CHOOSE(MONTH(_xlfn.MINIFS('CRONOGRAMA ATIVIDADES'!$F$5:$F$3004,'CRONOGRAMA ATIVIDADES'!$M$5:$M$3004,B17)),"jan","fev","mar","abr","mai","jun","jul","ago","set","out","nov","dez")&"/"&YEAR(_xlfn.MINIFS('CRONOGRAMA ATIVIDADES'!$F$5:$F$3004,'CRONOGRAMA ATIVIDADES'!$M$5:$M$3004,B17)),_xlfn.TEXTJOIN(" / ",TRUE,IF(('CRONOGRAMA ATIVIDADES'!$S$5:$S$304=B17)*('CRONOGRAMA ATIVIDADES'!$AA$5:$AA$304<>""),'CRONOGRAMA ATIVIDADES'!$AA$5:$AA$304,"")))))} | M17: ='VALOR POR PL'!L16 | N17: =IF('VALOR POR PL'!I16="DIRETO",'VALOR POR PL'!L16,0)
B18: ='VALOR POR PL'!C17 | C18: ='VALOR POR PL'!D17 | D18: =IF(OR('VALOR POR PL'!I17<>"DIRETO",'CP RESUMO'!$C$11=""),"",IFERROR(INDEX('CP RESUMO'!$D$11:$BW$11,MATCH(DATE($D$5,12,1),'CP RESUMO'!$D$4:$BW$4,0))/100,"")) | E18: =IF('VALOR POR PL'!I17<>"DIRETO","",'DIVERSOS'!$K$14) | F18: =SUMPRODUCT((YEAR('DIVERSOS'!$B$5:$B$76)=$D$5)*('DIVERSOS'!$C$5:$C$76+'DIVERSOS'!$D$5:$D$76)) | G18: =SUMPRODUCT((YEAR('MODELO PARA BI'!$H$1:$CA$1)=$D$5)*'MODELO PARA BI'!$H$9:$CA$9) | H18: =IF(ISNUMBER($G$5),G18*$G$5,0) | I18: =IF($F$53=0,0,F18/$F$53) | J18: =IF('VALOR POR PL'!L17=0,0,SUMPRODUCT(('DIVERSOS'!$B$5:$B$76<=DATE($D$5,12,1))*('DIVERSOS'!$C$5:$C$76+'DIVERSOS'!$D$5:$D$76))/'VALOR POR PL'!L17) | K18: {=IF(COUNTIF('CRONOGRAMA ATIVIDADES'!$M$5:$M$3004,B18)=0,"",IF(COUNTIFS('CRONOGRAMA ATIVIDADES'!$M$5:$M$3004,B18,'CRONOGRAMA ATIVIDADES'!$O$5:$O$3004,"CONCLUÍDA")=COUNTIF('CRONOGRAMA ATIVIDADES'!$M$5:$M$3004,B18),"Concluído (todas as "&COUNTIF('CRONOGRAMA ATIVIDADES'!$M$5:$M$3004,B18)&" atividades)",IF(COUNTIFS('CRONOGRAMA ATIVIDADES'!$M$5:$M$3004,B18,'CRONOGRAMA ATIVIDADES'!$O$5:$O$3004,"A INICIAR")=COUNTIF('CRONOGRAMA ATIVIDADES'!$M$5:$M$3004,B18),"Não iniciado · início previsto em "&CHOOSE(MONTH(_xlfn.MINIFS('CRONOGRAMA ATIVIDADES'!$F$5:$F$3004,'CRONOGRAMA ATIVIDADES'!$M$5:$M$3004,B18)),"jan","fev","mar","abr","mai","jun","jul","ago","set","out","nov","dez")&"/"&YEAR(_xlfn.MINIFS('CRONOGRAMA ATIVIDADES'!$F$5:$F$3004,'CRONOGRAMA ATIVIDADES'!$M$5:$M$3004,B18)),_xlfn.TEXTJOIN(" / ",TRUE,IF(('CRONOGRAMA ATIVIDADES'!$S$5:$S$304=B18)*('CRONOGRAMA ATIVIDADES'!$AA$5:$AA$304<>""),'CRONOGRAMA ATIVIDADES'!$AA$5:$AA$304,"")))))} | M18: ='VALOR POR PL'!L17 | N18: =IF('VALOR POR PL'!I17="DIRETO",'VALOR POR PL'!L17,0)
B19: ='VALOR POR PL'!C18 | C19: ='VALOR POR PL'!D18 | D19: =IF(OR('VALOR POR PL'!I18<>"DIRETO",'CP RESUMO'!$C$12=""),"",IFERROR(INDEX('CP RESUMO'!$D$12:$BW$12,MATCH(DATE($D$5,12,1),'CP RESUMO'!$D$4:$BW$4,0))/100,"")) | E19: =IF('VALOR POR PL'!I18<>"DIRETO","",'TRANSPORTES'!$K$14) | F19: =SUMPRODUCT((YEAR('TRANSPORTES'!$B$5:$B$76)=$D$5)*('TRANSPORTES'!$C$5:$C$76+'TRANSPORTES'!$D$5:$D$76)) | G19: =SUMPRODUCT((YEAR('MODELO PARA BI'!$H$1:$CA$1)=$D$5)*'MODELO PARA BI'!$H$46:$CA$46) | H19: =IF(ISNUMBER($G$5),G19*$G$5,0) | I19: =IF($F$53=0,0,F19/$F$53) | J19: =IF('VALOR POR PL'!L18=0,0,SUMPRODUCT(('TRANSPORTES'!$B$5:$B$76<=DATE($D$5,12,1))*('TRANSPORTES'!$C$5:$C$76+'TRANSPORTES'!$D$5:$D$76))/'VALOR POR PL'!L18) | K19: {=IF(COUNTIF('CRONOGRAMA ATIVIDADES'!$M$5:$M$3004,B19)=0,"",IF(COUNTIFS('CRONOGRAMA ATIVIDADES'!$M$5:$M$3004,B19,'CRONOGRAMA ATIVIDADES'!$O$5:$O$3004,"CONCLUÍDA")=COUNTIF('CRONOGRAMA ATIVIDADES'!$M$5:$M$3004,B19),"Concluído (todas as "&COUNTIF('CRONOGRAMA ATIVIDADES'!$M$5:$M$3004,B19)&" atividades)",IF(COUNTIFS('CRONOGRAMA ATIVIDADES'!$M$5:$M$3004,B19,'CRONOGRAMA ATIVIDADES'!$O$5:$O$3004,"A INICIAR")=COUNTIF('CRONOGRAMA ATIVIDADES'!$M$5:$M$3004,B19),"Não iniciado · início previsto em "&CHOOSE(MONTH(_xlfn.MINIFS('CRONOGRAMA ATIVIDADES'!$F$5:$F$3004,'CRONOGRAMA ATIVIDADES'!$M$5:$M$3004,B19)),"jan","fev","mar","abr","mai","jun","jul","ago","set","out","nov","dez")&"/"&YEAR(_xlfn.MINIFS('CRONOGRAMA ATIVIDADES'!$F$5:$F$3004,'CRONOGRAMA ATIVIDADES'!$M$5:$M$3004,B19)),_xlfn.TEXTJOIN(" / ",TRUE,IF(('CRONOGRAMA ATIVIDADES'!$S$5:$S$304=B19)*('CRONOGRAMA ATIVIDADES'!$AA$5:$AA$304<>""),'CRONOGRAMA ATIVIDADES'!$AA$5:$AA$304,"")))))} | M19: ='VALOR POR PL'!L18 | N19: =IF('VALOR POR PL'!I18="DIRETO",'VALOR POR PL'!L18,0)
B20: ='VALOR POR PL'!C19 | C20: ='VALOR POR PL'!D19 | D20: =IF(OR('VALOR POR PL'!I19<>"DIRETO",'CP RESUMO'!$C$13=""),"",IFERROR(INDEX('CP RESUMO'!$D$13:$BW$13,MATCH(DATE($D$5,12,1),'CP RESUMO'!$D$4:$BW$4,0))/100,"")) | E20: =IF('VALOR POR PL'!I19<>"DIRETO","",'CONSULTORIAS'!$K$14) | F20: =SUMPRODUCT((YEAR('CONSULTORIAS'!$B$5:$B$76)=$D$5)*('CONSULTORIAS'!$C$5:$C$76+'CONSULTORIAS'!$D$5:$D$76)) | G20: =SUMPRODUCT((YEAR('MODELO PARA BI'!$H$1:$CA$1)=$D$5)*'MODELO PARA BI'!$H$4:$CA$4) | H20: =IF(ISNUMBER($G$5),G20*$G$5,0) | I20: =IF($F$53=0,0,F20/$F$53) | J20: =IF('VALOR POR PL'!L19=0,0,SUMPRODUCT(('CONSULTORIAS'!$B$5:$B$76<=DATE($D$5,12,1))*('CONSULTORIAS'!$C$5:$C$76+'CONSULTORIAS'!$D$5:$D$76))/'VALOR POR PL'!L19) | K20: {=IF(COUNTIF('CRONOGRAMA ATIVIDADES'!$M$5:$M$3004,B20)=0,"",IF(COUNTIFS('CRONOGRAMA ATIVIDADES'!$M$5:$M$3004,B20,'CRONOGRAMA ATIVIDADES'!$O$5:$O$3004,"CONCLUÍDA")=COUNTIF('CRONOGRAMA ATIVIDADES'!$M$5:$M$3004,B20),"Concluído (todas as "&COUNTIF('CRONOGRAMA ATIVIDADES'!$M$5:$M$3004,B20)&" atividades)",IF(COUNTIFS('CRONOGRAMA ATIVIDADES'!$M$5:$M$3004,B20,'CRONOGRAMA ATIVIDADES'!$O$5:$O$3004,"A INICIAR")=COUNTIF('CRONOGRAMA ATIVIDADES'!$M$5:$M$3004,B20),"Não iniciado · início previsto em "&CHOOSE(MONTH(_xlfn.MINIFS('CRONOGRAMA ATIVIDADES'!$F$5:$F$3004,'CRONOGRAMA ATIVIDADES'!$M$5:$M$3004,B20)),"jan","fev","mar","abr","mai","jun","jul","ago","set","out","nov","dez")&"/"&YEAR(_xlfn.MINIFS('CRONOGRAMA ATIVIDADES'!$F$5:$F$3004,'CRONOGRAMA ATIVIDADES'!$M$5:$M$3004,B20)),_xlfn.TEXTJOIN(" / ",TRUE,IF(('CRONOGRAMA ATIVIDADES'!$S$5:$S$304=B20)*('CRONOGRAMA ATIVIDADES'!$AA$5:$AA$304<>""),'CRONOGRAMA ATIVIDADES'!$AA$5:$AA$304,"")))))} | M20: ='VALOR POR PL'!L19 | N20: =IF('VALOR POR PL'!I19="DIRETO",'VALOR POR PL'!L19,0)
B21: ='VALOR POR PL'!C20 | C21: ='VALOR POR PL'!D20 | D21: =IF(OR('VALOR POR PL'!I20<>"DIRETO",'CP RESUMO'!$C$14=""),"",IFERROR(INDEX('CP RESUMO'!$D$14:$BW$14,MATCH(DATE($D$5,12,1),'CP RESUMO'!$D$4:$BW$4,0))/100,"")) | E21: =IF('VALOR POR PL'!I20<>"DIRETO","",'MDO'!$K$14) | F21: =SUMPRODUCT((YEAR('MDO'!$B$5:$B$76)=$D$5)*('MDO'!$C$5:$C$76+'MDO'!$D$5:$D$76)) | G21: =SUMPRODUCT((YEAR('MODELO PARA BI'!$H$1:$CA$1)=$D$5)*'MODELO PARA BI'!$H$49:$CA$49) | H21: =IF(ISNUMBER($G$5),G21*$G$5,0) | I21: =IF($F$53=0,0,F21/$F$53) | J21: =IF('VALOR POR PL'!L20=0,0,SUMPRODUCT(('MDO'!$B$5:$B$76<=DATE($D$5,12,1))*('MDO'!$C$5:$C$76+'MDO'!$D$5:$D$76))/'VALOR POR PL'!L20) | K21: {=IF(COUNTIF('CRONOGRAMA ATIVIDADES'!$M$5:$M$3004,B21)=0,"",IF(COUNTIFS('CRONOGRAMA ATIVIDADES'!$M$5:$M$3004,B21,'CRONOGRAMA ATIVIDADES'!$O$5:$O$3004,"CONCLUÍDA")=COUNTIF('CRONOGRAMA ATIVIDADES'!$M$5:$M$3004,B21),"Concluído (todas as "&COUNTIF('CRONOGRAMA ATIVIDADES'!$M$5:$M$3004,B21)&" atividades)",IF(COUNTIFS('CRONOGRAMA ATIVIDADES'!$M$5:$M$3004,B21,'CRONOGRAMA ATIVIDADES'!$O$5:$O$3004,"A INICIAR")=COUNTIF('CRONOGRAMA ATIVIDADES'!$M$5:$M$3004,B21),"Não iniciado · início previsto em "&CHOOSE(MONTH(_xlfn.MINIFS('CRONOGRAMA ATIVIDADES'!$F$5:$F$3004,'CRONOGRAMA ATIVIDADES'!$M$5:$M$3004,B21)),"jan","fev","mar","abr","mai","jun","jul","ago","set","out","nov","dez")&"/"&YEAR(_xlfn.MINIFS('CRONOGRAMA ATIVIDADES'!$F$5:$F$3004,'CRONOGRAMA ATIVIDADES'!$M$5:$M$3004,B21)),_xlfn.TEXTJOIN(" / ",TRUE,IF(('CRONOGRAMA ATIVIDADES'!$S$5:$S$304=B21)*('CRONOGRAMA ATIVIDADES'!$AA$5:$AA$304<>""),'CRONOGRAMA ATIVIDADES'!$AA$5:$AA$304,"")))))} | M21: ='VALOR POR PL'!L20 | N21: =IF('VALOR POR PL'!I20="DIRETO",'VALOR POR PL'!L20,0)
B22: ='VALOR POR PL'!C21 | C22: ='VALOR POR PL'!D21 | D22: =IF(OR('VALOR POR PL'!I21<>"DIRETO",'CP RESUMO'!$C$15=""),"",IFERROR(INDEX('CP RESUMO'!$D$15:$BW$15,MATCH(DATE($D$5,12,1),'CP RESUMO'!$D$4:$BW$4,0))/100,"")) | E22: =IF('VALOR POR PL'!I21<>"DIRETO","",'EQUIP E FER'!$K$14) | F22: =SUMPRODUCT((YEAR('EQUIP E FER'!$B$5:$B$76)=$D$5)*('EQUIP E FER'!$C$5:$C$76+'EQUIP E FER'!$D$5:$D$76)) | G22: =SUMPRODUCT((YEAR('MODELO PARA BI'!$H$1:$CA$1)=$D$5)*'MODELO PARA BI'!$H$11:$CA$11) | H22: =IF(ISNUMBER($G$5),G22*$G$5,0) | I22: =IF($F$53=0,0,F22/$F$53) | J22: =IF('VALOR POR PL'!L21=0,0,SUMPRODUCT(('EQUIP E FER'!$B$5:$B$76<=DATE($D$5,12,1))*('EQUIP E FER'!$C$5:$C$76+'EQUIP E FER'!$D$5:$D$76))/'VALOR POR PL'!L21) | K22: {=IF(COUNTIF('CRONOGRAMA ATIVIDADES'!$M$5:$M$3004,B22)=0,"",IF(COUNTIFS('CRONOGRAMA ATIVIDADES'!$M$5:$M$3004,B22,'CRONOGRAMA ATIVIDADES'!$O$5:$O$3004,"CONCLUÍDA")=COUNTIF('CRONOGRAMA ATIVIDADES'!$M$5:$M$3004,B22),"Concluído (todas as "&COUNTIF('CRONOGRAMA ATIVIDADES'!$M$5:$M$3004,B22)&" atividades)",IF(COUNTIFS('CRONOGRAMA ATIVIDADES'!$M$5:$M$3004,B22,'CRONOGRAMA ATIVIDADES'!$O$5:$O$3004,"A INICIAR")=COUNTIF('CRONOGRAMA ATIVIDADES'!$M$5:$M$3004,B22),"Não iniciado · início previsto em "&CHOOSE(MONTH(_xlfn.MINIFS('CRONOGRAMA ATIVIDADES'!$F$5:$F$3004,'CRONOGRAMA ATIVIDADES'!$M$5:$M$3004,B22)),"jan","fev","mar","abr","mai","jun","jul","ago","set","out","nov","dez")&"/"&YEAR(_xlfn.MINIFS('CRONOGRAMA ATIVIDADES'!$F$5:$F$3004,'CRONOGRAMA ATIVIDADES'!$M$5:$M$3004,B22)),_xlfn.TEXTJOIN(" / ",TRUE,IF(('CRONOGRAMA ATIVIDADES'!$S$5:$S$304=B22)*('CRONOGRAMA ATIVIDADES'!$AA$5:$AA$304<>""),'CRONOGRAMA ATIVIDADES'!$AA$5:$AA$304,"")))))} | M22: ='VALOR POR PL'!L21 | N22: =IF('VALOR POR PL'!I21="DIRETO",'VALOR POR PL'!L21,0)
B23: 01 a 11 | C23: INDIRETOS | D23: =IFERROR(SUMPRODUCT(D12:D22,N12:N22)/SUMPRODUCT(ISNUMBER(D12:D22)*N12:N22),"") | E23: =IFERROR(SUMPRODUCT(E12:E22,N12:N22)/SUMPRODUCT(ISNUMBER(E12:E22)*N12:N22),"") | F23: =SUM(F12:F22) | G23: =SUM(G12:G22) | H23: =SUM(H12:H22) | I23: =IF($F$53=0,0,F23/$F$53) | J23: =IFERROR(SUMPRODUCT(J12:J22,M12:M22)/SUM(M12:M22),0) | M23: =SUM(M12:M22) | N23: =SUM(N12:N22)
B24: ='VALOR POR PL'!C22 | C24: ='VALOR POR PL'!D22 | D24: =IF(OR('VALOR POR PL'!I22<>"DIRETO",'CP RESUMO'!$C$16=""),"",IFERROR(INDEX('CP RESUMO'!$D$16:$BW$16,MATCH(DATE($D$5,12,1),'CP RESUMO'!$D$4:$BW$4,0))/100,"")) | E24: =IF('VALOR POR PL'!I22<>"DIRETO","",'SERV. INICIAIS'!$K$14) | F24: =SUMPRODUCT((YEAR('SERV. INICIAIS'!$B$5:$B$76)=$D$5)*('SERV. INICIAIS'!$C$5:$C$76+'SERV. INICIAIS'!$D$5:$D$76)) | G24: =SUMPRODUCT((YEAR('MODELO PARA BI'!$H$1:$CA$1)=$D$5)*'MODELO PARA BI'!$H$52:$CA$52) | H24: =IF(ISNUMBER($G$5),G24*$G$5,0) | I24: =IF($F$53=0,0,F24/$F$53) | J24: =IF('VALOR POR PL'!L22=0,0,SUMPRODUCT(('SERV. INICIAIS'!$B$5:$B$76<=DATE($D$5,12,1))*('SERV. INICIAIS'!$C$5:$C$76+'SERV. INICIAIS'!$D$5:$D$76))/'VALOR POR PL'!L22) | K24: {=IF(COUNTIF('CRONOGRAMA ATIVIDADES'!$M$5:$M$3004,B24)=0,"",IF(COUNTIFS('CRONOGRAMA ATIVIDADES'!$M$5:$M$3004,B24,'CRONOGRAMA ATIVIDADES'!$O$5:$O$3004,"CONCLUÍDA")=COUNTIF('CRONOGRAMA ATIVIDADES'!$M$5:$M$3004,B24),"Concluído (todas as "&COUNTIF('CRONOGRAMA ATIVIDADES'!$M$5:$M$3004,B24)&" atividades)",IF(COUNTIFS('CRONOGRAMA ATIVIDADES'!$M$5:$M$3004,B24,'CRONOGRAMA ATIVIDADES'!$O$5:$O$3004,"A INICIAR")=COUNTIF('CRONOGRAMA ATIVIDADES'!$M$5:$M$3004,B24),"Não iniciado · início previsto em "&CHOOSE(MONTH(_xlfn.MINIFS('CRONOGRAMA ATIVIDADES'!$F$5:$F$3004,'CRONOGRAMA ATIVIDADES'!$M$5:$M$3004,B24)),"jan","fev","mar","abr","mai","jun","jul","ago","set","out","nov","dez")&"/"&YEAR(_xlfn.MINIFS('CRONOGRAMA ATIVIDADES'!$F$5:$F$3004,'CRONOGRAMA ATIVIDADES'!$M$5:$M$3004,B24)),_xlfn.TEXTJOIN(" / ",TRUE,IF(('CRONOGRAMA ATIVIDADES'!$S$5:$S$304=B24)*('CRONOGRAMA ATIVIDADES'!$AA$5:$AA$304<>""),'CRONOGRAMA ATIVIDADES'!$AA$5:$AA$304,"")))))} | M24: ='VALOR POR PL'!L22 | N24: =IF('VALOR POR PL'!I22="DIRETO",'VALOR POR PL'!L22,0)
B25: ='VALOR POR PL'!C23 | C25: ='VALOR POR PL'!D23 | D25: =IF(OR('VALOR POR PL'!I23<>"DIRETO",'CP RESUMO'!$C$17=""),"",IFERROR(INDEX('CP RESUMO'!$D$17:$BW$17,MATCH(DATE($D$5,12,1),'CP RESUMO'!$D$4:$BW$4,0))/100,"")) | E25: =IF('VALOR POR PL'!I23<>"DIRETO","",'CONTENÇÃO'!$K$14) | F25: =SUMPRODUCT((YEAR('CONTENÇÃO'!$B$5:$B$76)=$D$5)*('CONTENÇÃO'!$C$5:$C$76+'CONTENÇÃO'!$D$5:$D$76)) | G25: =SUMPRODUCT((YEAR('MODELO PARA BI'!$H$1:$CA$1)=$D$5)*'MODELO PARA BI'!$H$6:$CA$6) | H25: =IF(ISNUMBER($G$5),G25*$G$5,0) | I25: =IF($F$53=0,0,F25/$F$53) | J25: =IF('VALOR POR PL'!L23=0,0,SUMPRODUCT(('CONTENÇÃO'!$B$5:$B$76<=DATE($D$5,12,1))*('CONTENÇÃO'!$C$5:$C$76+'CONTENÇÃO'!$D$5:$D$76))/'VALOR POR PL'!L23) | K25: {=IF(COUNTIF('CRONOGRAMA ATIVIDADES'!$M$5:$M$3004,B25)=0,"",IF(COUNTIFS('CRONOGRAMA ATIVIDADES'!$M$5:$M$3004,B25,'CRONOGRAMA ATIVIDADES'!$O$5:$O$3004,"CONCLUÍDA")=COUNTIF('CRONOGRAMA ATIVIDADES'!$M$5:$M$3004,B25),"Concluído (todas as "&COUNTIF('CRONOGRAMA ATIVIDADES'!$M$5:$M$3004,B25)&" atividades)",IF(COUNTIFS('CRONOGRAMA ATIVIDADES'!$M$5:$M$3004,B25,'CRONOGRAMA ATIVIDADES'!$O$5:$O$3004,"A INICIAR")=COUNTIF('CRONOGRAMA ATIVIDADES'!$M$5:$M$3004,B25),"Não iniciado · início previsto em "&CHOOSE(MONTH(_xlfn.MINIFS('CRONOGRAMA ATIVIDADES'!$F$5:$F$3004,'CRONOGRAMA ATIVIDADES'!$M$5:$M$3004,B25)),"jan","fev","mar","abr","mai","jun","jul","ago","set","out","nov","dez")&"/"&YEAR(_xlfn.MINIFS('CRONOGRAMA ATIVIDADES'!$F$5:$F$3004,'CRONOGRAMA ATIVIDADES'!$M$5:$M$3004,B25)),_xlfn.TEXTJOIN(" / ",TRUE,IF(('CRONOGRAMA ATIVIDADES'!$S$5:$S$304=B25)*('CRONOGRAMA ATIVIDADES'!$AA$5:$AA$304<>""),'CRONOGRAMA ATIVIDADES'!$AA$5:$AA$304,"")))))} | M25: ='VALOR POR PL'!L23 | N25: =IF('VALOR POR PL'!I23="DIRETO",'VALOR POR PL'!L23,0)
B26: ='VALOR POR PL'!C24 | C26: ='VALOR POR PL'!D24 | D26: =IF(OR('VALOR POR PL'!I24<>"DIRETO",'CP RESUMO'!$C$18=""),"",IFERROR(INDEX('CP RESUMO'!$D$18:$BW$18,MATCH(DATE($D$5,12,1),'CP RESUMO'!$D$4:$BW$4,0))/100,"")) | E26: =IF('VALOR POR PL'!I24<>"DIRETO","",'TERRAPLENAGEM'!$K$14) | F26: =SUMPRODUCT((YEAR('TERRAPLENAGEM'!$B$5:$B$76)=$D$5)*('TERRAPLENAGEM'!$C$5:$C$76+'TERRAPLENAGEM'!$D$5:$D$76)) | G26: =SUMPRODUCT((YEAR('MODELO PARA BI'!$H$1:$CA$1)=$D$5)*'MODELO PARA BI'!$H$44:$CA$44) | H26: =IF(ISNUMBER($G$5),G26*$G$5,0) | I26: =IF($F$53=0,0,F26/$F$53) | J26: =IF('VALOR POR PL'!L24=0,0,SUMPRODUCT(('TERRAPLENAGEM'!$B$5:$B$76<=DATE($D$5,12,1))*('TERRAPLENAGEM'!$C$5:$C$76+'TERRAPLENAGEM'!$D$5:$D$76))/'VALOR POR PL'!L24) | K26: {=IF(COUNTIF('CRONOGRAMA ATIVIDADES'!$M$5:$M$3004,B26)=0,"",IF(COUNTIFS('CRONOGRAMA ATIVIDADES'!$M$5:$M$3004,B26,'CRONOGRAMA ATIVIDADES'!$O$5:$O$3004,"CONCLUÍDA")=COUNTIF('CRONOGRAMA ATIVIDADES'!$M$5:$M$3004,B26),"Concluído (todas as "&COUNTIF('CRONOGRAMA ATIVIDADES'!$M$5:$M$3004,B26)&" atividades)",IF(COUNTIFS('CRONOGRAMA ATIVIDADES'!$M$5:$M$3004,B26,'CRONOGRAMA ATIVIDADES'!$O$5:$O$3004,"A INICIAR")=COUNTIF('CRONOGRAMA ATIVIDADES'!$M$5:$M$3004,B26),"Não iniciado · início previsto em "&CHOOSE(MONTH(_xlfn.MINIFS('CRONOGRAMA ATIVIDADES'!$F$5:$F$3004,'CRONOGRAMA ATIVIDADES'!$M$5:$M$3004,B26)),"jan","fev","mar","abr","mai","jun","jul","ago","set","out","nov","dez")&"/"&YEAR(_xlfn.MINIFS('CRONOGRAMA ATIVIDADES'!$F$5:$F$3004,'CRONOGRAMA ATIVIDADES'!$M$5:$M$3004,B26)),_xlfn.TEXTJOIN(" / ",TRUE,IF(('CRONOGRAMA ATIVIDADES'!$S$5:$S$304=B26)*('CRONOGRAMA ATIVIDADES'!$AA$5:$AA$304<>""),'CRONOGRAMA ATIVIDADES'!$AA$5:$AA$304,"")))))} | M26: ='VALOR POR PL'!L24 | N26: =IF('VALOR POR PL'!I24="DIRETO",'VALOR POR PL'!L24,0)
B27: ='VALOR POR PL'!C25 | C27: ='VALOR POR PL'!D25 | D27: =IF(OR('VALOR POR PL'!I25<>"DIRETO",'CP RESUMO'!$C$19=""),"",IFERROR(INDEX('CP RESUMO'!$D$19:$BW$19,MATCH(DATE($D$5,12,1),'CP RESUMO'!$D$4:$BW$4,0))/100,"")) | E27: =IF('VALOR POR PL'!I25<>"DIRETO","",'FUND. PROF'!$K$14) | F27: =SUMPRODUCT((YEAR('FUND. PROF'!$B$5:$B$76)=$D$5)*('FUND. PROF'!$C$5:$C$76+'FUND. PROF'!$D$5:$D$76)) | G27: =SUMPRODUCT((YEAR('MODELO PARA BI'!$H$1:$CA$1)=$D$5)*'MODELO PARA BI'!$H$15:$CA$15) | H27: =IF(ISNUMBER($G$5),G27*$G$5,0) | I27: =IF($F$53=0,0,F27/$F$53) | J27: =IF('VALOR POR PL'!L25=0,0,SUMPRODUCT(('FUND. PROF'!$B$5:$B$76<=DATE($D$5,12,1))*('FUND. PROF'!$C$5:$C$76+'FUND. PROF'!$D$5:$D$76))/'VALOR POR PL'!L25) | K27: {=IF(COUNTIF('CRONOGRAMA ATIVIDADES'!$M$5:$M$3004,B27)=0,"",IF(COUNTIFS('CRONOGRAMA ATIVIDADES'!$M$5:$M$3004,B27,'CRONOGRAMA ATIVIDADES'!$O$5:$O$3004,"CONCLUÍDA")=COUNTIF('CRONOGRAMA ATIVIDADES'!$M$5:$M$3004,B27),"Concluído (todas as "&COUNTIF('CRONOGRAMA ATIVIDADES'!$M$5:$M$3004,B27)&" atividades)",IF(COUNTIFS('CRONOGRAMA ATIVIDADES'!$M$5:$M$3004,B27,'CRONOGRAMA ATIVIDADES'!$O$5:$O$3004,"A INICIAR")=COUNTIF('CRONOGRAMA ATIVIDADES'!$M$5:$M$3004,B27),"Não iniciado · início previsto em "&CHOOSE(MONTH(_xlfn.MINIFS('CRONOGRAMA ATIVIDADES'!$F$5:$F$3004,'CRONOGRAMA ATIVIDADES'!$M$5:$M$3004,B27)),"jan","fev","mar","abr","mai","jun","jul","ago","set","out","nov","dez")&"/"&YEAR(_xlfn.MINIFS('CRONOGRAMA ATIVIDADES'!$F$5:$F$3004,'CRONOGRAMA ATIVIDADES'!$M$5:$M$3004,B27)),_xlfn.TEXTJOIN(" / ",TRUE,IF(('CRONOGRAMA ATIVIDADES'!$S$5:$S$304=B27)*('CRONOGRAMA ATIVIDADES'!$AA$5:$AA$304<>""),'CRONOGRAMA ATIVIDADES'!$AA$5:$AA$304,"")))))} | M27: ='VALOR POR PL'!L25 | N27: =IF('VALOR POR PL'!I25="DIRETO",'VALOR POR PL'!L25,0)
B28: ='VALOR POR PL'!C26 | C28: ='VALOR POR PL'!D26 | D28: =IF(OR('VALOR POR PL'!I26<>"DIRETO",'CP RESUMO'!$C$20=""),"",IFERROR(INDEX('CP RESUMO'!$D$20:$BW$20,MATCH(DATE($D$5,12,1),'CP RESUMO'!$D$4:$BW$4,0))/100,"")) | E28: =IF('VALOR POR PL'!I26<>"DIRETO","",'FUND. SUP'!$K$14) | F28: =SUMPRODUCT((YEAR('FUND. SUP'!$B$5:$B$76)=$D$5)*('FUND. SUP'!$C$5:$C$76+'FUND. SUP'!$D$5:$D$76)) | G28: =SUMPRODUCT((YEAR('MODELO PARA BI'!$H$1:$CA$1)=$D$5)*'MODELO PARA BI'!$H$16:$CA$16) | H28: =IF(ISNUMBER($G$5),G28*$G$5,0) | I28: =IF($F$53=0,0,F28/$F$53) | J28: =IF('VALOR POR PL'!L26=0,0,SUMPRODUCT(('FUND. SUP'!$B$5:$B$76<=DATE($D$5,12,1))*('FUND. SUP'!$C$5:$C$76+'FUND. SUP'!$D$5:$D$76))/'VALOR POR PL'!L26) | K28: {=IF(COUNTIF('CRONOGRAMA ATIVIDADES'!$M$5:$M$3004,B28)=0,"",IF(COUNTIFS('CRONOGRAMA ATIVIDADES'!$M$5:$M$3004,B28,'CRONOGRAMA ATIVIDADES'!$O$5:$O$3004,"CONCLUÍDA")=COUNTIF('CRONOGRAMA ATIVIDADES'!$M$5:$M$3004,B28),"Concluído (todas as "&COUNTIF('CRONOGRAMA ATIVIDADES'!$M$5:$M$3004,B28)&" atividades)",IF(COUNTIFS('CRONOGRAMA ATIVIDADES'!$M$5:$M$3004,B28,'CRONOGRAMA ATIVIDADES'!$O$5:$O$3004,"A INICIAR")=COUNTIF('CRONOGRAMA ATIVIDADES'!$M$5:$M$3004,B28),"Não iniciado · início previsto em "&CHOOSE(MONTH(_xlfn.MINIFS('CRONOGRAMA ATIVIDADES'!$F$5:$F$3004,'CRONOGRAMA ATIVIDADES'!$M$5:$M$3004,B28)),"jan","fev","mar","abr","mai","jun","jul","ago","set","out","nov","dez")&"/"&YEAR(_xlfn.MINIFS('CRONOGRAMA ATIVIDADES'!$F$5:$F$3004,'CRONOGRAMA ATIVIDADES'!$M$5:$M$3004,B28)),_xlfn.TEXTJOIN(" / ",TRUE,IF(('CRONOGRAMA ATIVIDADES'!$S$5:$S$304=B28)*('CRONOGRAMA ATIVIDADES'!$AA$5:$AA$304<>""),'CRONOGRAMA ATIVIDADES'!$AA$5:$AA$304,"")))))} | M28: ='VALOR POR PL'!L26 | N28: =IF('VALOR POR PL'!I26="DIRETO",'VALOR POR PL'!L26,0)
B29: 12 a 16 | C29: SERVIÇOS INICIAIS, CONTENÇÃO, TERRAPLENAGEM E FUNDAÇÕES | D29: =IFERROR(SUMPRODUCT(D24:D28,N24:N28)/SUMPRODUCT(ISNUMBER(D24:D28)*N24:N28),"") | E29: =IFERROR(SUMPRODUCT(E24:E28,N24:N28)/SUMPRODUCT(ISNUMBER(E24:E28)*N24:N28),"") | F29: =SUM(F24:F28) | G29: =SUM(G24:G28) | H29: =SUM(H24:H28) | I29: =IF($F$53=0,0,F29/$F$53) | J29: =IFERROR(SUMPRODUCT(J24:J28,M24:M28)/SUM(M24:M28),0) | M29: =SUM(M24:M28) | N29: =SUM(N24:N28)
B30: ='VALOR POR PL'!C27 | C30: ='VALOR POR PL'!D27 | D30: =IF(OR('VALOR POR PL'!I27<>"DIRETO",'CP RESUMO'!$C$21=""),"",IFERROR(INDEX('CP RESUMO'!$D$21:$BW$21,MATCH(DATE($D$5,12,1),'CP RESUMO'!$D$4:$BW$4,0))/100,"")) | E30: =IF('VALOR POR PL'!I27<>"DIRETO","",'ESTRUTURA'!$K$14) | F30: =SUMPRODUCT((YEAR('ESTRUTURA'!$B$5:$B$76)=$D$5)*('ESTRUTURA'!$C$5:$C$76+'ESTRUTURA'!$D$5:$D$76)) | G30: =SUMPRODUCT((YEAR('MODELO PARA BI'!$H$1:$CA$1)=$D$5)*'MODELO PARA BI'!$H$13:$CA$13) | H30: =IF(ISNUMBER($G$5),G30*$G$5,0) | I30: =IF($F$53=0,0,F30/$F$53) | J30: =IF('VALOR POR PL'!L27=0,0,SUMPRODUCT(('ESTRUTURA'!$B$5:$B$76<=DATE($D$5,12,1))*('ESTRUTURA'!$C$5:$C$76+'ESTRUTURA'!$D$5:$D$76))/'VALOR POR PL'!L27) | K30: {=IF(COUNTIF('CRONOGRAMA ATIVIDADES'!$M$5:$M$3004,B30)=0,"",IF(COUNTIFS('CRONOGRAMA ATIVIDADES'!$M$5:$M$3004,B30,'CRONOGRAMA ATIVIDADES'!$O$5:$O$3004,"CONCLUÍDA")=COUNTIF('CRONOGRAMA ATIVIDADES'!$M$5:$M$3004,B30),"Concluído (todas as "&COUNTIF('CRONOGRAMA ATIVIDADES'!$M$5:$M$3004,B30)&" atividades)",IF(COUNTIFS('CRONOGRAMA ATIVIDADES'!$M$5:$M$3004,B30,'CRONOGRAMA ATIVIDADES'!$O$5:$O$3004,"A INICIAR")=COUNTIF('CRONOGRAMA ATIVIDADES'!$M$5:$M$3004,B30),"Não iniciado · início previsto em "&CHOOSE(MONTH(_xlfn.MINIFS('CRONOGRAMA ATIVIDADES'!$F$5:$F$3004,'CRONOGRAMA ATIVIDADES'!$M$5:$M$3004,B30)),"jan","fev","mar","abr","mai","jun","jul","ago","set","out","nov","dez")&"/"&YEAR(_xlfn.MINIFS('CRONOGRAMA ATIVIDADES'!$F$5:$F$3004,'CRONOGRAMA ATIVIDADES'!$M$5:$M$3004,B30)),_xlfn.TEXTJOIN(" / ",TRUE,IF(('CRONOGRAMA ATIVIDADES'!$S$5:$S$304=B30)*('CRONOGRAMA ATIVIDADES'!$AA$5:$AA$304<>""),'CRONOGRAMA ATIVIDADES'!$AA$5:$AA$304,"")))))} | M30: ='VALOR POR PL'!L27 | N30: =IF('VALOR POR PL'!I27="DIRETO",'VALOR POR PL'!L27,0)
B31: ='VALOR POR PL'!C28 | C31: ='VALOR POR PL'!D28 | D31: =IF(OR('VALOR POR PL'!I28<>"DIRETO",'CP RESUMO'!$C$22=""),"",IFERROR(INDEX('CP RESUMO'!$D$22:$BW$22,MATCH(DATE($D$5,12,1),'CP RESUMO'!$D$4:$BW$4,0))/100,"")) | E31: =IF('VALOR POR PL'!I28<>"DIRETO","",'ALVENARIA'!$K$14) | F31: =SUMPRODUCT((YEAR('ALVENARIA'!$B$5:$B$76)=$D$5)*('ALVENARIA'!$C$5:$C$76+'ALVENARIA'!$D$5:$D$76)) | G31: =SUMPRODUCT((YEAR('MODELO PARA BI'!$H$1:$CA$1)=$D$5)*'MODELO PARA BI'!$H$2:$CA$2) | H31: =IF(ISNUMBER($G$5),G31*$G$5,0) | I31: =IF($F$53=0,0,F31/$F$53) | J31: =IF('VALOR POR PL'!L28=0,0,SUMPRODUCT(('ALVENARIA'!$B$5:$B$76<=DATE($D$5,12,1))*('ALVENARIA'!$C$5:$C$76+'ALVENARIA'!$D$5:$D$76))/'VALOR POR PL'!L28) | K31: {=IF(COUNTIF('CRONOGRAMA ATIVIDADES'!$M$5:$M$3004,B31)=0,"",IF(COUNTIFS('CRONOGRAMA ATIVIDADES'!$M$5:$M$3004,B31,'CRONOGRAMA ATIVIDADES'!$O$5:$O$3004,"CONCLUÍDA")=COUNTIF('CRONOGRAMA ATIVIDADES'!$M$5:$M$3004,B31),"Concluído (todas as "&COUNTIF('CRONOGRAMA ATIVIDADES'!$M$5:$M$3004,B31)&" atividades)",IF(COUNTIFS('CRONOGRAMA ATIVIDADES'!$M$5:$M$3004,B31,'CRONOGRAMA ATIVIDADES'!$O$5:$O$3004,"A INICIAR")=COUNTIF('CRONOGRAMA ATIVIDADES'!$M$5:$M$3004,B31),"Não iniciado · início previsto em "&CHOOSE(MONTH(_xlfn.MINIFS('CRONOGRAMA ATIVIDADES'!$F$5:$F$3004,'CRONOGRAMA ATIVIDADES'!$M$5:$M$3004,B31)),"jan","fev","mar","abr","mai","jun","jul","ago","set","out","nov","dez")&"/"&YEAR(_xlfn.MINIFS('CRONOGRAMA ATIVIDADES'!$F$5:$F$3004,'CRONOGRAMA ATIVIDADES'!$M$5:$M$3004,B31)),_xlfn.TEXTJOIN(" / ",TRUE,IF(('CRONOGRAMA ATIVIDADES'!$S$5:$S$304=B31)*('CRONOGRAMA ATIVIDADES'!$AA$5:$AA$304<>""),'CRONOGRAMA ATIVIDADES'!$AA$5:$AA$304,"")))))} | M31: ='VALOR POR PL'!L28 | N31: =IF('VALOR POR PL'!I28="DIRETO",'VALOR POR PL'!L28,0)
B32: ='VALOR POR PL'!C29 | C32: ='VALOR POR PL'!D29 | D32: =IF(OR('VALOR POR PL'!I29<>"DIRETO",'CP RESUMO'!$C$23=""),"",IFERROR(INDEX('CP RESUMO'!$D$23:$BW$23,MATCH(DATE($D$5,12,1),'CP RESUMO'!$D$4:$BW$4,0))/100,"")) | E32: =IF('VALOR POR PL'!I29<>"DIRETO","",'IMPERMEABILIZAÇÃO'!$K$14) | F32: =SUMPRODUCT((YEAR('IMPERMEABILIZAÇÃO'!$B$5:$B$76)=$D$5)*('IMPERMEABILIZAÇÃO'!$C$5:$C$76+'IMPERMEABILIZAÇÃO'!$D$5:$D$76)) | G32: =SUMPRODUCT((YEAR('MODELO PARA BI'!$H$1:$CA$1)=$D$5)*'MODELO PARA BI'!$H$17:$CA$17) | H32: =IF(ISNUMBER($G$5),G32*$G$5,0) | I32: =IF($F$53=0,0,F32/$F$53) | J32: =IF('VALOR POR PL'!L29=0,0,SUMPRODUCT(('IMPERMEABILIZAÇÃO'!$B$5:$B$76<=DATE($D$5,12,1))*('IMPERMEABILIZAÇÃO'!$C$5:$C$76+'IMPERMEABILIZAÇÃO'!$D$5:$D$76))/'VALOR POR PL'!L29) | K32: {=IF(COUNTIF('CRONOGRAMA ATIVIDADES'!$M$5:$M$3004,B32)=0,"",IF(COUNTIFS('CRONOGRAMA ATIVIDADES'!$M$5:$M$3004,B32,'CRONOGRAMA ATIVIDADES'!$O$5:$O$3004,"CONCLUÍDA")=COUNTIF('CRONOGRAMA ATIVIDADES'!$M$5:$M$3004,B32),"Concluído (todas as "&COUNTIF('CRONOGRAMA ATIVIDADES'!$M$5:$M$3004,B32)&" atividades)",IF(COUNTIFS('CRONOGRAMA ATIVIDADES'!$M$5:$M$3004,B32,'CRONOGRAMA ATIVIDADES'!$O$5:$O$3004,"A INICIAR")=COUNTIF('CRONOGRAMA ATIVIDADES'!$M$5:$M$3004,B32),"Não iniciado · início previsto em "&CHOOSE(MONTH(_xlfn.MINIFS('CRONOGRAMA ATIVIDADES'!$F$5:$F$3004,'CRONOGRAMA ATIVIDADES'!$M$5:$M$3004,B32)),"jan","fev","mar","abr","mai","jun","jul","ago","set","out","nov","dez")&"/"&YEAR(_xlfn.MINIFS('CRONOGRAMA ATIVIDADES'!$F$5:$F$3004,'CRONOGRAMA ATIVIDADES'!$M$5:$M$3004,B32)),_xlfn.TEXTJOIN(" / ",TRUE,IF(('CRONOGRAMA ATIVIDADES'!$S$5:$S$304=B32)*('CRONOGRAMA ATIVIDADES'!$AA$5:$AA$304<>""),'CRONOGRAMA ATIVIDADES'!$AA$5:$AA$304,"")))))} | M32: ='VALOR POR PL'!L29 | N32: =IF('VALOR POR PL'!I29="DIRETO",'VALOR POR PL'!L29,0)
B33: ='VALOR POR PL'!C30 | C33: ='VALOR POR PL'!D30 | D33: =IF(OR('VALOR POR PL'!I30<>"DIRETO",'CP RESUMO'!$C$24=""),"",IFERROR(INDEX('CP RESUMO'!$D$24:$BW$24,MATCH(DATE($D$5,12,1),'CP RESUMO'!$D$4:$BW$4,0))/100,"")) | E33: =IF('VALOR POR PL'!I30<>"DIRETO","",'INST. ELÉTRICA'!$K$14) | F33: =SUMPRODUCT((YEAR('INST. ELÉTRICA'!$B$5:$B$76)=$D$5)*('INST. ELÉTRICA'!$C$5:$C$76+'INST. ELÉTRICA'!$D$5:$D$76)) | G33: =SUMPRODUCT((YEAR('MODELO PARA BI'!$H$1:$CA$1)=$D$5)*'MODELO PARA BI'!$H$19:$CA$19) | H33: =IF(ISNUMBER($G$5),G33*$G$5,0) | I33: =IF($F$53=0,0,F33/$F$53) | J33: =IF('VALOR POR PL'!L30=0,0,SUMPRODUCT(('INST. ELÉTRICA'!$B$5:$B$76<=DATE($D$5,12,1))*('INST. ELÉTRICA'!$C$5:$C$76+'INST. ELÉTRICA'!$D$5:$D$76))/'VALOR POR PL'!L30) | K33: {=IF(COUNTIF('CRONOGRAMA ATIVIDADES'!$M$5:$M$3004,B33)=0,"",IF(COUNTIFS('CRONOGRAMA ATIVIDADES'!$M$5:$M$3004,B33,'CRONOGRAMA ATIVIDADES'!$O$5:$O$3004,"CONCLUÍDA")=COUNTIF('CRONOGRAMA ATIVIDADES'!$M$5:$M$3004,B33),"Concluído (todas as "&COUNTIF('CRONOGRAMA ATIVIDADES'!$M$5:$M$3004,B33)&" atividades)",IF(COUNTIFS('CRONOGRAMA ATIVIDADES'!$M$5:$M$3004,B33,'CRONOGRAMA ATIVIDADES'!$O$5:$O$3004,"A INICIAR")=COUNTIF('CRONOGRAMA ATIVIDADES'!$M$5:$M$3004,B33),"Não iniciado · início previsto em "&CHOOSE(MONTH(_xlfn.MINIFS('CRONOGRAMA ATIVIDADES'!$F$5:$F$3004,'CRONOGRAMA ATIVIDADES'!$M$5:$M$3004,B33)),"jan","fev","mar","abr","mai","jun","jul","ago","set","out","nov","dez")&"/"&YEAR(_xlfn.MINIFS('CRONOGRAMA ATIVIDADES'!$F$5:$F$3004,'CRONOGRAMA ATIVIDADES'!$M$5:$M$3004,B33)),_xlfn.TEXTJOIN(" / ",TRUE,IF(('CRONOGRAMA ATIVIDADES'!$S$5:$S$304=B33)*('CRONOGRAMA ATIVIDADES'!$AA$5:$AA$304<>""),'CRONOGRAMA ATIVIDADES'!$AA$5:$AA$304,"")))))} | M33: ='VALOR POR PL'!L30 | N33: =IF('VALOR POR PL'!I30="DIRETO",'VALOR POR PL'!L30,0)
B34: ='VALOR POR PL'!C31 | C34: ='VALOR POR PL'!D31 | D34: =IF(OR('VALOR POR PL'!I31<>"DIRETO",'CP RESUMO'!$C$25=""),"",IFERROR(INDEX('CP RESUMO'!$D$25:$BW$25,MATCH(DATE($D$5,12,1),'CP RESUMO'!$D$4:$BW$4,0))/100,"")) | E34: =IF('VALOR POR PL'!I31<>"DIRETO","",'INST. HIDRO'!$K$14) | F34: =SUMPRODUCT((YEAR('INST. HIDRO'!$B$5:$B$76)=$D$5)*('INST. HIDRO'!$C$5:$C$76+'INST. HIDRO'!$D$5:$D$76)) | G34: =SUMPRODUCT((YEAR('MODELO PARA BI'!$H$1:$CA$1)=$D$5)*'MODELO PARA BI'!$H$21:$CA$21) | H34: =IF(ISNUMBER($G$5),G34*$G$5,0) | I34: =IF($F$53=0,0,F34/$F$53) | J34: =IF('VALOR POR PL'!L31=0,0,SUMPRODUCT(('INST. HIDRO'!$B$5:$B$76<=DATE($D$5,12,1))*('INST. HIDRO'!$C$5:$C$76+'INST. HIDRO'!$D$5:$D$76))/'VALOR POR PL'!L31) | K34: {=IF(COUNTIF('CRONOGRAMA ATIVIDADES'!$M$5:$M$3004,B34)=0,"",IF(COUNTIFS('CRONOGRAMA ATIVIDADES'!$M$5:$M$3004,B34,'CRONOGRAMA ATIVIDADES'!$O$5:$O$3004,"CONCLUÍDA")=COUNTIF('CRONOGRAMA ATIVIDADES'!$M$5:$M$3004,B34),"Concluído (todas as "&COUNTIF('CRONOGRAMA ATIVIDADES'!$M$5:$M$3004,B34)&" atividades)",IF(COUNTIFS('CRONOGRAMA ATIVIDADES'!$M$5:$M$3004,B34,'CRONOGRAMA ATIVIDADES'!$O$5:$O$3004,"A INICIAR")=COUNTIF('CRONOGRAMA ATIVIDADES'!$M$5:$M$3004,B34),"Não iniciado · início previsto em "&CHOOSE(MONTH(_xlfn.MINIFS('CRONOGRAMA ATIVIDADES'!$F$5:$F$3004,'CRONOGRAMA ATIVIDADES'!$M$5:$M$3004,B34)),"jan","fev","mar","abr","mai","jun","jul","ago","set","out","nov","dez")&"/"&YEAR(_xlfn.MINIFS('CRONOGRAMA ATIVIDADES'!$F$5:$F$3004,'CRONOGRAMA ATIVIDADES'!$M$5:$M$3004,B34)),_xlfn.TEXTJOIN(" / ",TRUE,IF(('CRONOGRAMA ATIVIDADES'!$S$5:$S$304=B34)*('CRONOGRAMA ATIVIDADES'!$AA$5:$AA$304<>""),'CRONOGRAMA ATIVIDADES'!$AA$5:$AA$304,"")))))} | M34: ='VALOR POR PL'!L31 | N34: =IF('VALOR POR PL'!I31="DIRETO",'VALOR POR PL'!L31,0)
B35: ='VALOR POR PL'!C32 | C35: ='VALOR POR PL'!D32 | D35: =IF(OR('VALOR POR PL'!I32<>"DIRETO",'CP RESUMO'!$C$26=""),"",IFERROR(INDEX('CP RESUMO'!$D$26:$BW$26,MATCH(DATE($D$5,12,1),'CP RESUMO'!$D$4:$BW$4,0))/100,"")) | E35: =IF('VALOR POR PL'!I32<>"DIRETO","",'INST. INC'!$K$14) | F35: =SUMPRODUCT((YEAR('INST. INC'!$B$5:$B$76)=$D$5)*('INST. INC'!$C$5:$C$76+'INST. INC'!$D$5:$D$76)) | G35: =SUMPRODUCT((YEAR('MODELO PARA BI'!$H$1:$CA$1)=$D$5)*'MODELO PARA BI'!$H$18:$CA$18) | H35: =IF(ISNUMBER($G$5),G35*$G$5,0) | I35: =IF($F$53=0,0,F35/$F$53) | J35: =IF('VALOR POR PL'!L32=0,0,SUMPRODUCT(('INST. INC'!$B$5:$B$76<=DATE($D$5,12,1))*('INST. INC'!$C$5:$C$76+'INST. INC'!$D$5:$D$76))/'VALOR POR PL'!L32) | K35: {=IF(COUNTIF('CRONOGRAMA ATIVIDADES'!$M$5:$M$3004,B35)=0,"",IF(COUNTIFS('CRONOGRAMA ATIVIDADES'!$M$5:$M$3004,B35,'CRONOGRAMA ATIVIDADES'!$O$5:$O$3004,"CONCLUÍDA")=COUNTIF('CRONOGRAMA ATIVIDADES'!$M$5:$M$3004,B35),"Concluído (todas as "&COUNTIF('CRONOGRAMA ATIVIDADES'!$M$5:$M$3004,B35)&" atividades)",IF(COUNTIFS('CRONOGRAMA ATIVIDADES'!$M$5:$M$3004,B35,'CRONOGRAMA ATIVIDADES'!$O$5:$O$3004,"A INICIAR")=COUNTIF('CRONOGRAMA ATIVIDADES'!$M$5:$M$3004,B35),"Não iniciado · início previsto em "&CHOOSE(MONTH(_xlfn.MINIFS('CRONOGRAMA ATIVIDADES'!$F$5:$F$3004,'CRONOGRAMA ATIVIDADES'!$M$5:$M$3004,B35)),"jan","fev","mar","abr","mai","jun","jul","ago","set","out","nov","dez")&"/"&YEAR(_xlfn.MINIFS('CRONOGRAMA ATIVIDADES'!$F$5:$F$3004,'CRONOGRAMA ATIVIDADES'!$M$5:$M$3004,B35)),_xlfn.TEXTJOIN(" / ",TRUE,IF(('CRONOGRAMA ATIVIDADES'!$S$5:$S$304=B35)*('CRONOGRAMA ATIVIDADES'!$AA$5:$AA$304<>""),'CRONOGRAMA ATIVIDADES'!$AA$5:$AA$304,"")))))} | M35: ='VALOR POR PL'!L32 | N35: =IF('VALOR POR PL'!I32="DIRETO",'VALOR POR PL'!L32,0)
B36: ='VALOR POR PL'!C33 | C36: ='VALOR POR PL'!D33 | D36: =IF(OR('VALOR POR PL'!I33<>"DIRETO",'CP RESUMO'!$C$27=""),"",IFERROR(INDEX('CP RESUMO'!$D$27:$BW$27,MATCH(DATE($D$5,12,1),'CP RESUMO'!$D$4:$BW$4,0))/100,"")) | E36: =IF('VALOR POR PL'!I33<>"DIRETO","",'INST. ESP'!$K$14) | F36: =SUMPRODUCT((YEAR('INST. ESP'!$B$5:$B$76)=$D$5)*('INST. ESP'!$C$5:$C$76+'INST. ESP'!$D$5:$D$76)) | G36: =SUMPRODUCT((YEAR('MODELO PARA BI'!$H$1:$CA$1)=$D$5)*'MODELO PARA BI'!$H$20:$CA$20) | H36: =IF(ISNUMBER($G$5),G36*$G$5,0) | I36: =IF($F$53=0,0,F36/$F$53) | J36: =IF('VALOR POR PL'!L33=0,0,SUMPRODUCT(('INST. ESP'!$B$5:$B$76<=DATE($D$5,12,1))*('INST. ESP'!$C$5:$C$76+'INST. ESP'!$D$5:$D$76))/'VALOR POR PL'!L33) | K36: {=IF(COUNTIF('CRONOGRAMA ATIVIDADES'!$M$5:$M$3004,B36)=0,"",IF(COUNTIFS('CRONOGRAMA ATIVIDADES'!$M$5:$M$3004,B36,'CRONOGRAMA ATIVIDADES'!$O$5:$O$3004,"CONCLUÍDA")=COUNTIF('CRONOGRAMA ATIVIDADES'!$M$5:$M$3004,B36),"Concluído (todas as "&COUNTIF('CRONOGRAMA ATIVIDADES'!$M$5:$M$3004,B36)&" atividades)",IF(COUNTIFS('CRONOGRAMA ATIVIDADES'!$M$5:$M$3004,B36,'CRONOGRAMA ATIVIDADES'!$O$5:$O$3004,"A INICIAR")=COUNTIF('CRONOGRAMA ATIVIDADES'!$M$5:$M$3004,B36),"Não iniciado · início previsto em "&CHOOSE(MONTH(_xlfn.MINIFS('CRONOGRAMA ATIVIDADES'!$F$5:$F$3004,'CRONOGRAMA ATIVIDADES'!$M$5:$M$3004,B36)),"jan","fev","mar","abr","mai","jun","jul","ago","set","out","nov","dez")&"/"&YEAR(_xlfn.MINIFS('CRONOGRAMA ATIVIDADES'!$F$5:$F$3004,'CRONOGRAMA ATIVIDADES'!$M$5:$M$3004,B36)),_xlfn.TEXTJOIN(" / ",TRUE,IF(('CRONOGRAMA ATIVIDADES'!$S$5:$S$304=B36)*('CRONOGRAMA ATIVIDADES'!$AA$5:$AA$304<>""),'CRONOGRAMA ATIVIDADES'!$AA$5:$AA$304,"")))))} | M36: ='VALOR POR PL'!L33 | N36: =IF('VALOR POR PL'!I33="DIRETO",'VALOR POR PL'!L33,0)
B37: ='VALOR POR PL'!C34 | C37: ='VALOR POR PL'!D34 | D37: =IF(OR('VALOR POR PL'!I34<>"DIRETO",'CP RESUMO'!$C$28=""),"",IFERROR(INDEX('CP RESUMO'!$D$28:$BW$28,MATCH(DATE($D$5,12,1),'CP RESUMO'!$D$4:$BW$4,0))/100,"")) | E37: =IF('VALOR POR PL'!I34<>"DIRETO","",'ELEVADORES '!$K$14) | F37: =SUMPRODUCT((YEAR('ELEVADORES '!$B$5:$B$76)=$D$5)*('ELEVADORES '!$C$5:$C$76+'ELEVADORES '!$D$5:$D$76)) | G37: =SUMPRODUCT((YEAR('MODELO PARA BI'!$H$1:$CA$1)=$D$5)*'MODELO PARA BI'!$H$10:$CA$10) | H37: =IF(ISNUMBER($G$5),G37*$G$5,0) | I37: =IF($F$53=0,0,F37/$F$53) | J37: =IF('VALOR POR PL'!L34=0,0,SUMPRODUCT(('ELEVADORES '!$B$5:$B$76<=DATE($D$5,12,1))*('ELEVADORES '!$C$5:$C$76+'ELEVADORES '!$D$5:$D$76))/'VALOR POR PL'!L34) | K37: {=IF(COUNTIF('CRONOGRAMA ATIVIDADES'!$M$5:$M$3004,B37)=0,"",IF(COUNTIFS('CRONOGRAMA ATIVIDADES'!$M$5:$M$3004,B37,'CRONOGRAMA ATIVIDADES'!$O$5:$O$3004,"CONCLUÍDA")=COUNTIF('CRONOGRAMA ATIVIDADES'!$M$5:$M$3004,B37),"Concluído (todas as "&COUNTIF('CRONOGRAMA ATIVIDADES'!$M$5:$M$3004,B37)&" atividades)",IF(COUNTIFS('CRONOGRAMA ATIVIDADES'!$M$5:$M$3004,B37,'CRONOGRAMA ATIVIDADES'!$O$5:$O$3004,"A INICIAR")=COUNTIF('CRONOGRAMA ATIVIDADES'!$M$5:$M$3004,B37),"Não iniciado · início previsto em "&CHOOSE(MONTH(_xlfn.MINIFS('CRONOGRAMA ATIVIDADES'!$F$5:$F$3004,'CRONOGRAMA ATIVIDADES'!$M$5:$M$3004,B37)),"jan","fev","mar","abr","mai","jun","jul","ago","set","out","nov","dez")&"/"&YEAR(_xlfn.MINIFS('CRONOGRAMA ATIVIDADES'!$F$5:$F$3004,'CRONOGRAMA ATIVIDADES'!$M$5:$M$3004,B37)),_xlfn.TEXTJOIN(" / ",TRUE,IF(('CRONOGRAMA ATIVIDADES'!$S$5:$S$304=B37)*('CRONOGRAMA ATIVIDADES'!$AA$5:$AA$304<>""),'CRONOGRAMA ATIVIDADES'!$AA$5:$AA$304,"")))))} | M37: ='VALOR POR PL'!L34 | N37: =IF('VALOR POR PL'!I34="DIRETO",'VALOR POR PL'!L34,0)
B38: ='VALOR POR PL'!C35 | C38: ='VALOR POR PL'!D35 | D38: =IF(OR('VALOR POR PL'!I35<>"DIRETO",'CP RESUMO'!$C$29=""),"",IFERROR(INDEX('CP RESUMO'!$D$29:$BW$29,MATCH(DATE($D$5,12,1),'CP RESUMO'!$D$4:$BW$4,0))/100,"")) | E38: =IF('VALOR POR PL'!I35<>"DIRETO","",'ESQUADRIAS'!$K$14) | F38: =SUMPRODUCT((YEAR('ESQUADRIAS'!$B$5:$B$76)=$D$5)*('ESQUADRIAS'!$C$5:$C$76+'ESQUADRIAS'!$D$5:$D$76)) | G38: =SUMPRODUCT((YEAR('MODELO PARA BI'!$H$1:$CA$1)=$D$5)*'MODELO PARA BI'!$H$12:$CA$12) | H38: =IF(ISNUMBER($G$5),G38*$G$5,0) | I38: =IF($F$53=0,0,F38/$F$53) | J38: =IF('VALOR POR PL'!L35=0,0,SUMPRODUCT(('ESQUADRIAS'!$B$5:$B$76<=DATE($D$5,12,1))*('ESQUADRIAS'!$C$5:$C$76+'ESQUADRIAS'!$D$5:$D$76))/'VALOR POR PL'!L35) | K38: {=IF(COUNTIF('CRONOGRAMA ATIVIDADES'!$M$5:$M$3004,B38)=0,"",IF(COUNTIFS('CRONOGRAMA ATIVIDADES'!$M$5:$M$3004,B38,'CRONOGRAMA ATIVIDADES'!$O$5:$O$3004,"CONCLUÍDA")=COUNTIF('CRONOGRAMA ATIVIDADES'!$M$5:$M$3004,B38),"Concluído (todas as "&COUNTIF('CRONOGRAMA ATIVIDADES'!$M$5:$M$3004,B38)&" atividades)",IF(COUNTIFS('CRONOGRAMA ATIVIDADES'!$M$5:$M$3004,B38,'CRONOGRAMA ATIVIDADES'!$O$5:$O$3004,"A INICIAR")=COUNTIF('CRONOGRAMA ATIVIDADES'!$M$5:$M$3004,B38),"Não iniciado · início previsto em "&CHOOSE(MONTH(_xlfn.MINIFS('CRONOGRAMA ATIVIDADES'!$F$5:$F$3004,'CRONOGRAMA ATIVIDADES'!$M$5:$M$3004,B38)),"jan","fev","mar","abr","mai","jun","jul","ago","set","out","nov","dez")&"/"&YEAR(_xlfn.MINIFS('CRONOGRAMA ATIVIDADES'!$F$5:$F$3004,'CRONOGRAMA ATIVIDADES'!$M$5:$M$3004,B38)),_xlfn.TEXTJOIN(" / ",TRUE,IF(('CRONOGRAMA ATIVIDADES'!$S$5:$S$304=B38)*('CRONOGRAMA ATIVIDADES'!$AA$5:$AA$304<>""),'CRONOGRAMA ATIVIDADES'!$AA$5:$AA$304,"")))))} | M38: ='VALOR POR PL'!L35 | N38: =IF('VALOR POR PL'!I35="DIRETO",'VALOR POR PL'!L35,0)
B39: ='VALOR POR PL'!C36 | C39: ='VALOR POR PL'!D36 | D39: =IF(OR('VALOR POR PL'!I36<>"DIRETO",'CP RESUMO'!$C$30=""),"",IFERROR(INDEX('CP RESUMO'!$D$30:$BW$30,MATCH(DATE($D$5,12,1),'CP RESUMO'!$D$4:$BW$4,0))/100,"")) | E39: =IF('VALOR POR PL'!I36<>"DIRETO","",'SERRALHERIA'!$K$14) | F39: =SUMPRODUCT((YEAR('SERRALHERIA'!$B$5:$B$76)=$D$5)*('SERRALHERIA'!$C$5:$C$76+'SERRALHERIA'!$D$5:$D$76)) | G39: =SUMPRODUCT((YEAR('MODELO PARA BI'!$H$1:$CA$1)=$D$5)*'MODELO PARA BI'!$H$41:$CA$41) | H39: =IF(ISNUMBER($G$5),G39*$G$5,0) | I39: =IF($F$53=0,0,F39/$F$53) | J39: =IF('VALOR POR PL'!L36=0,0,SUMPRODUCT(('SERRALHERIA'!$B$5:$B$76<=DATE($D$5,12,1))*('SERRALHERIA'!$C$5:$C$76+'SERRALHERIA'!$D$5:$D$76))/'VALOR POR PL'!L36) | K39: {=IF(COUNTIF('CRONOGRAMA ATIVIDADES'!$M$5:$M$3004,B39)=0,"",IF(COUNTIFS('CRONOGRAMA ATIVIDADES'!$M$5:$M$3004,B39,'CRONOGRAMA ATIVIDADES'!$O$5:$O$3004,"CONCLUÍDA")=COUNTIF('CRONOGRAMA ATIVIDADES'!$M$5:$M$3004,B39),"Concluído (todas as "&COUNTIF('CRONOGRAMA ATIVIDADES'!$M$5:$M$3004,B39)&" atividades)",IF(COUNTIFS('CRONOGRAMA ATIVIDADES'!$M$5:$M$3004,B39,'CRONOGRAMA ATIVIDADES'!$O$5:$O$3004,"A INICIAR")=COUNTIF('CRONOGRAMA ATIVIDADES'!$M$5:$M$3004,B39),"Não iniciado · início previsto em "&CHOOSE(MONTH(_xlfn.MINIFS('CRONOGRAMA ATIVIDADES'!$F$5:$F$3004,'CRONOGRAMA ATIVIDADES'!$M$5:$M$3004,B39)),"jan","fev","mar","abr","mai","jun","jul","ago","set","out","nov","dez")&"/"&YEAR(_xlfn.MINIFS('CRONOGRAMA ATIVIDADES'!$F$5:$F$3004,'CRONOGRAMA ATIVIDADES'!$M$5:$M$3004,B39)),_xlfn.TEXTJOIN(" / ",TRUE,IF(('CRONOGRAMA ATIVIDADES'!$S$5:$S$304=B39)*('CRONOGRAMA ATIVIDADES'!$AA$5:$AA$304<>""),'CRONOGRAMA ATIVIDADES'!$AA$5:$AA$304,"")))))} | M39: ='VALOR POR PL'!L36 | N39: =IF('VALOR POR PL'!I36="DIRETO",'VALOR POR PL'!L36,0)
B40: ='VALOR POR PL'!C37 | C40: ='VALOR POR PL'!D37 | D40: =IF(OR('VALOR POR PL'!I37<>"DIRETO",'CP RESUMO'!$C$31=""),"",IFERROR(INDEX('CP RESUMO'!$D$31:$BW$31,MATCH(DATE($D$5,12,1),'CP RESUMO'!$D$4:$BW$4,0))/100,"")) | E40: =IF('VALOR POR PL'!I37<>"DIRETO","",'MARCENARIA'!$K$14) | F40: =SUMPRODUCT((YEAR('MARCENARIA'!$B$5:$B$76)=$D$5)*('MARCENARIA'!$C$5:$C$76+'MARCENARIA'!$D$5:$D$76)) | G40: =SUMPRODUCT((YEAR('MODELO PARA BI'!$H$1:$CA$1)=$D$5)*'MODELO PARA BI'!$H$25:$CA$25) | H40: =IF(ISNUMBER($G$5),G40*$G$5,0) | I40: =IF($F$53=0,0,F40/$F$53) | J40: =IF('VALOR POR PL'!L37=0,0,SUMPRODUCT(('MARCENARIA'!$B$5:$B$76<=DATE($D$5,12,1))*('MARCENARIA'!$C$5:$C$76+'MARCENARIA'!$D$5:$D$76))/'VALOR POR PL'!L37) | K40: {=IF(COUNTIF('CRONOGRAMA ATIVIDADES'!$M$5:$M$3004,B40)=0,"",IF(COUNTIFS('CRONOGRAMA ATIVIDADES'!$M$5:$M$3004,B40,'CRONOGRAMA ATIVIDADES'!$O$5:$O$3004,"CONCLUÍDA")=COUNTIF('CRONOGRAMA ATIVIDADES'!$M$5:$M$3004,B40),"Concluído (todas as "&COUNTIF('CRONOGRAMA ATIVIDADES'!$M$5:$M$3004,B40)&" atividades)",IF(COUNTIFS('CRONOGRAMA ATIVIDADES'!$M$5:$M$3004,B40,'CRONOGRAMA ATIVIDADES'!$O$5:$O$3004,"A INICIAR")=COUNTIF('CRONOGRAMA ATIVIDADES'!$M$5:$M$3004,B40),"Não iniciado · início previsto em "&CHOOSE(MONTH(_xlfn.MINIFS('CRONOGRAMA ATIVIDADES'!$F$5:$F$3004,'CRONOGRAMA ATIVIDADES'!$M$5:$M$3004,B40)),"jan","fev","mar","abr","mai","jun","jul","ago","set","out","nov","dez")&"/"&YEAR(_xlfn.MINIFS('CRONOGRAMA ATIVIDADES'!$F$5:$F$3004,'CRONOGRAMA ATIVIDADES'!$M$5:$M$3004,B40)),_xlfn.TEXTJOIN(" / ",TRUE,IF(('CRONOGRAMA ATIVIDADES'!$S$5:$S$304=B40)*('CRONOGRAMA ATIVIDADES'!$AA$5:$AA$304<>""),'CRONOGRAMA ATIVIDADES'!$AA$5:$AA$304,"")))))} | M40: ='VALOR POR PL'!L37 | N40: =IF('VALOR POR PL'!I37="DIRETO",'VALOR POR PL'!L37,0)
B41: ='VALOR POR PL'!C38 | C41: ='VALOR POR PL'!D38 | D41: =IF(OR('VALOR POR PL'!I38<>"DIRETO",'CP RESUMO'!$C$32=""),"",IFERROR(INDEX('CP RESUMO'!$D$32:$BW$32,MATCH(DATE($D$5,12,1),'CP RESUMO'!$D$4:$BW$4,0))/100,"")) | E41: =IF('VALOR POR PL'!I38<>"DIRETO","",'REV. PISOS'!$K$14) | F41: =SUMPRODUCT((YEAR('REV. PISOS'!$B$5:$B$76)=$D$5)*('REV. PISOS'!$C$5:$C$76+'REV. PISOS'!$D$5:$D$76)) | G41: =SUMPRODUCT((YEAR('MODELO PARA BI'!$H$1:$CA$1)=$D$5)*'MODELO PARA BI'!$H$33:$CA$33) | H41: =IF(ISNUMBER($G$5),G41*$G$5,0) | I41: =IF($F$53=0,0,F41/$F$53) | J41: =IF('VALOR POR PL'!L38=0,0,SUMPRODUCT(('REV. PISOS'!$B$5:$B$76<=DATE($D$5,12,1))*('REV. PISOS'!$C$5:$C$76+'REV. PISOS'!$D$5:$D$76))/'VALOR POR PL'!L38) | K41: {=IF(COUNTIF('CRONOGRAMA ATIVIDADES'!$M$5:$M$3004,B41)=0,"",IF(COUNTIFS('CRONOGRAMA ATIVIDADES'!$M$5:$M$3004,B41,'CRONOGRAMA ATIVIDADES'!$O$5:$O$3004,"CONCLUÍDA")=COUNTIF('CRONOGRAMA ATIVIDADES'!$M$5:$M$3004,B41),"Concluído (todas as "&COUNTIF('CRONOGRAMA ATIVIDADES'!$M$5:$M$3004,B41)&" atividades)",IF(COUNTIFS('CRONOGRAMA ATIVIDADES'!$M$5:$M$3004,B41,'CRONOGRAMA ATIVIDADES'!$O$5:$O$3004,"A INICIAR")=COUNTIF('CRONOGRAMA ATIVIDADES'!$M$5:$M$3004,B41),"Não iniciado · início previsto em "&CHOOSE(MONTH(_xlfn.MINIFS('CRONOGRAMA ATIVIDADES'!$F$5:$F$3004,'CRONOGRAMA ATIVIDADES'!$M$5:$M$3004,B41)),"jan","fev","mar","abr","mai","jun","jul","ago","set","out","nov","dez")&"/"&YEAR(_xlfn.MINIFS('CRONOGRAMA ATIVIDADES'!$F$5:$F$3004,'CRONOGRAMA ATIVIDADES'!$M$5:$M$3004,B41)),_xlfn.TEXTJOIN(" / ",TRUE,IF(('CRONOGRAMA ATIVIDADES'!$S$5:$S$304=B41)*('CRONOGRAMA ATIVIDADES'!$AA$5:$AA$304<>""),'CRONOGRAMA ATIVIDADES'!$AA$5:$AA$304,"")))))} | M41: ='VALOR POR PL'!L38 | N41: =IF('VALOR POR PL'!I38="DIRETO",'VALOR POR PL'!L38,0)
B42: ='VALOR POR PL'!C39 | C42: ='VALOR POR PL'!D39 | D42: =IF(OR('VALOR POR PL'!I39<>"DIRETO",'CP RESUMO'!$C$33=""),"",IFERROR(INDEX('CP RESUMO'!$D$33:$BW$33,MATCH(DATE($D$5,12,1),'CP RESUMO'!$D$4:$BW$4,0))/100,"")) | E42: =IF('VALOR POR PL'!I39<>"DIRETO","",'REV. PAREDE'!$K$14) | F42: =SUMPRODUCT((YEAR('REV. PAREDE'!$B$5:$B$76)=$D$5)*('REV. PAREDE'!$C$5:$C$76+'REV. PAREDE'!$D$5:$D$76)) | G42: =SUMPRODUCT((YEAR('MODELO PARA BI'!$H$1:$CA$1)=$D$5)*'MODELO PARA BI'!$H$34:$CA$34) | H42: =IF(ISNUMBER($G$5),G42*$G$5,0) | I42: =IF($F$53=0,0,F42/$F$53) | J42: =IF('VALOR POR PL'!L39=0,0,SUMPRODUCT(('REV. PAREDE'!$B$5:$B$76<=DATE($D$5,12,1))*('REV. PAREDE'!$C$5:$C$76+'REV. PAREDE'!$D$5:$D$76))/'VALOR POR PL'!L39) | K42: {=IF(COUNTIF('CRONOGRAMA ATIVIDADES'!$M$5:$M$3004,B42)=0,"",IF(COUNTIFS('CRONOGRAMA ATIVIDADES'!$M$5:$M$3004,B42,'CRONOGRAMA ATIVIDADES'!$O$5:$O$3004,"CONCLUÍDA")=COUNTIF('CRONOGRAMA ATIVIDADES'!$M$5:$M$3004,B42),"Concluído (todas as "&COUNTIF('CRONOGRAMA ATIVIDADES'!$M$5:$M$3004,B42)&" atividades)",IF(COUNTIFS('CRONOGRAMA ATIVIDADES'!$M$5:$M$3004,B42,'CRONOGRAMA ATIVIDADES'!$O$5:$O$3004,"A INICIAR")=COUNTIF('CRONOGRAMA ATIVIDADES'!$M$5:$M$3004,B42),"Não iniciado · início previsto em "&CHOOSE(MONTH(_xlfn.MINIFS('CRONOGRAMA ATIVIDADES'!$F$5:$F$3004,'CRONOGRAMA ATIVIDADES'!$M$5:$M$3004,B42)),"jan","fev","mar","abr","mai","jun","jul","ago","set","out","nov","dez")&"/"&YEAR(_xlfn.MINIFS('CRONOGRAMA ATIVIDADES'!$F$5:$F$3004,'CRONOGRAMA ATIVIDADES'!$M$5:$M$3004,B42)),_xlfn.TEXTJOIN(" / ",TRUE,IF(('CRONOGRAMA ATIVIDADES'!$S$5:$S$304=B42)*('CRONOGRAMA ATIVIDADES'!$AA$5:$AA$304<>""),'CRONOGRAMA ATIVIDADES'!$AA$5:$AA$304,"")))))} | M42: ='VALOR POR PL'!L39 | N42: =IF('VALOR POR PL'!I39="DIRETO",'VALOR POR PL'!L39,0)
B43: ='VALOR POR PL'!C40 | C43: ='VALOR POR PL'!D40 | D43: =IF(OR('VALOR POR PL'!I40<>"DIRETO",'CP RESUMO'!$C$34=""),"",IFERROR(INDEX('CP RESUMO'!$D$34:$BW$34,MATCH(DATE($D$5,12,1),'CP RESUMO'!$D$4:$BW$4,0))/100,"")) | E43: =IF('VALOR POR PL'!I40<>"DIRETO","",'REV. ACAB'!$K$14) | F43: =SUMPRODUCT((YEAR('REV. ACAB'!$B$5:$B$76)=$D$5)*('REV. ACAB'!$C$5:$C$76+'REV. ACAB'!$D$5:$D$76)) | G43: =SUMPRODUCT((YEAR('MODELO PARA BI'!$H$1:$CA$1)=$D$5)*'MODELO PARA BI'!$H$32:$CA$32) | H43: =IF(ISNUMBER($G$5),G43*$G$5,0) | I43: =IF($F$53=0,0,F43/$F$53) | J43: =IF('VALOR POR PL'!L40=0,0,SUMPRODUCT(('REV. ACAB'!$B$5:$B$76<=DATE($D$5,12,1))*('REV. ACAB'!$C$5:$C$76+'REV. ACAB'!$D$5:$D$76))/'VALOR POR PL'!L40) | K43: {=IF(COUNTIF('CRONOGRAMA ATIVIDADES'!$M$5:$M$3004,B43)=0,"",IF(COUNTIFS('CRONOGRAMA ATIVIDADES'!$M$5:$M$3004,B43,'CRONOGRAMA ATIVIDADES'!$O$5:$O$3004,"CONCLUÍDA")=COUNTIF('CRONOGRAMA ATIVIDADES'!$M$5:$M$3004,B43),"Concluído (todas as "&COUNTIF('CRONOGRAMA ATIVIDADES'!$M$5:$M$3004,B43)&" atividades)",IF(COUNTIFS('CRONOGRAMA ATIVIDADES'!$M$5:$M$3004,B43,'CRONOGRAMA ATIVIDADES'!$O$5:$O$3004,"A INICIAR")=COUNTIF('CRONOGRAMA ATIVIDADES'!$M$5:$M$3004,B43),"Não iniciado · início previsto em "&CHOOSE(MONTH(_xlfn.MINIFS('CRONOGRAMA ATIVIDADES'!$F$5:$F$3004,'CRONOGRAMA ATIVIDADES'!$M$5:$M$3004,B43)),"jan","fev","mar","abr","mai","jun","jul","ago","set","out","nov","dez")&"/"&YEAR(_xlfn.MINIFS('CRONOGRAMA ATIVIDADES'!$F$5:$F$3004,'CRONOGRAMA ATIVIDADES'!$M$5:$M$3004,B43)),_xlfn.TEXTJOIN(" / ",TRUE,IF(('CRONOGRAMA ATIVIDADES'!$S$5:$S$304=B43)*('CRONOGRAMA ATIVIDADES'!$AA$5:$AA$304<>""),'CRONOGRAMA ATIVIDADES'!$AA$5:$AA$304,"")))))} | M43: ='VALOR POR PL'!L40 | N43: =IF('VALOR POR PL'!I40="DIRETO",'VALOR POR PL'!L40,0)
B44: ='VALOR POR PL'!C41 | C44: ='VALOR POR PL'!D41 | D44: =IF(OR('VALOR POR PL'!I41<>"DIRETO",'CP RESUMO'!$C$35=""),"",IFERROR(INDEX('CP RESUMO'!$D$35:$BW$35,MATCH(DATE($D$5,12,1),'CP RESUMO'!$D$4:$BW$4,0))/100,"")) | E44: =IF('VALOR POR PL'!I41<>"DIRETO","",'PAVIMENTAÇÃO'!$K$14) | F44: =SUMPRODUCT((YEAR('PAVIMENTAÇÃO'!$B$5:$B$76)=$D$5)*('PAVIMENTAÇÃO'!$C$5:$C$76+'PAVIMENTAÇÃO'!$D$5:$D$76)) | G44: =SUMPRODUCT((YEAR('MODELO PARA BI'!$H$1:$CA$1)=$D$5)*'MODELO PARA BI'!$H$27:$CA$27) | H44: =IF(ISNUMBER($G$5),G44*$G$5,0) | I44: =IF($F$53=0,0,F44/$F$53) | J44: =IF('VALOR POR PL'!L41=0,0,SUMPRODUCT(('PAVIMENTAÇÃO'!$B$5:$B$76<=DATE($D$5,12,1))*('PAVIMENTAÇÃO'!$C$5:$C$76+'PAVIMENTAÇÃO'!$D$5:$D$76))/'VALOR POR PL'!L41) | K44: {=IF(COUNTIF('CRONOGRAMA ATIVIDADES'!$M$5:$M$3004,B44)=0,"",IF(COUNTIFS('CRONOGRAMA ATIVIDADES'!$M$5:$M$3004,B44,'CRONOGRAMA ATIVIDADES'!$O$5:$O$3004,"CONCLUÍDA")=COUNTIF('CRONOGRAMA ATIVIDADES'!$M$5:$M$3004,B44),"Concluído (todas as "&COUNTIF('CRONOGRAMA ATIVIDADES'!$M$5:$M$3004,B44)&" atividades)",IF(COUNTIFS('CRONOGRAMA ATIVIDADES'!$M$5:$M$3004,B44,'CRONOGRAMA ATIVIDADES'!$O$5:$O$3004,"A INICIAR")=COUNTIF('CRONOGRAMA ATIVIDADES'!$M$5:$M$3004,B44),"Não iniciado · início previsto em "&CHOOSE(MONTH(_xlfn.MINIFS('CRONOGRAMA ATIVIDADES'!$F$5:$F$3004,'CRONOGRAMA ATIVIDADES'!$M$5:$M$3004,B44)),"jan","fev","mar","abr","mai","jun","jul","ago","set","out","nov","dez")&"/"&YEAR(_xlfn.MINIFS('CRONOGRAMA ATIVIDADES'!$F$5:$F$3004,'CRONOGRAMA ATIVIDADES'!$M$5:$M$3004,B44)),_xlfn.TEXTJOIN(" / ",TRUE,IF(('CRONOGRAMA ATIVIDADES'!$S$5:$S$304=B44)*('CRONOGRAMA ATIVIDADES'!$AA$5:$AA$304<>""),'CRONOGRAMA ATIVIDADES'!$AA$5:$AA$304,"")))))} | M44: ='VALOR POR PL'!L41 | N44: =IF('VALOR POR PL'!I41="DIRETO",'VALOR POR PL'!L41,0)
B45: ='VALOR POR PL'!C42 | C45: ='VALOR POR PL'!D42 | D45: =IF(OR('VALOR POR PL'!I42<>"DIRETO",'CP RESUMO'!$C$36=""),"",IFERROR(INDEX('CP RESUMO'!$D$36:$BW$36,MATCH(DATE($D$5,12,1),'CP RESUMO'!$D$4:$BW$4,0))/100,"")) | E45: =IF('VALOR POR PL'!I42<>"DIRETO","",'REV. FACHADA'!$K$14) | F45: =SUMPRODUCT((YEAR('REV. FACHADA'!$B$5:$B$76)=$D$5)*('REV. FACHADA'!$C$5:$C$76+'REV. FACHADA'!$D$5:$D$76)) | G45: =SUMPRODUCT((YEAR('MODELO PARA BI'!$H$1:$CA$1)=$D$5)*'MODELO PARA BI'!$H$31:$CA$31) | H45: =IF(ISNUMBER($G$5),G45*$G$5,0) | I45: =IF($F$53=0,0,F45/$F$53) | J45: =IF('VALOR POR PL'!L42=0,0,SUMPRODUCT(('REV. FACHADA'!$B$5:$B$76<=DATE($D$5,12,1))*('REV. FACHADA'!$C$5:$C$76+'REV. FACHADA'!$D$5:$D$76))/'VALOR POR PL'!L42) | K45: {=IF(COUNTIF('CRONOGRAMA ATIVIDADES'!$M$5:$M$3004,B45)=0,"",IF(COUNTIFS('CRONOGRAMA ATIVIDADES'!$M$5:$M$3004,B45,'CRONOGRAMA ATIVIDADES'!$O$5:$O$3004,"CONCLUÍDA")=COUNTIF('CRONOGRAMA ATIVIDADES'!$M$5:$M$3004,B45),"Concluído (todas as "&COUNTIF('CRONOGRAMA ATIVIDADES'!$M$5:$M$3004,B45)&" atividades)",IF(COUNTIFS('CRONOGRAMA ATIVIDADES'!$M$5:$M$3004,B45,'CRONOGRAMA ATIVIDADES'!$O$5:$O$3004,"A INICIAR")=COUNTIF('CRONOGRAMA ATIVIDADES'!$M$5:$M$3004,B45),"Não iniciado · início previsto em "&CHOOSE(MONTH(_xlfn.MINIFS('CRONOGRAMA ATIVIDADES'!$F$5:$F$3004,'CRONOGRAMA ATIVIDADES'!$M$5:$M$3004,B45)),"jan","fev","mar","abr","mai","jun","jul","ago","set","out","nov","dez")&"/"&YEAR(_xlfn.MINIFS('CRONOGRAMA ATIVIDADES'!$F$5:$F$3004,'CRONOGRAMA ATIVIDADES'!$M$5:$M$3004,B45)),_xlfn.TEXTJOIN(" / ",TRUE,IF(('CRONOGRAMA ATIVIDADES'!$S$5:$S$304=B45)*('CRONOGRAMA ATIVIDADES'!$AA$5:$AA$304<>""),'CRONOGRAMA ATIVIDADES'!$AA$5:$AA$304,"")))))} | M45: ='VALOR POR PL'!L42 | N45: =IF('VALOR POR PL'!I42="DIRETO",'VALOR POR PL'!L42,0)
B46: ='VALOR POR PL'!C43 | C46: ='VALOR POR PL'!D43 | D46: =IF(OR('VALOR POR PL'!I43<>"DIRETO",'CP RESUMO'!$C$37=""),"",IFERROR(INDEX('CP RESUMO'!$D$37:$BW$37,MATCH(DATE($D$5,12,1),'CP RESUMO'!$D$4:$BW$4,0))/100,"")) | E46: =IF('VALOR POR PL'!I43<>"DIRETO","",'FORRO'!$K$14) | F46: =SUMPRODUCT((YEAR('FORRO'!$B$5:$B$76)=$D$5)*('FORRO'!$C$5:$C$76+'FORRO'!$D$5:$D$76)) | G46: =SUMPRODUCT((YEAR('MODELO PARA BI'!$H$1:$CA$1)=$D$5)*'MODELO PARA BI'!$H$14:$CA$14) | H46: =IF(ISNUMBER($G$5),G46*$G$5,0) | I46: =IF($F$53=0,0,F46/$F$53) | J46: =IF('VALOR POR PL'!L43=0,0,SUMPRODUCT(('FORRO'!$B$5:$B$76<=DATE($D$5,12,1))*('FORRO'!$C$5:$C$76+'FORRO'!$D$5:$D$76))/'VALOR POR PL'!L43) | K46: {=IF(COUNTIF('CRONOGRAMA ATIVIDADES'!$M$5:$M$3004,B46)=0,"",IF(COUNTIFS('CRONOGRAMA ATIVIDADES'!$M$5:$M$3004,B46,'CRONOGRAMA ATIVIDADES'!$O$5:$O$3004,"CONCLUÍDA")=COUNTIF('CRONOGRAMA ATIVIDADES'!$M$5:$M$3004,B46),"Concluído (todas as "&COUNTIF('CRONOGRAMA ATIVIDADES'!$M$5:$M$3004,B46)&" atividades)",IF(COUNTIFS('CRONOGRAMA ATIVIDADES'!$M$5:$M$3004,B46,'CRONOGRAMA ATIVIDADES'!$O$5:$O$3004,"A INICIAR")=COUNTIF('CRONOGRAMA ATIVIDADES'!$M$5:$M$3004,B46),"Não iniciado · início previsto em "&CHOOSE(MONTH(_xlfn.MINIFS('CRONOGRAMA ATIVIDADES'!$F$5:$F$3004,'CRONOGRAMA ATIVIDADES'!$M$5:$M$3004,B46)),"jan","fev","mar","abr","mai","jun","jul","ago","set","out","nov","dez")&"/"&YEAR(_xlfn.MINIFS('CRONOGRAMA ATIVIDADES'!$F$5:$F$3004,'CRONOGRAMA ATIVIDADES'!$M$5:$M$3004,B46)),_xlfn.TEXTJOIN(" / ",TRUE,IF(('CRONOGRAMA ATIVIDADES'!$S$5:$S$304=B46)*('CRONOGRAMA ATIVIDADES'!$AA$5:$AA$304<>""),'CRONOGRAMA ATIVIDADES'!$AA$5:$AA$304,"")))))} | M46: ='VALOR POR PL'!L43 | N46: =IF('VALOR POR PL'!I43="DIRETO",'VALOR POR PL'!L43,0)
B47: ='VALOR POR PL'!C44 | C47: ='VALOR POR PL'!D44 | D47: =IF(OR('VALOR POR PL'!I44<>"DIRETO",'CP RESUMO'!$C$38=""),"",IFERROR(INDEX('CP RESUMO'!$D$38:$BW$38,MATCH(DATE($D$5,12,1),'CP RESUMO'!$D$4:$BW$4,0))/100,"")) | E47: =IF('VALOR POR PL'!I44<>"DIRETO","",'LOUÇAS'!$K$14) | F47: =SUMPRODUCT((YEAR('LOUÇAS'!$B$5:$B$76)=$D$5)*('LOUÇAS'!$C$5:$C$76+'LOUÇAS'!$D$5:$D$76)) | G47: =SUMPRODUCT((YEAR('MODELO PARA BI'!$H$1:$CA$1)=$D$5)*'MODELO PARA BI'!$H$23:$CA$23) | H47: =IF(ISNUMBER($G$5),G47*$G$5,0) | I47: =IF($F$53=0,0,F47/$F$53) | J47: =IF('VALOR POR PL'!L44=0,0,SUMPRODUCT(('LOUÇAS'!$B$5:$B$76<=DATE($D$5,12,1))*('LOUÇAS'!$C$5:$C$76+'LOUÇAS'!$D$5:$D$76))/'VALOR POR PL'!L44) | K47: {=IF(COUNTIF('CRONOGRAMA ATIVIDADES'!$M$5:$M$3004,B47)=0,"",IF(COUNTIFS('CRONOGRAMA ATIVIDADES'!$M$5:$M$3004,B47,'CRONOGRAMA ATIVIDADES'!$O$5:$O$3004,"CONCLUÍDA")=COUNTIF('CRONOGRAMA ATIVIDADES'!$M$5:$M$3004,B47),"Concluído (todas as "&COUNTIF('CRONOGRAMA ATIVIDADES'!$M$5:$M$3004,B47)&" atividades)",IF(COUNTIFS('CRONOGRAMA ATIVIDADES'!$M$5:$M$3004,B47,'CRONOGRAMA ATIVIDADES'!$O$5:$O$3004,"A INICIAR")=COUNTIF('CRONOGRAMA ATIVIDADES'!$M$5:$M$3004,B47),"Não iniciado · início previsto em "&CHOOSE(MONTH(_xlfn.MINIFS('CRONOGRAMA ATIVIDADES'!$F$5:$F$3004,'CRONOGRAMA ATIVIDADES'!$M$5:$M$3004,B47)),"jan","fev","mar","abr","mai","jun","jul","ago","set","out","nov","dez")&"/"&YEAR(_xlfn.MINIFS('CRONOGRAMA ATIVIDADES'!$F$5:$F$3004,'CRONOGRAMA ATIVIDADES'!$M$5:$M$3004,B47)),_xlfn.TEXTJOIN(" / ",TRUE,IF(('CRONOGRAMA ATIVIDADES'!$S$5:$S$304=B47)*('CRONOGRAMA ATIVIDADES'!$AA$5:$AA$304<>""),'CRONOGRAMA ATIVIDADES'!$AA$5:$AA$304,"")))))} | M47: ='VALOR POR PL'!L44 | N47: =IF('VALOR POR PL'!I44="DIRETO",'VALOR POR PL'!L44,0)
B48: ='VALOR POR PL'!C45 | C48: ='VALOR POR PL'!D45 | D48: =IF(OR('VALOR POR PL'!I45<>"DIRETO",'CP RESUMO'!$C$39=""),"",IFERROR(INDEX('CP RESUMO'!$D$39:$BW$39,MATCH(DATE($D$5,12,1),'CP RESUMO'!$D$4:$BW$4,0))/100,"")) | E48: =IF('VALOR POR PL'!I45<>"DIRETO","",'PINTURA'!$K$14) | F48: =SUMPRODUCT((YEAR('PINTURA'!$B$5:$B$76)=$D$5)*('PINTURA'!$C$5:$C$76+'PINTURA'!$D$5:$D$76)) | G48: =SUMPRODUCT((YEAR('MODELO PARA BI'!$H$1:$CA$1)=$D$5)*'MODELO PARA BI'!$H$28:$CA$28) | H48: =IF(ISNUMBER($G$5),G48*$G$5,0) | I48: =IF($F$53=0,0,F48/$F$53) | J48: =IF('VALOR POR PL'!L45=0,0,SUMPRODUCT(('PINTURA'!$B$5:$B$76<=DATE($D$5,12,1))*('PINTURA'!$C$5:$C$76+'PINTURA'!$D$5:$D$76))/'VALOR POR PL'!L45) | K48: {=IF(COUNTIF('CRONOGRAMA ATIVIDADES'!$M$5:$M$3004,B48)=0,"",IF(COUNTIFS('CRONOGRAMA ATIVIDADES'!$M$5:$M$3004,B48,'CRONOGRAMA ATIVIDADES'!$O$5:$O$3004,"CONCLUÍDA")=COUNTIF('CRONOGRAMA ATIVIDADES'!$M$5:$M$3004,B48),"Concluído (todas as "&COUNTIF('CRONOGRAMA ATIVIDADES'!$M$5:$M$3004,B48)&" atividades)",IF(COUNTIFS('CRONOGRAMA ATIVIDADES'!$M$5:$M$3004,B48,'CRONOGRAMA ATIVIDADES'!$O$5:$O$3004,"A INICIAR")=COUNTIF('CRONOGRAMA ATIVIDADES'!$M$5:$M$3004,B48),"Não iniciado · início previsto em "&CHOOSE(MONTH(_xlfn.MINIFS('CRONOGRAMA ATIVIDADES'!$F$5:$F$3004,'CRONOGRAMA ATIVIDADES'!$M$5:$M$3004,B48)),"jan","fev","mar","abr","mai","jun","jul","ago","set","out","nov","dez")&"/"&YEAR(_xlfn.MINIFS('CRONOGRAMA ATIVIDADES'!$F$5:$F$3004,'CRONOGRAMA ATIVIDADES'!$M$5:$M$3004,B48)),_xlfn.TEXTJOIN(" / ",TRUE,IF(('CRONOGRAMA ATIVIDADES'!$S$5:$S$304=B48)*('CRONOGRAMA ATIVIDADES'!$AA$5:$AA$304<>""),'CRONOGRAMA ATIVIDADES'!$AA$5:$AA$304,"")))))} | M48: ='VALOR POR PL'!L45 | N48: =IF('VALOR POR PL'!I45="DIRETO",'VALOR POR PL'!L45,0)
B49: ='VALOR POR PL'!C46 | C49: ='VALOR POR PL'!D46 | D49: =IF(OR('VALOR POR PL'!I46<>"DIRETO",'CP RESUMO'!$C$40=""),"",IFERROR(INDEX('CP RESUMO'!$D$40:$BW$40,MATCH(DATE($D$5,12,1),'CP RESUMO'!$D$4:$BW$4,0))/100,"")) | E49: =IF('VALOR POR PL'!I46<>"DIRETO","",'PAISAGISMO'!$K$14) | F49: =SUMPRODUCT((YEAR('PAISAGISMO'!$B$5:$B$76)=$D$5)*('PAISAGISMO'!$C$5:$C$76+'PAISAGISMO'!$D$5:$D$76)) | G49: =SUMPRODUCT((YEAR('MODELO PARA BI'!$H$1:$CA$1)=$D$5)*'MODELO PARA BI'!$H$26:$CA$26) | H49: =IF(ISNUMBER($G$5),G49*$G$5,0) | I49: =IF($F$53=0,0,F49/$F$53) | J49: =IF('VALOR POR PL'!L46=0,0,SUMPRODUCT(('PAISAGISMO'!$B$5:$B$76<=DATE($D$5,12,1))*('PAISAGISMO'!$C$5:$C$76+'PAISAGISMO'!$D$5:$D$76))/'VALOR POR PL'!L46) | K49: {=IF(COUNTIF('CRONOGRAMA ATIVIDADES'!$M$5:$M$3004,B49)=0,"",IF(COUNTIFS('CRONOGRAMA ATIVIDADES'!$M$5:$M$3004,B49,'CRONOGRAMA ATIVIDADES'!$O$5:$O$3004,"CONCLUÍDA")=COUNTIF('CRONOGRAMA ATIVIDADES'!$M$5:$M$3004,B49),"Concluído (todas as "&COUNTIF('CRONOGRAMA ATIVIDADES'!$M$5:$M$3004,B49)&" atividades)",IF(COUNTIFS('CRONOGRAMA ATIVIDADES'!$M$5:$M$3004,B49,'CRONOGRAMA ATIVIDADES'!$O$5:$O$3004,"A INICIAR")=COUNTIF('CRONOGRAMA ATIVIDADES'!$M$5:$M$3004,B49),"Não iniciado · início previsto em "&CHOOSE(MONTH(_xlfn.MINIFS('CRONOGRAMA ATIVIDADES'!$F$5:$F$3004,'CRONOGRAMA ATIVIDADES'!$M$5:$M$3004,B49)),"jan","fev","mar","abr","mai","jun","jul","ago","set","out","nov","dez")&"/"&YEAR(_xlfn.MINIFS('CRONOGRAMA ATIVIDADES'!$F$5:$F$3004,'CRONOGRAMA ATIVIDADES'!$M$5:$M$3004,B49)),_xlfn.TEXTJOIN(" / ",TRUE,IF(('CRONOGRAMA ATIVIDADES'!$S$5:$S$304=B49)*('CRONOGRAMA ATIVIDADES'!$AA$5:$AA$304<>""),'CRONOGRAMA ATIVIDADES'!$AA$5:$AA$304,"")))))} | M49: ='VALOR POR PL'!L46 | N49: =IF('VALOR POR PL'!I46="DIRETO",'VALOR POR PL'!L46,0)
B50: ='VALOR POR PL'!C47 | C50: ='VALOR POR PL'!D47 | D50: =IF(OR('VALOR POR PL'!I47<>"DIRETO",'CP RESUMO'!$C$41=""),"",IFERROR(INDEX('CP RESUMO'!$D$41:$BW$41,MATCH(DATE($D$5,12,1),'CP RESUMO'!$D$4:$BW$4,0))/100,"")) | E50: =IF('VALOR POR PL'!I47<>"DIRETO","",'LIMPEZA'!$K$14) | F50: =SUMPRODUCT((YEAR('LIMPEZA'!$B$5:$B$76)=$D$5)*('LIMPEZA'!$C$5:$C$76+'LIMPEZA'!$D$5:$D$76)) | G50: =SUMPRODUCT((YEAR('MODELO PARA BI'!$H$1:$CA$1)=$D$5)*'MODELO PARA BI'!$H$24:$CA$24) | H50: =IF(ISNUMBER($G$5),G50*$G$5,0) | I50: =IF($F$53=0,0,F50/$F$53) | J50: =IF('VALOR POR PL'!L47=0,0,SUMPRODUCT(('LIMPEZA'!$B$5:$B$76<=DATE($D$5,12,1))*('LIMPEZA'!$C$5:$C$76+'LIMPEZA'!$D$5:$D$76))/'VALOR POR PL'!L47) | K50: {=IF(COUNTIF('CRONOGRAMA ATIVIDADES'!$M$5:$M$3004,B50)=0,"",IF(COUNTIFS('CRONOGRAMA ATIVIDADES'!$M$5:$M$3004,B50,'CRONOGRAMA ATIVIDADES'!$O$5:$O$3004,"CONCLUÍDA")=COUNTIF('CRONOGRAMA ATIVIDADES'!$M$5:$M$3004,B50),"Concluído (todas as "&COUNTIF('CRONOGRAMA ATIVIDADES'!$M$5:$M$3004,B50)&" atividades)",IF(COUNTIFS('CRONOGRAMA ATIVIDADES'!$M$5:$M$3004,B50,'CRONOGRAMA ATIVIDADES'!$O$5:$O$3004,"A INICIAR")=COUNTIF('CRONOGRAMA ATIVIDADES'!$M$5:$M$3004,B50),"Não iniciado · início previsto em "&CHOOSE(MONTH(_xlfn.MINIFS('CRONOGRAMA ATIVIDADES'!$F$5:$F$3004,'CRONOGRAMA ATIVIDADES'!$M$5:$M$3004,B50)),"jan","fev","mar","abr","mai","jun","jul","ago","set","out","nov","dez")&"/"&YEAR(_xlfn.MINIFS('CRONOGRAMA ATIVIDADES'!$F$5:$F$3004,'CRONOGRAMA ATIVIDADES'!$M$5:$M$3004,B50)),_xlfn.TEXTJOIN(" / ",TRUE,IF(('CRONOGRAMA ATIVIDADES'!$S$5:$S$304=B50)*('CRONOGRAMA ATIVIDADES'!$AA$5:$AA$304<>""),'CRONOGRAMA ATIVIDADES'!$AA$5:$AA$304,"")))))} | M50: ='VALOR POR PL'!L47 | N50: =IF('VALOR POR PL'!I47="DIRETO",'VALOR POR PL'!L47,0)
C51: DESEMBOLSO DO ANO (sem taxa de administração) | F51: =F23+F29+SUM(F30:F50) | G51: =G23+G29+SUM(G30:G50) | H51: =H23+H29+SUM(H30:H50) | I51: =IF($F$53=0,0,F51/$F$53)
B52: ='VALOR POR PL'!C48 | C52: ='VALOR POR PL'!D48 | F52: =SUMPRODUCT((YEAR('TAX. ADM'!$B$5:$B$76)=$D$5)*('TAX. ADM'!$C$5:$C$76+'TAX. ADM'!$D$5:$D$76)) | G52: =SUMPRODUCT((YEAR('MODELO PARA BI'!$H$1:$CA$1)=$D$5)*'MODELO PARA BI'!$H$43:$CA$43) | H52: =IF(ISNUMBER($G$5),G52*$G$5,0) | I52: =IF($F$53=0,0,F52/$F$53) | M52: ='VALOR POR PL'!L48
C53: DESEMBOLSO DO ANO COM TAXA DE ADMINISTRAÇÃO | F53: =F51+F52 | G53: =G51+G52 | H53: =H51+H52 | I53: =IF($F$53=0,0,F53/$F$53)
B54: Execução física = % acumulado 'Previsto' do cronograma físico-financeiro do Prevision (aba CP RESUMO) em dezembro do ano; no corte = % 'Realizado'. Situação em 31/12 = atividades do cronograma (aba CRONOGRAMA ATIVIDADES) concluídas ou em execução nessa data, pelo andar mais alto.

Sheet MODELO PARA BI
A1: COD EMPREENDIMENTO | B1: COD GRUPO 1 | C1: GRUPO 1 | D1: VALOR ORÇADO (INCC) | E1: SOMA DA DISTRIBUIÇÃO (INCC) | F1: VARIAÇÃO (ORÇADO − DISTRIBUÍDO) | H1: ='VALOR POR PL'!$P$6 | I1: =DATE(YEAR(H1),MONTH(H1)+1,1) | J1: =DATE(YEAR(I1),MONTH(I1)+1,1) | K1: =DATE(YEAR(J1),MONTH(J1)+1,1) | L1: =DATE(YEAR(K1),MONTH(K1)+1,1) | M1: =DATE(YEAR(L1),MONTH(L1)+1,1) | N1: =DATE(YEAR(M1),MONTH(M1)+1,1) | O1: =DATE(YEAR(N1),MONTH(N1)+1,1) | P1: =DATE(YEAR(O1),MONTH(O1)+1,1) | ... CA1: =DATE(YEAR(BZ1),MONTH(BZ1)+1,1)
B2: 1030-1070-280 | C2: ALVENARIA | D2: ='ALVENARIA'!$K$5 | E2: =SUM(H2:CA2) | F2: =IF(D2="","",D2-E2) | H2: ='ALVENARIA'!E5 | I2: ='ALVENARIA'!E6 | J2: ='ALVENARIA'!E7 | K2: ='ALVENARIA'!E8 | L2: ='ALVENARIA'!E9 | M2: ='ALVENARIA'!E10 | N2: ='ALVENARIA'!E11 | O2: ='ALVENARIA'!E12 | P2: ='ALVENARIA'!E13 | Q2: ='ALVENARIA'!E14 | R2: ='ALVENARIA'!E15 | S2: ='ALVENARIA'!E16 | T2: ='ALVENARIA'!E17 | U2: ='ALVENARIA'!E18 | V2: ='ALVENARIA'!E19 | W2: ='ALVENARIA'!E20 | X2: ='ALVENARIA'!E21 | Y2: ='ALVENARIA'!E22 | Z2: ='ALVENARIA'!E23 | AA2: ='ALVENARIA'!E24 | AB2: ='ALVENARIA'!E25 | AC2: ='ALVENARIA'!E26 | AD2: ='ALVENARIA'!E27 | AE2: ='ALVENARIA'!E28 | AF2: ='ALVENARIA'!E29 | AG2: ='ALVENARIA'!E30 | AH2: ='ALVENARIA'!E31 | AI2: ='ALVENARIA'!E32 | AJ2: ='ALVENARIA'!E33 | AK2: ='ALVENARIA'!E34 | AL2: ='ALVENARIA'!E35 | AM2: ='ALVENARIA'!E36 | AN2: ='ALVENARIA'!E37 | AO2: ='ALVENARIA'!E38 | AP2: ='ALVENARIA'!E39 | AQ2: ='ALVENARIA'!E40 | AR2: ='ALVENARIA'!E41 | AS2: ='ALVENARIA'!E42 | AT2: ='ALVENARIA'!E43 | AU2: ='ALVENARIA'!E44 | AV2: ='ALVENARIA'!E45 | AW2: ='ALVENARIA'!E46 | AX2: ='ALVENARIA'!E47 | AY2: ='ALVENARIA'!E48 | AZ2: ='ALVENARIA'!E49 | BA2: ='ALVENARIA'!E50 | BB2: ='ALVENARIA'!E51 | BC2: ='ALVENARIA'!E52 | BD2: ='ALVENARIA'!E53 | BE2: ='ALVENARIA'!E54 | BF2: ='ALVENARIA'!E55 | BG2: ='ALVENARIA'!E56 | BH2: ='ALVENARIA'!E57 | BI2: ='ALVENARIA'!E58 | BJ2: ='ALVENARIA'!E59 | BK2: ='ALVENARIA'!E60 | BL2: ='ALVENARIA'!E61 | BM2: ='ALVENARIA'!E62 | BN2: ='ALVENARIA'!E63 | BO2: ='ALVENARIA'!E64 | BP2: ='ALVENARIA'!E65 | BQ2: ='ALVENARIA'!E66 | BR2: ='ALVENARIA'!E67 | BS2: ='ALVENARIA'!E68 | BT2: ='ALVENARIA'!E69 | BU2: ='ALVENARIA'!E70 | BV2: ='ALVENARIA'!E71 | BW2: ='ALVENARIA'!E72 | BX2: ='ALVENARIA'!E73 | BY2: ='ALVENARIA'!E74 | BZ2: ='ALVENARIA'!E75 | CA2: ='ALVENARIA'!E76
B3: 1030-1070-140 | C3: BARRACAO DE OBRA | D3: ='BARRACÃO DE OBRA'!$K$5 | E3: =SUM(H3:CA3) | F3: =IF(D3="","",D3-E3) | H3: ='BARRACÃO DE OBRA'!E5 | I3: ='BARRACÃO DE OBRA'!E6 | J3: ='BARRACÃO DE OBRA'!E7 | K3: ='BARRACÃO DE OBRA'!E8 | L3: ='BARRACÃO DE OBRA'!E9 | M3: ='BARRACÃO DE OBRA'!E10 | N3: ='BARRACÃO DE OBRA'!E11 | O3: ='BARRACÃO DE OBRA'!E12 | P3: ='BARRACÃO DE OBRA'!E13 | Q3: ='BARRACÃO DE OBRA'!E14 | R3: ='BARRACÃO DE OBRA'!E15 | S3: ='BARRACÃO DE OBRA'!E16 | T3: ='BARRACÃO DE OBRA'!E17 | U3: ='BARRACÃO DE OBRA'!E18 | V3: ='BARRACÃO DE OBRA'!E19 | W3: ='BARRACÃO DE OBRA'!E20 | X3: ='BARRACÃO DE OBRA'!E21 | Y3: ='BARRACÃO DE OBRA'!E22 | Z3: ='BARRACÃO DE OBRA'!E23 | AA3: ='BARRACÃO DE OBRA'!E24 | AB3: ='BARRACÃO DE OBRA'!E25 | AC3: ='BARRACÃO DE OBRA'!E26 | AD3: ='BARRACÃO DE OBRA'!E27 | AE3: ='BARRACÃO DE OBRA'!E28 | AF3: ='BARRACÃO DE OBRA'!E29 | AG3: ='BARRACÃO DE OBRA'!E30 | AH3: ='BARRACÃO DE OBRA'!E31 | AI3: ='BARRACÃO DE OBRA'!E32 | AJ3: ='BARRACÃO DE OBRA'!E33 | AK3: ='BARRACÃO DE OBRA'!E34 | AL3: ='BARRACÃO DE OBRA'!E35 | AM3: ='BARRACÃO DE OBRA'!E36 | AN3: ='BARRACÃO DE OBRA'!E37 | AO3: ='BARRACÃO DE OBRA'!E38 | AP3: ='BARRACÃO DE OBRA'!E39 | AQ3: ='BARRACÃO DE OBRA'!E40 | AR3: ='BARRACÃO DE OBRA'!E41 | AS3: ='BARRACÃO DE OBRA'!E42 | AT3: ='BARRACÃO DE OBRA'!E43 | AU3: ='BARRACÃO DE OBRA'!E44 | AV3: ='BARRACÃO DE OBRA'!E45 | AW3: ='BARRACÃO DE OBRA'!E46 | AX3: ='BARRACÃO DE OBRA'!E47 | AY3: ='BARRACÃO DE OBRA'!E48 | AZ3: ='BARRACÃO DE OBRA'!E49 | BA3: ='BARRACÃO DE OBRA'!E50 | BB3: ='BARRACÃO DE OBRA'!E51 | BC3: ='BARRACÃO DE OBRA'!E52 | BD3: ='BARRACÃO DE OBRA'!E53 | BE3: ='BARRACÃO DE OBRA'!E54 | BF3: ='BARRACÃO DE OBRA'!E55 | BG3: ='BARRACÃO DE OBRA'!E56 | BH3: ='BARRACÃO DE OBRA'!E57 | BI3: ='BARRACÃO DE OBRA'!E58 | BJ3: ='BARRACÃO DE OBRA'!E59 | BK3: ='BARRACÃO DE OBRA'!E60 | BL3: ='BARRACÃO DE OBRA'!E61 | BM3: ='BARRACÃO DE OBRA'!E62 | BN3: ='BARRACÃO DE OBRA'!E63 | BO3: ='BARRACÃO DE OBRA'!E64 | BP3: ='BARRACÃO DE OBRA'!E65 | BQ3: ='BARRACÃO DE OBRA'!E66 | BR3: ='BARRACÃO DE OBRA'!E67 | BS3: ='BARRACÃO DE OBRA'!E68 | BT3: ='BARRACÃO DE OBRA'!E69 | BU3: ='BARRACÃO DE OBRA'!E70 | BV3: ='BARRACÃO DE OBRA'!E71 | BW3: ='BARRACÃO DE OBRA'!E72 | BX3: ='BARRACÃO DE OBRA'!E73 | BY3: ='BARRACÃO DE OBRA'!E74 | BZ3: ='BARRACÃO DE OBRA'!E75 | CA3: ='BARRACÃO DE OBRA'!E76
B4: 1030-1070-160 | C4: CONSULTORIAS (OBRAS) | D4: ='CONSULTORIAS'!$K$5 | E4: =SUM(H4:CA4) | F4: =IF(D4="","",D4-E4) | H4: ='CONSULTORIAS'!E5 | I4: ='CONSULTORIAS'!E6 | J4: ='CONSULTORIAS'!E7 | K4: ='CONSULTORIAS'!E8 | L4: ='CONSULTORIAS'!E9 | M4: ='CONSULTORIAS'!E10 | N4: ='CONSULTORIAS'!E11 | O4: ='CONSULTORIAS'!E12 | P4: ='CONSULTORIAS'!E13 | Q4: ='CONSULTORIAS'!E14 | R4: ='CONSULTORIAS'!E15 | S4: ='CONSULTORIAS'!E16 | T4: ='CONSULTORIAS'!E17 | U4: ='CONSULTORIAS'!E18 | V4: ='CONSULTORIAS'!E19 | W4: ='CONSULTORIAS'!E20 | X4: ='CONSULTORIAS'!E21 | Y4: ='CONSULTORIAS'!E22 | Z4: ='CONSULTORIAS'!E23 | AA4: ='CONSULTORIAS'!E24 | AB4: ='CONSULTORIAS'!E25 | AC4: ='CONSULTORIAS'!E26 | AD4: ='CONSULTORIAS'!E27 | AE4: ='CONSULTORIAS'!E28 | AF4: ='CONSULTORIAS'!E29 | AG4: ='CONSULTORIAS'!E30 | AH4: ='CONSULTORIAS'!E31 | AI4: ='CONSULTORIAS'!E32 | AJ4: ='CONSULTORIAS'!E33 | AK4: ='CONSULTORIAS'!E34 | AL4: ='CONSULTORIAS'!E35 | AM4: ='CONSULTORIAS'!E36 | AN4: ='CONSULTORIAS'!E37 | AO4: ='CONSULTORIAS'!E38 | AP4: ='CONSULTORIAS'!E39 | AQ4: ='CONSULTORIAS'!E40 | AR4: ='CONSULTORIAS'!E41 | AS4: ='CONSULTORIAS'!E42 | AT4: ='CONSULTORIAS'!E43 | AU4: ='CONSULTORIAS'!E44 | AV4: ='CONSULTORIAS'!E45 | AW4: ='CONSULTORIAS'!E46 | AX4: ='CONSULTORIAS'!E47 | AY4: ='CONSULTORIAS'!E48 | AZ4: ='CONSULTORIAS'!E49 | BA4: ='CONSULTORIAS'!E50 | BB4: ='CONSULTORIAS'!E51 | BC4: ='CONSULTORIAS'!E52 | BD4: ='CONSULTORIAS'!E53 | BE4: ='CONSULTORIAS'!E54 | BF4: ='CONSULTORIAS'!E55 | BG4: ='CONSULTORIAS'!E56 | BH4: ='CONSULTORIAS'!E57 | BI4: ='CONSULTORIAS'!E58 | BJ4: ='CONSULTORIAS'!E59 | BK4: ='CONSULTORIAS'!E60 | BL4: ='CONSULTORIAS'!E61 | BM4: ='CONSULTORIAS'!E62 | BN4: ='CONSULTORIAS'!E63 | BO4: ='CONSULTORIAS'!E64 | BP4: ='CONSULTORIAS'!E65 | BQ4: ='CONSULTORIAS'!E66 | BR4: ='CONSULTORIAS'!E67 | BS4: ='CONSULTORIAS'!E68 | BT4: ='CONSULTORIAS'!E69 | BU4: ='CONSULTORIAS'!E70 | BV4: ='CONSULTORIAS'!E71 | BW4: ='CONSULTORIAS'!E72 | BX4: ='CONSULTORIAS'!E73 | BY4: ='CONSULTORIAS'!E74 | BZ4: ='CONSULTORIAS'!E75 | CA4: ='CONSULTORIAS'!E76
B5: 1030-1070-170 | C5: CONSUMO DE ÁGUA, ENERGIA, ETC. | D5: ='CONSUMOS'!$K$5 | E5: =SUM(H5:CA5) | F5: =IF(D5="","",D5-E5) | H5: ='CONSUMOS'!E5 | I5: ='CONSUMOS'!E6 | J5: ='CONSUMOS'!E7 | K5: ='CONSUMOS'!E8 | L5: ='CONSUMOS'!E9 | M5: ='CONSUMOS'!E10 | N5: ='CONSUMOS'!E11 | O5: ='CONSUMOS'!E12 | P5: ='CONSUMOS'!E13 | Q5: ='CONSUMOS'!E14 | R5: ='CONSUMOS'!E15 | S5: ='CONSUMOS'!E16 | T5: ='CONSUMOS'!E17 | U5: ='CONSUMOS'!E18 | V5: ='CONSUMOS'!E19 | W5: ='CONSUMOS'!E20 | X5: ='CONSUMOS'!E21 | Y5: ='CONSUMOS'!E22 | Z5: ='CONSUMOS'!E23 | AA5: ='CONSUMOS'!E24 | AB5: ='CONSUMOS'!E25 | AC5: ='CONSUMOS'!E26 | AD5: ='CONSUMOS'!E27 | AE5: ='CONSUMOS'!E28 | AF5: ='CONSUMOS'!E29 | AG5: ='CONSUMOS'!E30 | AH5: ='CONSUMOS'!E31 | AI5: ='CONSUMOS'!E32 | AJ5: ='CONSUMOS'!E33 | AK5: ='CONSUMOS'!E34 | AL5: ='CONSUMOS'!E35 | AM5: ='CONSUMOS'!E36 | AN5: ='CONSUMOS'!E37 | AO5: ='CONSUMOS'!E38 | AP5: ='CONSUMOS'!E39 | AQ5: ='CONSUMOS'!E40 | AR5: ='CONSUMOS'!E41 | AS5: ='CONSUMOS'!E42 | AT5: ='CONSUMOS'!E43 | AU5: ='CONSUMOS'!E44 | AV5: ='CONSUMOS'!E45 | AW5: ='CONSUMOS'!E46 | AX5: ='CONSUMOS'!E47 | AY5: ='CONSUMOS'!E48 | AZ5: ='CONSUMOS'!E49 | BA5: ='CONSUMOS'!E50 | BB5: ='CONSUMOS'!E51 | BC5: ='CONSUMOS'!E52 | BD5: ='CONSUMOS'!E53 | BE5: ='CONSUMOS'!E54 | BF5: ='CONSUMOS'!E55 | BG5: ='CONSUMOS'!E56 | BH5: ='CONSUMOS'!E57 | BI5: ='CONSUMOS'!E58 | BJ5: ='CONSUMOS'!E59 | BK5: ='CONSUMOS'!E60 | BL5: ='CONSUMOS'!E61 | BM5: ='CONSUMOS'!E62 | BN5: ='CONSUMOS'!E63 | BO5: ='CONSUMOS'!E64 | BP5: ='CONSUMOS'!E65 | BQ5: ='CONSUMOS'!E66 | BR5: ='CONSUMOS'!E67 | BS5: ='CONSUMOS'!E68 | BT5: ='CONSUMOS'!E69 | BU5: ='CONSUMOS'!E70 | BV5: ='CONSUMOS'!E71 | BW5: ='CONSUMOS'!E72 | BX5: ='CONSUMOS'!E73 | BY5: ='CONSUMOS'!E74 | BZ5: ='CONSUMOS'!E75 | CA5: ='CONSUMOS'!E76
B6: 1030-1070-190 | C6: CONTENÇÃO | D6: ='CONTENÇÃO'!$K$5 | E6: =SUM(H6:CA6) | F6: =IF(D6="","",D6-E6) | H6: ='CONTENÇÃO'!E5 | I6: ='CONTENÇÃO'!E6 | J6: ='CONTENÇÃO'!E7 | K6: ='CONTENÇÃO'!E8 | L6: ='CONTENÇÃO'!E9 | M6: ='CONTENÇÃO'!E10 | N6: ='CONTENÇÃO'!E11 | O6: ='CONTENÇÃO'!E12 | P6: ='CONTENÇÃO'!E13 | Q6: ='CONTENÇÃO'!E14 | R6: ='CONTENÇÃO'!E15 | S6: ='CONTENÇÃO'!E16 | T6: ='CONTENÇÃO'!E17 | U6: ='CONTENÇÃO'!E18 | V6: ='CONTENÇÃO'!E19 | W6: ='CONTENÇÃO'!E20 | X6: ='CONTENÇÃO'!E21 | Y6: ='CONTENÇÃO'!E22 | Z6: ='CONTENÇÃO'!E23 | AA6: ='CONTENÇÃO'!E24 | AB6: ='CONTENÇÃO'!E25 | AC6: ='CONTENÇÃO'!E26 | AD6: ='CONTENÇÃO'!E27 | AE6: ='CONTENÇÃO'!E28 | AF6: ='CONTENÇÃO'!E29 | AG6: ='CONTENÇÃO'!E30 | AH6: ='CONTENÇÃO'!E31 | AI6: ='CONTENÇÃO'!E32 | AJ6: ='CONTENÇÃO'!E33 | AK6: ='CONTENÇÃO'!E34 | AL6: ='CONTENÇÃO'!E35 | AM6: ='CONTENÇÃO'!E36 | AN6: ='CONTENÇÃO'!E37 | AO6: ='CONTENÇÃO'!E38 | AP6: ='CONTENÇÃO'!E39 | AQ6: ='CONTENÇÃO'!E40 | AR6: ='CONTENÇÃO'!E41 | AS6: ='CONTENÇÃO'!E42 | AT6: ='CONTENÇÃO'!E43 | AU6: ='CONTENÇÃO'!E44 | AV6: ='CONTENÇÃO'!E45 | AW6: ='CONTENÇÃO'!E46 | AX6: ='CONTENÇÃO'!E47 | AY6: ='CONTENÇÃO'!E48 | AZ6: ='CONTENÇÃO'!E49 | BA6: ='CONTENÇÃO'!E50 | BB6: ='CONTENÇÃO'!E51 | BC6: ='CONTENÇÃO'!E52 | BD6: ='CONTENÇÃO'!E53 | BE6: ='CONTENÇÃO'!E54 | BF6: ='CONTENÇÃO'!E55 | BG6: ='CONTENÇÃO'!E56 | BH6: ='CONTENÇÃO'!E57 | BI6: ='CONTENÇÃO'!E58 | BJ6: ='CONTENÇÃO'!E59 | BK6: ='CONTENÇÃO'!E60 | BL6: ='CONTENÇÃO'!E61 | BM6: ='CONTENÇÃO'!E62 | BN6: ='CONTENÇÃO'!E63 | BO6: ='CONTENÇÃO'!E64 | BP6: ='CONTENÇÃO'!E65 | BQ6: ='CONTENÇÃO'!E66 | BR6: ='CONTENÇÃO'!E67 | BS6: ='CONTENÇÃO'!E68 | BT6: ='CONTENÇÃO'!E69 | BU6: ='CONTENÇÃO'!E70 | BV6: ='CONTENÇÃO'!E71 | BW6: ='CONTENÇÃO'!E72 | BX6: ='CONTENÇÃO'!E73 | BY6: ='CONTENÇÃO'!E74 | BZ6: ='CONTENÇÃO'!E75 | CA6: ='CONTENÇÃO'!E76
B7: 1030-1070-510 | C7: DEMOLIÇÃO | E7: =SUM(H7:CA7) | F7: =IF(D7="","",D7-E7)
B8: 1030-1070-550 | C8: DEVOLUÇÃO DE CAIXA DE OBRA | E8: =SUM(H8:CA8) | F8: =IF(D8="","",D8-E8)
B9: 1030-1070-560 | C9: DIVERSOS | D9: ='DIVERSOS'!$K$5 | E9: =SUM(H9:CA9) | F9: =IF(D9="","",D9-E9) | H9: ='DIVERSOS'!E5 | I9: ='DIVERSOS'!E6 | J9: ='DIVERSOS'!E7 | K9: ='DIVERSOS'!E8 | L9: ='DIVERSOS'!E9 | M9: ='DIVERSOS'!E10 | N9: ='DIVERSOS'!E11 | O9: ='DIVERSOS'!E12 | P9: ='DIVERSOS'!E13 | Q9: ='DIVERSOS'!E14 | R9: ='DIVERSOS'!E15 | S9: ='DIVERSOS'!E16 | T9: ='DIVERSOS'!E17 | U9: ='DIVERSOS'!E18 | V9: ='DIVERSOS'!E19 | W9: ='DIVERSOS'!E20 | X9: ='DIVERSOS'!E21 | Y9: ='DIVERSOS'!E22 | Z9: ='DIVERSOS'!E23 | AA9: ='DIVERSOS'!E24 | AB9: ='DIVERSOS'!E25 | AC9: ='DIVERSOS'!E26 | AD9: ='DIVERSOS'!E27 | AE9: ='DIVERSOS'!E28 | AF9: ='DIVERSOS'!E29 | AG9: ='DIVERSOS'!E30 | AH9: ='DIVERSOS'!E31 | AI9: ='DIVERSOS'!E32 | AJ9: ='DIVERSOS'!E33 | AK9: ='DIVERSOS'!E34 | AL9: ='DIVERSOS'!E35 | AM9: ='DIVERSOS'!E36 | AN9: ='DIVERSOS'!E37 | AO9: ='DIVERSOS'!E38 | AP9: ='DIVERSOS'!E39 | AQ9: ='DIVERSOS'!E40 | AR9: ='DIVERSOS'!E41 | AS9: ='DIVERSOS'!E42 | AT9: ='DIVERSOS'!E43 | AU9: ='DIVERSOS'!E44 | AV9: ='DIVERSOS'!E45 | AW9: ='DIVERSOS'!E46 | AX9: ='DIVERSOS'!E47 | AY9: ='DIVERSOS'!E48 | AZ9: ='DIVERSOS'!E49 | BA9: ='DIVERSOS'!E50 | BB9: ='DIVERSOS'!E51 | BC9: ='DIVERSOS'!E52 | BD9: ='DIVERSOS'!E53 | BE9: ='DIVERSOS'!E54 | BF9: ='DIVERSOS'!E55 | BG9: ='DIVERSOS'!E56 | BH9: ='DIVERSOS'!E57 | BI9: ='DIVERSOS'!E58 | BJ9: ='DIVERSOS'!E59 | BK9: ='DIVERSOS'!E60 | BL9: ='DIVERSOS'!E61 | BM9: ='DIVERSOS'!E62 | BN9: ='DIVERSOS'!E63 | BO9: ='DIVERSOS'!E64 | BP9: ='DIVERSOS'!E65 | BQ9: ='DIVERSOS'!E66 | BR9: ='DIVERSOS'!E67 | BS9: ='DIVERSOS'!E68 | BT9: ='DIVERSOS'!E69 | BU9: ='DIVERSOS'!E70 | BV9: ='DIVERSOS'!E71 | BW9: ='DIVERSOS'!E72 | BX9: ='DIVERSOS'!E73 | BY9: ='DIVERSOS'!E74 | BZ9: ='DIVERSOS'!E75 | CA9: ='DIVERSOS'!E76
B10: 1030-1070-400 | C10: ELEVADORES | D10: ='ELEVADORES '!$K$5 | E10: =SUM(H10:CA10) | F10: =IF(D10="","",D10-E10) | H10: ='ELEVADORES '!E5 | I10: ='ELEVADORES '!E6 | J10: ='ELEVADORES '!E7 | K10: ='ELEVADORES '!E8 | L10: ='ELEVADORES '!E9 | M10: ='ELEVADORES '!E10 | N10: ='ELEVADORES '!E11 | O10: ='ELEVADORES '!E12 | P10: ='ELEVADORES '!E13 | Q10: ='ELEVADORES '!E14 | R10: ='ELEVADORES '!E15 | S10: ='ELEVADORES '!E16 | T10: ='ELEVADORES '!E17 | U10: ='ELEVADORES '!E18 | V10: ='ELEVADORES '!E19 | W10: ='ELEVADORES '!E20 | X10: ='ELEVADORES '!E21 | Y10: ='ELEVADORES '!E22 | Z10: ='ELEVADORES '!E23 | AA10: ='ELEVADORES '!E24 | AB10: ='ELEVADORES '!E25 | AC10: ='ELEVADORES '!E26 | AD10: ='ELEVADORES '!E27 | AE10: ='ELEVADORES '!E28 | AF10: ='ELEVADORES '!E29 | AG10: ='ELEVADORES '!E30 | AH10: ='ELEVADORES '!E31 | AI10: ='ELEVADORES '!E32 | AJ10: ='ELEVADORES '!E33 | AK10: ='ELEVADORES '!E34 | AL10: ='ELEVADORES '!E35 | AM10: ='ELEVADORES '!E36 | AN10: ='ELEVADORES '!E37 | AO10: ='ELEVADORES '!E38 | AP10: ='ELEVADORES '!E39 | AQ10: ='ELEVADORES '!E40 | AR10: ='ELEVADORES '!E41 | AS10: ='ELEVADORES '!E42 | AT10: ='ELEVADORES '!E43 | AU10: ='ELEVADORES '!E44 | AV10: ='ELEVADORES '!E45 | AW10: ='ELEVADORES '!E46 | AX10: ='ELEVADORES '!E47 | AY10: ='ELEVADORES '!E48 | AZ10: ='ELEVADORES '!E49 | BA10: ='ELEVADORES '!E50 | BB10: ='ELEVADORES '!E51 | BC10: ='ELEVADORES '!E52 | BD10: ='ELEVADORES '!E53 | BE10: ='ELEVADORES '!E54 | BF10: ='ELEVADORES '!E55 | BG10: ='ELEVADORES '!E56 | BH10: ='ELEVADORES '!E57 | BI10: ='ELEVADORES '!E58 | BJ10: ='ELEVADORES '!E59 | BK10: ='ELEVADORES '!E60 | BL10: ='ELEVADORES '!E61 | BM10: ='ELEVADORES '!E62 | BN10: ='ELEVADORES '!E63 | BO10: ='ELEVADORES '!E64 | BP10: ='ELEVADORES '!E65 | BQ10: ='ELEVADORES '!E66 | BR10: ='ELEVADORES '!E67 | BS10: ='ELEVADORES '!E68 | BT10: ='ELEVADORES '!E69 | BU10: ='ELEVADORES '!E70 | BV10: ='ELEVADORES '!E71 | BW10: ='ELEVADORES '!E72 | BX10: ='ELEVADORES '!E73 | BY10: ='ELEVADORES '!E74 | BZ10: ='ELEVADORES '!E75 | CA10: ='ELEVADORES '!E76
B11: 1030-1070-450 | C11: EQUIPAMENTOS E FERRAMENTAS | D11: ='EQUIP E FER'!$K$5 | E11: =SUM(H11:CA11) | F11: =IF(D11="","",D11-E11) | H11: ='EQUIP E FER'!E5 | I11: ='EQUIP E FER'!E6 | J11: ='EQUIP E FER'!E7 | K11: ='EQUIP E FER'!E8 | L11: ='EQUIP E FER'!E9 | M11: ='EQUIP E FER'!E10 | N11: ='EQUIP E FER'!E11 | O11: ='EQUIP E FER'!E12 | P11: ='EQUIP E FER'!E13 | Q11: ='EQUIP E FER'!E14 | R11: ='EQUIP E FER'!E15 | S11: ='EQUIP E FER'!E16 | T11: ='EQUIP E FER'!E17 | U11: ='EQUIP E FER'!E18 | V11: ='EQUIP E FER'!E19 | W11: ='EQUIP E FER'!E20 | X11: ='EQUIP E FER'!E21 | Y11: ='EQUIP E FER'!E22 | Z11: ='EQUIP E FER'!E23 | AA11: ='EQUIP E FER'!E24 | AB11: ='EQUIP E FER'!E25 | AC11: ='EQUIP E FER'!E26 | AD11: ='EQUIP E FER'!E27 | AE11: ='EQUIP E FER'!E28 | AF11: ='EQUIP E FER'!E29 | AG11: ='EQUIP E FER'!E30 | AH11: ='EQUIP E FER'!E31 | AI11: ='EQUIP E FER'!E32 | AJ11: ='EQUIP E FER'!E33 | AK11: ='EQUIP E FER'!E34 | AL11: ='EQUIP E FER'!E35 | AM11: ='EQUIP E FER'!E36 | AN11: ='EQUIP E FER'!E37 | AO11: ='EQUIP E FER'!E38 | AP11: ='EQUIP E FER'!E39 | AQ11: ='EQUIP E FER'!E40 | AR11: ='EQUIP E FER'!E41 | AS11: ='EQUIP E FER'!E42 | AT11: ='EQUIP E FER'!E43 | AU11: ='EQUIP E FER'!E44 | AV11: ='EQUIP E FER'!E45 | AW11: ='EQUIP E FER'!E46 | AX11: ='EQUIP E FER'!E47 | AY11: ='EQUIP E FER'!E48 | AZ11: ='EQUIP E FER'!E49 | BA11: ='EQUIP E FER'!E50 | BB11: ='EQUIP E FER'!E51 | BC11: ='EQUIP E FER'!E52 | BD11: ='EQUIP E FER'!E53 | BE11: ='EQUIP E FER'!E54 | BF11: ='EQUIP E FER'!E55 | BG11: ='EQUIP E FER'!E56 | BH11: ='EQUIP E FER'!E57 | BI11: ='EQUIP E FER'!E58 | BJ11: ='EQUIP E FER'!E59 | BK11: ='EQUIP E FER'!E60 | BL11: ='EQUIP E FER'!E61 | BM11: ='EQUIP E FER'!E62 | BN11: ='EQUIP E FER'!E63 | BO11: ='EQUIP E FER'!E64 | BP11: ='EQUIP E FER'!E65 | BQ11: ='EQUIP E FER'!E66 | BR11: ='EQUIP E FER'!E67 | BS11: ='EQUIP E FER'!E68 | BT11: ='EQUIP E FER'!E69 | BU11: ='EQUIP E FER'!E70 | BV11: ='EQUIP E FER'!E71 | BW11: ='EQUIP E FER'!E72 | BX11: ='EQUIP E FER'!E73 | BY11: ='EQUIP E FER'!E74 | BZ11: ='EQUIP E FER'!E75 | CA11: ='EQUIP E FER'!E76
B12: 1030-1070-370 | C12: ESQUADRIAS | D12: ='ESQUADRIAS'!$K$5 | E12: =SUM(H12:CA12) | F12: =IF(D12="","",D12-E12) | H12: ='ESQUADRIAS'!E5 | I12: ='ESQUADRIAS'!E6 | J12: ='ESQUADRIAS'!E7 | K12: ='ESQUADRIAS'!E8 | L12: ='ESQUADRIAS'!E9 | M12: ='ESQUADRIAS'!E10 | N12: ='ESQUADRIAS'!E11 | O12: ='ESQUADRIAS'!E12 | P12: ='ESQUADRIAS'!E13 | Q12: ='ESQUADRIAS'!E14 | R12: ='ESQUADRIAS'!E15 | S12: ='ESQUADRIAS'!E16 | T12: ='ESQUADRIAS'!E17 | U12: ='ESQUADRIAS'!E18 | V12: ='ESQUADRIAS'!E19 | W12: ='ESQUADRIAS'!E20 | X12: ='ESQUADRIAS'!E21 | Y12: ='ESQUADRIAS'!E22 | Z12: ='ESQUADRIAS'!E23 | AA12: ='ESQUADRIAS'!E24 | AB12: ='ESQUADRIAS'!E25 | AC12: ='ESQUADRIAS'!E26 | AD12: ='ESQUADRIAS'!E27 | AE12: ='ESQUADRIAS'!E28 | AF12: ='ESQUADRIAS'!E29 | AG12: ='ESQUADRIAS'!E30 | AH12: ='ESQUADRIAS'!E31 | AI12: ='ESQUADRIAS'!E32 | AJ12: ='ESQUADRIAS'!E33 | AK12: ='ESQUADRIAS'!E34 | AL12: ='ESQUADRIAS'!E35 | AM12: ='ESQUADRIAS'!E36 | AN12: ='ESQUADRIAS'!E37 | AO12: ='ESQUADRIAS'!E38 | AP12: ='ESQUADRIAS'!E39 | AQ12: ='ESQUADRIAS'!E40 | AR12: ='ESQUADRIAS'!E41 | AS12: ='ESQUADRIAS'!E42 | AT12: ='ESQUADRIAS'!E43 | AU12: ='ESQUADRIAS'!E44 | AV12: ='ESQUADRIAS'!E45 | AW12: ='ESQUADRIAS'!E46 | AX12: ='ESQUADRIAS'!E47 | AY12: ='ESQUADRIAS'!E48 | AZ12: ='ESQUADRIAS'!E49 | BA12: ='ESQUADRIAS'!E50 | BB12: ='ESQUADRIAS'!E51 | BC12: ='ESQUADRIAS'!E52 | BD12: ='ESQUADRIAS'!E53 | BE12: ='ESQUADRIAS'!E54 | BF12: ='ESQUADRIAS'!E55 | BG12: ='ESQUADRIAS'!E56 | BH12: ='ESQUADRIAS'!E57 | BI12: ='ESQUADRIAS'!E58 | BJ12: ='ESQUADRIAS'!E59 | BK12: ='ESQUADRIAS'!E60 | BL12: ='ESQUADRIAS'!E61 | BM12: ='ESQUADRIAS'!E62 | BN12: ='ESQUADRIAS'!E63 | BO12: ='ESQUADRIAS'!E64 | BP12: ='ESQUADRIAS'!E65 | BQ12: ='ESQUADRIAS'!E66 | BR12: ='ESQUADRIAS'!E67 | BS12: ='ESQUADRIAS'!E68 | BT12: ='ESQUADRIAS'!E69 | BU12: ='ESQUADRIAS'!E70 | BV12: ='ESQUADRIAS'!E71 | BW12: ='ESQUADRIAS'!E72 | BX12: ='ESQUADRIAS'!E73 | BY12: ='ESQUADRIAS'!E74 | BZ12: ='ESQUADRIAS'!E75 | CA12: ='ESQUADRIAS'!E76
B13: 1030-1070-230 | C13: ESTRUTURA EM CONCRETO ARMADO | D13: ='ESTRUTURA'!$K$5 | E13: =SUM(H13:CA13) | F13: =IF(D13="","",D13-E13) | H13: ='ESTRUTURA'!E5 | I13: ='ESTRUTURA'!E6 | J13: ='ESTRUTURA'!E7 | K13: ='ESTRUTURA'!E8 | L13: ='ESTRUTURA'!E9 | M13: ='ESTRUTURA'!E10 | N13: ='ESTRUTURA'!E11 | O13: ='ESTRUTURA'!E12 | P13: ='ESTRUTURA'!E13 | Q13: ='ESTRUTURA'!E14 | R13: ='ESTRUTURA'!E15 | S13: ='ESTRUTURA'!E16 | T13: ='ESTRUTURA'!E17 | U13: ='ESTRUTURA'!E18 | V13: ='ESTRUTURA'!E19 | W13: ='ESTRUTURA'!E20 | X13: ='ESTRUTURA'!E21 | Y13: ='ESTRUTURA'!E22 | Z13: ='ESTRUTURA'!E23 | AA13: ='ESTRUTURA'!E24 | AB13: ='ESTRUTURA'!E25 | AC13: ='ESTRUTURA'!E26 | AD13: ='ESTRUTURA'!E27 | AE13: ='ESTRUTURA'!E28 | AF13: ='ESTRUTURA'!E29 | AG13: ='ESTRUTURA'!E30 | AH13: ='ESTRUTURA'!E31 | AI13: ='ESTRUTURA'!E32 | AJ13: ='ESTRUTURA'!E33 | AK13: ='ESTRUTURA'!E34 | AL13: ='ESTRUTURA'!E35 | AM13: ='ESTRUTURA'!E36 | AN13: ='ESTRUTURA'!E37 | AO13: ='ESTRUTURA'!E38 | AP13: ='ESTRUTURA'!E39 | AQ13: ='ESTRUTURA'!E40 | AR13: ='ESTRUTURA'!E41 | AS13: ='ESTRUTURA'!E42 | AT13: ='ESTRUTURA'!E43 | AU13: ='ESTRUTURA'!E44 | AV13: ='ESTRUTURA'!E45 | AW13: ='ESTRUTURA'!E46 | AX13: ='ESTRUTURA'!E47 | AY13: ='ESTRUTURA'!E48 | AZ13: ='ESTRUTURA'!E49 | BA13: ='ESTRUTURA'!E50 | BB13: ='ESTRUTURA'!E51 | BC13: ='ESTRUTURA'!E52 | BD13: ='ESTRUTURA'!E53 | BE13: ='ESTRUTURA'!E54 | BF13: ='ESTRUTURA'!E55 | BG13: ='ESTRUTURA'!E56 | BH13: ='ESTRUTURA'!E57 | BI13: ='ESTRUTURA'!E58 | BJ13: ='ESTRUTURA'!E59 | BK13: ='ESTRUTURA'!E60 | BL13: ='ESTRUTURA'!E61 | BM13: ='ESTRUTURA'!E62 | BN13: ='ESTRUTURA'!E63 | BO13: ='ESTRUTURA'!E64 | BP13: ='ESTRUTURA'!E65 | BQ13: ='ESTRUTURA'!E66 | BR13: ='ESTRUTURA'!E67 | BS13: ='ESTRUTURA'!E68 | BT13: ='ESTRUTURA'!E69 | BU13: ='ESTRUTURA'!E70 | BV13: ='ESTRUTURA'!E71 | BW13: ='ESTRUTURA'!E72 | BX13: ='ESTRUTURA'!E73 | BY13: ='ESTRUTURA'!E74 | BZ13: ='ESTRUTURA'!E75 | CA13: ='ESTRUTURA'!E76
B14: 1030-1070-350 | C14: FORRO | D14: ='FORRO'!$K$5 | E14: =SUM(H14:CA14) | F14: =IF(D14="","",D14-E14) | H14: ='FORRO'!E5 | I14: ='FORRO'!E6 | J14: ='FORRO'!E7 | K14: ='FORRO'!E8 | L14: ='FORRO'!E9 | M14: ='FORRO'!E10 | N14: ='FORRO'!E11 | O14: ='FORRO'!E12 | P14: ='FORRO'!E13 | Q14: ='FORRO'!E14 | R14: ='FORRO'!E15 | S14: ='FORRO'!E16 | T14: ='FORRO'!E17 | U14: ='FORRO'!E18 | V14: ='FORRO'!E19 | W14: ='FORRO'!E20 | X14: ='FORRO'!E21 | Y14: ='FORRO'!E22 | Z14: ='FORRO'!E23 | AA14: ='FORRO'!E24 | AB14: ='FORRO'!E25 | AC14: ='FORRO'!E26 | AD14: ='FORRO'!E27 | AE14: ='FORRO'!E28 | AF14: ='FORRO'!E29 | AG14: ='FORRO'!E30 | AH14: ='FORRO'!E31 | AI14: ='FORRO'!E32 | AJ14: ='FORRO'!E33 | AK14: ='FORRO'!E34 | AL14: ='FORRO'!E35 | AM14: ='FORRO'!E36 | AN14: ='FORRO'!E37 | AO14: ='FORRO'!E38 | AP14: ='FORRO'!E39 | AQ14: ='FORRO'!E40 | AR14: ='FORRO'!E41 | AS14: ='FORRO'!E42 | AT14: ='FORRO'!E43 | AU14: ='FORRO'!E44 | AV14: ='FORRO'!E45 | AW14: ='FORRO'!E46 | AX14: ='FORRO'!E47 | AY14: ='FORRO'!E48 | AZ14: ='FORRO'!E49 | BA14: ='FORRO'!E50 | BB14: ='FORRO'!E51 | BC14: ='FORRO'!E52 | BD14: ='FORRO'!E53 | BE14: ='FORRO'!E54 | BF14: ='FORRO'!E55 | BG14: ='FORRO'!E56 | BH14: ='FORRO'!E57 | BI14: ='FORRO'!E58 | BJ14: ='FORRO'!E59 | BK14: ='FORRO'!E60 | BL14: ='FORRO'!E61 | BM14: ='FORRO'!E62 | BN14: ='FORRO'!E63 | BO14: ='FORRO'!E64 | BP14: ='FORRO'!E65 | BQ14: ='FORRO'!E66 | BR14: ='FORRO'!E67 | BS14: ='FORRO'!E68 | BT14: ='FORRO'!E69 | BU14: ='FORRO'!E70 | BV14: ='FORRO'!E71 | BW14: ='FORRO'!E72 | BX14: ='FORRO'!E73 | BY14: ='FORRO'!E74 | BZ14: ='FORRO'!E75 | CA14: ='FORRO'!E76
B15: 1030-1070-200 | C15: FUNDAÇÃO PROFUNDA | D15: ='FUND. PROF'!$K$5 | E15: =SUM(H15:CA15) | F15: =IF(D15="","",D15-E15) | H15: ='FUND. PROF'!E5 | I15: ='FUND. PROF'!E6 | J15: ='FUND. PROF'!E7 | K15: ='FUND. PROF'!E8 | L15: ='FUND. PROF'!E9 | M15: ='FUND. PROF'!E10 | N15: ='FUND. PROF'!E11 | O15: ='FUND. PROF'!E12 | P15: ='FUND. PROF'!E13 | Q15: ='FUND. PROF'!E14 | R15: ='FUND. PROF'!E15 | S15: ='FUND. PROF'!E16 | T15: ='FUND. PROF'!E17 | U15: ='FUND. PROF'!E18 | V15: ='FUND. PROF'!E19 | W15: ='FUND. PROF'!E20 | X15: ='FUND. PROF'!E21 | Y15: ='FUND. PROF'!E22 | Z15: ='FUND. PROF'!E23 | AA15: ='FUND. PROF'!E24 | AB15: ='FUND. PROF'!E25 | AC15: ='FUND. PROF'!E26 | AD15: ='FUND. PROF'!E27 | AE15: ='FUND. PROF'!E28 | AF15: ='FUND. PROF'!E29 | AG15: ='FUND. PROF'!E30 | AH15: ='FUND. PROF'!E31 | AI15: ='FUND. PROF'!E32 | AJ15: ='FUND. PROF'!E33 | AK15: ='FUND. PROF'!E34 | AL15: ='FUND. PROF'!E35 | AM15: ='FUND. PROF'!E36 | AN15: ='FUND. PROF'!E37 | AO15: ='FUND. PROF'!E38 | AP15: ='FUND. PROF'!E39 | AQ15: ='FUND. PROF'!E40 | AR15: ='FUND. PROF'!E41 | AS15: ='FUND. PROF'!E42 | AT15: ='FUND. PROF'!E43 | AU15: ='FUND. PROF'!E44 | AV15: ='FUND. PROF'!E45 | AW15: ='FUND. PROF'!E46 | AX15: ='FUND. PROF'!E47 | AY15: ='FUND. PROF'!E48 | AZ15: ='FUND. PROF'!E49 | BA15: ='FUND. PROF'!E50 | BB15: ='FUND. PROF'!E51 | BC15: ='FUND. PROF'!E52 | BD15: ='FUND. PROF'!E53 | BE15: ='FUND. PROF'!E54 | BF15: ='FUND. PROF'!E55 | BG15: ='FUND. PROF'!E56 | BH15: ='FUND. PROF'!E57 | BI15: ='FUND. PROF'!E58 | BJ15: ='FUND. PROF'!E59 | BK15: ='FUND. PROF'!E60 | BL15: ='FUND. PROF'!E61 | BM15: ='FUND. PROF'!E62 | BN15: ='FUND. PROF'!E63 | BO15: ='FUND. PROF'!E64 | BP15: ='FUND. PROF'!E65 | BQ15: ='FUND. PROF'!E66 | BR15: ='FUND. PROF'!E67 | BS15: ='FUND. PROF'!E68 | BT15: ='FUND. PROF'!E69 | BU15: ='FUND. PROF'!E70 | BV15: ='FUND. PROF'!E71 | BW15: ='FUND. PROF'!E72 | BX15: ='FUND. PROF'!E73 | BY15: ='FUND. PROF'!E74 | BZ15: ='FUND. PROF'!E75 | CA15: ='FUND. PROF'!E76
B16: 1030-1070-210 | C16: FUNDAÇÃO SUPERFICIAL | D16: ='FUND. SUP'!$K$5 | E16: =SUM(H16:CA16) | F16: =IF(D16="","",D16-E16) | H16: ='FUND. SUP'!E5 | I16: ='FUND. SUP'!E6 | J16: ='FUND. SUP'!E7 | K16: ='FUND. SUP'!E8 | L16: ='FUND. SUP'!E9 | M16: ='FUND. SUP'!E10 | N16: ='FUND. SUP'!E11 | O16: ='FUND. SUP'!E12 | P16: ='FUND. SUP'!E13 | Q16: ='FUND. SUP'!E14 | R16: ='FUND. SUP'!E15 | S16: ='FUND. SUP'!E16 | T16: ='FUND. SUP'!E17 | U16: ='FUND. SUP'!E18 | V16: ='FUND. SUP'!E19 | W16: ='FUND. SUP'!E20 | X16: ='FUND. SUP'!E21 | Y16: ='FUND. SUP'!E22 | Z16: ='FUND. SUP'!E23 | AA16: ='FUND. SUP'!E24 | AB16: ='FUND. SUP'!E25 | AC16: ='FUND. SUP'!E26 | AD16: ='FUND. SUP'!E27 | AE16: ='FUND. SUP'!E28 | AF16: ='FUND. SUP'!E29 | AG16: ='FUND. SUP'!E30 | AH16: ='FUND. SUP'!E31 | AI16: ='FUND. SUP'!E32 | AJ16: ='FUND. SUP'!E33 | AK16: ='FUND. SUP'!E34 | AL16: ='FUND. SUP'!E35 | AM16: ='FUND. SUP'!E36 | AN16: ='FUND. SUP'!E37 | AO16: ='FUND. SUP'!E38 | AP16: ='FUND. SUP'!E39 | AQ16: ='FUND. SUP'!E40 | AR16: ='FUND. SUP'!E41 | AS16: ='FUND. SUP'!E42 | AT16: ='FUND. SUP'!E43 | AU16: ='FUND. SUP'!E44 | AV16: ='FUND. SUP'!E45 | AW16: ='FUND. SUP'!E46 | AX16: ='FUND. SUP'!E47 | AY16: ='FUND. SUP'!E48 | AZ16: ='FUND. SUP'!E49 | BA16: ='FUND. SUP'!E50 | BB16: ='FUND. SUP'!E51 | BC16: ='FUND. SUP'!E52 | BD16: ='FUND. SUP'!E53 | BE16: ='FUND. SUP'!E54 | BF16: ='FUND. SUP'!E55 | BG16: ='FUND. SUP'!E56 | BH16: ='FUND. SUP'!E57 | BI16: ='FUND. SUP'!E58 | BJ16: ='FUND. SUP'!E59 | BK16: ='FUND. SUP'!E60 | BL16: ='FUND. SUP'!E61 | BM16: ='FUND. SUP'!E62 | BN16: ='FUND. SUP'!E63 | BO16: ='FUND. SUP'!E64 | BP16: ='FUND. SUP'!E65 | BQ16: ='FUND. SUP'!E66 | BR16: ='FUND. SUP'!E67 | BS16: ='FUND. SUP'!E68 | BT16: ='FUND. SUP'!E69 | BU16: ='FUND. SUP'!E70 | BV16: ='FUND. SUP'!E71 | BW16: ='FUND. SUP'!E72 | BX16: ='FUND. SUP'!E73 | BY16: ='FUND. SUP'!E74 | BZ16: ='FUND. SUP'!E75 | CA16: ='FUND. SUP'!E76
B17: 1030-1070-290 | C17: IMPERMEABILIZAÇÃO | D17: ='IMPERMEABILIZAÇÃO'!$K$5 | E17: =SUM(H17:CA17) | F17: =IF(D17="","",D17-E17) | H17: ='IMPERMEABILIZAÇÃO'!E5 | I17: ='IMPERMEABILIZAÇÃO'!E6 | J17: ='IMPERMEABILIZAÇÃO'!E7 | K17: ='IMPERMEABILIZAÇÃO'!E8 | L17: ='IMPERMEABILIZAÇÃO'!E9 | M17: ='IMPERMEABILIZAÇÃO'!E10 | N17: ='IMPERMEABILIZAÇÃO'!E11 | O17: ='IMPERMEABILIZAÇÃO'!E12 | P17: ='IMPERMEABILIZAÇÃO'!E13 | Q17: ='IMPERMEABILIZAÇÃO'!E14 | R17: ='IMPERMEABILIZAÇÃO'!E15 | S17: ='IMPERMEABILIZAÇÃO'!E16 | T17: ='IMPERMEABILIZAÇÃO'!E17 | U17: ='IMPERMEABILIZAÇÃO'!E18 | V17: ='IMPERMEABILIZAÇÃO'!E19 | W17: ='IMPERMEABILIZAÇÃO'!E20 | X17: ='IMPERMEABILIZAÇÃO'!E21 | Y17: ='IMPERMEABILIZAÇÃO'!E22 | Z17: ='IMPERMEABILIZAÇÃO'!E23 | AA17: ='IMPERMEABILIZAÇÃO'!E24 | AB17: ='IMPERMEABILIZAÇÃO'!E25 | AC17: ='IMPERMEABILIZAÇÃO'!E26 | AD17: ='IMPERMEABILIZAÇÃO'!E27 | AE17: ='IMPERMEABILIZAÇÃO'!E28 | AF17: ='IMPERMEABILIZAÇÃO'!E29 | AG17: ='IMPERMEABILIZAÇÃO'!E30 | AH17: ='IMPERMEABILIZAÇÃO'!E31 | AI17: ='IMPERMEABILIZAÇÃO'!E32 | AJ17: ='IMPERMEABILIZAÇÃO'!E33 | AK17: ='IMPERMEABILIZAÇÃO'!E34 | AL17: ='IMPERMEABILIZAÇÃO'!E35 | AM17: ='IMPERMEABILIZAÇÃO'!E36 | AN17: ='IMPERMEABILIZAÇÃO'!E37 | AO17: ='IMPERMEABILIZAÇÃO'!E38 | AP17: ='IMPERMEABILIZAÇÃO'!E39 | AQ17: ='IMPERMEABILIZAÇÃO'!E40 | AR17: ='IMPERMEABILIZAÇÃO'!E41 | AS17: ='IMPERMEABILIZAÇÃO'!E42 | AT17: ='IMPERMEABILIZAÇÃO'!E43 | AU17: ='IMPERMEABILIZAÇÃO'!E44 | AV17: ='IMPERMEABILIZAÇÃO'!E45 | AW17: ='IMPERMEABILIZAÇÃO'!E46 | AX17: ='IMPERMEABILIZAÇÃO'!E47 | AY17: ='IMPERMEABILIZAÇÃO'!E48 | AZ17: ='IMPERMEABILIZAÇÃO'!E49 | BA17: ='IMPERMEABILIZAÇÃO'!E50 | BB17: ='IMPERMEABILIZAÇÃO'!E51 | BC17: ='IMPERMEABILIZAÇÃO'!E52 | BD17: ='IMPERMEABILIZAÇÃO'!E53 | BE17: ='IMPERMEABILIZAÇÃO'!E54 | BF17: ='IMPERMEABILIZAÇÃO'!E55 | BG17: ='IMPERMEABILIZAÇÃO'!E56 | BH17: ='IMPERMEABILIZAÇÃO'!E57 | BI17: ='IMPERMEABILIZAÇÃO'!E58 | BJ17: ='IMPERMEABILIZAÇÃO'!E59 | BK17: ='IMPERMEABILIZAÇÃO'!E60 | BL17: ='IMPERMEABILIZAÇÃO'!E61 | BM17: ='IMPERMEABILIZAÇÃO'!E62 | BN17: ='IMPERMEABILIZAÇÃO'!E63 | BO17: ='IMPERMEABILIZAÇÃO'!E64 | BP17: ='IMPERMEABILIZAÇÃO'!E65 | BQ17: ='IMPERMEABILIZAÇÃO'!E66 | BR17: ='IMPERMEABILIZAÇÃO'!E67 | BS17: ='IMPERMEABILIZAÇÃO'!E68 | BT17: ='IMPERMEABILIZAÇÃO'!E69 | BU17: ='IMPERMEABILIZAÇÃO'!E70 | BV17: ='IMPERMEABILIZAÇÃO'!E71 | BW17: ='IMPERMEABILIZAÇÃO'!E72 | BX17: ='IMPERMEABILIZAÇÃO'!E73 | BY17: ='IMPERMEABILIZAÇÃO'!E74 | BZ17: ='IMPERMEABILIZAÇÃO'!E75 | CA17: ='IMPERMEABILIZAÇÃO'!E76
B18: 1030-1070-260 | C18: INSTALAÇÕES COMBATE INCÊNDIO | D18: ='INST. INC'!$K$5 | E18: =SUM(H18:CA18) | F18: =IF(D18="","",D18-E18) | H18: ='INST. INC'!E5 | I18: ='INST. INC'!E6 | J18: ='INST. INC'!E7 | K18: ='INST. INC'!E8 | L18: ='INST. INC'!E9 | M18: ='INST. INC'!E10 | N18: ='INST. INC'!E11 | O18: ='INST. INC'!E12 | P18: ='INST. INC'!E13 | Q18: ='INST. INC'!E14 | R18: ='INST. INC'!E15 | S18: ='INST. INC'!E16 | T18: ='INST. INC'!E17 | U18: ='INST. INC'!E18 | V18: ='INST. INC'!E19 | W18: ='INST. INC'!E20 | X18: ='INST. INC'!E21 | Y18: ='INST. INC'!E22 | Z18: ='INST. INC'!E23 | AA18: ='INST. INC'!E24 | AB18: ='INST. INC'!E25 | AC18: ='INST. INC'!E26 | AD18: ='INST. INC'!E27 | AE18: ='INST. INC'!E28 | AF18: ='INST. INC'!E29 | AG18: ='INST. INC'!E30 | AH18: ='INST. INC'!E31 | AI18: ='INST. INC'!E32 | AJ18: ='INST. INC'!E33 | AK18: ='INST. INC'!E34 | AL18: ='INST. INC'!E35 | AM18: ='INST. INC'!E36 | AN18: ='INST. INC'!E37 | AO18: ='INST. INC'!E38 | AP18: ='INST. INC'!E39 | AQ18: ='INST. INC'!E40 | AR18: ='INST. INC'!E41 | AS18: ='INST. INC'!E42 | AT18: ='INST. INC'!E43 | AU18: ='INST. INC'!E44 | AV18: ='INST. INC'!E45 | AW18: ='INST. INC'!E46 | AX18: ='INST. INC'!E47 | AY18: ='INST. INC'!E48 | AZ18: ='INST. INC'!E49 | BA18: ='INST. INC'!E50 | BB18: ='INST. INC'!E51 | BC18: ='INST. INC'!E52 | BD18: ='INST. INC'!E53 | BE18: ='INST. INC'!E54 | BF18: ='INST. INC'!E55 | BG18: ='INST. INC'!E56 | BH18: ='INST. INC'!E57 | BI18: ='INST. INC'!E58 | BJ18: ='INST. INC'!E59 | BK18: ='INST. INC'!E60 | BL18: ='INST. INC'!E61 | BM18: ='INST. INC'!E62 | BN18: ='INST. INC'!E63 | BO18: ='INST. INC'!E64 | BP18: ='INST. INC'!E65 | BQ18: ='INST. INC'!E66 | BR18: ='INST. INC'!E67 | BS18: ='INST. INC'!E68 | BT18: ='INST. INC'!E69 | BU18: ='INST. INC'!E70 | BV18: ='INST. INC'!E71 | BW18: ='INST. INC'!E72 | BX18: ='INST. INC'!E73 | BY18: ='INST. INC'!E74 | BZ18: ='INST. INC'!E75 | CA18: ='INST. INC'!E76
B19: 1030-1070-240 | C19: INSTALAÇÕES ELÉTRICAS | D19: ='INST. ELÉTRICA'!$K$5 | E19: =SUM(H19:CA19) | F19: =IF(D19="","",D19-E19) | H19: ='INST. ELÉTRICA'!E5 | I19: ='INST. ELÉTRICA'!E6 | J19: ='INST. ELÉTRICA'!E7 | K19: ='INST. ELÉTRICA'!E8 | L19: ='INST. ELÉTRICA'!E9 | M19: ='INST. ELÉTRICA'!E10 | N19: ='INST. ELÉTRICA'!E11 | O19: ='INST. ELÉTRICA'!E12 | P19: ='INST. ELÉTRICA'!E13 | Q19: ='INST. ELÉTRICA'!E14 | R19: ='INST. ELÉTRICA'!E15 | S19: ='INST. ELÉTRICA'!E16 | T19: ='INST. ELÉTRICA'!E17 | U19: ='INST. ELÉTRICA'!E18 | V19: ='INST. ELÉTRICA'!E19 | W19: ='INST. ELÉTRICA'!E20 | X19: ='INST. ELÉTRICA'!E21 | Y19: ='INST. ELÉTRICA'!E22 | Z19: ='INST. ELÉTRICA'!E23 | AA19: ='INST. ELÉTRICA'!E24 | AB19: ='INST. ELÉTRICA'!E25 | AC19: ='INST. ELÉTRICA'!E26 | AD19: ='INST. ELÉTRICA'!E27 | AE19: ='INST. ELÉTRICA'!E28 | AF19: ='INST. ELÉTRICA'!E29 | AG19: ='INST. ELÉTRICA'!E30 | AH19: ='INST. ELÉTRICA'!E31 | AI19: ='INST. ELÉTRICA'!E32 | AJ19: ='INST. ELÉTRICA'!E33 | AK19: ='INST. ELÉTRICA'!E34 | AL19: ='INST. ELÉTRICA'!E35 | AM19: ='INST. ELÉTRICA'!E36 | AN19: ='INST. ELÉTRICA'!E37 | AO19: ='INST. ELÉTRICA'!E38 | AP19: ='INST. ELÉTRICA'!E39 | AQ19: ='INST. ELÉTRICA'!E40 | AR19: ='INST. ELÉTRICA'!E41 | AS19: ='INST. ELÉTRICA'!E42 | AT19: ='INST. ELÉTRICA'!E43 | AU19: ='INST. ELÉTRICA'!E44 | AV19: ='INST. ELÉTRICA'!E45 | AW19: ='INST. ELÉTRICA'!E46 | AX19: ='INST. ELÉTRICA'!E47 | AY19: ='INST. ELÉTRICA'!E48 | AZ19: ='INST. ELÉTRICA'!E49 | BA19: ='INST. ELÉTRICA'!E50 | BB19: ='INST. ELÉTRICA'!E51 | BC19: ='INST. ELÉTRICA'!E52 | BD19: ='INST. ELÉTRICA'!E53 | BE19: ='INST. ELÉTRICA'!E54 | BF19: ='INST. ELÉTRICA'!E55 | BG19: ='INST. ELÉTRICA'!E56 | BH19: ='INST. ELÉTRICA'!E57 | BI19: ='INST. ELÉTRICA'!E58 | BJ19: ='INST. ELÉTRICA'!E59 | BK19: ='INST. ELÉTRICA'!E60 | BL19: ='INST. ELÉTRICA'!E61 | BM19: ='INST. ELÉTRICA'!E62 | BN19: ='INST. ELÉTRICA'!E63 | BO19: ='INST. ELÉTRICA'!E64 | BP19: ='INST. ELÉTRICA'!E65 | BQ19: ='INST. ELÉTRICA'!E66 | BR19: ='INST. ELÉTRICA'!E67 | BS19: ='INST. ELÉTRICA'!E68 | BT19: ='INST. ELÉTRICA'!E69 | BU19: ='INST. ELÉTRICA'!E70 | BV19: ='INST. ELÉTRICA'!E71 | BW19: ='INST. ELÉTRICA'!E72 | BX19: ='INST. ELÉTRICA'!E73 | BY19: ='INST. ELÉTRICA'!E74 | BZ19: ='INST. ELÉTRICA'!E75 | CA19: ='INST. ELÉTRICA'!E76
B20: 1030-1070-270 | C20: INSTALAÇÕES ESPECIAIS | D20: ='INST. ESP'!$K$5 | E20: =SUM(H20:CA20) | F20: =IF(D20="","",D20-E20) | H20: ='INST. ESP'!E5 | I20: ='INST. ESP'!E6 | J20: ='INST. ESP'!E7 | K20: ='INST. ESP'!E8 | L20: ='INST. ESP'!E9 | M20: ='INST. ESP'!E10 | N20: ='INST. ESP'!E11 | O20: ='INST. ESP'!E12 | P20: ='INST. ESP'!E13 | Q20: ='INST. ESP'!E14 | R20: ='INST. ESP'!E15 | S20: ='INST. ESP'!E16 | T20: ='INST. ESP'!E17 | U20: ='INST. ESP'!E18 | V20: ='INST. ESP'!E19 | W20: ='INST. ESP'!E20 | X20: ='INST. ESP'!E21 | Y20: ='INST. ESP'!E22 | Z20: ='INST. ESP'!E23 | AA20: ='INST. ESP'!E24 | AB20: ='INST. ESP'!E25 | AC20: ='INST. ESP'!E26 | AD20: ='INST. ESP'!E27 | AE20: ='INST. ESP'!E28 | AF20: ='INST. ESP'!E29 | AG20: ='INST. ESP'!E30 | AH20: ='INST. ESP'!E31 | AI20: ='INST. ESP'!E32 | AJ20: ='INST. ESP'!E33 | AK20: ='INST. ESP'!E34 | AL20: ='INST. ESP'!E35 | AM20: ='INST. ESP'!E36 | AN20: ='INST. ESP'!E37 | AO20: ='INST. ESP'!E38 | AP20: ='INST. ESP'!E39 | AQ20: ='INST. ESP'!E40 | AR20: ='INST. ESP'!E41 | AS20: ='INST. ESP'!E42 | AT20: ='INST. ESP'!E43 | AU20: ='INST. ESP'!E44 | AV20: ='INST. ESP'!E45 | AW20: ='INST. ESP'!E46 | AX20: ='INST. ESP'!E47 | AY20: ='INST. ESP'!E48 | AZ20: ='INST. ESP'!E49 | BA20: ='INST. ESP'!E50 | BB20: ='INST. ESP'!E51 | BC20: ='INST. ESP'!E52 | BD20: ='INST. ESP'!E53 | BE20: ='INST. ESP'!E54 | BF20: ='INST. ESP'!E55 | BG20: ='INST. ESP'!E56 | BH20: ='INST. ESP'!E57 | BI20: ='INST. ESP'!E58 | BJ20: ='INST. ESP'!E59 | BK20: ='INST. ESP'!E60 | BL20: ='INST. ESP'!E61 | BM20: ='INST. ESP'!E62 | BN20: ='INST. ESP'!E63 | BO20: ='INST. ESP'!E64 | BP20: ='INST. ESP'!E65 | BQ20: ='INST. ESP'!E66 | BR20: ='INST. ESP'!E67 | BS20: ='INST. ESP'!E68 | BT20: ='INST. ESP'!E69 | BU20: ='INST. ESP'!E70 | BV20: ='INST. ESP'!E71 | BW20: ='INST. ESP'!E72 | BX20: ='INST. ESP'!E73 | BY20: ='INST. ESP'!E74 | BZ20: ='INST. ESP'!E75 | CA20: ='INST. ESP'!E76
B21: 1030-1070-250 | C21: INSTALAÇÕES HIDROSANITÁRIAS | D21: ='INST. HIDRO'!$K$5 | E21: =SUM(H21:CA21) | F21: =IF(D21="","",D21-E21) | H21: ='INST. HIDRO'!E5 | I21: ='INST. HIDRO'!E6 | J21: ='INST. HIDRO'!E7 | K21: ='INST. HIDRO'!E8 | L21: ='INST. HIDRO'!E9 | M21: ='INST. HIDRO'!E10 | N21: ='INST. HIDRO'!E11 | O21: ='INST. HIDRO'!E12 | P21: ='INST. HIDRO'!E13 | Q21: ='INST. HIDRO'!E14 | R21: ='INST. HIDRO'!E15 | S21: ='INST. HIDRO'!E16 | T21: ='INST. HIDRO'!E17 | U21: ='INST. HIDRO'!E18 | V21: ='INST. HIDRO'!E19 | W21: ='INST. HIDRO'!E20 | X21: ='INST. HIDRO'!E21 | Y21: ='INST. HIDRO'!E22 | Z21: ='INST. HIDRO'!E23 | AA21: ='INST. HIDRO'!E24 | AB21: ='INST. HIDRO'!E25 | AC21: ='INST. HIDRO'!E26 | AD21: ='INST. HIDRO'!E27 | AE21: ='INST. HIDRO'!E28 | AF21: ='INST. HIDRO'!E29 | AG21: ='INST. HIDRO'!E30 | AH21: ='INST. HIDRO'!E31 | AI21: ='INST. HIDRO'!E32 | AJ21: ='INST. HIDRO'!E33 | AK21: ='INST. HIDRO'!E34 | AL21: ='INST. HIDRO'!E35 | AM21: ='INST. HIDRO'!E36 | AN21: ='INST. HIDRO'!E37 | AO21: ='INST. HIDRO'!E38 | AP21: ='INST. HIDRO'!E39 | AQ21: ='INST. HIDRO'!E40 | AR21: ='INST. HIDRO'!E41 | AS21: ='INST. HIDRO'!E42 | AT21: ='INST. HIDRO'!E43 | AU21: ='INST. HIDRO'!E44 | AV21: ='INST. HIDRO'!E45 | AW21: ='INST. HIDRO'!E46 | AX21: ='INST. HIDRO'!E47 | AY21: ='INST. HIDRO'!E48 | AZ21: ='INST. HIDRO'!E49 | BA21: ='INST. HIDRO'!E50 | BB21: ='INST. HIDRO'!E51 | BC21: ='INST. HIDRO'!E52 | BD21: ='INST. HIDRO'!E53 | BE21: ='INST. HIDRO'!E54 | BF21: ='INST. HIDRO'!E55 | BG21: ='INST. HIDRO'!E56 | BH21: ='INST. HIDRO'!E57 | BI21: ='INST. HIDRO'!E58 | BJ21: ='INST. HIDRO'!E59 | BK21: ='INST. HIDRO'!E60 | BL21: ='INST. HIDRO'!E61 | BM21: ='INST. HIDRO'!E62 | BN21: ='INST. HIDRO'!E63 | BO21: ='INST. HIDRO'!E64 | BP21: ='INST. HIDRO'!E65 | BQ21: ='INST. HIDRO'!E66 | BR21: ='INST. HIDRO'!E67 | BS21: ='INST. HIDRO'!E68 | BT21: ='INST. HIDRO'!E69 | BU21: ='INST. HIDRO'!E70 | BV21: ='INST. HIDRO'!E71 | BW21: ='INST. HIDRO'!E72 | BX21: ='INST. HIDRO'!E73 | BY21: ='INST. HIDRO'!E74 | BZ21: ='INST. HIDRO'!E75 | CA21: ='INST. HIDRO'!E76
B22: 1030-1070-130 | C22: LEVANTAMENTO TOPOGRÁFICO | E22: =SUM(H22:CA22) | F22: =IF(D22="","",D22-E22)
B23: 1030-1070-410 | C23: LOUÇAS SANITÁRIAS | D23: ='LOUÇAS'!$K$5 | E23: =SUM(H23:CA23) | F23: =IF(D23="","",D23-E23) | H23: ='LOUÇAS'!E5 | I23: ='LOUÇAS'!E6 | J23: ='LOUÇAS'!E7 | K23: ='LOUÇAS'!E8 | L23: ='LOUÇAS'!E9 | M23: ='LOUÇAS'!E10 | N23: ='LOUÇAS'!E11 | O23: ='LOUÇAS'!E12 | P23: ='LOUÇAS'!E13 | Q23: ='LOUÇAS'!E14 | R23: ='LOUÇAS'!E15 | S23: ='LOUÇAS'!E16 | T23: ='LOUÇAS'!E17 | U23: ='LOUÇAS'!E18 | V23: ='LOUÇAS'!E19 | W23: ='LOUÇAS'!E20 | X23: ='LOUÇAS'!E21 | Y23: ='LOUÇAS'!E22 | Z23: ='LOUÇAS'!E23 | AA23: ='LOUÇAS'!E24 | AB23: ='LOUÇAS'!E25 | AC23: ='LOUÇAS'!E26 | AD23: ='LOUÇAS'!E27 | AE23: ='LOUÇAS'!E28 | AF23: ='LOUÇAS'!E29 | AG23: ='LOUÇAS'!E30 | AH23: ='LOUÇAS'!E31 | AI23: ='LOUÇAS'!E32 | AJ23: ='LOUÇAS'!E33 | AK23: ='LOUÇAS'!E34 | AL23: ='LOUÇAS'!E35 | AM23: ='LOUÇAS'!E36 | AN23: ='LOUÇAS'!E37 | AO23: ='LOUÇAS'!E38 | AP23: ='LOUÇAS'!E39 | AQ23: ='LOUÇAS'!E40 | AR23: ='LOUÇAS'!E41 | AS23: ='LOUÇAS'!E42 | AT23: ='LOUÇAS'!E43 | AU23: ='LOUÇAS'!E44 | AV23: ='LOUÇAS'!E45 | AW23: ='LOUÇAS'!E46 | AX23: ='LOUÇAS'!E47 | AY23: ='LOUÇAS'!E48 | AZ23: ='LOUÇAS'!E49 | BA23: ='LOUÇAS'!E50 | BB23: ='LOUÇAS'!E51 | BC23: ='LOUÇAS'!E52 | BD23: ='LOUÇAS'!E53 | BE23: ='LOUÇAS'!E54 | BF23: ='LOUÇAS'!E55 | BG23: ='LOUÇAS'!E56 | BH23: ='LOUÇAS'!E57 | BI23: ='LOUÇAS'!E58 | BJ23: ='LOUÇAS'!E59 | BK23: ='LOUÇAS'!E60 | BL23: ='LOUÇAS'!E61 | BM23: ='LOUÇAS'!E62 | BN23: ='LOUÇAS'!E63 | BO23: ='LOUÇAS'!E64 | BP23: ='LOUÇAS'!E65 | BQ23: ='LOUÇAS'!E66 | BR23: ='LOUÇAS'!E67 | BS23: ='LOUÇAS'!E68 | BT23: ='LOUÇAS'!E69 | BU23: ='LOUÇAS'!E70 | BV23: ='LOUÇAS'!E71 | BW23: ='LOUÇAS'!E72 | BX23: ='LOUÇAS'!E73 | BY23: ='LOUÇAS'!E74 | BZ23: ='LOUÇAS'!E75 | CA23: ='LOUÇAS'!E76
B24: 1030-1070-440 | C24: LIMPEZA FINAL DE OBRA | D24: ='LIMPEZA'!$K$5 | E24: =SUM(H24:CA24) | F24: =IF(D24="","",D24-E24) | H24: ='LIMPEZA'!E5 | I24: ='LIMPEZA'!E6 | J24: ='LIMPEZA'!E7 | K24: ='LIMPEZA'!E8 | L24: ='LIMPEZA'!E9 | M24: ='LIMPEZA'!E10 | N24: ='LIMPEZA'!E11 | O24: ='LIMPEZA'!E12 | P24: ='LIMPEZA'!E13 | Q24: ='LIMPEZA'!E14 | R24: ='LIMPEZA'!E15 | S24: ='LIMPEZA'!E16 | T24: ='LIMPEZA'!E17 | U24: ='LIMPEZA'!E18 | V24: ='LIMPEZA'!E19 | W24: ='LIMPEZA'!E20 | X24: ='LIMPEZA'!E21 | Y24: ='LIMPEZA'!E22 | Z24: ='LIMPEZA'!E23 | AA24: ='LIMPEZA'!E24 | AB24: ='LIMPEZA'!E25 | AC24: ='LIMPEZA'!E26 | AD24: ='LIMPEZA'!E27 | AE24: ='LIMPEZA'!E28 | AF24: ='LIMPEZA'!E29 | AG24: ='LIMPEZA'!E30 | AH24: ='LIMPEZA'!E31 | AI24: ='LIMPEZA'!E32 | AJ24: ='LIMPEZA'!E33 | AK24: ='LIMPEZA'!E34 | AL24: ='LIMPEZA'!E35 | AM24: ='LIMPEZA'!E36 | AN24: ='LIMPEZA'!E37 | AO24: ='LIMPEZA'!E38 | AP24: ='LIMPEZA'!E39 | AQ24: ='LIMPEZA'!E40 | AR24: ='LIMPEZA'!E41 | AS24: ='LIMPEZA'!E42 | AT24: ='LIMPEZA'!E43 | AU24: ='LIMPEZA'!E44 | AV24: ='LIMPEZA'!E45 | AW24: ='LIMPEZA'!E46 | AX24: ='LIMPEZA'!E47 | AY24: ='LIMPEZA'!E48 | AZ24: ='LIMPEZA'!E49 | BA24: ='LIMPEZA'!E50 | BB24: ='LIMPEZA'!E51 | BC24: ='LIMPEZA'!E52 | BD24: ='LIMPEZA'!E53 | BE24: ='LIMPEZA'!E54 | BF24: ='LIMPEZA'!E55 | BG24: ='LIMPEZA'!E56 | BH24: ='LIMPEZA'!E57 | BI24: ='LIMPEZA'!E58 | BJ24: ='LIMPEZA'!E59 | BK24: ='LIMPEZA'!E60 | BL24: ='LIMPEZA'!E61 | BM24: ='LIMPEZA'!E62 | BN24: ='LIMPEZA'!E63 | BO24: ='LIMPEZA'!E64 | BP24: ='LIMPEZA'!E65 | BQ24: ='LIMPEZA'!E66 | BR24: ='LIMPEZA'!E67 | BS24: ='LIMPEZA'!E68 | BT24: ='LIMPEZA'!E69 | BU24: ='LIMPEZA'!E70 | BV24: ='LIMPEZA'!E71 | BW24: ='LIMPEZA'!E72 | BX24: ='LIMPEZA'!E73 | BY24: ='LIMPEZA'!E74 | BZ24: ='LIMPEZA'!E75 | CA24: ='LIMPEZA'!E76
B25: 1030-1070-540 | C25: MARCENARIA | D25: ='MARCENARIA'!$K$5 | E25: =SUM(H25:CA25) | F25: =IF(D25="","",D25-E25) | H25: ='MARCENARIA'!E5 | I25: ='MARCENARIA'!E6 | J25: ='MARCENARIA'!E7 | K25: ='MARCENARIA'!E8 | L25: ='MARCENARIA'!E9 | M25: ='MARCENARIA'!E10 | N25: ='MARCENARIA'!E11 | O25: ='MARCENARIA'!E12 | P25: ='MARCENARIA'!E13 | Q25: ='MARCENARIA'!E14 | R25: ='MARCENARIA'!E15 | S25: ='MARCENARIA'!E16 | T25: ='MARCENARIA'!E17 | U25: ='MARCENARIA'!E18 | V25: ='MARCENARIA'!E19 | W25: ='MARCENARIA'!E20 | X25: ='MARCENARIA'!E21 | Y25: ='MARCENARIA'!E22 | Z25: ='MARCENARIA'!E23 | AA25: ='MARCENARIA'!E24 | AB25: ='MARCENARIA'!E25 | AC25: ='MARCENARIA'!E26 | AD25: ='MARCENARIA'!E27 | AE25: ='MARCENARIA'!E28 | AF25: ='MARCENARIA'!E29 | AG25: ='MARCENARIA'!E30 | AH25: ='MARCENARIA'!E31 | AI25: ='MARCENARIA'!E32 | AJ25: ='MARCENARIA'!E33 | AK25: ='MARCENARIA'!E34 | AL25: ='MARCENARIA'!E35 | AM25: ='MARCENARIA'!E36 | AN25: ='MARCENARIA'!E37 | AO25: ='MARCENARIA'!E38 | AP25: ='MARCENARIA'!E39 | AQ25: ='MARCENARIA'!E40 | AR25: ='MARCENARIA'!E41 | AS25: ='MARCENARIA'!E42 | AT25: ='MARCENARIA'!E43 | AU25: ='MARCENARIA'!E44 | AV25: ='MARCENARIA'!E45 | AW25: ='MARCENARIA'!E46 | AX25: ='MARCENARIA'!E47 | AY25: ='MARCENARIA'!E48 | AZ25: ='MARCENARIA'!E49 | BA25: ='MARCENARIA'!E50 | BB25: ='MARCENARIA'!E51 | BC25: ='MARCENARIA'!E52 | BD25: ='MARCENARIA'!E53 | BE25: ='MARCENARIA'!E54 | BF25: ='MARCENARIA'!E55 | BG25: ='MARCENARIA'!E56 | BH25: ='MARCENARIA'!E57 | BI25: ='MARCENARIA'!E58 | BJ25: ='MARCENARIA'!E59 | BK25: ='MARCENARIA'!E60 | BL25: ='MARCENARIA'!E61 | BM25: ='MARCENARIA'!E62 | BN25: ='MARCENARIA'!E63 | BO25: ='MARCENARIA'!E64 | BP25: ='MARCENARIA'!E65 | BQ25: ='MARCENARIA'!E66 | BR25: ='MARCENARIA'!E67 | BS25: ='MARCENARIA'!E68 | BT25: ='MARCENARIA'!E69 | BU25: ='MARCENARIA'!E70 | BV25: ='MARCENARIA'!E71 | BW25: ='MARCENARIA'!E72 | BX25: ='MARCENARIA'!E73 | BY25: ='MARCENARIA'!E74 | BZ25: ='MARCENARIA'!E75 | CA25: ='MARCENARIA'!E76
B26: 1030-1070-430 | C26: PAISAGISMO | D26: ='PAISAGISMO'!$K$5 | E26: =SUM(H26:CA26) | F26: =IF(D26="","",D26-E26) | H26: ='PAISAGISMO'!E5 | I26: ='PAISAGISMO'!E6 | J26: ='PAISAGISMO'!E7 | K26: ='PAISAGISMO'!E8 | L26: ='PAISAGISMO'!E9 | M26: ='PAISAGISMO'!E10 | N26: ='PAISAGISMO'!E11 | O26: ='PAISAGISMO'!E12 | P26: ='PAISAGISMO'!E13 | Q26: ='PAISAGISMO'!E14 | R26: ='PAISAGISMO'!E15 | S26: ='PAISAGISMO'!E16 | T26: ='PAISAGISMO'!E17 | U26: ='PAISAGISMO'!E18 | V26: ='PAISAGISMO'!E19 | W26: ='PAISAGISMO'!E20 | X26: ='PAISAGISMO'!E21 | Y26: ='PAISAGISMO'!E22 | Z26: ='PAISAGISMO'!E23 | AA26: ='PAISAGISMO'!E24 | AB26: ='PAISAGISMO'!E25 | AC26: ='PAISAGISMO'!E26 | AD26: ='PAISAGISMO'!E27 | AE26: ='PAISAGISMO'!E28 | AF26: ='PAISAGISMO'!E29 | AG26: ='PAISAGISMO'!E30 | AH26: ='PAISAGISMO'!E31 | AI26: ='PAISAGISMO'!E32 | AJ26: ='PAISAGISMO'!E33 | AK26: ='PAISAGISMO'!E34 | AL26: ='PAISAGISMO'!E35 | AM26: ='PAISAGISMO'!E36 | AN26: ='PAISAGISMO'!E37 | AO26: ='PAISAGISMO'!E38 | AP26: ='PAISAGISMO'!E39 | AQ26: ='PAISAGISMO'!E40 | AR26: ='PAISAGISMO'!E41 | AS26: ='PAISAGISMO'!E42 | AT26: ='PAISAGISMO'!E43 | AU26: ='PAISAGISMO'!E44 | AV26: ='PAISAGISMO'!E45 | AW26: ='PAISAGISMO'!E46 | AX26: ='PAISAGISMO'!E47 | AY26: ='PAISAGISMO'!E48 | AZ26: ='PAISAGISMO'!E49 | BA26: ='PAISAGISMO'!E50 | BB26: ='PAISAGISMO'!E51 | BC26: ='PAISAGISMO'!E52 | BD26: ='PAISAGISMO'!E53 | BE26: ='PAISAGISMO'!E54 | BF26: ='PAISAGISMO'!E55 | BG26: ='PAISAGISMO'!E56 | BH26: ='PAISAGISMO'!E57 | BI26: ='PAISAGISMO'!E58 | BJ26: ='PAISAGISMO'!E59 | BK26: ='PAISAGISMO'!E60 | BL26: ='PAISAGISMO'!E61 | BM26: ='PAISAGISMO'!E62 | BN26: ='PAISAGISMO'!E63 | BO26: ='PAISAGISMO'!E64 | BP26: ='PAISAGISMO'!E65 | BQ26: ='PAISAGISMO'!E66 | BR26: ='PAISAGISMO'!E67 | BS26: ='PAISAGISMO'!E68 | BT26: ='PAISAGISMO'!E69 | BU26: ='PAISAGISMO'!E70 | BV26: ='PAISAGISMO'!E71 | BW26: ='PAISAGISMO'!E72 | BX26: ='PAISAGISMO'!E73 | BY26: ='PAISAGISMO'!E74 | BZ26: ='PAISAGISMO'!E75 | CA26: ='PAISAGISMO'!E76
B27: 1030-1070-420 | C27: PAVIMENTAÇÃO | D27: ='PAVIMENTAÇÃO'!$K$5 | E27: =SUM(H27:CA27) | F27: =IF(D27="","",D27-E27) | H27: ='PAVIMENTAÇÃO'!E5 | I27: ='PAVIMENTAÇÃO'!E6 | J27: ='PAVIMENTAÇÃO'!E7 | K27: ='PAVIMENTAÇÃO'!E8 | L27: ='PAVIMENTAÇÃO'!E9 | M27: ='PAVIMENTAÇÃO'!E10 | N27: ='PAVIMENTAÇÃO'!E11 | O27: ='PAVIMENTAÇÃO'!E12 | P27: ='PAVIMENTAÇÃO'!E13 | Q27: ='PAVIMENTAÇÃO'!E14 | R27: ='PAVIMENTAÇÃO'!E15 | S27: ='PAVIMENTAÇÃO'!E16 | T27: ='PAVIMENTAÇÃO'!E17 | U27: ='PAVIMENTAÇÃO'!E18 | V27: ='PAVIMENTAÇÃO'!E19 | W27: ='PAVIMENTAÇÃO'!E20 | X27: ='PAVIMENTAÇÃO'!E21 | Y27: ='PAVIMENTAÇÃO'!E22 | Z27: ='PAVIMENTAÇÃO'!E23 | AA27: ='PAVIMENTAÇÃO'!E24 | AB27: ='PAVIMENTAÇÃO'!E25 | AC27: ='PAVIMENTAÇÃO'!E26 | AD27: ='PAVIMENTAÇÃO'!E27 | AE27: ='PAVIMENTAÇÃO'!E28 | AF27: ='PAVIMENTAÇÃO'!E29 | AG27: ='PAVIMENTAÇÃO'!E30 | AH27: ='PAVIMENTAÇÃO'!E31 | AI27: ='PAVIMENTAÇÃO'!E32 | AJ27: ='PAVIMENTAÇÃO'!E33 | AK27: ='PAVIMENTAÇÃO'!E34 | AL27: ='PAVIMENTAÇÃO'!E35 | AM27: ='PAVIMENTAÇÃO'!E36 | AN27: ='PAVIMENTAÇÃO'!E37 | AO27: ='PAVIMENTAÇÃO'!E38 | AP27: ='PAVIMENTAÇÃO'!E39 | AQ27: ='PAVIMENTAÇÃO'!E40 | AR27: ='PAVIMENTAÇÃO'!E41 | AS27: ='PAVIMENTAÇÃO'!E42 | AT27: ='PAVIMENTAÇÃO'!E43 | AU27: ='PAVIMENTAÇÃO'!E44 | AV27: ='PAVIMENTAÇÃO'!E45 | AW27: ='PAVIMENTAÇÃO'!E46 | AX27: ='PAVIMENTAÇÃO'!E47 | AY27: ='PAVIMENTAÇÃO'!E48 | AZ27: ='PAVIMENTAÇÃO'!E49 | BA27: ='PAVIMENTAÇÃO'!E50 | BB27: ='PAVIMENTAÇÃO'!E51 | BC27: ='PAVIMENTAÇÃO'!E52 | BD27: ='PAVIMENTAÇÃO'!E53 | BE27: ='PAVIMENTAÇÃO'!E54 | BF27: ='PAVIMENTAÇÃO'!E55 | BG27: ='PAVIMENTAÇÃO'!E56 | BH27: ='PAVIMENTAÇÃO'!E57 | BI27: ='PAVIMENTAÇÃO'!E58 | BJ27: ='PAVIMENTAÇÃO'!E59 | BK27: ='PAVIMENTAÇÃO'!E60 | BL27: ='PAVIMENTAÇÃO'!E61 | BM27: ='PAVIMENTAÇÃO'!E62 | BN27: ='PAVIMENTAÇÃO'!E63 | BO27: ='PAVIMENTAÇÃO'!E64 | BP27: ='PAVIMENTAÇÃO'!E65 | BQ27: ='PAVIMENTAÇÃO'!E66 | BR27: ='PAVIMENTAÇÃO'!E67 | BS27: ='PAVIMENTAÇÃO'!E68 | BT27: ='PAVIMENTAÇÃO'!E69 | BU27: ='PAVIMENTAÇÃO'!E70 | BV27: ='PAVIMENTAÇÃO'!E71 | BW27: ='PAVIMENTAÇÃO'!E72 | BX27: ='PAVIMENTAÇÃO'!E73 | BY27: ='PAVIMENTAÇÃO'!E74 | BZ27: ='PAVIMENTAÇÃO'!E75 | CA27: ='PAVIMENTAÇÃO'!E76
B28: 1030-1070-390 | C28: PINTURA | D28: ='PINTURA'!$K$5 | E28: =SUM(H28:CA28) | F28: =IF(D28="","",D28-E28) | H28: ='PINTURA'!E5 | I28: ='PINTURA'!E6 | J28: ='PINTURA'!E7 | K28: ='PINTURA'!E8 | L28: ='PINTURA'!E9 | M28: ='PINTURA'!E10 | N28: ='PINTURA'!E11 | O28: ='PINTURA'!E12 | P28: ='PINTURA'!E13 | Q28: ='PINTURA'!E14 | R28: ='PINTURA'!E15 | S28: ='PINTURA'!E16 | T28: ='PINTURA'!E17 | U28: ='PINTURA'!E18 | V28: ='PINTURA'!E19 | W28: ='PINTURA'!E20 | X28: ='PINTURA'!E21 | Y28: ='PINTURA'!E22 | Z28: ='PINTURA'!E23 | AA28: ='PINTURA'!E24 | AB28: ='PINTURA'!E25 | AC28: ='PINTURA'!E26 | AD28: ='PINTURA'!E27 | AE28: ='PINTURA'!E28 | AF28: ='PINTURA'!E29 | AG28: ='PINTURA'!E30 | AH28: ='PINTURA'!E31 | AI28: ='PINTURA'!E32 | AJ28: ='PINTURA'!E33 | AK28: ='PINTURA'!E34 | AL28: ='PINTURA'!E35 | AM28: ='PINTURA'!E36 | AN28: ='PINTURA'!E37 | AO28: ='PINTURA'!E38 | AP28: ='PINTURA'!E39 | AQ28: ='PINTURA'!E40 | AR28: ='PINTURA'!E41 | AS28: ='PINTURA'!E42 | AT28: ='PINTURA'!E43 | AU28: ='PINTURA'!E44 | AV28: ='PINTURA'!E45 | AW28: ='PINTURA'!E46 | AX28: ='PINTURA'!E47 | AY28: ='PINTURA'!E48 | AZ28: ='PINTURA'!E49 | BA28: ='PINTURA'!E50 | BB28: ='PINTURA'!E51 | BC28: ='PINTURA'!E52 | BD28: ='PINTURA'!E53 | BE28: ='PINTURA'!E54 | BF28: ='PINTURA'!E55 | BG28: ='PINTURA'!E56 | BH28: ='PINTURA'!E57 | BI28: ='PINTURA'!E58 | BJ28: ='PINTURA'!E59 | BK28: ='PINTURA'!E60 | BL28: ='PINTURA'!E61 | BM28: ='PINTURA'!E62 | BN28: ='PINTURA'!E63 | BO28: ='PINTURA'!E64 | BP28: ='PINTURA'!E65 | BQ28: ='PINTURA'!E66 | BR28: ='PINTURA'!E67 | BS28: ='PINTURA'!E68 | BT28: ='PINTURA'!E69 | BU28: ='PINTURA'!E70 | BV28: ='PINTURA'!E71 | BW28: ='PINTURA'!E72 | BX28: ='PINTURA'!E73 | BY28: ='PINTURA'!E74 | BZ28: ='PINTURA'!E75 | CA28: ='PINTURA'!E76
B29: 1030-1070-100 | C29: PROJETOS | D29: ='PROJETO'!$K$5 | E29: =SUM(H29:CA29) | F29: =IF(D29="","",D29-E29) | H29: ='PROJETO'!E5 | I29: ='PROJETO'!E6 | J29: ='PROJETO'!E7 | K29: ='PROJETO'!E8 | L29: ='PROJETO'!E9 | M29: ='PROJETO'!E10 | N29: ='PROJETO'!E11 | O29: ='PROJETO'!E12 | P29: ='PROJETO'!E13 | Q29: ='PROJETO'!E14 | R29: ='PROJETO'!E15 | S29: ='PROJETO'!E16 | T29: ='PROJETO'!E17 | U29: ='PROJETO'!E18 | V29: ='PROJETO'!E19 | W29: ='PROJETO'!E20 | X29: ='PROJETO'!E21 | Y29: ='PROJETO'!E22 | Z29: ='PROJETO'!E23 | AA29: ='PROJETO'!E24 | AB29: ='PROJETO'!E25 | AC29: ='PROJETO'!E26 | AD29: ='PROJETO'!E27 | AE29: ='PROJETO'!E28 | AF29: ='PROJETO'!E29 | AG29: ='PROJETO'!E30 | AH29: ='PROJETO'!E31 | AI29: ='PROJETO'!E32 | AJ29: ='PROJETO'!E33 | AK29: ='PROJETO'!E34 | AL29: ='PROJETO'!E35 | AM29: ='PROJETO'!E36 | AN29: ='PROJETO'!E37 | AO29: ='PROJETO'!E38 | AP29: ='PROJETO'!E39 | AQ29: ='PROJETO'!E40 | AR29: ='PROJETO'!E41 | AS29: ='PROJETO'!E42 | AT29: ='PROJETO'!E43 | AU29: ='PROJETO'!E44 | AV29: ='PROJETO'!E45 | AW29: ='PROJETO'!E46 | AX29: ='PROJETO'!E47 | AY29: ='PROJETO'!E48 | AZ29: ='PROJETO'!E49 | BA29: ='PROJETO'!E50 | BB29: ='PROJETO'!E51 | BC29: ='PROJETO'!E52 | BD29: ='PROJETO'!E53 | BE29: ='PROJETO'!E54 | BF29: ='PROJETO'!E55 | BG29: ='PROJETO'!E56 | BH29: ='PROJETO'!E57 | BI29: ='PROJETO'!E58 | BJ29: ='PROJETO'!E59 | BK29: ='PROJETO'!E60 | BL29: ='PROJETO'!E61 | BM29: ='PROJETO'!E62 | BN29: ='PROJETO'!E63 | BO29: ='PROJETO'!E64 | BP29: ='PROJETO'!E65 | BQ29: ='PROJETO'!E66 | BR29: ='PROJETO'!E67 | BS29: ='PROJETO'!E68 | BT29: ='PROJETO'!E69 | BU29: ='PROJETO'!E70 | BV29: ='PROJETO'!E71 | BW29: ='PROJETO'!E72 | BX29: ='PROJETO'!E73 | BY29: ='PROJETO'!E74 | BZ29: ='PROJETO'!E75 | CA29: ='PROJETO'!E76
B30: 1030-1070-570 | C30: REEMBOLSO MATERIAIS E SERVIÇOS | E30: =SUM(H30:CA30) | F30: =IF(D30="","",D30-E30)
B31: 1030-1070-360 | C31: REVESTIMENTO DIVERSOS - FACHADA | D31: ='REV. FACHADA'!$K$5 | E31: =SUM(H31:CA31) | F31: =IF(D31="","",D31-E31) | H31: ='REV. FACHADA'!E5 | I31: ='REV. FACHADA'!E6 | J31: ='REV. FACHADA'!E7 | K31: ='REV. FACHADA'!E8 | L31: ='REV. FACHADA'!E9 | M31: ='REV. FACHADA'!E10 | N31: ='REV. FACHADA'!E11 | O31: ='REV. FACHADA'!E12 | P31: ='REV. FACHADA'!E13 | Q31: ='REV. FACHADA'!E14 | R31: ='REV. FACHADA'!E15 | S31: ='REV. FACHADA'!E16 | T31: ='REV. FACHADA'!E17 | U31: ='REV. FACHADA'!E18 | V31: ='REV. FACHADA'!E19 | W31: ='REV. FACHADA'!E20 | X31: ='REV. FACHADA'!E21 | Y31: ='REV. FACHADA'!E22 | Z31: ='REV. FACHADA'!E23 | AA31: ='REV. FACHADA'!E24 | AB31: ='REV. FACHADA'!E25 | AC31: ='REV. FACHADA'!E26 | AD31: ='REV. FACHADA'!E27 | AE31: ='REV. FACHADA'!E28 | AF31: ='REV. FACHADA'!E29 | AG31: ='REV. FACHADA'!E30 | AH31: ='REV. FACHADA'!E31 | AI31: ='REV. FACHADA'!E32 | AJ31: ='REV. FACHADA'!E33 | AK31: ='REV. FACHADA'!E34 | AL31: ='REV. FACHADA'!E35 | AM31: ='REV. FACHADA'!E36 | AN31: ='REV. FACHADA'!E37 | AO31: ='REV. FACHADA'!E38 | AP31: ='REV. FACHADA'!E39 | AQ31: ='REV. FACHADA'!E40 | AR31: ='REV. FACHADA'!E41 | AS31: ='REV. FACHADA'!E42 | AT31: ='REV. FACHADA'!E43 | AU31: ='REV. FACHADA'!E44 | AV31: ='REV. FACHADA'!E45 | AW31: ='REV. FACHADA'!E46 | AX31: ='REV. FACHADA'!E47 | AY31: ='REV. FACHADA'!E48 | AZ31: ='REV. FACHADA'!E49 | BA31: ='REV. FACHADA'!E50 | BB31: ='REV. FACHADA'!E51 | BC31: ='REV. FACHADA'!E52 | BD31: ='REV. FACHADA'!E53 | BE31: ='REV. FACHADA'!E54 | BF31: ='REV. FACHADA'!E55 | BG31: ='REV. FACHADA'!E56 | BH31: ='REV. FACHADA'!E57 | BI31: ='REV. FACHADA'!E58 | BJ31: ='REV. FACHADA'!E59 | BK31: ='REV. FACHADA'!E60 | BL31: ='REV. FACHADA'!E61 | BM31: ='REV. FACHADA'!E62 | BN31: ='REV. FACHADA'!E63 | BO31: ='REV. FACHADA'!E64 | BP31: ='REV. FACHADA'!E65 | BQ31: ='REV. FACHADA'!E66 | BR31: ='REV. FACHADA'!E67 | BS31: ='REV. FACHADA'!E68 | BT31: ='REV. FACHADA'!E69 | BU31: ='REV. FACHADA'!E70 | BV31: ='REV. FACHADA'!E71 | BW31: ='REV. FACHADA'!E72 | BX31: ='REV. FACHADA'!E73 | BY31: ='REV. FACHADA'!E74 | BZ31: ='REV. FACHADA'!E75 | CA31: ='REV. FACHADA'!E76
B32: 1030-1070-490 | C32: REVESTIMENTOS DE ACABAMENTO | D32: ='REV. ACAB'!$K$5 | E32: =SUM(H32:CA32) | F32: =IF(D32="","",D32-E32) | H32: ='REV. ACAB'!E5 | I32: ='REV. ACAB'!E6 | J32: ='REV. ACAB'!E7 | K32: ='REV. ACAB'!E8 | L32: ='REV. ACAB'!E9 | M32: ='REV. ACAB'!E10 | N32: ='REV. ACAB'!E11 | O32: ='REV. ACAB'!E12 | P32: ='REV. ACAB'!E13 | Q32: ='REV. ACAB'!E14 | R32: ='REV. ACAB'!E15 | S32: ='REV. ACAB'!E16 | T32: ='REV. ACAB'!E17 | U32: ='REV. ACAB'!E18 | V32: ='REV. ACAB'!E19 | W32: ='REV. ACAB'!E20 | X32: ='REV. ACAB'!E21 | Y32: ='REV. ACAB'!E22 | Z32: ='REV. ACAB'!E23 | AA32: ='REV. ACAB'!E24 | AB32: ='REV. ACAB'!E25 | AC32: ='REV. ACAB'!E26 | AD32: ='REV. ACAB'!E27 | AE32: ='REV. ACAB'!E28 | AF32: ='REV. ACAB'!E29 | AG32: ='REV. ACAB'!E30 | AH32: ='REV. ACAB'!E31 | AI32: ='REV. ACAB'!E32 | AJ32: ='REV. ACAB'!E33 | AK32: ='REV. ACAB'!E34 | AL32: ='REV. ACAB'!E35 | AM32: ='REV. ACAB'!E36 | AN32: ='REV. ACAB'!E37 | AO32: ='REV. ACAB'!E38 | AP32: ='REV. ACAB'!E39 | AQ32: ='REV. ACAB'!E40 | AR32: ='REV. ACAB'!E41 | AS32: ='REV. ACAB'!E42 | AT32: ='REV. ACAB'!E43 | AU32: ='REV. ACAB'!E44 | AV32: ='REV. ACAB'!E45 | AW32: ='REV. ACAB'!E46 | AX32: ='REV. ACAB'!E47 | AY32: ='REV. ACAB'!E48 | AZ32: ='REV. ACAB'!E49 | BA32: ='REV. ACAB'!E50 | BB32: ='REV. ACAB'!E51 | BC32: ='REV. ACAB'!E52 | BD32: ='REV. ACAB'!E53 | BE32: ='REV. ACAB'!E54 | BF32: ='REV. ACAB'!E55 | BG32: ='REV. ACAB'!E56 | BH32: ='REV. ACAB'!E57 | BI32: ='REV. ACAB'!E58 | BJ32: ='REV. ACAB'!E59 | BK32: ='REV. ACAB'!E60 | BL32: ='REV. ACAB'!E61 | BM32: ='REV. ACAB'!E62 | BN32: ='REV. ACAB'!E63 | BO32: ='REV. ACAB'!E64 | BP32: ='REV. ACAB'!E65 | BQ32: ='REV. ACAB'!E66 | BR32: ='REV. ACAB'!E67 | BS32: ='REV. ACAB'!E68 | BT32: ='REV. ACAB'!E69 | BU32: ='REV. ACAB'!E70 | BV32: ='REV. ACAB'!E71 | BW32: ='REV. ACAB'!E72 | BX32: ='REV. ACAB'!E73 | BY32: ='REV. ACAB'!E74 | BZ32: ='REV. ACAB'!E75 | CA32: ='REV. ACAB'!E76
B33: 1030-1070-320 | C33: REVESTIMENTOS DE MASSA EM PISOS | D33: ='REV. PISOS'!$K$5 | E33: =SUM(H33:CA33) | F33: =IF(D33="","",D33-E33) | H33: ='REV. PISOS'!E5 | I33: ='REV. PISOS'!E6 | J33: ='REV. PISOS'!E7 | K33: ='REV. PISOS'!E8 | L33: ='REV. PISOS'!E9 | M33: ='REV. PISOS'!E10 | N33: ='REV. PISOS'!E11 | O33: ='REV. PISOS'!E12 | P33: ='REV. PISOS'!E13 | Q33: ='REV. PISOS'!E14 | R33: ='REV. PISOS'!E15 | S33: ='REV. PISOS'!E16 | T33: ='REV. PISOS'!E17 | U33: ='REV. PISOS'!E18 | V33: ='REV. PISOS'!E19 | W33: ='REV. PISOS'!E20 | X33: ='REV. PISOS'!E21 | Y33: ='REV. PISOS'!E22 | Z33: ='REV. PISOS'!E23 | AA33: ='REV. PISOS'!E24 | AB33: ='REV. PISOS'!E25 | AC33: ='REV. PISOS'!E26 | AD33: ='REV. PISOS'!E27 | AE33: ='REV. PISOS'!E28 | AF33: ='REV. PISOS'!E29 | AG33: ='REV. PISOS'!E30 | AH33: ='REV. PISOS'!E31 | AI33: ='REV. PISOS'!E32 | AJ33: ='REV. PISOS'!E33 | AK33: ='REV. PISOS'!E34 | AL33: ='REV. PISOS'!E35 | AM33: ='REV. PISOS'!E36 | AN33: ='REV. PISOS'!E37 | AO33: ='REV. PISOS'!E38 | AP33: ='REV. PISOS'!E39 | AQ33: ='REV. PISOS'!E40 | AR33: ='REV. PISOS'!E41 | AS33: ='REV. PISOS'!E42 | AT33: ='REV. PISOS'!E43 | AU33: ='REV. PISOS'!E44 | AV33: ='REV. PISOS'!E45 | AW33: ='REV. PISOS'!E46 | AX33: ='REV. PISOS'!E47 | AY33: ='REV. PISOS'!E48 | AZ33: ='REV. PISOS'!E49 | BA33: ='REV. PISOS'!E50 | BB33: ='REV. PISOS'!E51 | BC33: ='REV. PISOS'!E52 | BD33: ='REV. PISOS'!E53 | BE33: ='REV. PISOS'!E54 | BF33: ='REV. PISOS'!E55 | BG33: ='REV. PISOS'!E56 | BH33: ='REV. PISOS'!E57 | BI33: ='REV. PISOS'!E58 | BJ33: ='REV. PISOS'!E59 | BK33: ='REV. PISOS'!E60 | BL33: ='REV. PISOS'!E61 | BM33: ='REV. PISOS'!E62 | BN33: ='REV. PISOS'!E63 | BO33: ='REV. PISOS'!E64 | BP33: ='REV. PISOS'!E65 | BQ33: ='REV. PISOS'!E66 | BR33: ='REV. PISOS'!E67 | BS33: ='REV. PISOS'!E68 | BT33: ='REV. PISOS'!E69 | BU33: ='REV. PISOS'!E70 | BV33: ='REV. PISOS'!E71 | BW33: ='REV. PISOS'!E72 | BX33: ='REV. PISOS'!E73 | BY33: ='REV. PISOS'!E74 | BZ33: ='REV. PISOS'!E75 | CA33: ='REV. PISOS'!E76
B34: 1030-1070-300 | C34: REVESTIMENTOS DE MASSA EM PAREDES | D34: ='REV. PAREDE'!$K$5 | E34: =SUM(H34:CA34) | F34: =IF(D34="","",D34-E34) | H34: ='REV. PAREDE'!E5 | I34: ='REV. PAREDE'!E6 | J34: ='REV. PAREDE'!E7 | K34: ='REV. PAREDE'!E8 | L34: ='REV. PAREDE'!E9 | M34: ='REV. PAREDE'!E10 | N34: ='REV. PAREDE'!E11 | O34: ='REV. PAREDE'!E12 | P34: ='REV. PAREDE'!E13 | Q34: ='REV. PAREDE'!E14 | R34: ='REV. PAREDE'!E15 | S34: ='REV. PAREDE'!E16 | T34: ='REV. PAREDE'!E17 | U34: ='REV. PAREDE'!E18 | V34: ='REV. PAREDE'!E19 | W34: ='REV. PAREDE'!E20 | X34: ='REV. PAREDE'!E21 | Y34: ='REV. PAREDE'!E22 | Z34: ='REV. PAREDE'!E23 | AA34: ='REV. PAREDE'!E24 | AB34: ='REV. PAREDE'!E25 | AC34: ='REV. PAREDE'!E26 | AD34: ='REV. PAREDE'!E27 | AE34: ='REV. PAREDE'!E28 | AF34: ='REV. PAREDE'!E29 | AG34: ='REV. PAREDE'!E30 | AH34: ='REV. PAREDE'!E31 | AI34: ='REV. PAREDE'!E32 | AJ34: ='REV. PAREDE'!E33 | AK34: ='REV. PAREDE'!E34 | AL34: ='REV. PAREDE'!E35 | AM34: ='REV. PAREDE'!E36 | AN34: ='REV. PAREDE'!E37 | AO34: ='REV. PAREDE'!E38 | AP34: ='REV. PAREDE'!E39 | AQ34: ='REV. PAREDE'!E40 | AR34: ='REV. PAREDE'!E41 | AS34: ='REV. PAREDE'!E42 | AT34: ='REV. PAREDE'!E43 | AU34: ='REV. PAREDE'!E44 | AV34: ='REV. PAREDE'!E45 | AW34: ='REV. PAREDE'!E46 | AX34: ='REV. PAREDE'!E47 | AY34: ='REV. PAREDE'!E48 | AZ34: ='REV. PAREDE'!E49 | BA34: ='REV. PAREDE'!E50 | BB34: ='REV. PAREDE'!E51 | BC34: ='REV. PAREDE'!E52 | BD34: ='REV. PAREDE'!E53 | BE34: ='REV. PAREDE'!E54 | BF34: ='REV. PAREDE'!E55 | BG34: ='REV. PAREDE'!E56 | BH34: ='REV. PAREDE'!E57 | BI34: ='REV. PAREDE'!E58 | BJ34: ='REV. PAREDE'!E59 | BK34: ='REV. PAREDE'!E60 | BL34: ='REV. PAREDE'!E61 | BM34: ='REV. PAREDE'!E62 | BN34: ='REV. PAREDE'!E63 | BO34: ='REV. PAREDE'!E64 | BP34: ='REV. PAREDE'!E65 | BQ34: ='REV. PAREDE'!E66 | BR34: ='REV. PAREDE'!E67 | BS34: ='REV. PAREDE'!E68 | BT34: ='REV. PAREDE'!E69 | BU34: ='REV. PAREDE'!E70 | BV34: ='REV. PAREDE'!E71 | BW34: ='REV. PAREDE'!E72 | BX34: ='REV. PAREDE'!E73 | BY34: ='REV. PAREDE'!E74 | BZ34: ='REV. PAREDE'!E75 | CA34: ='REV. PAREDE'!E76
B35: 1030-1070-580 | C35: REVESTIMENTOS DIVERSOS-FACHADA | E35: =SUM(H35:CA35) | F35: =IF(D35="","",D35-E35)
B36: 1030-1070-310 | C36: REVESTIMENTOS DIVERSOS-PAREDE | E36: =SUM(H36:CA36) | F36: =IF(D36="","",D36-E36)
B37: 1030-1070-330 | C37: REVESTIMENTOS DIVERSOS-PISOS | E37: =SUM(H37:CA37) | F37: =IF(D37="","",D37-E37)
B38: 1030-1070-340 | C38: RODAPÉS/SOLEIRAS/PEITORIL/ADUELAS | E38: =SUM(H38:CA38) | F38: =IF(D38="","",D38-E38)
B39: 1030-1070-220 | C39: EQUIPAMENTOS DE PROTEÇÃO COLETIVA | E39: =SUM(H39:CA39) | F39: =IF(D39="","",D39-E39)
B40: 1030-1070-110 | C40: SEGUROS | D40: ='SEGUROS'!$K$5 | E40: =SUM(H40:CA40) | F40: =IF(D40="","",D40-E40) | H40: ='SEGUROS'!E5 | I40: ='SEGUROS'!E6 | J40: ='SEGUROS'!E7 | K40: ='SEGUROS'!E8 | L40: ='SEGUROS'!E9 | M40: ='SEGUROS'!E10 | N40: ='SEGUROS'!E11 | O40: ='SEGUROS'!E12 | P40: ='SEGUROS'!E13 | Q40: ='SEGUROS'!E14 | R40: ='SEGUROS'!E15 | S40: ='SEGUROS'!E16 | T40: ='SEGUROS'!E17 | U40: ='SEGUROS'!E18 | V40: ='SEGUROS'!E19 | W40: ='SEGUROS'!E20 | X40: ='SEGUROS'!E21 | Y40: ='SEGUROS'!E22 | Z40: ='SEGUROS'!E23 | AA40: ='SEGUROS'!E24 | AB40: ='SEGUROS'!E25 | AC40: ='SEGUROS'!E26 | AD40: ='SEGUROS'!E27 | AE40: ='SEGUROS'!E28 | AF40: ='SEGUROS'!E29 | AG40: ='SEGUROS'!E30 | AH40: ='SEGUROS'!E31 | AI40: ='SEGUROS'!E32 | AJ40: ='SEGUROS'!E33 | AK40: ='SEGUROS'!E34 | AL40: ='SEGUROS'!E35 | AM40: ='SEGUROS'!E36 | AN40: ='SEGUROS'!E37 | AO40: ='SEGUROS'!E38 | AP40: ='SEGUROS'!E39 | AQ40: ='SEGUROS'!E40 | AR40: ='SEGUROS'!E41 | AS40: ='SEGUROS'!E42 | AT40: ='SEGUROS'!E43 | AU40: ='SEGUROS'!E44 | AV40: ='SEGUROS'!E45 | AW40: ='SEGUROS'!E46 | AX40: ='SEGUROS'!E47 | AY40: ='SEGUROS'!E48 | AZ40: ='SEGUROS'!E49 | BA40: ='SEGUROS'!E50 | BB40: ='SEGUROS'!E51 | BC40: ='SEGUROS'!E52 | BD40: ='SEGUROS'!E53 | BE40: ='SEGUROS'!E54 | BF40: ='SEGUROS'!E55 | BG40: ='SEGUROS'!E56 | BH40: ='SEGUROS'!E57 | BI40: ='SEGUROS'!E58 | BJ40: ='SEGUROS'!E59 | BK40: ='SEGUROS'!E60 | BL40: ='SEGUROS'!E61 | BM40: ='SEGUROS'!E62 | BN40: ='SEGUROS'!E63 | BO40: ='SEGUROS'!E64 | BP40: ='SEGUROS'!E65 | BQ40: ='SEGUROS'!E66 | BR40: ='SEGUROS'!E67 | BS40: ='SEGUROS'!E68 | BT40: ='SEGUROS'!E69 | BU40: ='SEGUROS'!E70 | BV40: ='SEGUROS'!E71 | BW40: ='SEGUROS'!E72 | BX40: ='SEGUROS'!E73 | BY40: ='SEGUROS'!E74 | BZ40: ='SEGUROS'!E75 | CA40: ='SEGUROS'!E76
B41: 1030-1070-380 | C41: SERRALHERIA | D41: ='SERRALHERIA'!$K$5 | E41: =SUM(H41:CA41) | F41: =IF(D41="","",D41-E41) | H41: ='SERRALHERIA'!E5 | I41: ='SERRALHERIA'!E6 | J41: ='SERRALHERIA'!E7 | K41: ='SERRALHERIA'!E8 | L41: ='SERRALHERIA'!E9 | M41: ='SERRALHERIA'!E10 | N41: ='SERRALHERIA'!E11 | O41: ='SERRALHERIA'!E12 | P41: ='SERRALHERIA'!E13 | Q41: ='SERRALHERIA'!E14 | R41: ='SERRALHERIA'!E15 | S41: ='SERRALHERIA'!E16 | T41: ='SERRALHERIA'!E17 | U41: ='SERRALHERIA'!E18 | V41: ='SERRALHERIA'!E19 | W41: ='SERRALHERIA'!E20 | X41: ='SERRALHERIA'!E21 | Y41: ='SERRALHERIA'!E22 | Z41: ='SERRALHERIA'!E23 | AA41: ='SERRALHERIA'!E24 | AB41: ='SERRALHERIA'!E25 | AC41: ='SERRALHERIA'!E26 | AD41: ='SERRALHERIA'!E27 | AE41: ='SERRALHERIA'!E28 | AF41: ='SERRALHERIA'!E29 | AG41: ='SERRALHERIA'!E30 | AH41: ='SERRALHERIA'!E31 | AI41: ='SERRALHERIA'!E32 | AJ41: ='SERRALHERIA'!E33 | AK41: ='SERRALHERIA'!E34 | AL41: ='SERRALHERIA'!E35 | AM41: ='SERRALHERIA'!E36 | AN41: ='SERRALHERIA'!E37 | AO41: ='SERRALHERIA'!E38 | AP41: ='SERRALHERIA'!E39 | AQ41: ='SERRALHERIA'!E40 | AR41: ='SERRALHERIA'!E41 | AS41: ='SERRALHERIA'!E42 | AT41: ='SERRALHERIA'!E43 | AU41: ='SERRALHERIA'!E44 | AV41: ='SERRALHERIA'!E45 | AW41: ='SERRALHERIA'!E46 | AX41: ='SERRALHERIA'!E47 | AY41: ='SERRALHERIA'!E48 | AZ41: ='SERRALHERIA'!E49 | BA41: ='SERRALHERIA'!E50 | BB41: ='SERRALHERIA'!E51 | BC41: ='SERRALHERIA'!E52 | BD41: ='SERRALHERIA'!E53 | BE41: ='SERRALHERIA'!E54 | BF41: ='SERRALHERIA'!E55 | BG41: ='SERRALHERIA'!E56 | BH41: ='SERRALHERIA'!E57 | BI41: ='SERRALHERIA'!E58 | BJ41: ='SERRALHERIA'!E59 | BK41: ='SERRALHERIA'!E60 | BL41: ='SERRALHERIA'!E61 | BM41: ='SERRALHERIA'!E62 | BN41: ='SERRALHERIA'!E63 | BO41: ='SERRALHERIA'!E64 | BP41: ='SERRALHERIA'!E65 | BQ41: ='SERRALHERIA'!E66 | BR41: ='SERRALHERIA'!E67 | BS41: ='SERRALHERIA'!E68 | BT41: ='SERRALHERIA'!E69 | BU41: ='SERRALHERIA'!E70 | BV41: ='SERRALHERIA'!E71 | BW41: ='SERRALHERIA'!E72 | BX41: ='SERRALHERIA'!E73 | BY41: ='SERRALHERIA'!E74 | BZ41: ='SERRALHERIA'!E75 | CA41: ='SERRALHERIA'!E76
B42: 1030-1070-150 | C42: LIGAÇÕES PROVISÓRIAS AGUA, ENERGIA,TELEFONIA, ESGOTO | D42: ='LIG. PROVISÓRIAS'!$K$5 | E42: =SUM(H42:CA42) | F42: =IF(D42="","",D42-E42) | H42: ='LIG. PROVISÓRIAS'!E5 | I42: ='LIG. PROVISÓRIAS'!E6 | J42: ='LIG. PROVISÓRIAS'!E7 | K42: ='LIG. PROVISÓRIAS'!E8 | L42: ='LIG. PROVISÓRIAS'!E9 | M42: ='LIG. PROVISÓRIAS'!E10 | N42: ='LIG. PROVISÓRIAS'!E11 | O42: ='LIG. PROVISÓRIAS'!E12 | P42: ='LIG. PROVISÓRIAS'!E13 | Q42: ='LIG. PROVISÓRIAS'!E14 | R42: ='LIG. PROVISÓRIAS'!E15 | S42: ='LIG. PROVISÓRIAS'!E16 | T42: ='LIG. PROVISÓRIAS'!E17 | U42: ='LIG. PROVISÓRIAS'!E18 | V42: ='LIG. PROVISÓRIAS'!E19 | W42: ='LIG. PROVISÓRIAS'!E20 | X42: ='LIG. PROVISÓRIAS'!E21 | Y42: ='LIG. PROVISÓRIAS'!E22 | Z42: ='LIG. PROVISÓRIAS'!E23 | AA42: ='LIG. PROVISÓRIAS'!E24 | AB42: ='LIG. PROVISÓRIAS'!E25 | AC42: ='LIG. PROVISÓRIAS'!E26 | AD42: ='LIG. PROVISÓRIAS'!E27 | AE42: ='LIG. PROVISÓRIAS'!E28 | AF42: ='LIG. PROVISÓRIAS'!E29 | AG42: ='LIG. PROVISÓRIAS'!E30 | AH42: ='LIG. PROVISÓRIAS'!E31 | AI42: ='LIG. PROVISÓRIAS'!E32 | AJ42: ='LIG. PROVISÓRIAS'!E33 | AK42: ='LIG. PROVISÓRIAS'!E34 | AL42: ='LIG. PROVISÓRIAS'!E35 | AM42: ='LIG. PROVISÓRIAS'!E36 | AN42: ='LIG. PROVISÓRIAS'!E37 | AO42: ='LIG. PROVISÓRIAS'!E38 | AP42: ='LIG. PROVISÓRIAS'!E39 | AQ42: ='LIG. PROVISÓRIAS'!E40 | AR42: ='LIG. PROVISÓRIAS'!E41 | AS42: ='LIG. PROVISÓRIAS'!E42 | AT42: ='LIG. PROVISÓRIAS'!E43 | AU42: ='LIG. PROVISÓRIAS'!E44 | AV42: ='LIG. PROVISÓRIAS'!E45 | AW42: ='LIG. PROVISÓRIAS'!E46 | AX42: ='LIG. PROVISÓRIAS'!E47 | AY42: ='LIG. PROVISÓRIAS'!E48 | AZ42: ='LIG. PROVISÓRIAS'!E49 | BA42: ='LIG. PROVISÓRIAS'!E50 | BB42: ='LIG. PROVISÓRIAS'!E51 | BC42: ='LIG. PROVISÓRIAS'!E52 | BD42: ='LIG. PROVISÓRIAS'!E53 | BE42: ='LIG. PROVISÓRIAS'!E54 | BF42: ='LIG. PROVISÓRIAS'!E55 | BG42: ='LIG. PROVISÓRIAS'!E56 | BH42: ='LIG. PROVISÓRIAS'!E57 | BI42: ='LIG. PROVISÓRIAS'!E58 | BJ42: ='LIG. PROVISÓRIAS'!E59 | BK42: ='LIG. PROVISÓRIAS'!E60 | BL42: ='LIG. PROVISÓRIAS'!E61 | BM42: ='LIG. PROVISÓRIAS'!E62 | BN42: ='LIG. PROVISÓRIAS'!E63 | BO42: ='LIG. PROVISÓRIAS'!E64 | BP42: ='LIG. PROVISÓRIAS'!E65 | BQ42: ='LIG. PROVISÓRIAS'!E66 | BR42: ='LIG. PROVISÓRIAS'!E67 | BS42: ='LIG. PROVISÓRIAS'!E68 | BT42: ='LIG. PROVISÓRIAS'!E69 | BU42: ='LIG. PROVISÓRIAS'!E70 | BV42: ='LIG. PROVISÓRIAS'!E71 | BW42: ='LIG. PROVISÓRIAS'!E72 | BX42: ='LIG. PROVISÓRIAS'!E73 | BY42: ='LIG. PROVISÓRIAS'!E74 | BZ42: ='LIG. PROVISÓRIAS'!E75 | CA42: ='LIG. PROVISÓRIAS'!E76
B43: 1030-1070-470 | C43: TAXA DE ADMINISTRAÇÃO | D43: ='TAX. ADM'!$K$5 | E43: =SUM(H43:CA43) | F43: =IF(D43="","",D43-E43) | H43: ='TAX. ADM'!E5 | I43: ='TAX. ADM'!E6 | J43: ='TAX. ADM'!E7 | K43: ='TAX. ADM'!E8 | L43: ='TAX. ADM'!E9 | M43: ='TAX. ADM'!E10 | N43: ='TAX. ADM'!E11 | O43: ='TAX. ADM'!E12 | P43: ='TAX. ADM'!E13 | Q43: ='TAX. ADM'!E14 | R43: ='TAX. ADM'!E15 | S43: ='TAX. ADM'!E16 | T43: ='TAX. ADM'!E17 | U43: ='TAX. ADM'!E18 | V43: ='TAX. ADM'!E19 | W43: ='TAX. ADM'!E20 | X43: ='TAX. ADM'!E21 | Y43: ='TAX. ADM'!E22 | Z43: ='TAX. ADM'!E23 | AA43: ='TAX. ADM'!E24 | AB43: ='TAX. ADM'!E25 | AC43: ='TAX. ADM'!E26 | AD43: ='TAX. ADM'!E27 | AE43: ='TAX. ADM'!E28 | AF43: ='TAX. ADM'!E29 | AG43: ='TAX. ADM'!E30 | AH43: ='TAX. ADM'!E31 | AI43: ='TAX. ADM'!E32 | AJ43: ='TAX. ADM'!E33 | AK43: ='TAX. ADM'!E34 | AL43: ='TAX. ADM'!E35 | AM43: ='TAX. ADM'!E36 | AN43: ='TAX. ADM'!E37 | AO43: ='TAX. ADM'!E38 | AP43: ='TAX. ADM'!E39 | AQ43: ='TAX. ADM'!E40 | AR43: ='TAX. ADM'!E41 | AS43: ='TAX. ADM'!E42 | AT43: ='TAX. ADM'!E43 | AU43: ='TAX. ADM'!E44 | AV43: ='TAX. ADM'!E45 | AW43: ='TAX. ADM'!E46 | AX43: ='TAX. ADM'!E47 | AY43: ='TAX. ADM'!E48 | AZ43: ='TAX. ADM'!E49 | BA43: ='TAX. ADM'!E50 | BB43: ='TAX. ADM'!E51 | BC43: ='TAX. ADM'!E52 | BD43: ='TAX. ADM'!E53 | BE43: ='TAX. ADM'!E54 | BF43: ='TAX. ADM'!E55 | BG43: ='TAX. ADM'!E56 | BH43: ='TAX. ADM'!E57 | BI43: ='TAX. ADM'!E58 | BJ43: ='TAX. ADM'!E59 | BK43: ='TAX. ADM'!E60 | BL43: ='TAX. ADM'!E61 | BM43: ='TAX. ADM'!E62 | BN43: ='TAX. ADM'!E63 | BO43: ='TAX. ADM'!E64 | BP43: ='TAX. ADM'!E65 | BQ43: ='TAX. ADM'!E66 | BR43: ='TAX. ADM'!E67 | BS43: ='TAX. ADM'!E68 | BT43: ='TAX. ADM'!E69 | BU43: ='TAX. ADM'!E70 | BV43: ='TAX. ADM'!E71 | BW43: ='TAX. ADM'!E72 | BX43: ='TAX. ADM'!E73 | BY43: ='TAX. ADM'!E74 | BZ43: ='TAX. ADM'!E75 | CA43: ='TAX. ADM'!E76
B44: 1030-1070-180 | C44: TERRAPLENAGEM | D44: ='TERRAPLENAGEM'!$K$5 | E44: =SUM(H44:CA44) | F44: =IF(D44="","",D44-E44) | H44: ='TERRAPLENAGEM'!E5 | I44: ='TERRAPLENAGEM'!E6 | J44: ='TERRAPLENAGEM'!E7 | K44: ='TERRAPLENAGEM'!E8 | L44: ='TERRAPLENAGEM'!E9 | M44: ='TERRAPLENAGEM'!E10 | N44: ='TERRAPLENAGEM'!E11 | O44: ='TERRAPLENAGEM'!E12 | P44: ='TERRAPLENAGEM'!E13 | Q44: ='TERRAPLENAGEM'!E14 | R44: ='TERRAPLENAGEM'!E15 | S44: ='TERRAPLENAGEM'!E16 | T44: ='TERRAPLENAGEM'!E17 | U44: ='TERRAPLENAGEM'!E18 | V44: ='TERRAPLENAGEM'!E19 | W44: ='TERRAPLENAGEM'!E20 | X44: ='TERRAPLENAGEM'!E21 | Y44: ='TERRAPLENAGEM'!E22 | Z44: ='TERRAPLENAGEM'!E23 | AA44: ='TERRAPLENAGEM'!E24 | AB44: ='TERRAPLENAGEM'!E25 | AC44: ='TERRAPLENAGEM'!E26 | AD44: ='TERRAPLENAGEM'!E27 | AE44: ='TERRAPLENAGEM'!E28 | AF44: ='TERRAPLENAGEM'!E29 | AG44: ='TERRAPLENAGEM'!E30 | AH44: ='TERRAPLENAGEM'!E31 | AI44: ='TERRAPLENAGEM'!E32 | AJ44: ='TERRAPLENAGEM'!E33 | AK44: ='TERRAPLENAGEM'!E34 | AL44: ='TERRAPLENAGEM'!E35 | AM44: ='TERRAPLENAGEM'!E36 | AN44: ='TERRAPLENAGEM'!E37 | AO44: ='TERRAPLENAGEM'!E38 | AP44: ='TERRAPLENAGEM'!E39 | AQ44: ='TERRAPLENAGEM'!E40 | AR44: ='TERRAPLENAGEM'!E41 | AS44: ='TERRAPLENAGEM'!E42 | AT44: ='TERRAPLENAGEM'!E43 | AU44: ='TERRAPLENAGEM'!E44 | AV44: ='TERRAPLENAGEM'!E45 | AW44: ='TERRAPLENAGEM'!E46 | AX44: ='TERRAPLENAGEM'!E47 | AY44: ='TERRAPLENAGEM'!E48 | AZ44: ='TERRAPLENAGEM'!E49 | BA44: ='TERRAPLENAGEM'!E50 | BB44: ='TERRAPLENAGEM'!E51 | BC44: ='TERRAPLENAGEM'!E52 | BD44: ='TERRAPLENAGEM'!E53 | BE44: ='TERRAPLENAGEM'!E54 | BF44: ='TERRAPLENAGEM'!E55 | BG44: ='TERRAPLENAGEM'!E56 | BH44: ='TERRAPLENAGEM'!E57 | BI44: ='TERRAPLENAGEM'!E58 | BJ44: ='TERRAPLENAGEM'!E59 | BK44: ='TERRAPLENAGEM'!E60 | BL44: ='TERRAPLENAGEM'!E61 | BM44: ='TERRAPLENAGEM'!E62 | BN44: ='TERRAPLENAGEM'!E63 | BO44: ='TERRAPLENAGEM'!E64 | BP44: ='TERRAPLENAGEM'!E65 | BQ44: ='TERRAPLENAGEM'!E66 | BR44: ='TERRAPLENAGEM'!E67 | BS44: ='TERRAPLENAGEM'!E68 | BT44: ='TERRAPLENAGEM'!E69 | BU44: ='TERRAPLENAGEM'!E70 | BV44: ='TERRAPLENAGEM'!E71 | BW44: ='TERRAPLENAGEM'!E72 | BX44: ='TERRAPLENAGEM'!E73 | BY44: ='TERRAPLENAGEM'!E74 | BZ44: ='TERRAPLENAGEM'!E75 | CA44: ='TERRAPLENAGEM'!E76
B45: 1030-1070-600 | C45: TOPOGRAFIA | E45: =SUM(H45:CA45) | F45: =IF(D45="","",D45-E45)
B46: 1030-1070-460 | C46: TRANSPORTES | D46: ='TRANSPORTES'!$K$5 | E46: =SUM(H46:CA46) | F46: =IF(D46="","",D46-E46) | H46: ='TRANSPORTES'!E5 | I46: ='TRANSPORTES'!E6 | J46: ='TRANSPORTES'!E7 | K46: ='TRANSPORTES'!E8 | L46: ='TRANSPORTES'!E9 | M46: ='TRANSPORTES'!E10 | N46: ='TRANSPORTES'!E11 | O46: ='TRANSPORTES'!E12 | P46: ='TRANSPORTES'!E13 | Q46: ='TRANSPORTES'!E14 | R46: ='TRANSPORTES'!E15 | S46: ='TRANSPORTES'!E16 | T46: ='TRANSPORTES'!E17 | U46: ='TRANSPORTES'!E18 | V46: ='TRANSPORTES'!E19 | W46: ='TRANSPORTES'!E20 | X46: ='TRANSPORTES'!E21 | Y46: ='TRANSPORTES'!E22 | Z46: ='TRANSPORTES'!E23 | AA46: ='TRANSPORTES'!E24 | AB46: ='TRANSPORTES'!E25 | AC46: ='TRANSPORTES'!E26 | AD46: ='TRANSPORTES'!E27 | AE46: ='TRANSPORTES'!E28 | AF46: ='TRANSPORTES'!E29 | AG46: ='TRANSPORTES'!E30 | AH46: ='TRANSPORTES'!E31 | AI46: ='TRANSPORTES'!E32 | AJ46: ='TRANSPORTES'!E33 | AK46: ='TRANSPORTES'!E34 | AL46: ='TRANSPORTES'!E35 | AM46: ='TRANSPORTES'!E36 | AN46: ='TRANSPORTES'!E37 | AO46: ='TRANSPORTES'!E38 | AP46: ='TRANSPORTES'!E39 | AQ46: ='TRANSPORTES'!E40 | AR46: ='TRANSPORTES'!E41 | AS46: ='TRANSPORTES'!E42 | AT46: ='TRANSPORTES'!E43 | AU46: ='TRANSPORTES'!E44 | AV46: ='TRANSPORTES'!E45 | AW46: ='TRANSPORTES'!E46 | AX46: ='TRANSPORTES'!E47 | AY46: ='TRANSPORTES'!E48 | AZ46: ='TRANSPORTES'!E49 | BA46: ='TRANSPORTES'!E50 | BB46: ='TRANSPORTES'!E51 | BC46: ='TRANSPORTES'!E52 | BD46: ='TRANSPORTES'!E53 | BE46: ='TRANSPORTES'!E54 | BF46: ='TRANSPORTES'!E55 | BG46: ='TRANSPORTES'!E56 | BH46: ='TRANSPORTES'!E57 | BI46: ='TRANSPORTES'!E58 | BJ46: ='TRANSPORTES'!E59 | BK46: ='TRANSPORTES'!E60 | BL46: ='TRANSPORTES'!E61 | BM46: ='TRANSPORTES'!E62 | BN46: ='TRANSPORTES'!E63 | BO46: ='TRANSPORTES'!E64 | BP46: ='TRANSPORTES'!E65 | BQ46: ='TRANSPORTES'!E66 | BR46: ='TRANSPORTES'!E67 | BS46: ='TRANSPORTES'!E68 | BT46: ='TRANSPORTES'!E69 | BU46: ='TRANSPORTES'!E70 | BV46: ='TRANSPORTES'!E71 | BW46: ='TRANSPORTES'!E72 | BX46: ='TRANSPORTES'!E73 | BY46: ='TRANSPORTES'!E74 | BZ46: ='TRANSPORTES'!E75 | CA46: ='TRANSPORTES'!E76
B47: 1030-1070-480 | C47: ESTRUTURA EM COBERTURA METÁLICA | E47: =SUM(H47:CA47) | F47: =IF(D47="","",D47-E47)
B48: 1030-1070-500 | C48: REFORÇO ESTRUTURAL | E48: =SUM(H48:CA48) | F48: =IF(D48="","",D48-E48)
B49: 1030-1070-530 | C49: MÃO DE OBRA PRÓPRIA | D49: ='MDO'!$K$5 | E49: =SUM(H49:CA49) | F49: =IF(D49="","",D49-E49) | H49: ='MDO'!E5 | I49: ='MDO'!E6 | J49: ='MDO'!E7 | K49: ='MDO'!E8 | L49: ='MDO'!E9 | M49: ='MDO'!E10 | N49: ='MDO'!E11 | O49: ='MDO'!E12 | P49: ='MDO'!E13 | Q49: ='MDO'!E14 | R49: ='MDO'!E15 | S49: ='MDO'!E16 | T49: ='MDO'!E17 | U49: ='MDO'!E18 | V49: ='MDO'!E19 | W49: ='MDO'!E20 | X49: ='MDO'!E21 | Y49: ='MDO'!E22 | Z49: ='MDO'!E23 | AA49: ='MDO'!E24 | AB49: ='MDO'!E25 | AC49: ='MDO'!E26 | AD49: ='MDO'!E27 | AE49: ='MDO'!E28 | AF49: ='MDO'!E29 | AG49: ='MDO'!E30 | AH49: ='MDO'!E31 | AI49: ='MDO'!E32 | AJ49: ='MDO'!E33 | AK49: ='MDO'!E34 | AL49: ='MDO'!E35 | AM49: ='MDO'!E36 | AN49: ='MDO'!E37 | AO49: ='MDO'!E38 | AP49: ='MDO'!E39 | AQ49: ='MDO'!E40 | AR49: ='MDO'!E41 | AS49: ='MDO'!E42 | AT49: ='MDO'!E43 | AU49: ='MDO'!E44 | AV49: ='MDO'!E45 | AW49: ='MDO'!E46 | AX49: ='MDO'!E47 | AY49: ='MDO'!E48 | AZ49: ='MDO'!E49 | BA49: ='MDO'!E50 | BB49: ='MDO'!E51 | BC49: ='MDO'!E52 | BD49: ='MDO'!E53 | BE49: ='MDO'!E54 | BF49: ='MDO'!E55 | BG49: ='MDO'!E56 | BH49: ='MDO'!E57 | BI49: ='MDO'!E58 | BJ49: ='MDO'!E59 | BK49: ='MDO'!E60 | BL49: ='MDO'!E61 | BM49: ='MDO'!E62 | BN49: ='MDO'!E63 | BO49: ='MDO'!E64 | BP49: ='MDO'!E65 | BQ49: ='MDO'!E66 | BR49: ='MDO'!E67 | BS49: ='MDO'!E68 | BT49: ='MDO'!E69 | BU49: ='MDO'!E70 | BV49: ='MDO'!E71 | BW49: ='MDO'!E72 | BX49: ='MDO'!E73 | BY49: ='MDO'!E74 | BZ49: ='MDO'!E75 | CA49: ='MDO'!E76
B50: 1030-1070-120 | C50: TAXAS DIVERSAS | D50: ='TAX. DIVERSAS'!$K$5 | E50: =SUM(H50:CA50) | F50: =IF(D50="","",D50-E50) | H50: ='TAX. DIVERSAS'!E5 | I50: ='TAX. DIVERSAS'!E6 | J50: ='TAX. DIVERSAS'!E7 | K50: ='TAX. DIVERSAS'!E8 | L50: ='TAX. DIVERSAS'!E9 | M50: ='TAX. DIVERSAS'!E10 | N50: ='TAX. DIVERSAS'!E11 | O50: ='TAX. DIVERSAS'!E12 | P50: ='TAX. DIVERSAS'!E13 | Q50: ='TAX. DIVERSAS'!E14 | R50: ='TAX. DIVERSAS'!E15 | S50: ='TAX. DIVERSAS'!E16 | T50: ='TAX. DIVERSAS'!E17 | U50: ='TAX. DIVERSAS'!E18 | V50: ='TAX. DIVERSAS'!E19 | W50: ='TAX. DIVERSAS'!E20 | X50: ='TAX. DIVERSAS'!E21 | Y50: ='TAX. DIVERSAS'!E22 | Z50: ='TAX. DIVERSAS'!E23 | AA50: ='TAX. DIVERSAS'!E24 | AB50: ='TAX. DIVERSAS'!E25 | AC50: ='TAX. DIVERSAS'!E26 | AD50: ='TAX. DIVERSAS'!E27 | AE50: ='TAX. DIVERSAS'!E28 | AF50: ='TAX. DIVERSAS'!E29 | AG50: ='TAX. DIVERSAS'!E30 | AH50: ='TAX. DIVERSAS'!E31 | AI50: ='TAX. DIVERSAS'!E32 | AJ50: ='TAX. DIVERSAS'!E33 | AK50: ='TAX. DIVERSAS'!E34 | AL50: ='TAX. DIVERSAS'!E35 | AM50: ='TAX. DIVERSAS'!E36 | AN50: ='TAX. DIVERSAS'!E37 | AO50: ='TAX. DIVERSAS'!E38 | AP50: ='TAX. DIVERSAS'!E39 | AQ50: ='TAX. DIVERSAS'!E40 | AR50: ='TAX. DIVERSAS'!E41 | AS50: ='TAX. DIVERSAS'!E42 | AT50: ='TAX. DIVERSAS'!E43 | AU50: ='TAX. DIVERSAS'!E44 | AV50: ='TAX. DIVERSAS'!E45 | AW50: ='TAX. DIVERSAS'!E46 | AX50: ='TAX. DIVERSAS'!E47 | AY50: ='TAX. DIVERSAS'!E48 | AZ50: ='TAX. DIVERSAS'!E49 | BA50: ='TAX. DIVERSAS'!E50 | BB50: ='TAX. DIVERSAS'!E51 | BC50: ='TAX. DIVERSAS'!E52 | BD50: ='TAX. DIVERSAS'!E53 | BE50: ='TAX. DIVERSAS'!E54 | BF50: ='TAX. DIVERSAS'!E55 | BG50: ='TAX. DIVERSAS'!E56 | BH50: ='TAX. DIVERSAS'!E57 | BI50: ='TAX. DIVERSAS'!E58 | BJ50: ='TAX. DIVERSAS'!E59 | BK50: ='TAX. DIVERSAS'!E60 | BL50: ='TAX. DIVERSAS'!E61 | BM50: ='TAX. DIVERSAS'!E62 | BN50: ='TAX. DIVERSAS'!E63 | BO50: ='TAX. DIVERSAS'!E64 | BP50: ='TAX. DIVERSAS'!E65 | BQ50: ='TAX. DIVERSAS'!E66 | BR50: ='TAX. DIVERSAS'!E67 | BS50: ='TAX. DIVERSAS'!E68 | BT50: ='TAX. DIVERSAS'!E69 | BU50: ='TAX. DIVERSAS'!E70 | BV50: ='TAX. DIVERSAS'!E71 | BW50: ='TAX. DIVERSAS'!E72 | BX50: ='TAX. DIVERSAS'!E73 | BY50: ='TAX. DIVERSAS'!E74 | BZ50: ='TAX. DIVERSAS'!E75 | CA50: ='TAX. DIVERSAS'!E76
B51: 1030-1070-590 | C51: SEGURANÇA DO TRABALHO | E51: =SUM(H51:CA51) | F51: =IF(D51="","",D51-E51)
B52: 1030-1070-520 | C52: SERVIÇOS INICIAIS | D52: ='SERV. INICIAIS'!$K$5 | E52: =SUM(H52:CA52) | F52: =IF(D52="","",D52-E52) | H52: ='SERV. INICIAIS'!E5 | I52: ='SERV. INICIAIS'!E6 | J52: ='SERV. INICIAIS'!E7 | K52: ='SERV. INICIAIS'!E8 | L52: ='SERV. INICIAIS'!E9 | M52: ='SERV. INICIAIS'!E10 | N52: ='SERV. INICIAIS'!E11 | O52: ='SERV. INICIAIS'!E12 | P52: ='SERV. INICIAIS'!E13 | Q52: ='SERV. INICIAIS'!E14 | R52: ='SERV. INICIAIS'!E15 | S52: ='SERV. INICIAIS'!E16 | T52: ='SERV. INICIAIS'!E17 | U52: ='SERV. INICIAIS'!E18 | V52: ='SERV. INICIAIS'!E19 | W52: ='SERV. INICIAIS'!E20 | X52: ='SERV. INICIAIS'!E21 | Y52: ='SERV. INICIAIS'!E22 | Z52: ='SERV. INICIAIS'!E23 | AA52: ='SERV. INICIAIS'!E24 | AB52: ='SERV. INICIAIS'!E25 | AC52: ='SERV. INICIAIS'!E26 | AD52: ='SERV. INICIAIS'!E27 | AE52: ='SERV. INICIAIS'!E28 | AF52: ='SERV. INICIAIS'!E29 | AG52: ='SERV. INICIAIS'!E30 | AH52: ='SERV. INICIAIS'!E31 | AI52: ='SERV. INICIAIS'!E32 | AJ52: ='SERV. INICIAIS'!E33 | AK52: ='SERV. INICIAIS'!E34 | AL52: ='SERV. INICIAIS'!E35 | AM52: ='SERV. INICIAIS'!E36 | AN52: ='SERV. INICIAIS'!E37 | AO52: ='SERV. INICIAIS'!E38 | AP52: ='SERV. INICIAIS'!E39 | AQ52: ='SERV. INICIAIS'!E40 | AR52: ='SERV. INICIAIS'!E41 | AS52: ='SERV. INICIAIS'!E42 | AT52: ='SERV. INICIAIS'!E43 | AU52: ='SERV. INICIAIS'!E44 | AV52: ='SERV. INICIAIS'!E45 | AW52: ='SERV. INICIAIS'!E46 | AX52: ='SERV. INICIAIS'!E47 | AY52: ='SERV. INICIAIS'!E48 | AZ52: ='SERV. INICIAIS'!E49 | BA52: ='SERV. INICIAIS'!E50 | BB52: ='SERV. INICIAIS'!E51 | BC52: ='SERV. INICIAIS'!E52 | BD52: ='SERV. INICIAIS'!E53 | BE52: ='SERV. INICIAIS'!E54 | BF52: ='SERV. INICIAIS'!E55 | BG52: ='SERV. INICIAIS'!E56 | BH52: ='SERV. INICIAIS'!E57 | BI52: ='SERV. INICIAIS'!E58 | BJ52: ='SERV. INICIAIS'!E59 | BK52: ='SERV. INICIAIS'!E60 | BL52: ='SERV. INICIAIS'!E61 | BM52: ='SERV. INICIAIS'!E62 | BN52: ='SERV. INICIAIS'!E63 | BO52: ='SERV. INICIAIS'!E64 | BP52: ='SERV. INICIAIS'!E65 | BQ52: ='SERV. INICIAIS'!E66 | BR52: ='SERV. INICIAIS'!E67 | BS52: ='SERV. INICIAIS'!E68 | BT52: ='SERV. INICIAIS'!E69 | BU52: ='SERV. INICIAIS'!E70 | BV52: ='SERV. INICIAIS'!E71 | BW52: ='SERV. INICIAIS'!E72 | BX52: ='SERV. INICIAIS'!E73 | BY52: ='SERV. INICIAIS'!E74 | BZ52: ='SERV. INICIAIS'!E75 | CA52: ='SERV. INICIAIS'!E76
B53: 1040-1110-115 | C53: COMERCIAIS | E53: =SUM(H53:CA53) | F53: =IF(D53="","",D53-E53)
B54: 1040-1130-110 | C54: INCORPORAÇÃO / LEGALIZAÇÃO | E54: =SUM(H54:CA54) | F54: =IF(D54="","",D54-E54)
B55: 1040-1130-110 | C55: INCORPORAÇÃO / LEGALIZAÇÃO | E55: =SUM(H55:CA55) | F55: =IF(D55="","",D55-E55)
B56: 1030-1090-100 | C56: MEDIDAS COMPENSATÓRIAS | E56: =SUM(H56:CA56) | F56: =IF(D56="","",D56-E56)
B57: 1040-1110-130 | E57: =SUM(H57:CA57) | F57: =IF(D57="","",D57-E57)
C59: SOMA SEM TAXA DE ADM. (INCC) | D59: =SUM(D2:D57)-D43 | E59: =SUM(E2:E57)-E43 | H59: =SUM(H2:H57)-H43 | I59: =SUM(I2:I57)-I43 | J59: =SUM(J2:J57)-J43 | K59: =SUM(K2:K57)-K43 | L59: =SUM(L2:L57)-L43 | M59: =SUM(M2:M57)-M43 | N59: =SUM(N2:N57)-N43 | O59: =SUM(O2:O57)-O43 | ... CA59: =SUM(CA2:CA57)-CA43
C60: TAXA DE ADMINISTRAÇÃO (INCC) | D60: =D43 | E60: =E43 | H60: =H43 | I60: =I43 | J60: =J43 | K60: =K43 | L60: =L43 | M60: =M43 | N60: =N43 | O60: =O43 | ... CA60: =CA43
C61: TOTAL (INCC) | D61: =D59+D60 | E61: =E59+E60 | H61: =H59+H60 | I61: =I59+I60 | J61: =J59+J60 | K61: =K59+K60 | L61: =L59+L60 | M61: =M59+M60 | N61: =N59+N60 | O61: =O59+O60 | ... CA61: =CA59+CA60
C62: ="INCORRIDO ATÉ -> "&TEXT('VALOR POR PL'!$P$5,"mm/aaaa")
